Workbook
Name \E: #REF!
Name \E: #REF!
Name _____________________MS798: #REF!
Name _____________________MS798: #REF!
Name _____________________tab1: #REF!
Name _____________________tab2: #REF!
Name _____________________tab6798: #REF!
Name ____________________MS798: #REF!
Name ____________________tab1: #REF!
Name ____________________tab2: #REF!
Name ____________________tab6798: #REF!
Name ___________________MS798: #REF!
Name ___________________tab1: #REF!
Name ___________________tab2: #REF!
Name ___________________tab6798: #REF!
Name __________________MS798: #REF!
Name __________________tab1: #REF!
Name __________________tab2: #REF!
Name __________________tab6798: #REF!
Name _________________MS798: #REF!
Name _________________prt1: #N/A
Name _________________prt2: #N/A
Name _________________prt3: #N/A
Name _________________prt4: #N/A
Name _________________prt5: #N/A
Name _________________prt6: #N/A
Name _________________prt7: #N/A
Name _________________prt8: #N/A
Name _________________tab1: #REF!
Name _________________tab2: #REF!
Name _________________tab6798: #REF!
Name ________________MS798: #REF!
Name ________________prt1: #N/A
Name ________________prt2: #N/A
Name ________________prt3: #N/A
Name ________________prt4: #N/A
Name ________________prt5: #N/A
Name ________________prt6: #N/A
Name ________________prt7: #N/A
Name ________________prt8: #N/A
Name ________________tab1: #REF!
Name ________________tab2: #REF!
Name ________________tab6798: #REF!
Name _______________MS798: #REF!
Name _______________prt1: #N/A
Name _______________prt2: #N/A
Name _______________prt3: #N/A
Name _______________prt4: #N/A
Name _______________prt5: #N/A
Name _______________prt6: #N/A
Name _______________prt7: #N/A
Name _______________prt8: #N/A
Name _______________tab1: #REF!
Name _______________tab2: #REF!
Name _______________tab6798: #REF!
Name ______________MS798: #REF!
Name ______________prt1: #N/A
Name ______________prt2: #N/A
Name ______________prt3: #N/A
Name ______________prt4: #N/A

Sheet табл 1
A1: 1-кесте | I1: Таблица 1
A3: НЕГІЗГІ МАКРОЭКОНОМИКАЛЫҚ ИНДИКАТОРЛАР/
A4: ОСНОВНЫЕ МАКРОЭКОНОМИЧЕСКИЕ ИНДИКАТОРЫ
A6: Атауы | B6: 2019 жыл/ 2019 год | C6: 2020 жыл/ 2020 год | D6: 2021 жыл/ 2021 год | E6: 2022 жыл/ 2022 год | F6: 2023 жыл/ 2023 год | G6: 2024 жыл/ 2024 год | H6: 2025 ж. 1 наурыздағы есеп/ отчет на 1 марта 2025 г. | I6: Наименование
A7: 1 | B7: 2 | C7: 3 | D7: 4 | E7: 5 | F7: 6 | G7: 7 | H7: 8 | I7: 9
A8: Жалпы ішкi өнiм, млрд. теңге | B8: 69532.626 | C8: 70649 | D8: 83951.587 | E8: 65487.797 | F8: 120561.1 | G8: 84962.621 | H8: 135251.66 | I8: Валовой внутренний продукт, млрд.тенге январь-декабрь 2024 год (опер. данные)
A9: өткен жылдың тиiстi кезеңiндегi нақты есептеудегi %-бен | B9: 104.5 | C9: 97.5 | D9: 103.3 | E9: 103 | F9: 105.1 | G9: 104.1 | H9: 104.8 | I9: в % к соответствующему периоду предыдущего года
A10: Өнеркәсiп өнiмiнiң көлемi, млрд. теңге | B10: 29380.342 | C10: 26743.4 | D10: 37047.6 | E10: 4157.4 | F10: 46401.716 | G10: 50124.86 | H10: 9112 | I10: Объем промышленного производства, млрд.тенге (январь-февраль 2025г.)
A11: өткен жылдың тиiстi кезеңiне %-бен | B11: 104.1 | C11: 99.3 | D11: 103.8 | E11: 97.2 | F11: 104.3 | G11: 102.8 | H11: 105.9 | I11: в % к соответствующему периоду предыдущего года
A12: Мембюджетке кірістер, млрд. теңге | B12: 12758.479 | C12: 14521.191 | D12: 15847.431 | E12: 20248.101 | F12: 24917.246 | G12: ='[46]табл 2 '!C8/1000 -> 27132.165 | H12: ='табл 2 '!C8/1000 -> 5021.3126 | I12: Доходы в госбюджет, млрд.тенге
A13: ЖIӨ-ге %-бен | B13: 18.502241 | C13: 20.535071 | D13: =D12/D8*100 -> 18.876869 | E13: =E12/E8*100 -> 30.918891 | G13: =G12/G8*100 -> 31.934237 | H13: =H12/H8*100 -> 3.71257 | I13: в % к ВВП
A14: Мембюджеттен шығындар, млрд. теңге | B14: 13535.581 | C14: 16725.097 | D14: 17951.888 | E14: 21532.543 | F14: 26760 | G14: ='[46]табл 2 '!C18/1000 -> 30318.236 | H14: ='табл 2 '!C18/1000 -> 4380.2348 | I14: Затраты из госбюджета, млрд. тенге
A15: ЖIӨ-ге %-бен | B15: 19.629188 | C15: 23.651714 | D15: =D14/D8*100 -> 21.38362 | E15: =E14/E8*100 -> 32.880238 | F15: 35.421743 | G15: =G14/G8*100 -> 35.684206 | H15: =H14/H8*100 -> 3.2385811 | I15: в % к ВВП
A16: Таза бюджеттік кредит беру, млрд. теңге | B16: 262.88084 | C16: 261.98101 | D16: 267.33754 | E16: 592.68034 | F16: 466.44174 | G16: ='[46]табл 2 '!C34/1000 -> 198.40855 | H16: ='табл 3'!F34/1000 -> 12.537673 | I16: Чистое бюджетное кредитование, млрд. тенге
A17: ЖIӨ-ге %-бен | B17: 0.38122761 | C17: 0.37047917 | D17: =D16/D8*100 -> 0.31844251 | E17: =E16/E8*100 -> 0.9050241 | F17: 0.61742075 | G17: =G16/G8*100 -> 0.23352452 | H17: =H16/H8*100 -> 0.0092698848 | I17: в % к ВВП
A18: Қаржылық активтермен болатын операциялар бойынша сальдо, млрд. теңге | B18: 245.32373 | C18: 340.26326 | D18: 163.01136 | E18: 292.00158 | F18: 501.9047 | G18: ='[46]табл 2 '!C37/1000 -> 201.56181 | H18: ='табл 2 '!C37/1000 -> 68.054292 | I18: Сальдо по операциям с финансовыми активами, млрд.тенге
A19: ЖIӨ-ге %-бен | B19: 0.35576643 | C19: 0.48118163 | D19: =D18/D8*100 -> 0.19417306 | E19: =E18/E8*100 -> 0.44588701 | F19: 0.66436244 | G19: =G18/G8*100 -> 0.23723586 | H19: =H18/H8*100 -> 0.050316787 | I19: в % к ВВП
A20: Мембюджеттiң тапшылығы (-) / профицитi (+), млрд. теңге | B20: -1285.3067 | C20: -2806.1502 | D20: -2534.8062 | E20: -2169.1247 | F20: -2811.1006 | G20: ='[46]табл 2 '!C40/1000 -> -3586.0419 | H20: ='табл 3'!F40/1000 -> 560.48587 | I20: Дефицит (-) / профицит (+) госбюджета, млрд.тенге
A21: ЖIӨ-ге %-бен | B21: -1.8639412 | C21: -3.9683036 | D21: =D20/D8*100 -> -3.0193666 | E21: =E20/E8*100 -> -3.3122579 | F21: -3.7210045 | G21: =G20/G8*100 -> -4.2207288 | H21: =H20/H8*100 -> 0.4144022 | I21: в % к ВВП
A22: Тұтыну бағаларының индексі өткен жылдың айына, %-бен | B22: 105.4 | C22: 107.5 | D22: 108.4 | E22: 120.3 | F22: 109.5 | G22: 108.9 | H22: 109.4 | I22: Индекс потребительских цен к февралю предыдущего года, в %
A23: орташа есеппен өткен жылдың тиiстi кезеңiндегi кезге арналған, %-бен | B23: 105.3 | C23: 106.8 | D23: 108 | E23: 115 | G23: 108.6 | H23: 108.8 | I23: в среднем за период к соответствующему периоду предыдущего года, в %
A24: Орташа айлық атаулы жалақы 1 қызметкердың, теңге | B24: 186815 | C24: 220848 | D24: 268051 | E24: 303055 | F24: 350542 | G24: 390328 | H24: 434982 | I24: Среднемесячная номинальная заработная плата 1 работника, тенге (4 квартал 2024г.)
A25: өткен жылдың тиiстi кезеңiне %-бен | B25: 114.8 | C25: 104.4 | D25: 115.3 | E25: 112.2 | F25: 116.9 | G25: 111.3 | H25: 110.5 | I25: в % к соответствующему периоду предыдущего года
A26: Экспорт, млн. АҚШ долл. | B26: 58065.6 | C26: 46 949,7 2 | D26: 54549.5 | E26: ____ | F26: 71274.7 | G26: 73884.5 | H26: 5107.9 | I26: Экспорт, млн. долл. США (январь 2025г.)
A27: өткен жылдың тиiстi кезеңiне %-бен | B27: 95 | C27: 80.9 | D27: 124.5 | I27: в % к соответствующему периоду предыдущего года
A28: Импорт, млн. АҚШ долл. | B28: 39709.3 | C28: 38 081,4 2 | D28: 36825.9 | E28: ____ | F28: 54643.5 | G28: 53590.3 | H28: 4035.9 | I28: Импорт, млн. долл. США (январь 2025г.)
A29: өткен жылдың тиiстi кезеңiне %-бен | B29: 118 | C29: 95.9 | D29: 104.2 | I29: в % к соответствующему периоду предыдущего года
A30: Сауда балансының сальдосы, млн. АҚШ долл. | B30: 18356.3 | C30: 8969 | D30: 17723.6 | E30: ____ | F30: 16631.2 | G30: =G26-G28 -> 20294.2 | H30: =H26-H28 -> 1072 | I30: Сальдо торгового баланса, млн. долл. США
A31: Теңгенiң АҚШ долларына қарағандағы ресми айырбас бағамы: | I31: Официальный обменный курс тенге к доллару США:
A32: кезеңнiң аяғындағы | B32: 381.18 | C32: 420.71 | D32: 433.83 | E32: 459.92 | F32: 448.17 | G32: 525.11 | H32: 501.49 | I32: на конец периода
A33: кезең бойынша орташа | B33: 382.75 | C33: 412.95 | D33: 433.66 | E33: 460.48 | F33: 451.28 | G33: 469.44 | H33: 506.03 | I33: в среднем за период февраль 2025 года
A35: Ақпарат көзi: / Источник:
A36: Қазақстан Республикасының Қаржы министрлiгi / Министерство финансов Республики Казахстан.
A37: Ұлттық статистика бюросы Қазақстан Республикасының Стратегиялық жоспарлау және реформалар агенттігі / Бюро национальной статистики Агентства по стратегическому планированию и реформам Республики Казахстан
A38: Қазақстан Республикасының Ұлттық Банкi / Национальный Банк Республики Казахстан.
A39: Ескерту: / Примечание:
A40: 1 - Ұлттық статистика бюросы Қазақстан Республикасының Стратегиялық жоспарлау және реформалар агенттігінің деректері бойынша /Объем ВВП по отчетным данным Бюро национальной статистики Агентства по стратегическому планированию и реформам Республики Казахстан
A41: 2 - Ұлттық статистика бюросы Қазақстан Республикасының Стратегиялық жоспарлау және реформалар агенттігінің деректері бойынша /По данным Бюро национальной статистики Агентства по стратегическому планированию и реформам Республики Казахстан
A42: 3 - Ұлттық статистика бюросы Қазақстан Республикасының Стратегиялық жоспарлау және реформалар агенттігінің деректері бойынша /По данным Бюро национальной статистики Агентства по стратегическому планированию и реформам Республики Казахстан

Sheet табл 2 
A1: 2-кесте | F1: Таблица - 2
A2: МЕМЛЕКЕТТІК ЖӘНЕ РЕСПУБЛИКАЛЫҚ | F2: СРАВНИТЕЛЬНЫЙ АНАЛИЗ ИСПОЛНЕНИЯ
A3: БЮДЖЕТТЕР АТҚАРЫЛУЫНЫҢ САЛЫСТЫРМА ТАЛДАУЫ | F3: ГОСУДАРСТВЕННОГО И РЕСПУБЛИКАНСКОГО БЮДЖЕТОВ
A5: Атауы | B5: Мемлекеттік бюджет / Государственный бюджет | F5: Республикалық бюджет / Республиканский бюджет | J5: Наименование
B6: 2025 жылға түзету енгізілген бюджет (млн. теңге)/ скорректированный бюджет на 2025 год (млн.тенге) | C6: 2025 жылғы қаңтар-ақпан атқарылуы (млн. теңге)/ исполнение за январь-февраль 2025 года (млн.тенге) | D6: бір жылға түзету енгізілген бюджеттің атқарылу %-ы/% исполнения к скорректированному бюджету на год | E6: 2024 ж. қаңтар-ақпан %-бен 2025 ж. қаңтар-ақпанына/ 2025 г. январь-февраль в % к январю-февралю 2024 г. | F6: 2025 жылға түзету енгізілген бюджет (млн. теңге)/ скорректированный бюджет на 2025 год (млн.тенге) | G6: 2025 жылғы қаңтар-ақпан атқарылуы (млн. теңге)/ исполнение за январь-февраль 2025 года (млн.тенге) | H6: бір жылға түзету енгізілген бюджеттің атқарылу %-ы/% исполнения к скорректированному бюджету на год | I6: 2024 ж. қаңтар-ақпан %-бен 2025 ж. қаңтар-ақпанына/ 2025 г. январь-февраль в % к январю-февралю 2024 г.
A7: 1 | B7: 2 | C7: 3 | D7: 4 | E7: 5 | F7: 6 | G7: 7 | H7: 8 | I7: 9 | J7: 10
A8: I. КІРІСТЕР | B8: 28637489 | C8: 5021312.6 | D8: 17.534054 | E8: 118.86761 | F8: 21392055 | G8: 3634592.6 | H8: 16.990386 | I8: 121.60965 | J8: I. ДОХОДЫ
A9: Салықтық түсімдер оның iшiнде: | B9: 22588651 | C9: 3726749.7 | D9: 16.498328 | E9: 120.50161 | F9: 15193344 | G9: 2301508.5 | H9: 15.148137 | I9: 124.43169 | J9: Налоговые поступления, в том числе:
A10: корпорациялық табыс салығы | B10: 6573801.5 | C10: 928750.33 | D10: 14.128056 | E10: 129.83955 | F10: 5087546.7 | G10: 696571.35 | H10: 13.691695 | I10: 135.17772 | J10: корпоративный подоходный налог
A11: жеке табыс салығы | B11: 2449704.2 | C11: 500641.49 | D11: 20.436814 | E11: 112.94908 | F11: 0 | G11: 0 | H11: 0 | I11: 0 | J11: индивидуальный подоходный налог
A12: әлеуметтік салық | B12: 1613288.1 | C12: 341000.69 | D12: 21.136999 | E12: 112.68821 | F12: 0 | G12: 0 | H12: 0 | I12: 0 | J12: социальный налог
A13: қосылған құн салығы | B13: 6510033 | C13: 1105855.5 | D13: 16.986942 | E13: 121.86388 | F13: 6510033 | G13: 1105855.5 | H13: 16.986942 | I13: 121.86388 | J13: налог на добавленную стоимость
A14: акциздер | B14: 923315.43 | C14: 138324.24 | D14: 14.981255 | E14: 108.97919 | F14: 149702.35 | G14: 18199.007 | H14: 12.156794 | I14: 86.66342 | J14: акцизы
A15: Салықтық емес түсімдер | B15: 533506.6 | C15: 265249.93 | D15: 49.718209 | E15: 298.12003 | F15: 435325.85 | G15: 182604.09 | H15: 41.94653 | I15: 380.70455 | J15: Неналоговые поступления
A16: Негізгі капиталды сатудан түсетін түсімдер | B16: 265331.23 | C16: 29312.957 | D16: 11.047685 | E16: 68.77941 | F16: 5200 | G16: 558.11164 | H16: 10.732916 | I16: 11.955534 | J16: Поступления от продажи основного капитала
A17: Трансферттердің түсімдері | B17: 5250000 | C17: 1000000 | D17: 19.047619 | E17: 100 | F17: 5758184.9 | G17: 1149921.9 | H17: 19.970215 | I17: 105.83844 | J17: Поступления трансфертов
A18: II. ШЫҒЫНДАР | B18: 32167783 | C18: 4380234.8 | D18: 13.616838 | E18: 105.64626 | F18: 25193022 | G18: 3638727.6 | H18: 14.443394 | I18: 99.40659 | J18: II. ЗАТРАТЫ
A19: 1. Жалпы сипаттағы мемлекеттiк қызметтер | B19: 1564077.7 | C19: 285493.39 | D19: 18.253147 | E19: 104.83023 | F19: 1110934 | G19: 209111.92 | H19: 18.823073 | I19: 102.74469 | J19: 1. Государственные услуги общего характера
... A32: 14. Борышқа қызмет көрсету | B32: 2554145.6 | C32: 532224.77 | D32: 20.837684 | E32: 120.85358 | F32: 2502000 | G32: 529604.87 | H32: 21.167261 | I32: 120.55036 | J32: 14. Обслуживание долга
F33: 5774300.9 | G33: 776551.01 | H33: 13.448399 | I33: 103.52425 | J33: 15. Трансферты
A34: III. ТАЗА БЮДЖЕТТІК КРЕДИТ БЕРУ | B34: 324882.8 | C34: 12537.673 | D34: 3.8591373 | E34: 30.20462 | F34: 252140.98 | G34: 9424.1552 | H34: 3.7376531 | I34: 21.28575 | J34: III. ЧИСТОЕ БЮДЖЕТНОЕ КРЕДИТОВАНИЕ
A35: Бюджеттік кредиттер | B35: 594996.13 | C35: 25137.485 | D35: 4.2248149 | E35: 49.08786 | F35: 510480 | G35: 20000 | H35: 3.9178812 | I35: 40 | J35: Бюджетные кредиты
A36: Бюджеттік кредиттерді өтеу | B36: 270113.33 | C36: 12599.811 | D36: 4.6646389 | E36: 129.89428 | F36: 258339.02 | G36: 10575.845 | H36: 4.0937853 | I36: 184.71405 | J36: Погашение бюджетных кредитов
A37: IV. ҚАРЖЫ АКТИВТЕРІМЕН ОПЕРАЦИЯЛАР БОЙЫНША САЛЬДО - ҚАРЖЫ АК | B37: 472725.23 | C37: 68054.292 | D37: 14.396162 | E37: 322.46093 | F37: 46891.3 | G37: 76.74548 | H37: 0.16366678 | I37: 0.76544 | J37: IV. САЛЬДО ПО ОПЕРАЦИЯМ С ФИНАНСОВЫМИ АКТИВАМИ
A38: Қаржылық активтерді сатып алу | B38: 472923.34 | C38: 68246.713 | D38: 14.43082 | E38: 320.68461 | F38: 46891.3 | G38: 76.74548 | H38: 0.16366678 | I38: 0.76544 | J38: Приобретение финансовых активов
A39: Мемлекеттің қаржы активтерін сатудан түсетін түсімдер | B39: 198.1 | C39: 192.42119 | D39: 97.133364 | E39: 108.77085 | J39: Поступления от продажи финансовых активов государства
A40: V. БЮДЖЕТ ТАПШЫЛЫҒЫ (ПРОФИЦИТІ) | B40: -4327902 | C40: 560485.87 | D40: -12.950521 | E40: 3606.0883 | F40: -4100000 | G40: -13635.906 | H40: 0.33258307 | I40: -1.87819 | J40: V. ДЕФИЦИТ (ПРОФИЦИТ) БЮДЖЕТА
A41: VI. БЮДЖЕТТІҢ МҰНАЙҒА ҚАТЫСТЫ ЕМЕС ТАПШЫЛЫҒЫ (ПРОФИЦИТІ) | B41: -11227602 | C41: -558145.66 | D41: 4.9711921 | E41: -51.16406 | F41: -10999700 | G41: -1132267.4 | H41: 10.293621 | I41: -61.78982 | J41: VI. НЕНЕФТЯНОЙ ДЕФИЦИТ (ПРОФИЦИТ) БЮДЖЕТА

Sheet табл 3
A1: 3-кесте | E1: Таблица 3
A2: МЕМЛЕКЕТТІК БЮДЖЕТТІҢ АТҚАРЫЛУЫ | E2: ИСПОЛНЕНИЕ ГОСУДАРСТВЕННОГО БЮДЖЕТА
A3: (млн.теңге) | E3: (млн. тенге)
A5: Атауы | B5: 2022 ж. есеп/ 2022 г. отчет | C5: 2023 ж. есеп/ 2023 г. отчет | D5: 2024 ж. есеп/ 2024 г. отчет | F5: 2025 ж. қантар-ақпан есеп/январь-феврал отчет 2025 г. | G5: Наименование
D6: жылдық/ годовой | E6: қантар-ақпан/январь-феврал
A7: 1 | B7: 2 | C7: 3 | D7: 4 | E7: 5 | F7: 6 | G7: 7
A8: I. КІРІСТЕР | B8: 20248101 | C8: 24917246 | D8: 27132165 | E8: 4224290.1 | F8: 5021312.6 | G8: I. ДОХОДЫ#
A9: Салықтық түсімдер_x000D_ оның iшiнде: | B9: 14843311 | C9: 18912204 | D9: 19700517 | E9: 3092697.1 | F9: 3726749.7 | G9: Налоговые поступления,_x000D_ в том числе:
A10: корпорациялық табыс салығы | B10: 3962495.8 | C10: 5045696.1 | D10: 5213291.4 | E10: 715306.19 | F10: 928750.33 | G10: корпоративный подоходный налог
A11: жеке табыс салығы | B11: 1499712.4 | C11: 1992384.9 | D11: 2451640 | E11: 443245.31 | F11: 500641.49 | G11: индивидуальный подоходный налог
A12: әлеуметтік салық | B12: 1035129 | C12: 1321272.8 | D12: 1579329.4 | E12: 302605.48 | F12: 341000.69 | G12: социальный налог
A13: қосылған құн салығы | B13: 4226358.8 | C13: 5674110.6 | D13: 5179378.1 | E13: 907451.41 | F13: 1105855.5 | G13: налог на добавленную стоимость
A14: акциздер | B14: 757266.87 | C14: 840215.7 | D14: 844909.98 | E14: 126927.2 | F14: 138324.24 | G14: акцизы
A15: Салықтық емес түсімдер | B15: 584848.01 | C15: 1822932.9 | D15: 1629968 | E15: 88974.203 | F15: 265249.93 | G15: Неналоговые поступления
A16: Негізгі капиталды сатудан түсетін түсімдер | B16: 239941.5 | C16: 182108.73 | D16: 201680.05 | E16: 42618.795 | F16: 29312.957 | G16: Поступления от продажи основного капитала
A17: Трансферттердің түсімдері | B17: 4580000 | C17: 4000000 | D17: 5600000 | E17: 1000000 | F17: 1000000 | G17: Поступления трансфертов
A18: II. ШЫҒЫНДАР | B18: 21532543 | C18: 26760000 | D18: 30318236 | E18: 4146133.5 | F18: 4380234.8 | G18: II. ЗАТРАТЫ#
A19: 1. Жалпы сипаттағы мемлекеттiк қызметтер | B19: 1211805.7 | C19: 1489124.1 | D19: 1766404.2 | E19: 272338.8 | F19: 285493.39 | G19: 1. Государственные услуги общего характера
... A32: 14. Борышқа қызмет көрсету | B32: 1357551.8 | C32: 1865649 | D32: 2232329.2 | E32: 440388.08 | F32: 532224.77 | G32: 14. Обслуживание долга
A33: 15. Трансферттер | B33: 140421.01 | C33: - | D33: - | E33: - | F33: - | G33: 15. Трансферты
A34: III. ТАЗА БЮДЖЕТТІК КРЕДИТ БЕРУ | B34: 592680.34 | C34: 466441.74 | D34: 198408.55 | E34: 41509.119 | F34: 12537.673 | G34: III. ЧИСТОЕ БЮДЖЕТНОЕ КРЕДИТОВАНИЕ#
A35: Бюджеттік кредиттер | B35: 742434.13 | C35: 712385.4 | D35: 519749.13 | E35: 51209.17 | F35: 25137.485 | G35: Бюджетные кредиты
A36: Бюджеттік кредиттерді өтеу | B36: 149753.78 | C36: 245943.66 | D36: 321340.58 | E36: 9700.0511 | F36: 12599.811 | G36: Погашение бюджетных кредитов
A37: IV. ҚАРЖЫ АКТИВТЕРІМЕН ОПЕРАЦИЯЛАР БОЙЫНША САЛЬДО - ҚАРЖЫ АК | B37: 292001.58 | C37: 501904.7 | D37: 201561.81 | E37: 21104.663 | F37: 68054.292 | G37: IV. САЛЬДО ПО ОПЕРАЦИЯМ С ФИНАНСОВЫМИ АКТИВАМИ#
A38: Қаржылық активтерді сатып алу | B38: 293189.28 | C38: 503365.1 | D38: 202951.32 | E38: 21281.568 | F38: 68246.713 | G38: Приобретение финансовых активов
A39: Мемлекеттің қаржы активтерін сатудан түсетін түсімдер | B39: 1187.6999 | C39: 1460.4064 | D39: 1389.5083 | E39: 176.90512 | F39: 192.42119 | G39: Поступления от продажи финансовых активов государства
A40: V. БЮДЖЕТ ТАПШЫЛЫҒЫ (ПРОФИЦИТІ) | B40: -2169124.7 | C40: -2811100.6 | D40: -3586041.9 | E40: 15542.766 | F40: 560485.87 | G40: V. ДЕФИЦИТ (ПРОФИЦИТ) БЮДЖЕТА#
A41: VI. БЮДЖЕТТІҢ МҰНАЙҒА ҚАТЫСТЫ ЕМЕС ТАПШЫЛЫҒЫ (ПРОФИЦИТІ) | B41: -8370502.3 | C41: -8454245.5 | D41: -10784416 | E41: -1090893.9 | F41: -558145.66 | G41: VI. НЕНЕФТЯНОЙ ДЕФИЦИТ (ПРОФИЦИТ) БЮДЖЕТА#
A42: VII. БЮДЖЕТТІҢ ТАПШЫЛЫҒЫН ҚАРЖЫЛАНДЫРУ (ПРОФИЦИТТІ ПАЙДАЛАНУ | B42: 2169124.7 | C42: 2811100.6 | D42: 3586041.9 | E42: -15542.766 | F42: -560485.87 | G42: VII. ФИНАНСИРОВАНИЕ ДЕФИЦИТА (ИСПОЛЬЗОВАНИЕ ПРОФИЦИТА) БЮДЖЕТА
A43: Ішкі | B43: 2312930.2 | C43: 3221830.7 | D43: 3293971.1 | E43: 67576.348 | F43: -519102.66 | G43: Внутреннее
A44: Түсімдер | B44: 3925848 | C44: 5179541.7 | D44: 5785457.6 | E44: 737219.58 | F44: 221927.57 | G44: Поступление
A45: Өтеу | B45: 1612917.7 | C45: 1957711 | D45: 2491486.6 | E45: 669643.23 | F45: 741030.23 | G45: Погашение
... A48: Өтеу | B48: 209770.89 | C48: 662602.27 | D48: 1155152.7 | E48: 94548.874 | F48: 106694.99 | G48: Погашение

Sheet табл 4
A1: 4-кесте | G1: Таблица 4
A3: МЕМЛЕКЕТТІК БЮДЖЕТКЕ ТҮСІМДЕР/_x000D_ ПОСТУПЛЕНИЯ В ГОСУДАРСТВЕННЫЙ БЮДЖЕТ
A5: (млн.теңге) | G5: (млн.тенге)
A7: Санаты/ Категория | B7: Сыныбы/ Класс | C7: Сыныпшасы/ Подкласс | D7: Ерешелігі/ Специфика | E7: Атауы | F7: 2025 ж. қаңтар-ақпан есеп/_x000D_ январь-февраль отчет 2025 г. | G7: Наименование
A8: 1 | B8: 2 | C8: 3 | D8: 4 | E8: 5 | F8: 6 | G8: 7
E9: ТҮСІМДЕР | F9: 5034104.9 | G9: ПОСТУПЛЕНИЯ
E10: оның ішінде: | G10: в том числе:
E11: КІРІСТЕР | F11: 5021312.6 | G11: ДОХОДЫ
A12: 1 | B12: L01 Класс дохода | C12: L01 Подкласс дохода | D12: L01 Специфика дохода | E12: Салықтық түсімдер | F12: 3726749.7 | G12: Налоговые поступления
A13: L01 Категория дохода | B13: 01 | C13: L01 Подкласс дохода | D13: L01 Специфика дохода | E13: Табыс салығы | F13: 1429391.8 | G13: Подоходный налог
A14: L01 Категория дохода | B14: L01 Класс дохода | C14: 1 | D14: L01 Специфика дохода | E14: Корпорациялық табыс салығы | F14: 928750.33 | G14: Корпоративный подоходный налог
A15: 1 | B15: 01 | C15: 1 | D15: 10 | E15: Мұнай секторы ұйымдарынан түсетін түсімдерді қоспағанда, ірі кәсіпкерлік субъектілерінен – заңды тұлғалардан алынатын корпоративтік табыс салығы | F15: 696571.35 | G15: Корпоративный подоходный налог с юридических лиц – субъектов крупного предпринимательства, за исключением поступлений от организаций нефтяного сектора
D16: 11 | E16: Ірі кәсіпкерлік субъектілерінен және мұнай секторы ұйымдарынан түсетін түсімдерді қоспағанда, заңды тұлғалардан алынатын корпоративтік табыс салығы | F16: 232178.98 | G16: Корпоративный подоходный налог с юридических лиц, за исключением поступлений от субъектов крупного предпринимательства и организаций нефтяного сектора
A17: L01 Категория дохода | B17: L01 Класс дохода | C17: 2 | D17: L01 Специфика дохода | E17: Жеке табыс салығы | F17: 500641.49 | G17: Индивидуальный подоходный налог
C18: 2 | D18: 01 | E18: Төлем көзінен салық салынатын табыстардан ұсталатын жеке табыс салығы | F18: 344188.03 | G18: Индивидуальный подоходный налог с доходов, облагаемых у источника выплаты
D19: 02 | E19: Төлем көзінен салық салынбайтын табыстардан ұсталатын жеке табыс салығы | F19: 154249.29 | G19: Индивидуальный подоходный налог с доходов, не облагаемых у источника выплаты
D20: 05 | E20: Төлем көзінен салық салынбайтын шетелдік азаматтар табыстарынан ұсталатын жеке табыс салығы | F20: 2204.1678 | G20: Индивидуальный подоходный налог с доходов иностранных граждан, не облагаемых у источника выплаты
A21: L01 Категория дохода | B21: 03 | C21: L01 Подкласс дохода | D21: L01 Специфика дохода | E21: Әлеуметтiк салық | F21: 341000.69 | G21: Социальный налог
A22: L01 Категория дохода | B22: L01 Класс дохода | C22: 1 | D22: L01 Специфика дохода | E22: Әлеуметтік салық | F22: 341000.69 | G22: Социальный налог
B23: 03 | C23: 1 | D23: 01 | E23: Әлеуметтік салық | F23: 341000.69 | G23: Социальный налог
A24: L01 Категория дохода | B24: 04 | C24: L01 Подкласс дохода | D24: L01 Специфика дохода | E24: Меншiкке салынатын салықтар | F24: 160435.5 | G24: Hалоги на собственность
A25: L01 Категория дохода | B25: L01 Класс дохода | C25: 1 | D25: L01 Специфика дохода | E25: Мүлiкке салынатын салықтар | F25: 152083.55 | G25: Hалоги на имущество
B26: 04 | C26: 1 | D26: 01 | E26: Заңды тұлғалардың және жеке кәсіпкерлердің мүлкіне салынатын салық | F26: 151464.05 | G26: Налог на имущество юридических лиц и индивидуальных предпринимателей
D27: 02 | E27: Жеке тұлғалардың мүлкiне салынатын салық | F27: 619.49564 | G27: Hалог на имущество физических лиц
A28: L01 Категория дохода | B28: L01 Класс дохода | C28: 3 | D28: L01 Специфика дохода | E28: Жер салығы | F28: 3867.9594 | G28: Земельный налог
C29: 3 | D29: 02 | E29: Жер салығы | F29: 3867.9594 | G29: Земельный налог
A30: L01 Категория дохода | B30: L01 Класс дохода | C30: 4 | D30: L01 Специфика дохода | E30: Көлiк құралдарына салынатын салық | F30: 3713.7595 | G30: Hалог на транспортные средства
C31: 4 | D31: 01 | E31: Заңды тұлғалардан көлiк құралдарына салынатын салық | F31: 385.22226 | G31: Hалог на транспортные средства с юридических лиц
D32: 02 | E32: Жеке тұлғалардан көлiк құралдарына салынатын салық | F32: 3328.5372 | G32: Hалог на транспортные средства с физических лиц
A33: L01 Категория дохода | B33: L01 Класс дохода | C33: 5 | D33: L01 Специфика дохода | E33: Бірыңғай жер салығы | F33: 770.23487 | G33: Единый земельный налог
C34: 5 | D34: 01 | E34: Бірыңғай жер салығы | F34: 770.23487 | G34: Единый земельный налог
A35: L01 Категория дохода | B35: 05 | C35: L01 Подкласс дохода | D35: L01 Специфика дохода | E35: Тауарларға, жұмыстарға және қызметтерге салынатын iшкi салықтар | F35: 1550880.5 | G35: Внутренние налоги на товары, работы и услуги
A36: L01 Категория дохода | B36: L01 Класс дохода | C36: 1 | D36: L01 Специфика дохода | E36: Қосылған құн салығы | F36: 1105855.5 | G36: Налог на добавленную стоимость
B37: 05 | C37: 1 | D37: 01 | E37: Қазақстан Республикасының аумағында өндiрiлген тауарларға, орындалған жұмыстарға және көрсетілген қызметтерге салынатын қосылған құн салығы | F37: 588316.43 | G37: Hалог на добавленную стоимость на произведенные товары, выполненные работы и оказанные услуги на территории Республики Казахстан
D38: 02 | E38: Ресей Федерациясы және Беларусь Республикасының аумағынан импортталатын тауарларға салынатын қосылған құн салығынан басқа, Қазақстан Республикасының аумағына импортталатын тауарларға салынатын қосылған құн салығы | F38: 269675.7 | G38: Hалог на добавленную стоимость на товары, импортируемые на территорию Республики Казахстан, кроме налога на добавленнуюстоимость на товары, импортируемые с территории Российской Федерации и Республики Беларусь
D39: 04 | E39: Резидент емес үшін қосылған құн салығы | F39: 52040.043 | G39: Налог на добавленную стоимость за нерезидента
D40: 14 | E40: Салық төлеушінің бұрын бюджеттен қайтарылған және салықтық тексеру жүргізу барысында қайтарылуы расталмаған қосылған құн салығының асып кеткен сомасын аударуы (қайтаруы), өсімпұл сомасын аударуы | F40: 533.09975 | G40: Перечисление (возврат) налогоплательщиком суммы превышения налога на добавленную стоимость, ранее возвращенной из бюджета и не подтвержденной к возврату при проведении налоговой проверки, перечисление суммы пени
D41: 15 | E41: ЕАЭО мүше мемлекеттер аумағынан импортталған тауарларға қосылған құн салығы | F41: 181953.04 | G41: Налог на добавленную стоимость на товары, импортированные с территории государств-членов ЕАЭС
D42: 16 | E42: Тауарлармен электрондық сауданы жүзеге асыру, жеке тұлғаларға электрондық нысанда қызметтер көрсету кезінде шетелдік компаниялардан түсетін қосылған құн салығы | F42: 13337.202 | G42: Налог на добавленную стоимость с иностранных интернет компаний при осуществлении электронной торговли товарами, оказании услуг в электронной форме физическим лицам
A43: L01 Категория дохода | B43: L01 Класс дохода | C43: 2 | D43: L01 Специфика дохода | E43: Акциздер | F43: 138324.24 | G43: Акцизы
C44: 2 | D44: 74 | E44: Қазақстан Республикасының аумағында өндірілген спирттiң және (немесе) шарап материалының, алкоголь өнімдерінің барлық түрлерi | F44: 17279.517 | G44: Все виды спирта и (или) виноматериала, алкогольной продукции, произведенных на территории Республики Казахстан
D45: 75 | E45: Қазақстан Республикасының аумағында өндірілген темекі өнімдері, жеңiл автомобильдер (арнайы мүгедектігі бар адамдарға арналған, қолмен басқарылатын немесе қолмен басқару бейімдегіші бар автомобильдерден басқа) | F45: 33323.158 | G45: Табачные изделия, легковые автомобили (кроме автомобилей с ручным управлением или адаптером ручного управления, специально предназначенных для лиц с инвалидностью), произведенные на территории Республики Казахстан
D46: 76 | E46: Қазақстан Республикасының аумағына Кеден одағына мүше мемлекеттердің аумағынан әкелінетін темекі өнімдері | F46: 4106.5058 | G46: Табачные изделия, ввозимые на территорию Республики Казахстан с территории государств-членов Таможенного союза
D47: 77 | E47: Қазақстан Республикасының аумағына Кеден одағына мүше мемлекеттердің аумағынан әкелінетін спирттiң және (немесе) шарап материалының, алкоголь өнімдерінің барлық түрлерi | F47: 2782.2992 | G47: Все виды спирта и (или) виноматериала, алкогольной продукции, ввозимых на территорию Республики Казахстан с территории государств-членов Таможенного союза
D48: 78 | E48: Қазақстан Республикасының аумағына Кеден одағына мүше мемлекеттердің аумағынан әкелінетін акцизделетін өнімнің өзге түрлері | F48: 4.3997715 | G48: Прочие виды подакцизных продукций, ввозимых на территорию Республики Казахстан с территории государств-членов Таможенного союза
D49: 79 | E49: Қазақстан Республикасы аумағына Кеден одағына мүше мемлекеттердің аумағынан әкелінетін бензин (авиациялықты қоспағанда) және дизель отыны | F49: 1008.8749 | G49: Бензин (за исключением авиационного) и дизельное топливо, ввозимых на территорию Республики Казахстан с территории государств-членов Таможенного союза
D50: 80 | E50: Кеден одағына мүше болып табылмайтын мемлекеттердің аумағынан әкелінетін, Қазақстан Республикасының аумағына импортталатын спирттің және (немесе) шарап материалының, алкоголь өнімдерінің барлық түрлері | F50: 2379.0343 | G50: Все виды спирта и (или) виноматериала, алкогольной продукции, импортируемых на территорию Республики Казахстан с территории государств, не являющихся членами Таможенного союза
D51: 81 | E51: Кеден одағына мүше болып табылмайтын мемлекеттердің аумағынан әкелінетін, Қазақстан Республикасының аумағына импортталатын темекі өнімдері | F51: 7298.2036 | G51: Табачные изделия, импортируемые на территорию Республики Казахстан с территории государств, не являющихся членами Таможенного союза
D52: 82 | E52: Кеден одағына мүше болып табылмайтын мемлекеттердің аумағынан әкелінетін, Қазақстан Республикасының аумағына импортталатын акцизделетін өнімдердің өзге түрлері | F52: 604.0667 | G52: Прочие виды подакцизных продукций, импортируемые на территорию Республики Казахстан с территории государств, не являющихся членами Таможенного союза
D53: 83 | E53: Кеден одағына мүше болып табылмайтын мемлекеттер аумағынан әкелінетін, Қазақстан Республикасының аумағына импортталатын бензин (авиациялықты қоспағанда) және дизель отыны | F53: 15.622548 | G53: Бензин (за исключением авиационного) и дизельное топливо, импортируемых на территорию Республики Казахстан с территории государств, не являющихся членами Таможенного союза
D54: 84 | E54: Қазақстан Республикасының аумағында өндірілген бензин (авиациялықты қоспағанда) және дизель отыны | F54: 69522.555 | G54: Бензин (за исключением авиационного) и дизельное топливо, произведенных на территории Республики Казахстан
A55: L01 Категория дохода | B55: L01 Класс дохода | C55: 3 | D55: L01 Специфика дохода | E55: Табиғи және басқа да ресурстарды пайдаланғаны үшiн түсетiн түсiмдер | F55: 289153.15 | G55: Поступления за использование природных и других ресурсов
C56: 3 | D56: 01 | E56: Қалааралық және (немесе) халықаралық телефон байланысын көрсеткені үшін төлем,тағыда ұялы байланыс | F56: 2.3104093 | G56: Плата за предоставление междугородной и (или) международнойтелефонной связи, а также сотовой связи
D57: 03 | E57: Жер бетіне жақын көздердегі су ресурстарын пайдаланғаны үшін төлем | F57: 373.03724 | G57: Плата за пользование водными ресурсами поверхностных источников
D58: 04 | E58: Орманды пайдаланғаны үшiн төлем | F58: 291.25835 | G58: Плата за лесные пользования
D59: 05 | E59: Бонустар, мұнай секторы ұйымдарынан түсетін түсімдерден басқа | F59: 10154.905 | G59: Бонусы, за исключением поступлений от организаций нефтяногосектора
D60: 06 | E60: Пайдалы қазбаларды өндіруге салынатын салық, мұнай секторы ұйымдарынан түсетін түсімдерден басқа | F60: 237002.82 | G60: Налог на добычу полезных ископаемых, за исключением поступлений от организаций нефтяного сектора
D61: 07 | E61: Мұнай секторы ұйымдарынан түсетін түсімдерді қоспағанда, экспортқа салынатын рента салығы | F61: 827.62482 | G61: Рентный налог на экспорт, за исключением поступлений от организаций нефтяного сектора
D62: 09 | E62: Радиожиілік спектрін пайдаланғаны үшін төлем | F62: 224.07792 | G62: Плата за использование радиочастотного спектра
D63: 11 | E63: Жануарлар дүниесін пайдаланғаны үшін төлем | F63: 146.3301 | G63: Плата за пользование животным миром
D64: 13 | E64: Республикалық маңызы бар ерекше қорғалатын табиғи аумақтарды пайдаланғаны үшін төлем | F64: -4.2021501 | G64: Плата за использование особо охраняемых природных территорий республиканского значения
D65: 14 | E65: Жергілікті маңызы бар ерекше қорғалатын табиғи аумақтарды пайдаланғаны үшін төлем | F65: 0.66770017 | G65: Плата за использование особо охраняемых природных территорий местного значения
D66: 15 | E66: Жер учаскелерін пайдаланғаны үшін төлем | F66: 8520.1625 | G66: Плата за пользование земельными участками
D67: 16 | E67: Қоршаған ортаға жағымсыз әсер еткені үшін төлемақы | F67: 29054.948 | G67: Плата за негативное воздействие на окружающую среду
D68: 17 | E68: Цифрлық майнинг үшін төлемақы | F68: 1072.4956 | G68: Плата за цифровой майнинг
D69: 19 | E69: Тарихи шығындарды өтеу бойынша төлемдер | F69: 1486.7155 | G69: Платеж по возмещению исторических затрат
A70: L01 Категория дохода | B70: L01 Класс дохода | C70: 4 | D70: L01 Специфика дохода | E70: Кәсiпкерлiк және кәсiби қызметтi жүргiзгенi үшiн алынатын алымдар | F70: 13507.132 | G70: Сборы за ведение предпринимательской и профессиональной деятельности
C71: 4 | D71: 02 | E71: Жекелеген қызмет түрлерімен айналысу құқығы үшін алым (жекелеген қызмет түрлерімен айналысуға арналған лицензияларды бергені үшін алым) | F71: 1059.6603 | G71: Сбор за право занятия отдельными видами деятельности (сбор за выдачу лицензий на занятие отдельными видами деятельности)
D72: 06 | E72: Автокөлік құралдарының Қазақстан Республикасының аумағы арқылы өткені үшін алынатын алым | F72: 2561.7629 | G72: Сбор за проезд автотранспортных средств по территории Республики Казахстан
D73: 13 | E73: Телевизиялық және радио хабарын тарататын ұйымдарға радиожиілік өрісін пайдалануға рұқсат бергені үшін алынатын алым | F73: 0 | G73: Сбор за выдачу разрешения на использование радиочастотного спектра телевизионным и радиовещательным организациям
D74: 19 | E74: Сыртқы (көрнекі) жарнаманы аудандық маңызы бар қалалар, ауылдар, кенттер, ауылдық округтер аумақтары арқылы өтетін республикалық маңызы бар жалпыға ортақ пайдаланылатын автомобиль жолдарының бөлiнген белдеуiндегі жарнаманы тұрақты орналастыру объектілерінде орналастырғаны үшін төлемақыны қоспағанда, сыртқы (көрнекi) жарнаманы республикалық маңызы бар жалпыға ортақ пайдаланылатын автомобиль жолдарының бөлiнген белдеу | F74: 2.682697 | G74: Плата за размещение наружной (визуальной) рекламы на объектах стационарного размещения рекламы в полосе отвода автомобильных дорог общего пользования республиканского значения, заисключением платы за размещение наружной (визуальной) рекламы на объектах стационарного размещения рекламы в полосе отвода автомобильных дорог общего пользования республиканского значения, проходящих через территории городов районного значе
D75: 20 | E75: Сыртқы (көрнекі) жарнаманы аудандық маңызы бар қалалар, ауылдар, кенттер, ауылдық округтер аумақтары арқылы өтетін облыстық маңызы бар жалпыға ортақ пайдаланылатын автомобиль жолдарының бөлiнген белдеуiндегі жарнаманы тұрақты орналастыру объектілерінде орналастырғаны үшін төлемақыны қоспағанда, сыртқы (көрнекi) жарнаманы облыстық маңызы бар жалпыға ортақ пайдаланылатын автомобиль жолдарының бөлiнген белдеуiндегі жарн | F75: 0.226485 | G75: Плата за размещение наружной (визуальной) рекламы на объектах стационарного размещения рекламы в полосе отвода автомобильных дорог общего пользования областного значения, за исключением платы за размещение наружной (визуальной) рекламы на объектах стационарного размещения рекламы в полосе отвода автомобильных дорог общего пользования областного значения, проходящих через территории городов районного значения, сел, по
D76: 24 | E76: Сыртқы (көрнекі) жарнаманы республикалық маңызы бар қаладағы, астанадағы үй-жайлардың шегінен тыс ашық кеңістікте орналастырғаны үшін төлемақы | F76: 1568.0014 | G76: Плата за размещение наружной (визуальной) рекламы на открытом пространстве за пределами помещений в городе республиканского значения, столице
D77: 25 | E77: Сыртқы (көрнекі) жарнаманы – аудандық маңызы бар жалпыға ортақ пайдаланылатын автомобиль жолдарының бөлінген белдеуіндегі жарнаманы тұрақты орналастыру объектілерінде, аудандық маңызы бар қаладағы, ауылдағы, кенттегі үй-жайлардың шегінен тыс ашық кеңістікте орналастырғаны үшін төлемақыны қоспағанда, сыртқы (көрнекі) жарнаманы облыстық маңызы бар қаладағы үй-жайлардың шегінен тыс ашық кеңістікте орналастырғаны үшін тө | F77: 355.41842 | G77: Плата за размещение наружной (визуальной) рекламы на открытом пространстве за пределами помещений в городе областного значения, за исключением платы за размещение наружной (визуальной) рекламы на объектах стационарного размещения рекламы вполосе отвода автомобильных дорог общего пользования районного значения, на открытом пространстве за пределами помещений в городе районного значения, селе, поселке
D78: 28 | E78: Республикалық бюджетке төленетін тіркелгені үшін алым | F78: 19.340296 | G78: Регистрационный сбор, зачисляемый в республиканский бюджет
D79: 29 | E79: Жергілікті бюджетке төленетін тіркелгені үшін алым | F79: 5940.9262 | G79: Регистрационный сбор, зачисляемый в местный бюджет
D80: 30 | E80: Сыртқы (көрнекі) жарнаманы аудандық маңызы бар қалалар, ауылдар, кенттер, ауылдық округтер аумақтары арқылы өтетін республикалық, облыстық және аудандық маңызы бар жалпыға ортақ пайдаланылатын автомобиль жолдарының бөлiнген белдеуiндегі жарнаманы тұрақты орналастыру объектілерінде және аудандық маңызы бар қаладағы, ауылдағы, кенттегі үй-жайлардың шегінен тыс ашық кеңістікте орналастырғаны үшін төлемақы | F80: 54.813186 | G80: Плата за размещение наружной (визуальной) рекламы на объектах стационарного размещения рекламы в полосе отвода автомобильных дорог общего пользования республиканского, областногои районного значения, проходящих через территории городов районного значения, сел, поселков, сельских округов и на открытом пространстве за пределами помещений в городе районного значения, селе, поселке
D81: 31 | E81: Микроқаржы ұйымдарын есептік тіркеуден өткізгені және оларды микроқаржы ұйымдарының тізіліміне енгізгені үшін алым | F81: 0 | G81: Сбор за прохождение учетной регистрации микрофинансовых организаций и включение их в реестр микрофинансовых организаций
D82: 32 | E82: Банк және сақтандыру нарықтарына қатысушылар үшін рұқсат беру құжаттарын, келісім бергені үшін алым | F82: 2.7081 | G82: Сбор за выдачу разрешительных документов, согласия для участников банковского и страхового рынков
D83: 33 | E83: Қазақстан Республикасына шетелдік жұмыс күшін тартуға рұқсатты бергені немесе ұзартқаны үшін алым | F83: 938.69448 | G83: Сбор за выдачу или продление разрешения на привлечение иностранной рабочей силы в Республику Казахстан
... D85: 35 | E85: Азаматтық авиация саласындағы уәкілетті ұйым Қазақстан Республикасының әуе кеңістігін пайдалануды және авиация қызметінреттейтін Қазақстан Республикасының заңнамасында белгіленген сертификаттау талаптарына сәйкестігіне беретін сертификаттарды бергені үшін алым | F85: 0 | G85: Сбор за выдачу сертификатов, выдаваемых уполномоченной организацией в сфере гражданской авиации, на соответствие сертификационным требованиям, установленным законодательством Республики Казахстан и деятельность авиации
A86: L01 Категория дохода | B86: L01 Класс дохода | C86: 5 | D86: L01 Специфика дохода | E86: Ойын бизнесіне салық | F86: 4040.4854 | G86: Налог на игорный бизнес
C87: 5 | D87: 01 | E87: Ойын бизнесіне салық | F87: 4040.4854 | G87: Налог на игорный бизнес
A88: L01 Категория дохода | B88: 06 | C88: L01 Подкласс дохода | D88: L01 Специфика дохода | E88: Халықаралық сауда мен сыртқы операцияларға салынатын салықтар | F88: 222660.82 | G88: Hалоги на международную торговлю и внешние операции
A89: L01 Категория дохода | B89: L01 Класс дохода | C89: 1 | D89: L01 Специфика дохода | E89: Кеден төлемдерi | F89: 211524.5 | G89: Таможенные платежи
B90: 06 | C90: 1 | D90: 01 | E90: Еуразиялық экономикалық одақ туралы шартқа сәйкес төленген әкелінетін кедендік баждары (баламалы қолданылатын өзге де баждар, салықтар мен алымдар) | F90: 7867.8474 | G90: Ввозные таможенные пошлины (иные пошлины, налоги и сборы, имеющие эквивалентное действие), уплаченные в соответствии с Договором о Евразийском экономическом союзе
D91: 02 | E91: Әкетілетін тауарларға салынатын кедендік баждар | F91: 2230.2912 | G91: Таможенные пошлины на вывозимые товары
D92: 04 | E92: Кеден бажының бірыңғай ставкасын қолданумен жеке тұлғалардан өндіріп алынатын жеке пайдалануына әкелінетін тауарларға салынатын кеден баждары, салықтары | F92: 527.81597 | G92: Таможенные пошлины, налоги на ввозимые физическими лицами товары для личного пользования с применением единых ставок таможенных пошлин, налогов
D93: 05 | E93: Әкелінетін тауарларға жиынтық кедендік төлем | F93: 67.89594 | G93: Совокупный таможенный платеж на ввозимые товары
D94: 06 | E94: Ресей Федерациясымен бөлінген кедендік баж | F94: 68822.448 | G94: Таможенные пошлины, распределенные Российской Федерацией
D95: 07 | E95: Беларусь Республикасымен бөлінген кедендік баж | F95: 3853.8271 | G95: Таможенные пошлины, распределенные Республикой Беларусь
D96: 10 | E96: Мұнайға салынатын кедендік әкету бажы | F96: 118631.53 | G96: Вывозные таможенные пошлины на сырую нефть
D97: 11 | E97: Мұнайдан өндірілген тауарларға салынатын кедендік әкету бажы | F97: 4355.6109 | G97: Вывозные таможенные пошлины на товары, выработанные из нефти
D98: 12 | E98: Кеден одағында кедендік әкелу баждарын (баламалы қолданысы бар өзге де баждарды, салықтар мен алымдарды) есепке жатқызужәне бөлу тәртібін белгілеу және қолдану туралы келісім күшіне енгенге дейін төлеу жөніндегі міндеті туындаған әкелінетін тауарларға және (немесе) әкелінетін кедендік баждарға арналған кедендік баждар, сондай-ақ жер қойнауын пайдалану саласындағы келісімшарттар шеңберінде, оның ішінде Қазақстан Респ | F98: 644.30294 | G98: Таможенные пошлины на ввозимые товары и (или) ввозные таможенные пошлины, обязанность по уплате которых возникла до вступления в силу Соглашения об установлении и применении в таможенном союзе порядка зачисления и распределения ввозных таможенных пошлин (иных пошлин, налогов и сборов, имеющих эквивалентное действие), а также таможенные пошлины на товары ввозимые в рамках контрактов в сфере недропользования, в том чис
D99: 13 | E99: Армения Республикасымен бөлінген кедендік баждар | F99: 1573.9119 | G99: Таможенные пошлины, распределенные Республикой Армения
D100: 17 | E100: Қырғыз Республикасы бөлген кедендік баждар | F100: 2407.4773 | G100: Таможенные пошлины, распределенные Кыргызской Республикой
D101: 19 | E101: Алдағы кедендік баждарды, кедендік алымдарды, салықтарды, арнайы, демпингке қарсы, өтемақы баждарын төлеу есебіне, сондай-ақ кедендік баждарды, салықтарды арнайы, демпингке қарсы,өтемақы баждарын төлеу жөніндегі міндеттің орындалуын қамтамасыз ету ретінде Еуразиялық экономикалық одақтың және Қазақстан Республикасының кеден заңнамасына сәйкес енгізілетін аванстық төлемдер | F101: 541.53757 | G101: Авансовые платежи, вносимые в соответствии с таможенным законодательством Евразийского экономического союза и Республики Казахстан, в счет уплаты предстоящих таможенных платежей, налогов, специальных, антидемпинговых, компенсационных пошлин, а также в качестве обеспечения исполнения обязанности по уплате таможенных пошлин, налогов, специальных, антидемпинговых, компенсационных пошлин
A102: L01 Категория дохода | B102: L01 Класс дохода | C102: 2 | D102: L01 Специфика дохода | E102: Халықаралық сауда мен операцияларға салынатын басқа да салықтар | F102: 11136.32 | G102: Прочие налоги на международную торговлю и операции
C103: 2 | D103: 01 | E103: Қазақстан Республикасының кеден заңнамасына сәйкес төленетін кедендік алымдар | F103: 9107.3809 | G103: Таможенные сборы, уплачиваемые в соответствии с таможенным законодательством Республики Казахстан
D104: 02 | E104: Еуразиялық экономикалық одақ туралы шартқа сәйкес төленген арнайы, демпингке қарсы, өтемақы баждары | F104: 163.23803 | G104: Специальные, антидемпинговые, компенсационные пошлины, уплаченные в соответствии с Договором о Евразийском экономическом союзе
...

Sheet табл 5
B2: Кесте 5 | D2: Таблица 5
B3: ШЫҒЫСТАРДЫҢ ВЕДОМСТВОЛЫҚ | D3: ИСПОЛНЕНИЕ ГОСУДАРСТВЕННОГО БЮДЖЕТА
B4: СЫНЫПТАМАСЫ БОЙЫНША | D4: ПО ВЕДОМСТВЕННОЙ
B5: МЕМЛЕКЕТТІК БЮДЖЕТТІҢ АТҚАРАЛУЫ | D5: КЛАССИФИКАЦИИ РАСХОДОВ
B6: (млн. теңге) | D6: (млн. тенге)
B8: Бағдарламалард_x000D_ ың_x000D_ əкімшісі/_x000D_ Администратор_x000D_ программ | C8: Атауы | D8: 2025 ж. қаңтар-ақпан есеп/_x000D_ январь-февраль 2025 г. | E8: Наименование
B9: 1 | C9: 2 | D9: 3 | E9: 4
C10: БАРЛЫҒЫ | D10: 4473619 | E10: ВСЕГО
B11: 101 | C11: Қазақстан Республикасы Президентінің Әкімшілігі | D11: 2447.5945 | E11: Администрация Президента Республики Казахстан
B12: 106 | C12: Адам құқықтары жөніндегі ұлттық орталық | D12: 292.40694 | E12: Национальный центр по правам человека
B13: 107 | C13: Қазақстан Республикасы Жоғары Сот Кеңесінің Аппараты | D13: 298.27046 | E13: Аппарат Высшего Судебного Совета Республики Казахстан
B14: 109 | C14: Қазақстан Республикасы үкіметінің Аппараты_x000D_ | D14: 1113.2111 | E14: Аппарат Правительства Республики Казахстан
B15: 110 | C15: Облыс мәслихатының аппараты | D15: 450.50985 | E15: Аппарат маслихата области
B16: 111 | C16: Республикалық маңызы бар қала, астана мәслихатының аппараты | D16: 90.997243 | E16: Аппарат маслихата города республиканского значения, столицы
B17: 112 | C17: Аудан (облыстық маңызы бар қала) мәслихатының аппараты | D17: 2351.5673 | E17: Аппарат маслихата района (города областного значения)
B18: 120 | C18: Облыс әкімінің аппараты | D18: 6390.5994 | E18: Аппарат акима области
B19: 121 | C19: Республикалық маңызы бар қала, астана әкімінің аппараты | D19: 1278.3601 | E19: Аппарат акима города республиканского значения, столицы
B20: 122 | C20: Аудан (облыстық маңызы бар қала) әкімінің аппараты | D20: 14810.773 | E20: Аппарат акима района (города областного значения)
B21: 123 | C21: Қаладағы аудан, аудандық маңызы бар қала, кент, ауыл, ауылдық округ әкімінің аппараты | D21: 49040.969 | E21: Аппарат акима района в городе, города районного значения, поселка, села, сельского округа
B22: 124 | C22: Аудандық маңызы бар қала, ауыл, кент, ауылдық округ әкімінің аппараты | D22: 35672.104 | E22: Аппарат акима города районного значения, села, поселка, сельского округа
... B222: 821 | C222: Ауданның (облыстық маңызы бар қаланың) қоғамдық даму бөлімі | D222: 153.83387 | E222: Отдел общественного развития района (города областного значения)

Sheet табл 6
A1: 6-кесте | D1: Таблица 6
A2: ШЫҒЫНДАРДЫҢ ЭКОНОМИКАЛЫҚ ЖІКТЕМЕСІ | D2: ИСПОЛНЕНИЕ ГОСУДАРСТВЕННОГО БЮДЖЕТА ПО
A3: БОЙЫНША МЕМЛЕКЕТТІК БЮДЖЕТТІК ОРЫНДАЛУЫ | D3: ЭКОНОМИЧЕСКОЙ КЛАССИФИКАЦИИ РАСХОДОВ
A4: (млн.теңге) | D4: (млн.тенге)
A5: Cанаты/_x000D_ Категория | B5: Iшкi сыныбы/_x000D_ Подкласс | C5: Атауы | D5: 2025 ж. қаңтар-ақпан/январь-февраль отчет 2025 г. | E5: Наименование
A7: 1 | B7: 2 | C7: 3 | D7: 4 | E7: 5
C8: БАРЛЫҒЫ | D8: 4473619 | E8: ВСЕГО
A9: 1 | C9: Ағымдағы шығындар | D9: 4092577.8 | E9: Текущие затраты
A10: 1 | B10: 110 | C10: Жалақы | D10: 691990.29 | E10: Заработная плата
B11: 120 | C11: Жұмыс берушілердің жарналары | D11: 68687.421 | E11: Взносы работодателей
B12: 130 | C12: Қазақстан Республикасының заңнамалық актілеріне сәйкес азаматтардың жекелеген санаттарына жалақы төлеу және жарналар аудару | D12: 25289.276 | E12: Выплата заработной платы отдельным категориям граждан и отчисления взносов в соответствии с законодательными актами Республики Казахстан
B13: 140 | C13: Қорлар сатып алу | D13: 44785.107 | E13: Приобретение запасов
B14: 150 | C14: Қызметтер мен жұмыстарды сатып алу | D14: 621259.64 | E14: Приобретение услуг и работ
B15: 160 | C15: Басқа да ағымдағы шығындар | D15: 361199.94 | E15: Другие текущие затраты
B16: 210 | C16: Ішкі қарыздар бойынша сыйақы төлемдері | D16: 455632.53 | E16: Выплаты вознаграждений по внутренним займам
B17: 220 | C17: Сыртқы заемдар бойынша сыйақылар төлеу | D17: 76592.236 | E17: Выплаты вознаграждений по внешним займам
B18: 310 | C18: Бюджеттік субсидиялар | D18: 292235.77 | E18: Бюджетные субсидии
B19: 320 | C19: Жеке тұлғаларға берілетін трансферттер | D19: 1115853 | E19: Трансферты физическим лицам
B20: 340 | C20: Шетелге берiлетiн ағымдағы трансферттер | D20: 52.531823 | E20: Текущие трансферты за границу
B21: 360 | C21: Нысаналы жарна | D21: 339000 | E21: Целевой взнос
A22: 2 | C22: Күрделі шығындар | D22: 253696.28 | E22: Капитальные затраты
A23: 2 | B23: 410 | C23: Негiзгi құралдарды, материалдық емес және биологиялық активтерді сатып алу | D23: 41324.858 | E23: Приобретение основных средств, нематериальных и биологических активов
B24: 420 | C24: Негізгі қаражатты күрделі жөндеу | D24: 25849.442 | E24: Капитальный ремонт основных средств
B25: 430 | C25: Дамуға бағытталған күрделі шығындар | D25: 186521.98 | E25: Капитальные затраты, направленные на развитие
A26: 3 | C26: Бюджеттік кредиттер | D26: 25137.485 | E26: Бюджетные кредиты
A27: 3 | B27: 510 | C27: Ішкі бюджеттік кредиттер | D27: 25137.485 | E27: Внутренние бюджетные кредиты
A28: 4 | C28: Қаржы активтерін сатып алу | D28: 68606.713 | E28: Приобретение финансовых активов
A29: 4 | B29: 610 | C29: Қаржы активтерін сатып алу | D29: 68529.968 | E29: Приобретение финансовых активов
B30: 620 | C30: Елден тысқары жерлерден қаржы активтерін сатып алу | D30: 76.74548 | E30: Приобретение финансовых активов за пределами страны
A31: 6 | C31: Мемлекеттік-жекешелік әріптестік жобалар бойынша мемлекеттік міндеттемелерді орындау | D31: 33600.763 | E31: Выполнение государственных обязательств по проектам государственно-частного партнерства
A32: 6 | B32: 810 | C32: Мемлекеттік концессиялық міндеттемелерді орындау | D32: 33600.763 | E32: Выполнение государственных концессионных обязательств

Sheet табл 7
A1: 7-кесте | E1: Таблица 7
A2: РЕСПУБЛИКАЛЫҚ БЮДЖЕТТІҢ АТҚАРЫЛУЫ | E2: ИСПОЛНЕНИЕ РЕСПУБЛИКАНСКОГО БЮДЖЕТА
A3: (млн.теңге) | E3: (млн. тенге)
A5: Атауы | B5: 2022 ж. есеп/ 2022 г. отчет | C5: 2023 ж. есеп/ 2023 г. отчет | D5: 2024 ж. есеп/ 2024 г. отчет | F5: 2025 ж. қантар-ақпан есеп/январь-феврал отчет 2025 г. | G5: Наименование
D6: жылдық/ годовой | E6: қантар-ақпан/январь-феврал
A7: 1 | B7: 2 | C7: 3 | D7: 4 | E7: 5 | F7: 6 | G7: 7
A8: I. КІРІСТЕР | B8: 15963398 | C8: 19037979 | D8: 19624012 | E8: 2988736.9 | F8: 3634592.6 | G8: I. ДОХОДЫ#
A9: Салықтық түсімдер_x000D_ оның iшiнде: | B9: 10026825 | C9: 12912428 | D9: 12307810 | E9: 1849616 | F9: 2301508.5 | G9: Налоговые поступления,_x000D_ в том числе:
A10: корпорациялық табыс салығы | B10: 2920802.8 | C10: 3889594.5 | D10: 3653190.8 | E10: 515300.42 | F10: 696571.35 | G10: корпоративный подоходный налог
A11: қосылған құн салығы | B11: 4226358.8 | C11: 5674110.6 | D11: 5179378.1 | E11: 907451.41 | F11: 1105855.5 | G11: налог на добавленную стоимость
A12: акциздер | B12: 153619.22 | C12: 161890.43 | D12: 125189.66 | E12: 20999.642 | F12: 18199.007 | G12: акцизы
A13: Салықтық емес түсімдер | B13: 438204.42 | C13: 1617610.1 | D13: 1201438.2 | E13: 47964.777 | F13: 182604.09 | G13: Неналоговые поступления
A14: Негізгі капиталды сатудан түсетін түсімдер | B14: 6954.9546 | C14: 735.69631 | D14: 6170.4309 | E14: 4668.2284 | F14: 558.11164 | G14: Поступления от продажи основного капитала
A15: Трансферттердің түсімдері | B15: 5491414.1 | C15: 4507205 | D15: 6108593.6 | E15: 1086487.9 | F15: 1149921.9 | G15: Поступления трансфертов
A16: II. ШЫҒЫНДАР | B16: 17791797 | C16: 21547819 | D16: 23106552 | E16: 3660449.2 | F16: 3638727.6 | G16: II. ЗАТРАТЫ#
A17: 1. Жалпы сипаттағы мемлекеттiк қызметтер | B17: 1047844 | C17: 1137687.2 | D17: 1293447.3 | E17: 203525.77 | F17: 209111.92 | G17: 1. Государственные услуги общего характера
A18: 2. Қорғаныс | B18: 1073075.9 | C18: 1100070.9 | D18: 1038491.2 | E18: 127423.11 | F18: 80846.186 | G18: 2. Оборона
A19: 3. Қоғамдық тәртіп, қауіпсіздік, құқықтық, сот, қылмыстық-атқару қызметі | B19: 1074316.3 | C19: 1275903.8 | D19: 1287986.9 | E19: 149503.98 | F19: 158301.8 | G19: 3. Общественный порядок, безопасность, правовая, судебная, уголовно-исполнительная деятельность
... A45: Өтеу | B45: 208253.95 | C45: 660721.39 | D45: 1154283.9 | E45: 93680.118 | F45: 106694.99 | G45: Погашение

Sheet табл 8 (дох)
B2: 8-кесте | H2: Таблица 8
F3: РЕСПУБЛИКАЛЫҚ БЮДЖЕТТІҢ АТҚАРЫЛУЫ/ ИСПОЛНЕНИЕ РЕСПУБЛИКАНСКОГО БЮДЖЕТА
B4: (млн.теңге) | H4: (млн.тенге)
B5: Санаты/ Категория | C5: Сыныбы/ Класс | D5: Сыныпшасы/ Подкласс | E5: Ерешелігі/ Специфика | F5: Атауы | G5: 2025 ж. қаңтар-ақпан есеп/_x000D_ январь-февраль отчет 2025 г. | H5: Наименование
B6: 1 | C6: 2 | D6: 3 | E6: 4 | F6: 5 | G6: 6 | H6: 7
F7: ТҮСІМДЕР | G7: 3645168.4 | H7: ПОСТУПЛЕНИЯ
F8: оның ішінде: | H8: в том числе:
F9: КІРІСТЕР | G9: 3634592.6 | H9: ДОХОДЫ
B10: 1 | F10: Салықтық түсімдер | G10: 2301508.5 | H10: Налоговые поступления
C11: 01 | F11: Табыс салығы | G11: 696571.35 | H11: Подоходный налог
D12: 1 | F12: Корпорациялық табыс салығы | G12: 696571.35 | H12: Корпоративный подоходный налог
B13: 1 | C13: 01 | D13: 1 | E13: 10 | F13: Мұнай секторы ұйымдарынан түсетін түсімдерді қоспағанда, ірі кәсіпкерлік субъектілерінен – заңды тұлғалардан алынатын корпоративтік табыс салығы | G13: 696571.35 | H13: Корпоративный подоходный налог с юридических лиц – субъектов крупного предпринимательства, за исключением поступлений от организаций нефтяного сектора
C14: 05 | F14: Тауарларға, жұмыстарға және қызметтерге салынатын iшкi салықтар | G14: 1379961.5 | H14: Внутренние налоги на товары, работы и услуги
D15: 1 | F15: Қосылған құн салығы | G15: 1105855.5 | H15: Налог на добавленную стоимость
C16: 05 | D16: 1 | E16: 01 | F16: Қазақстан Республикасының аумағында өндiрiлген тауарларға, орындалған жұмыстарға және көрсетілген қызметтерге салынатын қосылған құн салығы | G16: 588316.43 | H16: Hалог на добавленную стоимость на произведенные товары, выполненные работы и оказанные услуги на территории Республики Казахстан
E17: 02 | F17: Ресей Федерациясы және Беларусь Республикасының аумағынан импортталатын тауарларға салынатын қосылған құн салығынан басқа, Қазақстан Республикасының аумағына импортталатын тауарларға салынатын қосылған құн салығы | G17: 269675.7 | H17: Hалог на добавленную стоимость на товары, импортируемые на территорию Республики Казахстан, кроме налога на добавленнуюстоимость на товары, импортируемые с территории Российской Федерации и Республики Беларусь
E18: 04 | F18: Резидент емес үшін қосылған құн салығы | G18: 52040.043 | H18: Налог на добавленную стоимость за нерезидента
E19: 14 | F19: Салық төлеушінің бұрын бюджеттен қайтарылған және салықтық тексеру жүргізу барысында қайтарылуы расталмаған қосылған құн салығының асып кеткен сомасын аударуы (қайтаруы), өсімпұл сомасын аударуы | G19: 533.09975 | H19: Перечисление (возврат) налогоплательщиком суммы превышения налога на добавленную стоимость, ранее возвращенной из бюджета и не подтвержденной к возврату при проведении налоговой проверки, перечисление суммы пени
E20: 15 | F20: ЕАЭО мүше мемлекеттер аумағынан импортталған тауарларға қосылған құн салығы | G20: 181953.04 | H20: Налог на добавленную стоимость на товары, импортированные с территории государств-членов ЕАЭС
E21: 16 | F21: Тауарлармен электрондық сауданы жүзеге асыру, жеке тұлғаларға электрондық нысанда қызметтер көрсету кезінде шетелдік компаниялардан түсетін қосылған құн салығы | G21: 13337.202 | H21: Налог на добавленную стоимость с иностранных интернет компаний при осуществлении электронной торговли товарами, оказании услуг в электронной форме физическим лицам
D22: 2 | F22: Акциздер | G22: 18199.007 | H22: Акцизы
D23: 2 | E23: 76 | F23: Қазақстан Республикасының аумағына Кеден одағына мүше мемлекеттердің аумағынан әкелінетін темекі өнімдері | G23: 4106.5058 | H23: Табачные изделия, ввозимые на территорию Республики Казахстан с территории государств-членов Таможенного союза
E24: 77 | F24: Қазақстан Республикасының аумағына Кеден одағына мүше мемлекеттердің аумағынан әкелінетін спирттiң және (немесе) шарап материалының, алкоголь өнімдерінің барлық түрлерi | G24: 2782.2992 | H24: Все виды спирта и (или) виноматериала, алкогольной продукции, ввозимых на территорию Республики Казахстан с территории государств-членов Таможенного союза
E25: 78 | F25: Қазақстан Республикасының аумағына Кеден одағына мүше мемлекеттердің аумағынан әкелінетін акцизделетін өнімнің өзге түрлері | G25: 4.3997715 | H25: Прочие виды подакцизных продукций, ввозимых на территорию Республики Казахстан с территории государств-членов Таможенного союза
E26: 79 | F26: Қазақстан Республикасы аумағына Кеден одағына мүше мемлекеттердің аумағынан әкелінетін бензин (авиациялықты қоспағанда) және дизель отыны | G26: 1008.8749 | H26: Бензин (за исключением авиационного) и дизельное топливо, ввозимых на территорию Республики Казахстан с территории государств-членов Таможенного союза
E27: 80 | F27: Кеден одағына мүше болып табылмайтын мемлекеттердің аумағынан әкелінетін, Қазақстан Республикасының аумағына импортталатын спирттің және (немесе) шарап материалының, алкоголь өнімдерінің барлық түрлері | G27: 2379.0343 | H27: Все виды спирта и (или) виноматериала, алкогольной продукции, импортируемых на территорию Республики Казахстан с территории государств, не являющихся членами Таможенного союза
E28: 81 | F28: Кеден одағына мүше болып табылмайтын мемлекеттердің аумағынан әкелінетін, Қазақстан Республикасының аумағына импортталатын темекі өнімдері | G28: 7298.2036 | H28: Табачные изделия, импортируемые на территорию Республики Казахстан с территории государств, не являющихся членами Таможенного союза
E29: 82 | F29: Кеден одағына мүше болып табылмайтын мемлекеттердің аумағынан әкелінетін, Қазақстан Республикасының аумағына импортталатын акцизделетін өнімдердің өзге түрлері | G29: 604.0667 | H29: Прочие виды подакцизных продукций, импортируемые на территорию Республики Казахстан с территории государств, не являющихся членами Таможенного союза
E30: 83 | F30: Кеден одағына мүше болып табылмайтын мемлекеттер аумағынан әкелінетін, Қазақстан Республикасының аумағына импортталатын бензин (авиациялықты қоспағанда) және дизель отыны | G30: 15.622548 | H30: Бензин (за исключением авиационного) и дизельное топливо, импортируемых на территорию Республики Казахстан с территории государств, не являющихся членами Таможенного союза
D31: 3 | F31: Табиғи және басқа да ресурстарды пайдаланғаны үшiн түсетiн түсiмдер | G31: 249280.03 | H31: Поступления за использование природных и других ресурсов
D32: 3 | E32: 01 | F32: Қалааралық және (немесе) халықаралық телефон байланысын көрсеткені үшін төлем,тағыда ұялы байланыс | G32: 2.3104093 | H32: Плата за предоставление междугородной и (или) международнойтелефонной связи, а также сотовой связи
E33: 05 | F33: Бонустар, мұнай секторы ұйымдарынан түсетін түсімдерден басқа | G33: 10154.905 | H33: Бонусы, за исключением поступлений от организаций нефтяногосектора
E34: 06 | F34: Пайдалы қазбаларды өндіруге салынатын салық, мұнай секторы ұйымдарынан түсетін түсімдерден басқа | G34: 237002.82 | H34: Налог на добычу полезных ископаемых, за исключением поступлений от организаций нефтяного сектора
E35: 07 | F35: Мұнай секторы ұйымдарынан түсетін түсімдерді қоспағанда, экспортқа салынатын рента салығы | G35: 827.62482 | H35: Рентный налог на экспорт, за исключением поступлений от организаций нефтяного сектора
E36: 09 | F36: Радиожиілік спектрін пайдаланғаны үшін төлем | G36: 224.07792 | H36: Плата за использование радиочастотного спектра
E37: 13 | F37: Республикалық маңызы бар ерекше қорғалатын табиғи аумақтарды пайдаланғаны үшін төлем | G37: -4.2021501 | H37: Плата за использование особо охраняемых природных территорий республиканского значения
E38: 17 | F38: Цифрлық майнинг үшін төлемақы | G38: 1072.4956 | H38: Плата за цифровой майнинг
D39: 4 | F39: Кәсiпкерлiк және кәсiби қызметтi жүргiзгенi үшiн алынатын алымдар | G39: 2586.494 | H39: Сборы за ведение предпринимательской и профессиональной деятельности
D40: 4 | E40: 06 | F40: Автокөлік құралдарының Қазақстан Республикасының аумағы арқылы өткені үшін алынатын алым | G40: 2561.7629 | H40: Сбор за проезд автотранспортных средств по территории Республики Казахстан
E41: 13 | F41: Телевизиялық және радио хабарын тарататын ұйымдарға радиожиілік өрісін пайдалануға рұқсат бергені үшін алынатын алым | G41: 0 | H41: Сбор за выдачу разрешения на использование радиочастотного спектра телевизионным и радиовещательным организациям
E42: 19 | F42: Сыртқы (көрнекі) жарнаманы аудандық маңызы бар қалалар, ауылдар, кенттер, ауылдық округтер аумақтары арқылы өтетін республикалық маңызы бар жалпыға ортақ пайдаланылатын автомобиль жолдарының бөлiнген белдеуiндегі жарнаманы тұрақты орналаст | G42: 2.682697 | H42: Плата за размещение наружной (визуальной) рекламы на объектах стационарного размещения рекламы в полосе отвода автомобильных дорог общего пользования республиканского значения, заисключением платы за размещение наружной (визуальной) реклам
E43: 28 | F43: Республикалық бюджетке төленетін тіркелгені үшін алым | G43: 19.340296 | H43: Регистрационный сбор, зачисляемый в республиканский бюджет
E44: 31 | F44: Микроқаржы ұйымдарын есептік тіркеуден өткізгені және оларды микроқаржы ұйымдарының тізіліміне енгізгені үшін алым | G44: 0 | H44: Сбор за прохождение учетной регистрации микрофинансовых организаций и включение их в реестр микрофинансовых организаций
E45: 32 | F45: Банк және сақтандыру нарықтарына қатысушылар үшін рұқсат беру құжаттарын, келісім бергені үшін алым | G45: 2.7081 | H45: Сбор за выдачу разрешительных документов, согласия для участников банковского и страхового рынков
E46: 35 | F46: Азаматтық авиация саласындағы уәкілетті ұйым Қазақстан Республикасының әуе кеңістігін пайдалануды және авиация қызметінреттейтін Қазақстан Республикасының заңнамасында белгіленген сертификаттау талаптарына сәйкестігіне беретін сертификатта | G46: 0 | H46: Сбор за выдачу сертификатов, выдаваемых уполномоченной организацией в сфере гражданской авиации, на соответствие сертификационным требованиям, установленным законодательством Республики Казахстан и деятельность авиации
D47: 5 | F47: Ойын бизнесіне салық | G47: 4040.4854 | H47: Налог на игорный бизнес
D48: 5 | E48: 01 | F48: Ойын бизнесіне салық | G48: 4040.4854 | H48: Налог на игорный бизнес
C49: 06 | F49: Халықаралық сауда мен сыртқы операцияларға салынатын салықтар | G49: 222660.82 | H49: Hалоги на международную торговлю и внешние операции
D50: 1 | F50: Кеден төлемдерi | G50: 211524.5 | H50: Таможенные платежи
C51: 06 | D51: 1 | E51: 01 | F51: Еуразиялық экономикалық одақ туралы шартқа сәйкес төленген әкелінетін кедендік баждары (баламалы қолданылатын өзге де баждар, салықтар мен алымдар) | G51: 7867.8474 | H51: Ввозные таможенные пошлины (иные пошлины, налоги и сборы, имеющие эквивалентное действие), уплаченные в соответствии с Договором о Евразийском экономическом союзе
E52: 02 | F52: Әкетілетін тауарларға салынатын кедендік баждар | G52: 2230.2912 | H52: Таможенные пошлины на вывозимые товары
E53: 04 | F53: Кеден бажының бірыңғай ставкасын қолданумен жеке тұлғалардан өндіріп алынатын жеке пайдалануына әкелінетін тауарларға салынатын кеден баждары, салықтары | G53: 527.81597 | H53: Таможенные пошлины, налоги на ввозимые физическими лицами товары для личного пользования с применением единых ставок таможенных пошлин, налогов
E54: 05 | F54: Әкелінетін тауарларға жиынтық кедендік төлем | G54: 67.89594 | H54: Совокупный таможенный платеж на ввозимые товары
E55: 06 | F55: Ресей Федерациясымен бөлінген кедендік баж | G55: 68822.448 | H55: Таможенные пошлины, распределенные Российской Федерацией
E56: 07 | F56: Беларусь Республикасымен бөлінген кедендік баж | G56: 3853.8271 | H56: Таможенные пошлины, распределенные Республикой Беларусь
E57: 10 | F57: Мұнайға салынатын кедендік әкету бажы | G57: 118631.53 | H57: Вывозные таможенные пошлины на сырую нефть
E58: 11 | F58: Мұнайдан өндірілген тауарларға салынатын кедендік әкету бажы | G58: 4355.6109 | H58: Вывозные таможенные пошлины на товары, выработанные из нефти
E59: 12 | F59: Кеден одағында кедендік әкелу баждарын (баламалы қолданысы бар өзге де баждарды, салықтар мен алымдарды) есепке жатқызужәне бөлу тәртібін белгілеу және қолдану туралы келісім күшіне енгенге дейін төлеу жөніндегі міндеті туындаған әкелінеті | G59: 644.30294 | H59: Таможенные пошлины на ввозимые товары и (или) ввозные таможенные пошлины, обязанность по уплате которых возникла до вступления в силу Соглашения об установлении и применении в таможенном союзе порядка зачисления и распределения ввозных тамо
E60: 13 | F60: Армения Республикасымен бөлінген кедендік баждар | G60: 1573.9119 | H60: Таможенные пошлины, распределенные Республикой Армения
E61: 17 | F61: Қырғыз Республикасы бөлген кедендік баждар | G61: 2407.4773 | H61: Таможенные пошлины, распределенные Кыргызской Республикой
E62: 19 | F62: Алдағы кедендік баждарды, кедендік алымдарды, салықтарды, арнайы, демпингке қарсы, өтемақы баждарын төлеу есебіне, сондай-ақ кедендік баждарды, салықтарды арнайы, демпингке қарсы,өтемақы баждарын төлеу жөніндегі міндеттің орындалуын қамтам | G62: 541.53757 | H62: Авансовые платежи, вносимые в соответствии с таможенным законодательством Евразийского экономического союза и Республики Казахстан, в счет уплаты предстоящих таможенных платежей, налогов, специальных, антидемпинговых, компенсационных пошлин
D63: 2 | F63: Халықаралық сауда мен операцияларға салынатын басқа да салықтар | G63: 11136.32 | H63: Прочие налоги на международную торговлю и операции
D64: 2 | E64: 01 | F64: Қазақстан Республикасының кеден заңнамасына сәйкес төленетін кедендік алымдар | G64: 9107.3809 | H64: Таможенные сборы, уплачиваемые в соответствии с таможенным законодательством Республики Казахстан
E65: 02 | F65: Еуразиялық экономикалық одақ туралы шартқа сәйкес төленген арнайы, демпингке қарсы, өтемақы баждары | G65: 163.23803 | H65: Специальные, антидемпинговые, компенсационные пошлины, уплаченные в соответствии с Договором о Евразийском экономическом союзе
E66: 05 | F66: Беларусь Республикасынан түсетін арнайы, демпингке қарсы, өтемақы баждары | G66: 127.60298 | H66: Специальные, антидемпинговые, компенсационные пошлины, поступившие от Республики Беларусь
E67: 06 | F67: Ресей Федерациясынан түсетін арнайы, демпингке қарсы, өтемақы баждары | G67: 1685.9267 | H67: Специальные, антидемпинговые, компенсационные пошлины, поступившие от Российской Федерации
E68: 08 | F68: Бөлуге жатпайтын арнайы, демпингке қарсы, өтемақы баждары | G68: 0.2903702 | H68: Специальные, антидемпинговые, компенсационные пошлины, не подлежащие распределению
E69: 09 | F69: Армения Республикасынан түсетін арнайы, демпингке қарсы, өтемақы баждары | G69: 18.550171 | H69: Специальные, антидемпинговые, компенсационные пошлины, поступившие от Республики Армения
E70: 11 | F70: Қырғыз Республикасынан түскен арнайы, демпингке қарсы, өтемақы баждары | G70: 33.330868 | H70: Специальные, антидемпинговые, компенсационные пошлины, поступившие от Кыргызской Республики
C71: 07 | F71: Басқа да салықтар | G71: 1621.9726 | H71: Прочие налоги
D72: 1 | F72: Басқа да салықтар | G72: 1621.9726 | H72: Прочие налоги
C73: 07 | D73: 1 | E73: 09 | F73: Республикалық бюджетке түсетін өзге де салық түсiмдері | G73: 1621.9726 | H73: Прочие налоговые поступления в республиканский бюджет
C74: 08 | F74: Заңдық мәнді іс-әрекеттерді жасағаны және (немесе) оған уәкілеттігі бар мемлекеттік органдар немесе лауазымды адамдар құжаттар бергені үшін алынатын міндетті төлемдер | G74: 692.81686 | H74: Обязательные платежи, взимаемые за совершение юридически значимых действий и (или) выдачу документов, уполномоченными на то государственными органами или должностными лицами
D75: 1 | F75: Мемлекеттік баж | G75: 692.81686 | H75: Государственная пошлина
C76: 08 | D76: 1 | E76: 01 | F76: Консулдық алым | G76: 474.18478 | H76: Консульский сбор
E77: 25 | F77: Республикалық бюджетке төленетін мемлекеттік баж | G77: 218.63207 | H77: Государственная пошлина, зачисляемая в республиканский бюджет
B78: 2 | F78: Салықтық емес түсiмдер | G78: 182604.09 | H78: Неналоговые поступления
C79: 01 | F79: Кәсiпкерлiк қызмет пен меншiктен түсетiн кiрiстер | G79: 25207.555 | H79: Доходы от государственной собственности
D80: 1 | F80: Мемлекеттік кәсіпорындардың таза кірісі бөлігінің түсімдері | G80: 11.274784 | H80: Поступления части чистого дохода государственных предприятий
B81: 2 | C81: 01 | D81: 1 | E81: 01 | F81: Республикалық мемлекеттік кәсіпорындардың таза кірісінің бір бөлігінің түсімдері | G81: 11.274784 | H81: Поступления части чистого дохода республиканских государственных предприятий
D82: 3 | F82: Мемлекет меншігіндегі акциялардың мемлекеттік пакеттеріне дивидендтер | G82: 5.344851 | H82: Дивиденды на государственные пакеты акций, находящиеся в государственной собственности
D83: 3 | E83: 01 | F83: Республика меншігіндегі акциялардың мемлекеттік пакетіне дивидендтер | G83: 5.344851 | H83: Дивиденды на государственные пакеты акций, находящиеся в республиканской собственности
D84: 4 | F84: Мемлекет меншігіндегі, заңды тұлғалардағы қатысу үлесіне кірістер | G84: 0.01249 | H84: Доходы на доли участия в юридических лицах, находящиеся в государственной собственности
D85: 4 | E85: 01 | F85: Республикалық меншіктегі заңды тұлғаларға қатысу үлесіне кірістер | G85: 0.01249 | H85: Доходы на доли участия в юридических лицах, находящиеся в республиканской собственности
D86: 5 | F86: Мемлекет меншігіндегі мүлікті жалға беруден түсетін кірістер | G86: 16413.971 | H86: Доходы от аренды имущества, находящегося в государственной собственности
D87: 5 | E87: 01 | F87: Республика меншігіндегі мүлікті жалға алудан түсетін кірістер | G87: 532.46577 | H87: Доходы от аренды имущества, находящегося в республиканскойсобственности
E88: 02 | F88: Әскери полигондарды пайдаланғаны үшін жалгерлік төлемнен түсетін түсімдер | G88: 0 | H88: Поступления арендной платы за пользование военными полигонами
E89: 03 | F89: «Байқоныр» кешенін пайдаланғаны үшін жалгерлік төлемнен түсетін түсімдер | G89: 15881.505 | H89: Поступления арендной платы за пользование комплексом «Байконур»
D90: 6 | F90: Бюджет қаражатын банк шоттарына орналастырғаны үшін сыйақылар | G90: 665.57746 | H90: Вознаграждения за размещение бюджетных средств на банковских счетах
D91: 6 | E91: 01 | F91: Қазақстан Республикасы Үкіметінің Қазақстан Республикасы Ұлттық банкіндегі депозиттері бойынша және бірыңғай қазынашылық шоттағы ақшаның күн сайынғы қалдығына сыйақылар | G91: 665.57746 | H91: Вознаграждения по депозитам Правительства Республики Казахстан в Национальном Банке Республики Казахстан и на ежедневный остаток денег на едином казначейском счете
D92: 7 | F92: Мемлекеттік бюджеттен берілген кредиттер бойынша сыйақылар | G92: 119.51513 | H92: Вознаграждения по кредитам, выданным из государственного бюджета
D93: 7 | E93: 01 | F93: Облыстардың, республикалық маңызы бар қаланың, астананың жергілікті атқарушы органдарына ішкі көздер есебінен республикалық бюджеттен берілген бюджеттік кредиттер бойынша сыйақылар | G93: 5.5126287 | H93: Вознаграждения по бюджетным кредитам, выданным из республиканского бюджета за счет внутренних источников местным исполнительным органам областей, города республиканского значения,столицы
E94: 02 | F94: Облыстардың, республикалық маңызы бар қаланың, астананың жергілікті атқарушы органдарына үкіметтік сыртқы қарыздар қаражаты есебінен республикалық бюджеттен берілген бюджеттік кредиттер бойынша сыйақылар | G94: 0 | H94: Вознаграждения по бюджетным кредитам, выданным из республиканского бюджета за счет средств правительственных внешних займов местным исполнительным органам областей, города республиканского значения, столицы
E95: 04 | F95: Мамандандырылған ұйымдарға ішкі көздер есебінен республикалық бюджеттен берілген бюджеттік кредиттер бойынша сыйақылар | G95: 113.9737 | H95: Вознаграждения по бюджетным кредитам, выданным из республиканского бюджета за счет внутренних источников специализированным организациям
E96: 10 | F96: Заңды тұлғаларға үкіметтік сыртқы қарыздар қаражаты есебінен республикалық бюджеттен 2005 жылға дейін берілген бюджеттік кредиттер бойынша сыйақылар | G96: 0.0288 | H96: Вознаграждения по бюджетным кредитам, выданным из республиканского бюджета до 2005 года за счет средств правительственных внешних займов юридическим лицам
E97: 14 | F97: Шетелдік мемлекеттерге берілген бюджеттік кредиттер бойынша сыйақылар | G97: 0 | H97: Вознаграждения по бюджетным кредитам, выданным иностранным государствам
D98: 9 | F98: Мемлекет меншігінен түсетін басқа да кірістер | G98: 7991.8594 | H98: Прочие доходы от государственной собственности
D99: 9 | E99: 01 | F99: Ауыл шаруашылығы және орман алқаптарын ауыл және орман шаруашылықтарын жүргізуге байланысты емес мақсаттарға пайдалану үшін алған кезде ауыл шаруашылығы және орман шаруашылығы өндірістерінің шығасыларын өтеуден түсетін түсімдер | G99: 955.88864 | H99: Поступления от возмещения потерь сельскохозяйственного и лесохозяйственного производства при изъятии сельскохозяйственных и лесных угодий для использования их в целях, не связанных с ведением сельского и лесного хозяйства
E100: 03 | F100: Жер қойнауы туралы ақпаратты пайдалануға берілгені үшін ақы | G100: 0.000388 | H100: Плата за предоставление в пользование информации о недрах
E101: 05 | F101: Қару-жарақты және әскери техниканы сатудан түсетін кірістер | G101: 98.583812 | H101: Доходы от продажи вооружения и военной техники
...

Sheet табл 8 (расх)
A3: (млн.теңге) | G3: (млн. тенге)
A6: Санаты/ Категория | B6: Сыныбы/ Класс | C6: Сыныпшасы/ Подкласс | D6: Ерешелігі/ Специфика | E6: Атауы | F6: 2025 қаңтар-ақпан есеп/_x000D_ январь-февраль отчет 2025г. | G6: Наименование
A7: 1 | B7: 2 | C7: 3 | D7: 4 | E7: 5 | F7: 6 | G7: 7
E8: ШЫҒЫСТАР | F8: 3658804.3 | G8: РАСХОДЫ
E9: оның ішінде: | G9: в том числе:
E10: II. ШЫҒЫНДАР | F10: 3638727.6 | G10: II. ЗАТРАТЫ
A11: 01 | E11: Жалпы сипаттағы мемлекеттiк қызметтер | F11: 209111.92 | G11: Государственные услуги общего характера
B12: 1 | E12: Мемлекеттiк басқарудың жалпы функцияларын орындайтын өкiлдi, атқарушы және басқа органдар | F12: 36932.294 | G12: Представительные, исполнительные и другие органы, выполняющие общие функции государственного управления
C13: 101 | E13: Қазақстан Республикасы Президентінің Әкімшілігі | F13: 2447.5945 | G13: Администрация Президента Республики Казахстан
A14: 01 | B14: 1 | C14: 101 | D14: 001 | E14: Мемлекет басшысының қызметін қамтамасыз ету | F14: 2447.5945 | G14: Обеспечение деятельности Главы государства
C15: 106 | E15: Адам құқықтары жөніндегі ұлттық орталық | F15: 292.40694 | G15: Национальный центр по правам человека
C16: 106 | D16: 001 | E16: Адамның және азаматтың құқықтары мен бостандықтарының сақталуын қадағалау жөніндегі қызметтер | F16: 232.22694 | G16: Услуги по наблюдению за соблюдением прав и свобод человека и гражданина
D17: 005 | E17: Қазақстандағы ұлттық құқық қорғау тетіктерінің тиімділігін күшейту | F17: 60.18 | G17: Усиление эффективности национальных правозащитных механизмов в Казахстане
C18: 107 | E18: Қазақстан Республикасы Жоғары Сот Кеңесінің Аппараты | F18: 189.53042 | G18: Аппарат Высшего Судебного Совета Республики Казахстан
C19: 107 | D19: 001 | E19: Қазақстан Республикасы Жоғары Сот Кеңесінің қызметін қамтамасыз ету жөнінде көрсетілетін қызметтер | F19: 189.53042 | G19: Услуги по обеспечению деятельности Высшего Судебного СоветаРеспублики Казахстан
C20: 109 | E20: Қазақстан Республикасы үкіметінің Аппараты_x000D_ | F20: 821.05498 | G20: Аппарат Правительства Республики Казахстан
C21: 109 | D21: 001 | E21: Қазақстан Республикасы Премьер-Министрінің қызметін қамтамасыз ету жөніндегі көрсетілетін қызметтер | F21: 821.05498 | G21: Услуги по обеспечению деятельности Премьер-Министра Республики Казахстан
C22: 626 | E22: Қазақстан Республикасының Стратегиялық жоспарлау және реформалар агенттігі | F22: 3834.6082 | G22: Агентство по стратегическому планированию и реформам Республики Казахстан
C23: 626 | D23: 001 | E23: Реформаларды қалыптастыруға және тиімді іске асыруға жәрдемдесу жөніндегі көрсетілетін қызметтер, стратегиялық жоспарлау, мемлекеттік статистикалық қызмет салаларында мемлекеттік саясатты жүзеге асыру, мемлекеттік басқару жүйесі мен квазиме | F23: 3834.6082 | G23: Услуги по содействию в формировании и эффективной реализации реформ, осуществление государственной политики в сферах стратегического планирования, государственной статистической деятельности, участие в совершенствовании системы государствен
C24: 637 | E24: Қазақстан Республикасы Конституциялық Сотының Аппараты | F24: 292.20671 | G24: Аппарат Конституционного Суда Республики Казахстан
C25: 637 | D25: 001 | E25: Республика аумағында Қазақстан Республикасы Конституциясының үстемдігін қамтамасыз ету | F25: 292.20671 | G25: Обеспечение верховенства Конституции Республики Казахстан на территории Республики
C26: 690 | E26: Қазақстан Республикасының Орталық сайлау комиссиясы | F26: 714.10583 | G26: Центральная избирательная комиссия Республики Казахстан
C27: 690 | D27: 001 | E27: Сайлау өткізуді ұйымдастыру | F27: 148.90815 | G27: Организация проведения выборов
D28: 002 | E28: Сайлау өткізу | F28: 565.19768 | G28: Проведение выборов
D29: 004 | E29: Облыстық бюджеттерге аудандардың (облыстық маңызы бар қалалардың) әкімдерін сайлауды қамтамасыз етуге және өткізуге берілетін ағымдағы нысаналы трансферттер | F29: 0 | G29: Целевые текущие трансферты областным бюджетам на обеспечение и проведение выборов акимов районов (городов областного значения)
C30: 693 | E30: Материалдық-техникалық қамтамасыз ету басқармасы | F30: 3155.5009 | G30: Управление материально-технического обеспечения
C31: 693 | D31: 001 | E31: Қазақстан Республикасы Парламентінің қызметін қамтамасыз ету жөніндегі көрсетілетін қызметтер | F31: 3155.5009 | G31: Услуги по обеспечению деятельности Парламента Республики Казахстан
C32: 694 | E32: Қазақстан Республикасы Президентiнiң Іс басқармасы | F32: 25185.286 | G32: Управление Делами Президента Республики Казахстан
C33: 694 | D33: 001 | E33: Қазақстан Республикасы Президенті Іс Басқармасының мемлекеттік функциялары мен өкілеттіктерін жүзеге асыруды қамтамасыз ету жөніндегі қызметтер | F33: 11906.841 | G33: Услуги по обеспечению осуществления государственных функцийи полномочий Управления делами Президента Республики Казахстан
D34: 009 | E34: Қазақстан Республикасы Президенттік орталығының қызметін қамтамасыз ету жөніндегі көрсетілетін қызметтер | F34: 179.60433 | G34: Услуги по обеспечению деятельности Президентского центра Республики Казахстан
D35: 139 | E35: Қазақстан Республикасы Үкіметінің шұғыл шығындарға арналғанрезервінің есебінен дамуға бағытталған іс-шаралар өткізу | F35: 13098.84 | G35: Проведение мероприятий, направленных на развитие за счет резерва Правительства Республики Казахстан на неотложные затраты
B36: 2 | E36: Қаржылық қызмет | F36: 2666.3859 | G36: Финансовая деятельность
C37: 217 | E37: Қазақстан Республикасының Қаржы министрлiгi | F37: 1965.4307 | G37: Министерство финансов Республики Казахстан
B38: 2 | C38: 217 | D38: 002 | E38: Халықаралық қаржы ұйымдары қаржыландыратын инвестициялық жобалардың аудитiн жүзеге асыру | F38: 0 | G38: Осуществление аудита инвестиционных проектов, финансируемыхмеждународными финансовыми организациями
D39: 094 | E39: Мемлекеттік активтерді басқару | F39: 7.054391 | G39: Управление государственными активами
D40: 205 | E40: Шекарадағы өткізу пункттерін жаңғырту және техникалық толықжарақтандыру | F40: 1958.3763 | G40: Модернизация и техническое дооснащение пунктов пропуска на границе
C41: 406 | E41: Қазақстан Республикасының Жоғары аудиторлық палатасы | F41: 700.95524 | G41: Высшая аудиторская палата Республики Казахстан
C42: 406 | D42: 001 | E42: Қазақстан Республикасы Жоғары аудиторлық палатасының қызметін қамтамасыз ету жөніндегі көрсетілетін қызметтер | F42: 700.95524 | G42: Услуги по обеспечению деятельности Высшей аудиторской палаты Республики Казахстан
D43: 101 | E43: Өкілдiк шығындарға арналған қаражат есебiнен іс-шаралар өткізу | F43: 0 | G43: Проведение мероприятий за счет средств на представительскиезатраты
B44: 3 | E44: Сыртқы саяси қызмет | F44: 18487.54 | G44: Внешнеполитическая деятельность
C45: 204 | E45: Қазақстан Республикасының Сыртқы iстер министрлiгi | F45: 18487.54 | G45: Министерство иностранных дел Республики Казахстан
B46: 3 | C46: 204 | D46: 001 | E46: Сыртқы саяси қызметті үйлестіру жөніндегі көрсетілетін қызметтер | F46: 16710.311 | G46: Услуги по координации внешнеполитической деятельности
D47: 005 | E47: Шетелдік іссапарлар | F47: 600 | G47: Заграничные командировки
D48: 008 | E48: Шетелдегі дипломатиялық өкілдіктердің арнайы, инженерлік-техникалық және нақты қорғалуын қамтамасыз ету | F48: 47.350806 | G48: Обеспечение специальной, инженерно-технической и физическойзащиты дипломатических представительств за рубежом
D49: 013 | E49: Халықаралық ұйымдарда, Тәуелсіз Мемлекеттер Достастығының жарғылық және басқа органдарында Қазақстан Республикасының мүддесін білдіру | F49: 83.274842 | G49: Представление интересов Республики Казахстан в международных организациях, уставных и других органах Содружества Независимых Государств
D50: 017 | E50: Қазақстан Республикасының халықаралық ұйымдарға, өзге де халықаралық және басқа органдарға қатысуы | F50: 44.742529 | G50: Участие Республики Казахстан в международных организациях, иных международных и прочих органах
D51: 019 | E51: Ақпараттық-имидждік саясаттың іске асырылуын қамтамасыз ету | F51: 900.59399 | G51: Обеспечение реализации информационно-имиджевой политики
D52: 045 | E52: Халықаралық бағыттағы үкіметтік емес ұйымдардың қызметін гранттық қаржыландыру | F52: 0 | G52: Грантовое финансирование деятельности неправительственных организаций на международном направлении
D53: 101 | E53: Өкілдiк шығындарға арналған қаражат есебiнен іс-шаралар өткізу | F53: 101.26738 | G53: Проведение мероприятий за счет средств на представительскиезатраты
C54: 243 | E54: Қазақстан Республикасының Ұлттық экономика министрлігі | F54: 0 | G54: Министерство национальной экономики Республики Казахстан
C55: 243 | D55: 057 | E55: Қазақстанның Экономикалық ынтымақтастық және даму ұйымымен ынтымақтастығы шеңберінде Қазақстанның Экономикалық ынтымақтастық және даму ұйымының бастамалары мен құралдарына қатысуы | F55: 0 | G55: Участие Казахстана в инициативах и инструментах Организацииэкономического сотрудничества и развития в рамках сотрудничества Казахстана с Организацией экономического сотрудничества и развития
D56: 096 | E56: Қазақстан Республикасы мен Экономикалық ынтымақтастық және даму ұйымының арасындағы ынтымақтастық шеңберінде Қазақстан Республикасының әлеуметтік-экономикалық жағдайына зерттеулер жүргізу Қазақстан Республикасы мен Экономикалық ынтымақтас | F56: 0 | G56: Проведение исследования социально-экономического положения Республики Казахстан в рамках сотрудничества между Республикой Казахстан и Организацией экономического сотрудничества и развития
B57: 4 | E57: Iргелi ғылыми зерттеулер | F57: 50618.078 | G57: Фундаментальные научные исследования
C58: 202 | E58: Қазақстан Республикасының Төтенше жағдайлар министрлiгi | F58: 53.5647 | G58: Министерство по чрезвычайным ситуациям Республики Казахстан
B59: 4 | C59: 202 | D59: 131 | E59: Ғылыми және (немесе) ғылыми-техникалық қызмет субъектілерінбазалық қаржыландыруды қамтамасыз ету | F59: 53.5647 | G59: Обеспечение базового финансирования субъектов научной и (или) научно-технической деятельности
C60: 207 | E60: Қазақстан Республикасының Экология және табиғи ресурстар министрлігі | F60: 560.5045 | G60: Министерство экологии и природных ресурсов Республики Казахстан
C61: 207 | D61: 131 | E61: Ғылыми және (немесе) ғылыми-техникалық қызмет субъектілерінбазалық қаржыландыруды қамтамасыз ету | F61: 560.5045 | G61: Обеспечение базового финансирования субъектов научной и (или) научно-технической деятельности
C62: 208 | E62: Қазақстан Республикасының Қорғаныс министрлiгi | F62: 0 | G62: Министерство обороны Республики Казахстан
C63: 208 | D63: 131 | E63: Ғылыми және (немесе) ғылыми-техникалық қызмет субъектілерінбазалық қаржыландыруды қамтамасыз ету | F63: 0 | G63: Обеспечение базового финансирования субъектов научной и (или) научно-технической деятельности
C64: 212 | E64: Қазақстан Республикасының Ауыл шаруашылығы министрлiгi | F64: 0 | G64: Министерство сельского хозяйства Республики Казахстан
C65: 212 | D65: 131 | E65: Ғылыми және (немесе) ғылыми-техникалық қызмет субъектілерін базалық қаржыландыруды қамтамасыз ету | F65: 0 | G65: Обеспечение базового финансирования субъектов научной и (или) научно-технической деятельности
C66: 213 | E66: Қазақстан Республикасының Еңбек және халықты әлеуметтiк қорғау министрлiгi | F66: 94.442 | G66: Министерство труда и социальной защиты населения РеспубликиКазахстан
C67: 213 | D67: 131 | E67: Ғылыми және (немесе) ғылыми-техникалық қызмет субъектілерін базалық қаржыландыруды қамтамасыз ету | F67: 94.442 | G67: Обеспечение базового финансирования субъектов научной и (или) научно-технической деятельности
C68: 223 | E68: Қазақстан Республикасының Цифрлық даму, инновациялар және аэроғарыш өнеркәсібі министрлігі | F68: 0 | G68: Министерство цифрового развития, инноваций и аэрокосмической промышленности Республики Казахстан
C69: 223 | D69: 131 | E69: Ғылыми және (немесе) ғылыми-техникалық қызмет субъектілерінбазалық қаржыландыруды қамтамасыз ету | F69: 0 | G69: Обеспечение базового финансирования субъектов научной и (или) научно-технической деятельности
C70: 224 | E70: Қазақстан Республикасының Оқу-ағарту министрлігі | F70: 0 | G70: Министерство просвещения Республики Казахстан
C71: 224 | D71: 131 | E71: Ғылыми және (немесе) ғылыми-техникалық қызмет субъектілерінбазалық қаржыландыруды қамтамасыз ету | F71: 0 | G71: Обеспечение базового финансирования субъектов научной и (или) научно-технической деятельности
C72: 226 | E72: Қазақстан Республикасының Денсаулық сақтау министрлігі | F72: 626.9325 | G72: Министерство здравоохранения Республики Казахстан
C73: 226 | D73: 131 | E73: Ғылыми және (немесе) ғылыми-техникалық қызмет субъектілерін базалық қаржыландыруды қамтамасыз ету | F73: 626.9325 | G73: Обеспечение базового финансирования субъектов научной и (или) научно-технической деятельности
C74: 227 | E74: Қазақстан Республикасының Ғылым және жоғары білім министрлігі | F74: 49221.196 | G74: Министерство науки и высшего образования Республики Казахстан
C75: 227 | D75: 130 | E75: Ғылыми және (немесе) ғылыми-техникалық қызмет субъектілерінбазалық қаржыландыру | F75: 0 | G75: Базовое финансирование субъектов научной и (или) научно-технической деятельности
D76: 131 | E76: Ғылыми және (немесе) ғылыми-техникалық қызмет субъектілерінбазалық қаржыландыруды қамтамасыз ету | F76: 1622.5502 | G76: Обеспечение базового финансирования субъектов научной и (или) научно-технической деятельности
D77: 217 | E77: Ғылымды дамыту | F77: 47598.646 | G77: Развитие науки
C78: 228 | E78: Қазақстан Республикасының Көлік министрлігі | F78: 5.707 | G78: Министерство транспорта Республики Казахстан
C79: 228 | D79: 131 | E79: Ғылыми және (немесе) ғылыми-техникалық қызмет субъектілерінбазалық қаржыландыруды қамтамасыз ету | F79: 5.707 | G79: Обеспечение базового финансирования субъектов научной и (или) научно-технической деятельности
C80: 229 | E80: Қазақстан Республикасының Өнеркәсіп және құрылыс министрлігі | F80: 0 | G80: Министерство промышленности и строительства Республики Казахстан
C81: 229 | D81: 131 | E81: Ғылыми және (немесе) ғылыми-техникалық қызмет субъектілерінбазалық қаржыландыруды қамтамасыз ету | F81: 0 | G81: Обеспечение базового финансирования субъектов научной и (или) научно-технической деятельности
C82: 241 | E82: Қазақстан Республикасының Энергетика министрлігі | F82: 0 | G82: Министерство энергетики Республики Казахстан
C83: 241 | D83: 131 | E83: Ғылыми және (немесе) ғылыми-техникалық қызмет субъектілерін базалық қаржыландыруды қамтамасыз ету | F83: 0 | G83: Обеспечение базового финансирования субъектов научной и (или) научно-технической деятельности
C84: 652 | E84: Қазақстан Республикасының Су ресурстары және ирригация министрлігі | F84: 55.7315 | G84: Министерство водных ресурсов и ирригации Республики Казахстан
C85: 652 | D85: 131 | E85: Ғылыми және (немесе) ғылыми-техникалық қызмет субъектілерінбазалық қаржыландыруды қамтамасыз ету | F85: 55.7315 | G85: Обеспечение базового финансирования субъектов научной и (или) научно-технической деятельности
B86: 5 | E86: Жоспарлау және статистикалық қызмет | F86: 560.51207 | G86: Планирование и статистическая деятельность
C87: 243 | E87: Қазақстан Республикасының Ұлттық экономика министрлігі | F87: 250.64 | G87: Министерство национальной экономики Республики Казахстан
B88: 5 | C88: 243 | D88: 006 | E88: Халықаралық ұйымдармен бірлесіп жүзеге асырылатын жобаларды зерттеулердің іске асырылуын қамтамасыз ету | F88: 250.64 | G88: Обеспечение реализации исследований проектов, осуществляемых совместно с международными организациями
C89: 626 | E89: Қазақстан Республикасының Стратегиялық жоспарлау және реформалар агенттігі | F89: 309.87207 | G89: Агентство по стратегическому планированию и реформам Республики Казахстан
C90: 626 | D90: 002 | E90: Статистикалық ақпаратты ұсынуды қамтамасыз ету | F90: 309.87207 | G90: Обеспечение предоставления статистической информации
D91: 003 | E91: Халықаралық міндеттемелерді орындау және орнықты даму мақсаттарына қол жеткізу мақсатында Қазақстан Республикасындағы балалар мен әйелдердің жағдайын мониторингтеу үшін мультииндикаторлық кластерлік зерттеп-қарауды жүргізу | F91: 0 | G91: Проведение мультииндикаторного кластерного обследования длямониторинга положения детей и женщин в Республике Казахстанв целях выполнения международных обязательств и достижения целей устойчивого развития
B92: 6 | E92: Жалпы кадрлық мәселелер | F92: 0 | G92: Общие кадровые вопросы
C93: 608 | E93: Қазақстан Республикасының Мемлекеттiк қызмет iстерi агенттiгi | F93: 0 | G93: Агентство Республики Казахстан по делам государственной службы
B94: 6 | C94: 608 | D94: 008 | E94: Мемлекеттік қызмет саласындағы өңірлік хабты институционалдық қолдау | F94: 0 | G94: Институциональная поддержка регионального хаба в сфере государственной службы
D95: 012 | E95: Республиканың мемлекеттiк қызмет кадрларын тестілеу жөніндегі көрсетілетін қызметтер | F95: 0 | G95: Услуги по тестированию кадров государственной службы республики
B96: 9 | E96: Жалпы сипаттағы өзге де мемлекеттiк қызметтер | F96: 99847.105 | G96: Прочие государственные услуги общего характера
C97: 201 | E97: Қазақстан Республикасының Iшкi iстер министрлiгi | F97: 24206.505 | G97: Министерство внутренних дел Республики Казахстан
B98: 9 | C98: 201 | D98: 001 | E98: Қоғамдық тәртіпті қорғау және қоғамдық қауіпсіздікті қамтамасыз ету, қылмыстық-атқару жүйесі саласындағы мемлекеттік саясатты айқындау және оның іске асырылуын ұйымдастыру жөніндегі көрсетілетін қызметтер | F98: 24206.505 | G98: Услуги по определению и организации реализации государственной политики в области охраны общественного порядка и обеспечения общественной безопасности, уголовно-исполнительной системы
C99: 204 | E99: Қазақстан Республикасының Сыртқы iстер министрлiгi | F99: 172.5 | G99: Министерство иностранных дел Республики Казахстан
C100: 204 | D100: 021 | E100: Шетелде Қазақстан Республикасы азаматтарының құқықтары мен мүдделерін қорғау жөніндегі іс-шараларды қамтамасыз ету | F100: 0 | G100: Обеспечение мероприятий по защите прав и интересов граждан Республики Казахстан за рубежом
D101: 022 | E101: Шетелдегі отандастармен және Қазақстан Республикасына келген этникалық қазақтармен байланыстарды және қатынастарды дамытуға жәрдемдесу | F101: 172.5 | G101: Содействие развитию связей и контактов с соотечественникамиза рубежом и этническими казахами, прибывшими в Республику Казахстан
D102: 028 | E102: Қазақстан Республикасы Сыртқы істер министрлігінің дипломатиялық қызметтің бірыңғай ақпараттық жүйесін құру | F102: 0 | G102: Создание единой информационной системы дипломатической службы Министерства иностранных дел Республики Казахстан
C103: 207 | E103: Қазақстан Республикасының Экология және табиғи ресурстар министрлігі | F103: 1320.285 | G103: Министерство экологии и природных ресурсов Республики Казахстан
C104: 207 | D104: 001 | E104: Экология және табиғи ресурстар саласындағы қызметті үйлестіру жөніндегі көрсетілетін қызметтер | F104: 1320.285 | G104: Услуги по координации деятельности в сфере экологии и природных ресурсов
...

Sheet табл 9
B2: Кесте 9 | D2: Таблица 9
B3: ШЫҒЫСТАРДЫҢ ВЕДОМСТВОЛЫҚ | D3: ИСПОЛНЕНИЕ РЕСПУБЛИКАНСКОГО БЮДЖЕТА
B4: СЫНЫПТАМАСЫ БОЙЫНША | D4: ПО ВЕДОМСТВЕННОЙ
B5: РЕСПУБЛИКАЛЫҚ БЮДЖЕТТІҢ АТҚАРАЛУЫ | D5: КЛАССИФИКАЦИИ РАСХОДОВ
B6: (млн. теңге) | D6: (млн. тенге)
B8: Бағдарламалард_x000D_ ың_x000D_ əкімшісі/_x000D_ Администратор_x000D_ программ | C8: Атауы | D8: 2025 ж. қаңтар-ақпан есеп/_x000D_ январь-февраль 2025 г. | E8: Наименование
B9: 1 | C9: 2 | D9: 3 | E9: 4
C10: БАРЛЫҒЫ | D10: 3658804.3 | E10: ВСЕГО
B11: 101 | C11: Қазақстан Республикасы Президентінің Әкімшілігі | D11: 2447.5945 | E11: Администрация Президента Республики Казахстан
B12: 106 | C12: Адам құқықтары жөніндегі ұлттық орталық | D12: 292.40694 | E12: Национальный центр по правам человека
B13: 107 | C13: Қазақстан Республикасы Жоғары Сот Кеңесінің Аппараты | D13: 298.27046 | E13: Аппарат Высшего Судебного Совета Республики Казахстан
B14: 109 | C14: Қазақстан Республикасы үкіметінің Аппараты_x000D_ | D14: 1113.2111 | E14: Аппарат Правительства Республики Казахстан
B15: 201 | C15: Қазақстан Республикасының Iшкi iстер министрлiгi | D15: 78191.833 | E15: Министерство внутренних дел Республики Казахстан
B16: 202 | C16: Қазақстан Республикасының Төтенше жағдайлар министрлiгi | D16: 14381.322 | E16: Министерство по чрезвычайным ситуациям Республики Казахстан
B17: 204 | C17: Қазақстан Республикасының Сыртқы iстер министрлiгi | D17: 18660.04 | E17: Министерство иностранных дел Республики Казахстан
B18: 207 | C18: Қазақстан Республикасының Экология және табиғи ресурстар министрлігі | D18: 17315.548 | E18: Министерство экологии и природных ресурсов Республики Казахстан
B19: 208 | C19: Қазақстан Республикасының Қорғаныс министрлiгi | D19: 73148.999 | E19: Министерство обороны Республики Казахстан
B20: 211 | C20: Қазақстан Республикасының Сауда және интеграция министрлігі | D20: 4220.2585 | E20: Министерство торговли и интеграции Республики Казахстан
B21: 212 | C21: Қазақстан Республикасының Ауыл шаруашылығы министрлiгi | D21: 36351.498 | E21: Министерство сельского хозяйства Республики Казахстан
B22: 213 | C22: Қазақстан Республикасының Еңбек және халықты әлеуметтiк қорғау министрлiгi | D22: 1014858.9 | E22: Министерство труда и социальной защиты населения РеспубликиКазахстан
... B49: 694 | C49: Қазақстан Республикасы Президентiнiң Іс басқармасы | D49: 39503.229 | E49: Управление Делами Президента Республики Казахстан

Sheet табл 10
A1: 10-кесте ШЫҒЫНДАРДЫҢ ЭКОНОМИКАЛЫҚ ЖІКТЕМЕСІ БОЙЫНША РЕСПУБЛИКАЛЫҚ БЮДЖЕТТІК ОРЫНДАЛУЫ (млн.теңге) | E1: Таблица 10 ИСПОЛНЕНИЕ РЕСПУБЛИКАНСКОГО БЮДЖЕТА ПО ЭКОНОМИЧЕСКОЙ КЛАССИФИКАЦИИ РАСХОДОВ (млн. тенге)
A3: Cанаты/_x000D_ Категория | B3: Iшкi сыныбы/_x000D_ Подкласс | C3: Ерекшелiгi/_x000D_ Специфика | D3: Атауы | F3: 2025 ж. қаңтар-ақпан/_x000D_ январь-февраль отчет 2025 г. | G3: Наименование
A4: 1 | B4: 2 | C4: 3 | D4: 4 | F4: 5 | G4: 6
D5: БАРЛЫҒЫ | F5: 3658804.3 | G5: ВСЕГО
A6: 1 | D6: Ағымдағы шығындар | F6: 3521478.6 | G6: Текущие затраты
A7: L01 Категория расходов | B7: 110 | D7: Жалақы | F7: 180170.78 | G7: Заработная плата
A8: 1 | B8: 110 | C8: 111 | D8: Еңбекке ақы төлеу | F8: 133384.19 | G8: Оплата труда
A9: 1 | C9: 112 | D9: Қосымша ақшалай төлемдер | F9: 22843.147 | G9: Дополнительные денежные выплаты
A10: 1 | C10: 113 | D10: Өтемақы төлемдері | F10: 22600.828 | G10: Компенсационные выплаты
A11: 1 | C11: 114 | D11: Міндетті кәсіптік зейнетақы жарналары | F11: 31.979699 | G11: Обязательные профессиональные пенсионные взносы
A12: 1 | C12: 116 | D12: Жұмыс берушілердің міндетті зейнетақы жарналары | F12: 1310.6316 | G12: Обязательные пенсионные взносы работодателей
A13: L01 Категория расходов | B13: 120 | D13: Жұмыс берушілердің жарналары | F13: 11315.499 | G13: Взносы работодателей
A14: 1 | B14: 120 | C14: 121 | D14: Әлеуметтік салық | F14: 4130.7945 | G14: Социальный налог
A15: 1 | C15: 122 | D15: Мемлекеттiк әлеуметтiк сақтандыру қорына әлеуметтiк аударымдар | F15: 5475.5657 | G15: Социальные отчисления в Государственный фонд социального страхования
A16: 1 | C16: 123 | D16: Мiндеттi сақтандыру жарналары | F16: 54.506088 | G16: Взносы на обязательное страхование
A17: 1 | C17: 124 | D17: Міндетті әлеуметтік медициналық сақтандыруға аударымдар | F17: 1654.6328 | G17: Отчисления на обязательное социальное медицинское страхование
A18: L01 Категория расходов | B18: 130 | D18: Қазақстан Республикасының заңнамалық актілеріне сәйкес азаматтардың жекелеген санаттарына жалақы төлеу және жарналар аудару | F18: 10064.033 | G18: Выплата заработной платы отдельным категориям граждан и отчисления взносов в соответствии с законодательными актами Республики Казахстан
A19: 1 | B19: 130 | C19: 131 | D19: Техникалық персоналдың еңбегіне ақы төлеу | F19: 8835.8075 | G19: Оплата труда технического персонала
A20: 1 | C20: 134 | D20: Алқа билерге сыйақылар төлеу | F20: 63.507774 | G20: Выплата вознаграждений присяжным заседателям
A21: 1 | C21: 135 | D21: Техникалық персонал бойынша жұмыс берушілердің жарналары | F21: 1109.4462 | G21: Взносы работодателей по техническому персоналу
A22: 1 | C22: 136 | D22: Техникалық персоналдың ел iшiндегi iссапарлары мен қызметтiк сапарлары | F22: 53.718961 | G22: Командировки и служебные разъезды внутри страны технического персонала
A23: 1 | C23: 137 | D23: Қорғаушы мәжілістердің қызметтiк сапарлар | F23: 1.552628 | G23: Командировочные расходы присяжных заседателей
A24: L01 Категория расходов | B24: 140 | D24: Қорлар сатып алу | F24: 15844.86 | G24: Приобретение запасов
A25: 1 | B25: 140 | C25: 141 | D25: Азық-түлiк өнiмдерiн сатып алу | F25: 11313.272 | G25: Приобретение продуктов питания
A26: 1 | C26: 142 | D26: Дәрілік заттар және медициналық мақсаттағы өзге де бұйымдарды сатып алу | F26: 164.19109 | G26: Приобретение лекарственных средств и прочих изделий медицинского назначения
A27: 1 | C27: 143 | D27: Заттай мүлiктердi, басқа да киім нысанын және арнаулы киім-кешектер сатып алу, тiгу және жөндеу | F27: 105.3942 | G27: Приобретение, пошив и ремонт предметов вещевого имущества идругого форменного и специального обмундирования
A28: 1 | C28: 144 | D28: Отын, жанар-жағар май материалдарын сатып алу | F28: 2986.3304 | G28: Приобретение топлива, горюче-смазочных материалов
A29: 1 | C29: 149 | D29: Өзге де қорларды сатып алу | F29: 1275.6723 | G29: Приобретение прочих запасов
A30: L01 Категория расходов | B30: 150 | D30: Қызметтер мен жұмыстарды сатып алу | F30: 231812.73 | G30: Приобретение услуг и работ
A31: 1 | B31: 150 | C31: 151 | D31: Коммуналдық қызметтерге ақы төлеу | F31: 7725.203 | G31: Оплата коммунальных услуг
A32: 1 | C32: 152 | D32: Байланыс қызметтерiне ақы төлеу | F32: 598.91959 | G32: Оплата услуг связи
A33: 1 | C33: 153 | D33: Көлiктiк қызмет көрсетулерге ақы төлеу | F33: 2128.309 | G33: Оплата транспортных услуг
A34: 1 | C34: 154 | D34: Зерттеулер бойынша қызметтерге ақы төлеу | F34: 48442.469 | G34: Оплата услуг по исследованиям
A35: 1 | C35: 156 | D35: Консалтингтік қызметтерге ақы төлеу | F35: 25.551938 | G35: Оплата консалтинговых услуг
A36: 1 | C36: 157 | D36: Форумдар, семинарлар, конференциялар өткізуге және имидждік іс-шараларға арналған қызметтерге ақы төлеу | F36: 2.599 | G36: Оплата услуг на проведение форумов, семинаров, конференций и на имиджевые мероприятия
A37: 1 | C37: 158 | D37: Ақпараттандыру саласындағы жұмыстар мен қызметтерге ақы төлеу | F37: 2787.6358 | G37: Оплата работ и услуг в сфере информатизации
A38: 1 | C38: 159 | D38: Өзге де қызметтер мен жұмыстарға ақы төлеу | F38: 170102.05 | G38: Оплата прочих услуг и работ
A39: L01 Категория расходов | B39: 160 | D39: Басқа да ағымдағы шығындар | F39: 244531.44 | G39: Другие текущие затраты
A40: 1 | B40: 160 | C40: 161 | D40: Ел iшiндегi iссапарлар мен қызметтiк сапарлар | F40: 2432.1186 | G40: Командировки и служебные разъезды внутри страны
A41: 1 | C41: 162 | D41: Елден тыс жерлерге iссапарлар мен қызметтiк сапарлар | F41: 1255.2853 | G41: Командировки и служебные разъезды за пределы страны
A42: 1 | C42: 164 | D42: Шетелдегi стипендиаттардың оқуына ақы төлеу | F42: 8750 | G42: Оплата обучения стипендиатов за рубежом
A43: 1 | C43: 165 | D43: Атқарушылық құжаттарының, сот актiлерiнiң орындалуы | F43: 836.53097 | G43: Исполнение исполнительных документов, судебных актов
A44: 1 | C44: 166 | D44: Нысаналы салым | F44: 2205.373 | G44: Целевой вклад
A45: 1 | C45: 167 | D45: Ерекше шығындар | F45: 88795.869 | G45: Особые затраты
A46: 1 | C46: 169 | D46: Өзге де ағымдағы шығындар | F46: 140256.26 | G46: Прочие текущие затраты
A47: L01 Категория расходов | B47: 210 | D47: Ішкі қарыздар бойынша сыйақы төлемдері | F47: 453012.64 | G47: Выплаты вознаграждений по внутренним займам
A48: 1 | B48: 210 | C48: 211 | D48: Қазақстан Республикасы Үкіметінің ішкі қарыздары бойынша сыйақыларды төлеу | F48: 453012.64 | G48: Выплаты вознаграждений по внутренним займам Правительства Республики Казахстан
A49: L01 Категория расходов | B49: 220 | D49: Сыртқы заемдар бойынша сыйақылар төлеу | F49: 76592.236 | G49: Выплаты вознаграждений по внешним займам
A50: 1 | B50: 220 | C50: 221 | D50: Қазақстан Республикасы Үкіметінің сыртқы қарыздары бойынша сыйақы төлемдері | F50: 76592.236 | G50: Выплаты вознаграждений по внешним займам Правительства Республики Казахстан
A51: L01 Категория расходов | B51: 310 | D51: Бюджеттік субсидиялар | F51: 33689.775 | G51: Бюджетные субсидии
A52: 1 | B52: 310 | C52: 311 | D52: Жеке және заңды тұлғаларға, оның ішінде шаруа (фермерлік) қожалықтарына берілетін субсидиялар | F52: 33689.775 | G52: Субсидии физическим и юридическим лицам, в том числе крестьянским (фермерским) хозяйствам
A53: L01 Категория расходов | B53: 320 | D53: Жеке тұлғаларға берілетін трансферттер | F53: 1068008.4 | G53: Трансферты физическим лицам
A54: 1 | B54: 320 | C54: 321 | D54: Арнайы мемлекеттік органдардың қызметкерлеріне және əскери қызметшілеріне тұрғын үй төлемдері | F54: 22015.646 | G54: Жилищные выплаты сотрудникам специальных государственных органов и военнослужащим
A55: 1 | C55: 322 | D55: Жеке тұлғаларға берiлетiн трансферттер | F55: 275262.46 | G55: Трансферты физическим лицам
A56: 1 | C56: 323 | D56: Зейнетақылар | F56: 737170.08 | G56: Пенсии
A57: 1 | C57: 324 | D57: Стипендиялар | F57: 33560.188 | G57: Стипендии
A58: L01 Категория расходов | B58: 330 | D58: Мемлекеттiк басқарудың басқа деңгейлерiне берiлетiн ағымдағытрансферттер | F58: 857383.69 | G58: Текущие трансферты другим уровням государственного управления
A59: 1 | B59: 330 | C59: 331 | D59: Субвенциялар | F59: 776551.01 | G59: Субвенции
A60: 1 | C60: 339 | D60: Мемлекеттiк басқарудың басқа деңгейлерiне берiлетiн ағымдағы трансферттер | F60: 80832.677 | G60: Текущие трансферты другим уровням государственного управления
A61: L01 Категория расходов | B61: 340 | D61: Шетелге берiлетiн ағымдағы трансферттер | F61: 52.531823 | G61: Текущие трансферты за границу
A62: 1 | B62: 340 | C62: 341 | D62: Шетелдегi ұйымдарға ағымдағы трансферттер | F62: 52.531823 | G62: Текущие трансферты за границу
A63: L01 Категория расходов | B63: 360 | D63: Нысаналы жарна | F63: 339000 | G63: Целевой взнос
A64: 1 | B64: 360 | C64: 361 | D64: Нысаналы жарна | F64: 339000 | G64: Целевой взнос
A65: 2 | D65: Күрделі шығындар | F65: 96555.865 | G65: Капитальные затраты
A66: L01 Категория расходов | B66: 410 | D66: Негiзгi құралдарды, материалдық емес және биологиялық активтерді сатып алу | F66: 34.456952 | G66: Приобретение основных средств, нематериальных и биологических активов
A67: 2 | B67: 410 | C67: 413 | D67: Көлік құралдарын сатып алу | F67: 33.389343 | G67: Приобретение транспортных средств
A68: 2 | C68: 414 | D68: Машиналар, жабдықтар, өндірістік және шаруашылық мүккамал құралдарын сатып алу | F68: 1.067609 | G68: Приобретение машин, оборудования, инструментов, производственного и хозяйственного инвентаря
A69: L01 Категория расходов | B69: 420 | D69: Негізгі қаражатты күрделі жөндеу | F69: 1183.8502 | G69: Капитальный ремонт основных средств
A70: 2 | B70: 420 | C70: 421 | D70: Жайларды, ғимараттарды, құрылыстарды, беру қондырғыларын күрделі жөндеу | F70: 1183.8502 | G70: Капитальный ремонт помещений, зданий, сооружений, передаточных устройств
A71: L01 Категория расходов | B71: 430 | D71: Дамуға бағытталған күрделі шығындар | F71: 42516.659 | G71: Капитальные затраты, направленные на развитие
A72: 2 | B72: 430 | C72: 431 | D72: Жаңа объектілерді салу және қолдағы объектілерді реконструкциялау | F72: 39193.507 | G72: Строительство новых объектов и реконструкция имеющихся объектов
A73: 2 | C73: 432 | D73: Жолдар салу | F73: 3024.9816 | G73: Строительство дорог
A74: 2 | C74: 434 | D74: Ақпараттық жүйелерді құру, енгізу және дамыту | F74: 298.1704 | G74: Создание, внедрение и развитие информационных систем
A75: L01 Категория расходов | B75: 440 | D75: Дамуға арналған нысаналы трансферттер | F75: 52820.898 | G75: Целевые трансферты на развитие
A76: 2 | B76: 440 | C76: 441 | D76: Мемлекеттік басқарудың басқа деңгейлерін дамытуға арналған нысаналы трансферттер | F76: 52820.898 | G76: Целевые трансферты на развитие другим уровням государственного управления
A77: 3 | D77: Бюджеттік кредиттер | F77: 20000 | G77: Бюджетные кредиты
A78: L01 Категория расходов | B78: 510 | D78: Ішкі бюджеттік кредиттер | F78: 20000 | G78: Внутренние бюджетные кредиты
A79: 3 | B79: 510 | C79: 513 | D79: Мамандандырылған ұйымдарға бюджеттік кредиттер | F79: 20000 | G79: Бюджетные кредиты специализированным организациям
A80: 4 | D80: Қаржы активтерін сатып алу | F80: 76.74548 | G80: Приобретение финансовых активов
A81: L01 Категория расходов | B81: 620 | D81: Елден тысқары жерлерден қаржы активтерін сатып алу | F81: 76.74548 | G81: Приобретение финансовых активов за пределами страны
A82: 4 | B82: 620 | C82: 621 | D82: Халқаралық ұйымдардың акцияларын сатып алу | F82: 76.74548 | G82: Приобретение акций международных организаций
A83: 6 | D83: Мемлекеттік-жекешелік әріптестік жобалар бойынша мемлекеттік міндеттемелерді орындау | F83: 20693.127 | G83: Выполнение государственных обязательств по проектам государственно-частного партнерства
A84: L01 Категория расходов | B84: 810 | D84: Мемлекеттік концессиялық міндеттемелерді орындау | F84: 20693.127 | G84: Выполнение государственных концессионных обязательств
A85: 6 | B85: 810 | C85: 812 | D85: Мемлекеттік-жекешелік әріптестік жобалар бойынша инвестициялық шығындарды өтеу бойынша мемлекеттік міндеттемелерді орындау | F85: 7796.6605 | G85: Выполнение государственных обязательств по компенсации инвестиционных затрат по проектам государственно-частного партнерства
A86: 6 | C86: 813 | D86: Мемлекеттік-жекешелік әріптестік жобалар бойынша операциялық (пайдалану) шығындарды өтеу бойынша мемлекеттік міндеттемелерді орындау | F86: 390.7835 | G86: Выполнение государственных обязательств по компенсации операционных (эксплуатационных) затрат по проектам государственно-частного п
A87: 6 | C87: 814 | D87: Мемлекеттік-жекешелік әріптестік объектісін басқаруды жүзеге асырғаны үшін сыйақы төлемі бойынша мемлекеттік міндеттемелерді орындау | F87: 12505.683 | G87: Выполнение государственных обязательств по выплате вознаграждений за осуществление управления объектом государственно-частного парт

Sheet таб 11
A1: 11-кесте ШЫҒЫНДАРДЫҢ ЭКОНОМИКАЛЫҚ ЖІКТЕМЕСІ БОЙЫНША ЖЕРГІЛІКТІ БЮДЖЕТТІК ОРЫНДАЛУЫ (млн.теңге) | E1: Таблица 11 ИСПОЛНЕНИЕ МЕСТНОГО БЮДЖЕТА ПО ЭКОНОМИЧЕСКОЙ КЛАССИФИКАЦИИ РАСХОДОВ (млн. тенге)
A3: Cанаты/_x000D_ Категория | B3: Iшкi сыныбы/_x000D_ Подкласс | C3: Ерекшелiгi/_x000D_ Специфика | D3: Атауы | F3: 2025 ж. қаңтар-ақпан/_x000D_ январь-февраль отчет 2025 г. | G3: Наименование
A4: 1 | B4: 2 | C4: 3 | D4: 4 | F4: 5 | G4: 6
D5: БАРЛЫҒЫ | F5: 1874984.8 | G5: ВСЕГО
A6: 1 | D6: Ағымдағы шығындар | F6: 1578448.4 | G6: Текущие затраты
A7: L01 Категория расходов | B7: 110 | D7: Жалақы | F7: 511819.52 | G7: Заработная плата
A8: 1 | B8: 110 | C8: 111 | D8: Еңбекке ақы төлеу | F8: 472592.14 | G8: Оплата труда
A9: 1 | C9: 112 | D9: Қосымша ақшалай төлемдер | F9: 21419.752 | G9: Дополнительные денежные выплаты
A10: 1 | C10: 113 | D10: Өтемақы төлемдері | F10: 10493.932 | G10: Компенсационные выплаты
A11: 1 | C11: 114 | D11: Міндетті кәсіптік зейнетақы жарналары | F11: 0.848984 | G11: Обязательные профессиональные пенсионные взносы
A12: 1 | C12: 116 | D12: Жұмыс берушілердің міндетті зейнетақы жарналары | F12: 7312.8429 | G12: Обязательные пенсионные взносы работодателей
A13: L01 Категория расходов | B13: 120 | D13: Жұмыс берушілердің жарналары | F13: 57371.922 | G13: Взносы работодателей
A14: 1 | B14: 120 | C14: 121 | D14: Әлеуметтік салық | F14: 25666.402 | G14: Социальный налог
A15: 1 | C15: 122 | D15: Мемлекеттiк әлеуметтiк сақтандыру қорына әлеуметтiк аударымдар | F15: 19157.278 | G15: Социальные отчисления в Государственный фонд социального страхования
A16: 1 | C16: 123 | D16: Мiндеттi сақтандыру жарналары | F16: 81.107866 | G16: Взносы на обязательное страхование
A17: 1 | C17: 124 | D17: Міндетті әлеуметтік медициналық сақтандыруға аударымдар | F17: 12467.134 | G17: Отчисления на обязательное социальное медицинское страхование
A18: L01 Категория расходов | B18: 130 | D18: Қазақстан Республикасының заңнамалық актілеріне сәйкес азаматтардың жекелеген санаттарына жалақы төлеу және жарналар аудару | F18: 15225.243 | G18: Выплата заработной платы отдельным категориям граждан и отчисления взносов в соответствии с законодательными актами Республики Казахстан
A19: 1 | B19: 130 | C19: 131 | D19: Техникалық персоналдың еңбегіне ақы төлеу | F19: 13222.357 | G19: Оплата труда технического персонала
A20: 1 | C20: 133 | D20: Негізгі жұмыс орны бойынша мәслихат депутаттарына орташа жалақыны өтеу | F20: 0.146834 | G20: Возмещение средней заработной платы депутатам маслихата по их основному месту работы
A21: 1 | C21: 135 | D21: Техникалық персонал бойынша жұмыс берушілердің жарналары | F21: 1731.3604 | G21: Взносы работодателей по техническому персоналу
A22: 1 | C22: 136 | D22: Техникалық персоналдың ел iшiндегi iссапарлары мен қызметтiк сапарлары | F22: 271.37879 | G22: Командировки и служебные разъезды внутри страны технического персонала
A23: L01 Категория расходов | B23: 140 | D23: Қорлар сатып алу | F23: 28940.247 | G23: Приобретение запасов
A24: 1 | B24: 140 | C24: 141 | D24: Азық-түлiк өнiмдерiн сатып алу | F24: 3819.5159 | G24: Приобретение продуктов питания
A25: 1 | C25: 142 | D25: Дәрілік заттар және медициналық мақсаттағы өзге де бұйымдарды сатып алу | F25: 11077.027 | G25: Приобретение лекарственных средств и прочих изделий медицинского назначения
A26: 1 | C26: 143 | D26: Заттай мүлiктердi, басқа да киім нысанын және арнаулы киім-кешектер сатып алу, тiгу және жөндеу | F26: 248.08091 | G26: Приобретение, пошив и ремонт предметов вещевого имущества идругого форменного и специального обмундирования
A27: 1 | C27: 144 | D27: Отын, жанар-жағар май материалдарын сатып алу | F27: 9679.0215 | G27: Приобретение топлива, горюче-смазочных материалов
A28: 1 | C28: 149 | D28: Өзге де қорларды сатып алу | F28: 4116.6019 | G28: Приобретение прочих запасов
A29: L01 Категория расходов | B29: 150 | D29: Қызметтер мен жұмыстарды сатып алу | F29: 389446.91 | G29: Приобретение услуг и работ
A30: 1 | B30: 150 | C30: 151 | D30: Коммуналдық қызметтерге ақы төлеу | F30: 30131.067 | G30: Оплата коммунальных услуг
A31: 1 | C31: 152 | D31: Байланыс қызметтерiне ақы төлеу | F31: 2406.7768 | G31: Оплата услуг связи
A32: 1 | C32: 153 | D32: Көлiктiк қызмет көрсетулерге ақы төлеу | F32: 1768.5909 | G32: Оплата транспортных услуг
A33: 1 | C33: 154 | D33: Зерттеулер бойынша қызметтерге ақы төлеу | F33: 12.428103 | G33: Оплата услуг по исследованиям
A34: 1 | C34: 155 | D34: Мемлекеттiк әлеуметтiк тапсырыс шеңберiнде көрсетілетін қызметтерге ақы төлеу | F34: 2895.8096 | G34: Оплата услуг в рамках государственного социального заказа
A35: 1 | C35: 157 | D35: Форумдар, семинарлар, конференциялар өткізуге және имидждік іс-шараларға арналған қызметтерге ақы төлеу | F35: 13.582428 | G35: Оплата услуг на проведение форумов, семинаров, конференций и на имиджевые мероприятия
A36: 1 | C36: 158 | D36: Ақпараттандыру саласындағы жұмыстар мен қызметтерге ақы төлеу | F36: 2161.0887 | G36: Оплата работ и услуг в сфере информатизации
A37: 1 | C37: 159 | D37: Өзге де қызметтер мен жұмыстарға ақы төлеу | F37: 350057.57 | G37: Оплата прочих услуг и работ
A38: L01 Категория расходов | B38: 160 | D38: Басқа да ағымдағы шығындар | F38: 116706.65 | G38: Другие текущие затраты
A39: 1 | B39: 160 | C39: 161 | D39: Ел iшiндегi iссапарлар мен қызметтiк сапарлар | F39: 4189.1089 | G39: Командировки и служебные разъезды внутри страны
A40: 1 | C40: 162 | D40: Елден тыс жерлерге iссапарлар мен қызметтiк сапарлар | F40: 543.72089 | G40: Командировки и служебные разъезды за пределы страны
A41: 1 | C41: 163 | D41: Жалпыға бiрдей мiндеттi орта бiлiм қорының шығындары | F41: 11120.267 | G41: Затраты Фонда всеобщего обязательного среднего образования
A42: 1 | C42: 165 | D42: Атқарушылық құжаттарының, сот актiлерiнiң орындалуы | F42: 8619.5694 | G42: Исполнение исполнительных документов, судебных актов
A43: 1 | C43: 169 | D43: Өзге де ағымдағы шығындар | F43: 92233.985 | G43: Прочие текущие затраты
A44: L01 Категория расходов | B44: 210 | D44: Ішкі қарыздар бойынша сыйақы төлемдері | F44: 2625.4297 | G44: Выплаты вознаграждений по внутренним займам
A45: 1 | B45: 210 | C45: 212 | D45: Жоғары тұрған бюджеттен жергiлiктi атқарушы органдар алған қарыздар бойынша сыйақы төлемдері | F45: 5.535457 | G45: Выплаты вознаграждений по займам, полученным из вышестоящего бюджета местными исполнительными органами
A46: 1 | C46: 213 | D46: Бұл ерекшелiкте жергілікті атқарушы органдардың ішкі қарыздары бойынша сыйақыларды төлеу іске асырылады | F46: 2619.8943 | G46: Выплаты вознаграждений по внутренним займам местных исполнительных органов
A47: L01 Категория расходов | B47: 310 | D47: Бюджеттік субсидиялар | F47: 258545.99 | G47: Бюджетные субсидии
A48: 1 | B48: 310 | C48: 311 | D48: Жеке және заңды тұлғаларға, оның ішінде шаруа (фермерлік) қожалықтарына берілетін субсидиялар | F48: 258545.99 | G48: Субсидии физическим и юридическим лицам, в том числе крестьянским (фермерским) хозяйствам
A49: L01 Категория расходов | B49: 320 | D49: Жеке тұлғаларға берілетін трансферттер | F49: 47844.641 | G49: Трансферты физическим лицам
A50: 1 | B50: 320 | C50: 321 | D50: Арнайы мемлекеттік органдардың қызметкерлеріне және əскери қызметшілеріне тұрғын үй төлемдері | F50: 5832.8421 | G50: Жилищные выплаты сотрудникам специальных государственных органов и военнослужащим
A51: 1 | C51: 322 | D51: Жеке тұлғаларға берiлетiн трансферттер | F51: 28598.979 | G51: Трансферты физическим лицам
A52: 1 | C52: 324 | D52: Стипендиялар | F52: 13412.82 | G52: Стипендии
A53: L01 Категория расходов | B53: 330 | D53: Мемлекеттiк басқарудың басқа деңгейлерiне берiлетiн ағымдағытрансферттер | F53: 144636.3 | G53: Текущие трансферты другим уровням государственного управления
A54: 1 | B54: 330 | C54: 332 | D54: Бюджеттiк алып қоюлар | F54: 137549.97 | G54: Бюджетные изъятия
A55: 1 | C55: 336 | D55: Бюджет заңнамасымен қарастырылған жағдайларда жалпы сипаттағы трансферттерды қайтару | F55: 1191.558 | G55: Возврат трансфертов общего характера в случаях, предусмотренных бюджетным законодательством
A56: 1 | C56: 338 | D56: Нысаналы трансферттерді қайтару | F56: 5260.036 | G56: Возврат целевых трансфертов
A57: 1 | C57: 339 | D57: Мемлекеттiк басқарудың басқа деңгейлерiне берiлетiн ағымдағы трансферттер | F57: 634.737 | G57: Текущие трансферты другим уровням государственного управления
A58: L01 Категория расходов | B58: 350 | D58: Өзге де ағымдағы трансферттер | F58: 5285.5965 | G58: Прочие текущие трансферты
A59: 1 | B59: 350 | C59: 352 | D59: Қазақстан Республикасының Ұлттық қорынан тартылған қаражаттың бір бөлігін қайтару | F59: 5285.5965 | G59: Возврат части средств, привлеченных из Национального фонда Республики Казахстан
A60: 2 | D60: Күрделі шығындар | F60: 209961.32 | G60: Капитальные затраты
A61: L01 Категория расходов | B61: 410 | D61: Негiзгi құралдарды, материалдық емес және биологиялық активтерді сатып алу | F61: 41290.401 | G61: Приобретение основных средств, нематериальных и биологических активов
A62: 2 | B62: 410 | C62: 411 | D62: Жер сатып алу | F62: 3138.2546 | G62: Приобретение земли
A63: 2 | C63: 412 | D63: Үй-жайлар, ғимараттар мен құрылыстарды, беру қондырғыларын сатып алу | F63: 29135.239 | G63: Приобретение помещений, зданий, сооружений, передаточных устройств
A64: 2 | C64: 413 | D64: Көлік құралдарын сатып алу | F64: 1912.9346 | G64: Приобретение транспортных средств
A65: 2 | C65: 414 | D65: Машиналар, жабдықтар, өндірістік және шаруашылық мүккамал құралдарын сатып алу | F65: 3626.0786 | G65: Приобретение машин, оборудования, инструментов, производственного и хозяйственного инвентаря
A66: 2 | C66: 416 | D66: Матери алдық емес активтерді сатып алу | F66: 3.4843814 | G66: Приобретение нематериальных активов
A67: 2 | C67: 417 | D67: Биологиялық активтерді сатып алу | F67: 10.615 | G67: Приобретение биологических активов
A68: 2 | C68: 418 | D68: Мемлекеттік кәсіпорындарды материалдық-техникалық жарақтандыру | F68: 3363.4582 | G68: Материально-техническое оснащение государственных предприятий
A69: 2 | C69: 419 | D69: Өзге де негізгі құралдарды сатып алу | F69: 100.33645 | G69: Приобретение прочих основных средств
A70: L01 Категория расходов | B70: 420 | D70: Негізгі қаражатты күрделі жөндеу | F70: 24665.592 | G70: Капитальный ремонт основных средств
A71: 2 | B71: 420 | C71: 421 | D71: Жайларды, ғимараттарды, құрылыстарды, беру қондырғыларын күрделі жөндеу | F71: 7429.3952 | G71: Капитальный ремонт помещений, зданий, сооружений, передаточных устройств
A72: 2 | C72: 422 | D72: Жолдарды күрделі жөндеу | F72: 12380.394 | G72: Капитальный ремонт дорог
A73: 2 | C73: 423 | D73: Мемлекеттiк кәсiпорындардың жайларын, ғимараттарын, құрылыстарын күрделі жөндеу | F73: 4607.5309 | G73: Капитальный ремонт помещений, зданий, сооружений государственных предприятий
A74: 2 | C74: 429 | D74: Өзге де негізгі қаражатты күрделі жөндеу | F74: 248.27105 | G74: Капитальный ремонт прочих основных средств
A75: L01 Категория расходов | B75: 430 | D75: Дамуға бағытталған күрделі шығындар | F75: 144005.32 | G75: Капитальные затраты, направленные на развитие
A76: 2 | B76: 430 | C76: 431 | D76: Жаңа объектілерді салу және қолдағы объектілерді реконструкциялау | F76: 129890.17 | G76: Строительство новых объектов и реконструкция имеющихся объектов
A77: 2 | C77: 432 | D77: Жолдар салу | F77: 14115.155 | G77: Строительство дорог
A78: 3 | D78: Бюджеттік кредиттер | F78: 5137.4848 | G78: Бюджетные кредиты
A79: L01 Категория расходов | B79: 510 | D79: Ішкі бюджеттік кредиттер | F79: 5137.4848 | G79: Внутренние бюджетные кредиты
A80: 3 | B80: 510 | C80: 513 | D80: Мамандандырылған ұйымдарға бюджеттік кредиттер | F80: 5119.4 | G80: Бюджетные кредиты специализированным организациям
A81: 3 | C81: 519 | D81: Өзге де ішкі бюджеттік кредиттер | F81: 18.0848 | G81: Прочие внутренние бюджетные кредиты
A82: 4 | D82: Қаржы активтерін сатып алу | F82: 68529.968 | G82: Приобретение финансовых активов
A83: L01 Категория расходов | B83: 610 | D83: Қаржы активтерін сатып алу | F83: 68529.968 | G83: Приобретение финансовых активов
A84: 4 | B84: 610 | C84: 612 | D84: Квазимемлекеттік сектордың жарғылық капиталын қалыптастыру және ұлғайту | F84: 68529.968 | G84: Формирование и увеличение уставных капиталов субъектов квазигосударственного сектора
A85: 6 | D85: Мемлекеттік-жекешелік әріптестік жобалар бойынша мемлекеттік міндеттемелерді орындау | F85: 12907.636 | G85: Выполнение государственных обязательств по проектам государственно-частного партнерства
A86: L01 Категория расходов | B86: 810 | D86: Мемлекеттік концессиялық міндеттемелерді орындау | F86: 12907.636 | G86: Выполнение государственных концессионных обязательств
A87: 6 | B87: 810 | C87: 812 | D87: Мемлекеттік-жекешелік әріптестік жобалар бойынша инвестициялық шығындарды өтеу бойынша мемлекеттік міндеттемелерді орындау | F87: 2391.4769 | G87: Выполнение государственных обязательств по компенсации инвестиционных затрат по проектам государственно-частного партнерства
A88: 6 | C88: 813 | D88: Мемлекеттік-жекешелік әріптестік жобалар бойынша операциялық (пайдалану) шығындарды өтеу бойынша мемлекеттік міндеттемелерді орындау | F88: 5388.0392 | G88: Выполнение государственных обязательств по компенсации операционных (эксплуатационных) затрат по проектам государственно-частного п
A89: 6 | C89: 814 | D89: Мемлекеттік-жекешелік әріптестік объектісін басқаруды жүзеге асырғаны үшін сыйақы төлемі бойынша мемлекеттік міндеттемелерді орындау | F89: 1734.6812 | G89: Выполнение государственных обязательств по выплате вознаграждений за осуществление управления объектом государственно-частного парт
A90: 6 | C90: 815 | D90: Мемлекеттік-жекешелік әріптестік жобалар бойынша өзге де төлемдер бойынша мемлекеттік міндеттемелерді орындау | F90: 3393.4383 | G90: Выполнение государственных обязательств по прочим выплатам по проектам государственно-частного партнерства

Sheet табл 12
A1: 12-кесте | E1: Таблица 12
A2: ЖЕРГІЛІКТІ БЮДЖЕТТЕРДІҢ АТҚАРЫЛУЫ | E2: ИСПОЛНЕНИЕ МЕСТНЫХ БЮДЖЕТОВ
A3: (млн.теңге) | E3: (млн. тенге)
A5: Атауы | B5: 2022 ж. есеп/ 2022 г. отчет | C5: 2023 ж. есеп/ 2023 г. отчет | D5: 2024 ж. есеп/ 2024 г. отчет | F5: 2025 ж. қантар-ақпан есеп/январь-феврал отчет 2025 г. | G5: Наименование
D6: жылдық/ годовой | E6: қантар-ақпан/январь-феврал
A7: 1 | B7: 2 | C7: 3 | D7: 4 | E7: 5 | F7: 6 | G7: 7
A8: I. КІРІСТЕР | B8: 10976144 | C8: 13552443 | D8: 15346311 | E8: 2145952.2 | F8: 2446890.2 | G8: I. ДОХОДЫ#
A9: Салықтық түсімдер_x000D_ оның iшiнде: | B9: 4816486 | C9: 5999776.2 | D9: 7392707.2 | E9: 1243081.1 | F9: 1425241.3 | G9: Налоговые поступления,_x000D_ в том числе:
A10: корпорациялық табыс салығы | B10: 1041693.1 | C10: 1156101.6 | D10: 1560100.6 | E10: 200005.78 | F10: 232178.98 | G10: корпоративный подоходный налог
A11: жеке табыс салығы | B11: 1499712.4 | C11: 1992384.9 | D11: 2451640 | E11: 443245.31 | F11: 500641.49 | G11: индивидуальный подоходный налог
A12: әлеуметтік салық | B12: 1035129 | C12: 1321272.8 | D12: 1579329.4 | E12: 302605.48 | F12: 341000.69 | G12: социальный налог
A13: акциздер | B13: 603647.65 | C13: 678325.27 | D13: 719720.32 | E13: 105927.56 | F13: 120125.23 | G13: акцизы
A14: Салықтық емес түсімдер | B14: 146944.73 | C14: 205639.7 | D14: 429128.27 | E14: 41018.051 | F14: 82689.528 | G14: Неналоговые поступления
A15: Негізгі капиталды сатудан түсетін түсімдер | B15: 232986.54 | C15: 181373.04 | D15: 195509.62 | E15: 37950.566 | F15: 28754.845 | G15: Поступления от продажи основного капитала
A16: Трансферттердің түсімдері | B16: 5779727.2 | C16: 7165654.2 | D16: 7328965.7 | E16: 823902.49 | F16: 910204.59 | G16: Поступления трансфертов
A17: II. ШЫҒЫНДАР | B17: 10443228 | C17: 12885357 | D17: 15049842 | E17: 1396083.2 | F17: 1801677.4 | G17: II. ЗАТРАТЫ#
A18: 1. Жалпы сипаттағы мемлекеттiк қызметтер | B18: 373213.62 | C18: 498739.23 | D18: 626197.96 | E18: 68813.084 | F18: 76381.479 | G18: 1. Государственные услуги общего характера
A19: 2. Қорғаныс | B19: 46952.254 | C19: 74063.282 | D19: 146000.92 | E19: 3899.0503 | F19: 11508.895 | G19: 2. Оборона
... A44: Өтеу | B44: 328271.04 | C44: 229127.97 | D44: 296668.47 | E44: 57726.382 | F44: 8153.1042 | G44: Погашение
A45: Сыртқы | B45: -1516.9375 | C45: -1880.877 | D45: -868.7564 | E45: -868.7564 | F45: - | G45: Внешнее
A46: Түсімдер | B46: - | C46: - | D46: - | E46: - | F46: - | G46: Поступление
A47: Өтеу | B47: 1516.9375 | C47: 1880.877 | D47: 868.7564 | E47: 868.7564 | F47: - | G47: Погашение

Sheet табл 12.1
A1: 12.1-кесте | E1: Таблица 12.1
A2: АҚМОЛА ОБЛЫСЫ | E2: ИСПОЛНЕНИЕ БЮДЖЕТА
A3: БЮДЖЕТІНІҢ АТҚАРЫЛУЫ | E3: АКМОЛИНСКАЯ ОБЛАСТЬ
A4: (млн.теңге) | E4: (млн. тенге)
A5: Атауы | B5: 2022 ж. есеп/ 2022 г. отчет | C5: 2023 ж. есеп/ 2023 г. отчет | D5: 2024 ж. есеп/ 2024 г. отчет | F5: 2025 ж. қантар-ақпан есеп/январь-феврал отчет 2025 г. | G5: Наименование
D6: жылдық/ годовой | E6: қантар-ақпан/январь-феврал
A7: 1 | B7: 2 | C7: 3 | D7: 4 | E7: 5 | F7: 6 | G7: 7
A8: I. КІРІСТЕР | B8: 479342.52 | C8: 630074.59 | D8: 707086.76 | E8: 94620.2 | F8: 93835.404 | G8: I. ДОХОДЫ
A9: Салықтық түсімдер_x000D_ оның iшiнде: | B9: 131206.29 | C9: 166838.2 | D9: 193200.14 | E9: 32705.487 | F9: 35114.466 | G9: Налоговые поступления,_x000D_ в том числе:
A10: корпорациялық табыс салығы | B10: 18604.661 | C10: 26898.106 | D10: 29578.991 | E10: 4259.1308 | F10: 3984.2212 | G10: корпоративный подоходный налог
A11: жеке табыс салығы | B11: 43758.869 | C11: 57696.794 | D11: 70347.91 | E11: 12141.49 | F11: 13423.79 | G11: индивидуальный подоходный налог
A12: әлеуметтік салық | B12: 27495.02 | C12: 36673.221 | D12: 43624.91 | E12: 7731.8365 | F12: 8609.3857 | G12: социальный налог
A13: акциздер | B13: 20076.53 | C13: 18706.909 | D13: 21122.258 | E13: 2482.1015 | F13: 3576.5699 | G13: акцизы
A14: Салықтық емес түсімдер | B14: 6880.8375 | C14: 10031.309 | D14: 17228.574 | E14: 2655.2999 | F14: 1143.6973 | G14: Неналоговые поступления
A15: Негізгі капиталды сатудан түсетін түсімдер | B15: 4360.0479 | C15: 4230.2271 | D15: 6929.2453 | E15: 611.78042 | F15: 1344.1282 | G15: Поступления от продажи основного капитала
A16: Трансферттердің түсімдері | B16: 336895.34 | C16: 448974.85 | D16: 489728.81 | E16: 58647.633 | F16: 56233.112 | G16: Поступления трансфертов
A17: II. ШЫҒЫНДАР | B17: 476797.2 | C17: 629557.51 | D17: 718203.43 | E17: 69338.495 | F17: 80806.061 | G17: II. ЗАТРАТЫ
A18: 1. Жалпы сипаттағы мемлекеттiк қызметтер | B18: 20688.527 | C18: 34057.909 | D18: 38754.396 | E18: 5050.6615 | F18: 5397.7943 | G18: 1. Государственные услуги общего характера
A19: 2. Қорғаныс | B19: 8863.386 | C19: 7702.9187 | D19: 8416.1057 | E19: 384.78108 | F19: 1727.8711 | G19: 2. Оборона
... A36: IV. ҚАРЖЫ АКТИВТЕРІМЕН ОПЕРАЦИЯЛАР БОЙЫНША САЛЬДО - ҚАРЖЫ АК | B36: 826.73116 | C36: -35.215556 | D36: 757.86449 | E36: -3.488566 | F36: -8.153623 | G36: IV. САЛЬДО ПО ОПЕРАЦИЯМ С ФИНАНСОВЫМИ АКТИВАМИ
A37: Қаржылық активтерді сатып алу | B37: 1153.9453 | C37: 18.642348 | D37: 835.0705 | F37: 0 | G37: Приобретение финансовых активов
A38: Мемлекеттің қаржы активтерін сатудан түсетін түсімдер | B38: 327.21411 | C38: 53.857904 | D38: 77.206015 | E38: 3.488566 | F38: 8.153623 | G38: Поступления от продажи финансовых активов государства
A39: V. БЮДЖЕТ ТАПШЫЛЫҒЫ (ПРОФИЦИТІ) | B39: -1730.8731 | C39: -13984.598 | D39: -12519.931 | E39: 25575.882 | F39: 12950.626 | G39: V. ДЕФИЦИТ (ПРОФИЦИТ) БЮДЖЕТА
A41: VII. БЮДЖЕТТІҢ ТАПШЫЛЫҒЫН ҚАРЖЫЛАНДЫРУ (ПРОФИЦИТТІ ПАЙДАЛАНУ | B41: 1730.8731 | C41: 13984.598 | D41: -12519.931 | E41: -25575.882 | F41: -12950.626 | G41: VII. ФИНАНСИРОВАНИЕ ДЕФИЦИТА (ИСПОЛЬЗОВАНИЕ ПРОФИЦИТА) БЮДЖЕТА
A42: Ішкі | B42: -4686.7639 | C42: -28337.013 | D42: 15222.376 | E42: -306791.91 | F42: -12950.626 | G42: Внутреннее
A43: Түсімдер | B43: 2463.8315 | C43: -22220.166 | D43: 26195.917 | E43: -306781.13 | F43: -12950.626 | G43: Поступление
A44: Өтеу | B44: 7150.5953 | C44: 6116.8467 | D44: 10973.542 | E44: 10.788471 | F44: - | G44: Погашение
A45: Сыртқы | B45: - | C45: - | D45: - | E45: - | F45: - | G45: Внешнее
A46: Түсімдер | B46: - | C46: - | D46: - | E46: - | F46: - | G46: Поступление
A47: Өтеу | B47: - | C47: - | D47: - | E47: - | F47: - | G47: Погашение

Sheet табл 12.2
A1: 12.2-кесте | E1: Таблица 12.2
A2: АҚТОБЕ ОБЛЫСЫ | E2: ИСПОЛНЕНИЕ БЮДЖЕТА
A3: БЮДЖЕТІНІҢ АТҚАРЫЛУЫ | E3: АКТЮБИНСКАЯ ОБЛАСТЬ
A4: (млн.теңге) | E4: (млн. тенге)
A5: Атауы | B5: 2022 ж. есеп/ 2022 г. отчет | C5: 2023 ж. есеп/ 2023 г. отчет | D5: 2024 ж. есеп/ 2024 г. отчет | F5: 2025 ж. қантар-ақпан есеп/январь-феврал отчет 2025 г. | G5: Наименование
D6: жылдық/ годовой | E6: қантар-ақпан/январь-феврал
A7: 1 | B7: 2 | C7: 3 | D7: 4 | E7: 5 | F7: 6 | G7: 7
A8: I. КІРІСТЕР | B8: 439365.9 | C8: 601085.02 | D8: 676122.67 | E8: 85849.016 | F8: 87507.931 | G8: I. ДОХОДЫ
A9: Салықтық түсімдер_x000D_ оның iшiнде: | B9: 169788.03 | C9: 217147.69 | D9: 258870.07 | E9: 46871.286 | F9: 52204.973 | G9: Налоговые поступления,_x000D_ в том числе:
A10: корпорациялық табыс салығы | B10: 22794.56 | C10: 27092.378 | D10: 35280.087 | E10: 4096.0307 | F10: 4944.5411 | G10: корпоративный подоходный налог
A11: жеке табыс салығы | B11: 53618.784 | C11: 71801.508 | D11: 89575.631 | E11: 17031.768 | F11: 19676.794 | G11: индивидуальный подоходный налог
A12: әлеуметтік салық | B12: 39432.497 | C12: 50661.538 | D12: 60866.559 | E12: 12331.449 | F12: 13301.27 | G12: социальный налог
A13: акциздер | B13: 11907.391 | C13: 12786.271 | D13: 18850.711 | E13: 2236.5916 | F13: 3020.5517 | G13: акцизы
A14: Салықтық емес түсімдер | B14: 9083.1145 | C14: 11013.336 | D14: 22063.261 | E14: 935.69649 | F14: 1575.0982 | G14: Неналоговые поступления
A15: Негізгі капиталды сатудан түсетін түсімдер | B15: 6278.8853 | C15: 5032.1948 | D15: 6404.1867 | E15: 344.86707 | F15: 520.94265 | G15: Поступления от продажи основного капитала
A16: Трансферттердің түсімдері | B16: 254215.87 | C16: 367891.79 | D16: 388785.15 | E16: 37697.167 | F16: 33206.917 | G16: Поступления трансфертов
A17: II. ШЫҒЫНДАР | B17: 430148.05 | C17: 572439.64 | D17: 692559.6 | E17: 56656.766 | F17: 64571.037 | G17: II. ЗАТРАТЫ
A18: 1. Жалпы сипаттағы мемлекеттiк қызметтер | B18: 18351.498 | C18: 38185.996 | D18: 53420.173 | E18: 3121.0792 | F18: 5075.5872 | G18: 1. Государственные услуги общего характера
A19: 2. Қорғаныс | B19: 2054.6106 | C19: 3456.9188 | D19: 6083.1211 | E19: 231.19473 | F19: 513.70749 | G19: 2. Оборона
... A35: Бюджеттік кредиттерді өтеу | B35: 3571.8238 | C35: 3030.0662 | D35: 9178.9425 | E35: 383.7114 | F35: 1384.6325 | G35: Погашение бюджетных кредитов
A36: IV. ҚАРЖЫ АКТИВТЕРІМЕН ОПЕРАЦИЯЛАР БОЙЫНША САЛЬДО - ҚАРЖЫ АК | B36: 170.24666 | C36: 102 | D36: 194.7798 | F36: 114.475 | G36: IV. САЛЬДО ПО ОПЕРАЦИЯМ С ФИНАНСОВЫМИ АКТИВАМИ
A37: Қаржылық активтерді сатып алу | B37: 168.3192 | C37: 102 | D37: 194.7798 | F37: 114.475 | G37: Приобретение финансовых активов
A38: Мемлекеттің қаржы активтерін сатудан түсетін түсімдер | B38: -1.927458 | G38: Поступления от продажи финансовых активов государства
A39: V. БЮДЖЕТ ТАПШЫЛЫҒЫ (ПРОФИЦИТІ) | B39: 3321.1958 | C39: 11136.075 | D39: -17543.714 | E39: 29575.962 | F39: 24207.051 | G39: V. ДЕФИЦИТ (ПРОФИЦИТ) БЮДЖЕТА
A41: VII. БЮДЖЕТТІҢ ТАПШЫЛЫҒЫН ҚАРЖЫЛАНДЫРУ (ПРОФИЦИТТІ ПАЙДАЛАНУ | B41: -3321.1958 | C41: -11136.075 | D41: -17543.714 | E41: -29575.962 | F41: -24207.051 | G41: VII. ФИНАНСИРОВАНИЕ ДЕФИЦИТА (ИСПОЛЬЗОВАНИЕ ПРОФИЦИТА) БЮДЖЕТА
A42: Ішкі | B42: -34443.176 | C42: -312074.58 | D42: -6027.6511 | E42: -354907.44 | F42: -24207.051 | G42: Внутреннее
A43: Түсімдер | B43: -23232.618 | C43: -301203.36 | D43: 7654.2188 | E43: -354907.07 | F43: -24183.327 | G43: Поступление
A44: Өтеу | B44: 11210.558 | C44: 10871.218 | D44: 13681.87 | E44: 0.3729 | F44: 23.7241 | G44: Погашение
A45: Сыртқы | B45: - | C45: - | D45: - | E45: - | F45: - | G45: Внешнее
A46: Түсімдер | B46: - | C46: - | D46: - | E46: - | F46: - | G46: Поступление
A47: Өтеу | B47: - | C47: - | D47: - | E47: - | F47: - | G47: Погашение

Sheet табл 12.3
A1: 12.3-кесте | E1: Таблица 12.3
A2: АЛМАТЫ ОБЛЫСЫ | E2: ИСПОЛНЕНИЕ БЮДЖЕТА
A3: БЮДЖЕТІНІҢ АТҚАРЫЛУЫ | E3: АЛМАТИНСКАЯ ОБЛАСТЬ
A4: (млн.теңге) | E4: (млн. тенге)
A5: Атауы | B5: 2022 ж. есеп/ 2022 г. отчет | C5: 2023 ж. есеп/ 2023 г. отчет | D5: 2024 ж. есеп/ 2024 г. отчет | F5: 2025 ж. қантар-ақпан есеп/январь-феврал отчет 2025 г. | G5: Наименование
D6: жылдық/ годовой | E6: қантар-ақпан/январь-феврал
A7: 1 | B7: 2 | C7: 3 | D7: 4 | E7: 5 | F7: 6 | G7: 7
A8: I. КІРІСТЕР | B8: 727110.2 | C8: 755699.04 | D8: 832469.88 | E8: 135521.3 | F8: 128892.52 | G8: I. ДОХОДЫ
A9: Салықтық түсімдер_x000D_ оның iшiнде: | B9: 420356.25 | C9: 388446.56 | D9: 491276.75 | E9: 88974.751 | F9: 85715.77 | G9: Налоговые поступления,_x000D_ в том числе:
A10: корпорациялық табыс салығы | B10: 76082.806 | C10: 34158.596 | D10: 57113.634 | E10: 7286.4129 | F10: 8721.5277 | G10: корпоративный подоходный налог
A11: жеке табыс салығы | B11: 79789.776 | C11: 85030.922 | D11: 118580.99 | E11: 35740.205 | F11: 20925.835 | G11: индивидуальный подоходный налог
A12: әлеуметтік салық | B12: 38557.426 | C12: 40395.425 | D12: 54091.398 | E12: 10469.526 | F12: 12103.884 | G12: социальный налог
A13: акциздер | B13: 192892.72 | C13: 199121.45 | D13: 226071.95 | E13: 29386.586 | F13: 37088.385 | G13: акцизы
A14: Салықтық емес түсімдер | B14: 6533.346 | C14: 5738.8874 | D14: 20653.374 | E14: 1648.5737 | F14: 2297.8549 | G14: Неналоговые поступления
A15: Негізгі капиталды сатудан түсетін түсімдер | B15: 7164.6916 | C15: 6153.3465 | D15: 8607.4865 | E15: 942.14498 | F15: 1377.7384 | G15: Поступления от продажи основного капитала
A16: Трансферттердің түсімдері | B16: 293055.91 | C16: 355360.25 | D16: 311932.27 | E16: 43955.831 | F16: 39501.159 | G16: Поступления трансфертов
A17: II. ШЫҒЫНДАР | B17: 709629.21 | C17: 752774.03 | D17: 838922.5 | E17: 89896.597 | F17: 97647.682 | G17: II. ЗАТРАТЫ
A18: 1. Жалпы сипаттағы мемлекеттiк қызметтер | B18: 31480.892 | C18: 26808.017 | D18: 24546.153 | E18: 3034.3648 | F18: 3277.0949 | G18: 1. Государственные услуги общего характера
A19: 2. Қорғаныс | B19: 1866.7625 | C19: 2158.7445 | D19: 4038.0936 | E19: 155.98447 | F19: 853.68374 | G19: 2. Оборона
... A37: Қаржылық активтерді сатып алу | B37: 3727.148 | C37: 7439.182 | D37: 8291.7479 | E37: 1341.557 | F37: 2500 | G37: Приобретение финансовых активов
A38: Мемлекеттің қаржы активтерін сатудан түсетін түсімдер | C38: 5.1049999 | G38: Поступления от продажи финансовых активов государства
A39: V. БЮДЖЕТ ТАПШЫЛЫҒЫ (ПРОФИЦИТІ) | B39: 14886.511 | C39: -32271.614 | D39: -19347.425 | E39: 44835.161 | F39: 28945.888 | G39: V. ДЕФИЦИТ (ПРОФИЦИТ) БЮДЖЕТА
A41: VII. БЮДЖЕТТІҢ ТАПШЫЛЫҒЫН ҚАРЖЫЛАНДЫРУ (ПРОФИЦИТТІ ПАЙДАЛАНУ | B41: -14886.511 | C41: 32271.614 | D41: -19347.425 | E41: -44835.161 | F41: -28945.888 | G41: VII. ФИНАНСИРОВАНИЕ ДЕФИЦИТА (ИСПОЛЬЗОВАНИЕ ПРОФИЦИТА) БЮДЖЕТА
A42: Ішкі | B42: -164838.76 | C42: 76147.561 | D42: 3774.7945 | E42: -467561.36 | F42: -28945.888 | G42: Внутреннее
A43: Түсімдер | B43: -153888.28 | C43: 80801.049 | D43: 15303.941 | E43: -461155.86 | F43: -27899.11 | G43: Поступление
A44: Өтеу | B44: 10950.477 | C44: 4653.4875 | D44: 11529.146 | E44: 6405.5064 | F44: 1046.778 | G44: Погашение
A45: Сыртқы | B45: - | C45: - | D45: - | E45: - | F45: - | G45: Внешнее
A46: Түсімдер | B46: - | C46: - | D46: - | E46: - | F46: - | G46: Поступление
A47: Өтеу | B47: - | C47: - | D47: - | E47: - | F47: - | G47: Погашение

Sheet табл 12.4
A1: 12.4-кесте | E1: Таблица 12.4
A2: АТЫРАУ ОБЛЫСЫ | E2: ИСПОЛНЕНИЕ БЮДЖЕТА
A3: БЮДЖЕТІНІҢ АТҚАРЫЛУЫ | E3: АТЫРАУСКАЯ ОБЛАСТЬ
A4: (млн.теңге) | E4: (млн. тенге)
A5: Атауы | B5: 2022 ж. есеп/ 2022 г. отчет | C5: 2023 ж. есеп/ 2023 г. отчет | D5: 2024 ж. есеп/ 2024 г. отчет | F5: 2025 ж. қантар-ақпан есеп/январь-феврал отчет 2025 г. | G5: Наименование
D6: жылдық/ годовой | E6: қантар-ақпан/январь-феврал
A7: 1 | B7: 2 | C7: 3 | D7: 4 | E7: 5 | F7: 6 | G7: 7
A8: I. КІРІСТЕР | B8: 681966.2 | C8: 733369.76 | D8: 898777.25 | E8: 150829.09 | F8: 184811.63 | G8: I. ДОХОДЫ
A9: Салықтық түсімдер_x000D_ оның iшiнде: | B9: 541393.16 | C9: 643622.37 | D9: 783514.64 | E9: 144781.93 | F9: 178980.19 | G9: Налоговые поступления,_x000D_ в том числе:
A10: корпорациялық табыс салығы | B10: 60789.753 | C10: 74074.302 | D10: 60322.062 | E10: 12548.839 | F10: 9811.6173 | G10: корпоративный подоходный налог
A11: жеке табыс салығы | B11: 160885.91 | C11: 176724.85 | D11: 170721.06 | E11: 30889.964 | F11: 31690.599 | G11: индивидуальный подоходный налог
A12: әлеуметтік салық | B12: 142985.12 | C12: 161262.4 | D12: 161395.59 | E12: 31850.304 | F12: 34369.268 | G12: социальный налог
A13: акциздер | B13: 82308.586 | C13: 120507.84 | D13: 122879.83 | E13: 18702.72 | F13: 23657.638 | G13: акцизы
A14: Салықтық емес түсімдер | B14: 8906.1194 | C14: 16168.04 | D14: 32940.563 | E14: 1266.4249 | F14: 1466.2549 | G14: Неналоговые поступления
A15: Негізгі капиталды сатудан түсетін түсімдер | B15: 7661.9213 | C15: 2333.9873 | D15: 2568.7507 | E15: 371.46106 | F15: 325.09477 | G15: Поступления от продажи основного капитала
A16: Трансферттердің түсімдері | B16: 124005.01 | C16: 71245.364 | D16: 79753.298 | E16: 4409.272 | F16: 4040.091 | G16: Поступления трансфертов
A17: II. ШЫҒЫНДАР | B17: 647544.75 | C17: 670273.07 | D17: 939255.77 | E17: 76986.92 | F17: 92681.954 | G17: II. ЗАТРАТЫ
A18: 1. Жалпы сипаттағы мемлекеттiк қызметтер | B18: 14547.242 | C18: 18263.609 | D18: 30985.339 | E18: 2064.2208 | F18: 3730.929 | G18: 1. Государственные услуги общего характера
A19: 2. Қорғаныс | B19: 2560.754 | C19: 3723.3195 | D19: 60454.116 | E19: 198.89099 | F19: 3339.4303 | G19: 2. Оборона
... A36: IV. ҚАРЖЫ АКТИВТЕРІМЕН ОПЕРАЦИЯЛАР БОЙЫНША САЛЬДО - ҚАРЖЫ АК | B36: 1901.2219 | C36: 9896.5255 | D36: 8503.6076 | E36: -6.668679 | F36: 11998.981 | G36: IV. САЛЬДО ПО ОПЕРАЦИЯМ С ФИНАНСОВЫМИ АКТИВАМИ
A37: Қаржылық активтерді сатып алу | B37: 1937.796 | C37: 9953.961 | D37: 8545.6732 | F37: 12000 | G37: Приобретение финансовых активов
A38: Мемлекеттің қаржы активтерін сатудан түсетін түсімдер | B38: 36.5741 | C38: 57.435537 | D38: 42.065678 | E38: 6.668679 | F38: 1.019055 | G38: Поступления от продажи финансовых активов государства
A39: V. БЮДЖЕТ ТАПШЫЛЫҒЫ (ПРОФИЦИТІ) | B39: 29253.003 | C39: 46715.894 | D39: -57025.507 | E39: 74347.222 | F39: 80190.279 | G39: V. ДЕФИЦИТ (ПРОФИЦИТ) БЮДЖЕТА
A41: VII. БЮДЖЕТТІҢ ТАПШЫЛЫҒЫН ҚАРЖЫЛАНДЫРУ (ПРОФИЦИТТІ ПАЙДАЛАНУ | B41: -29253.003 | C41: -46715.894 | D41: -57025.507 | E41: -74347.222 | F41: -80190.279 | G41: VII. ФИНАНСИРОВАНИЕ ДЕФИЦИТА (ИСПОЛЬЗОВАНИЕ ПРОФИЦИТА) БЮДЖЕТА
A42: Ішкі | B42: -331962.85 | C42: -471715.14 | D42: 643064.31 | E42: -892166.66 | F42: -80190.279 | G42: Внутреннее
A43: Түсімдер | B43: -319407 | C43: -461025.59 | D43: 652859.24 | E43: -892166.66 | F43: -79854.857 | G43: Поступление
A44: Өтеу | B44: 12555.846 | C44: 10689.549 | D44: 9794.9234 | E44: - | F44: 335.422 | G44: Погашение
A45: Сыртқы | B45: - | C45: - | D45: - | E45: - | F45: - | G45: Внешнее
A46: Түсімдер | B46: - | C46: - | D46: - | E46: - | F46: - | G46: Поступление
A47: Өтеу | B47: - | C47: - | D47: - | E47: - | F47: - | G47: Погашение

Sheet табл 12.5
A1: 12.5-кесте | E1: Таблица 12.5
A2: ШЫҒЫС-ҚАЗАҚСТАН ОБЛЫСЫ | E2: ИСПОЛНЕНИЕ БЮДЖЕТА
A3: БЮДЖЕТІНІҢ АТҚАРЫЛУЫ | E3: ВОСТ-КАЗАХСТАНСКАЯ ОБЛАСТЬ
A4: (млн.теңге) | E4: (млн. тенге)
A5: Атауы | B5: 2022 ж. есеп/ 2022 г. отчет | C5: 2023 ж. есеп/ 2023 г. отчет | D5: 2024 ж. есеп/ 2024 г. отчет | F5: 2025 ж. қантар-ақпан есеп/январь-феврал отчет 2025 г. | G5: Наименование
D6: жылдық/ годовой | E6: қантар-ақпан/январь-феврал
A7: 1 | B7: 2 | C7: 3 | D7: 4 | E7: 5 | F7: 6 | G7: 7
A8: I. КІРІСТЕР | B8: 562747.34 | C8: 485874.5 | D8: 554729.11 | E8: 76602.301 | F8: 73816.984 | G8: I. ДОХОДЫ
A9: Салықтық түсімдер_x000D_ оның iшiнде: | B9: 174505.46 | C9: 164390.14 | D9: 205394.71 | E9: 34077.639 | F9: 37516.528 | G9: Налоговые поступления,_x000D_ в том числе:
A10: корпорациялық табыс салығы | B10: 25605.38 | C10: 31322.068 | D10: 43204.659 | E10: 5125.526 | F10: 7778.9352 | G10: корпоративный подоходный налог
A11: жеке табыс салығы | B11: 65842.061 | C11: 63550.133 | D11: 79837.166 | E11: 14209.699 | F11: 15033.467 | G11: индивидуальный подоходный налог
A12: әлеуметтік салық | B12: 48405.527 | C12: 44809.692 | D12: 53880.619 | E12: 9951.6176 | F12: 9895.5226 | G12: социальный налог
A13: акциздер | B13: 248.72341 | C13: 170.14397 | D13: 180.05535 | E13: 26.512398 | F13: 28.463308 | G13: акцизы
A14: Салықтық емес түсімдер | B14: 7127.6867 | C14: 5257.0033 | D14: 6223.1357 | E14: 847.8443 | F14: 813.14117 | G14: Неналоговые поступления
A15: Негізгі капиталды сатудан түсетін түсімдер | B15: 19509.245 | C15: 6863.7925 | D15: 6662.0791 | E15: 236.03452 | F15: 308.81062 | G15: Поступления от продажи основного капитала
A16: Трансферттердің түсімдері | B16: 361604.95 | C16: 309363.57 | D16: 336449.19 | E16: 41440.783 | F16: 35178.503 | G16: Поступления трансфертов
A17: II. ШЫҒЫНДАР | B17: 439783.11 | C17: 474312.87 | D17: 547229.27 | E17: 53495.849 | F17: 59356.767 | G17: II. ЗАТРАТЫ
A18: 1. Жалпы сипаттағы мемлекеттiк қызметтер | B18: 18081.748 | C18: 28901.504 | D18: 34187.037 | E18: 3975.061 | F18: 3825.7732 | G18: 1. Государственные услуги общего характера
A19: 2. Қорғаныс | B19: 1524.8654 | C19: 2283.3219 | D19: 4437.5789 | E19: 102.87892 | F19: 227.76649 | G19: 2. Оборона
... A44: Өтеу | B44: 13287.252 | C44: 8649.0233 | D44: 17926.718 | E44: 116.33521 | F44: 1544.5987 | G44: Погашение
A45: Сыртқы | B45: - | C45: - | D45: - | E45: - | F45: - | G45: Внешнее
A46: Түсімдер | B46: - | C46: - | D46: - | E46: - | F46: - | G46: Поступление
A47: Өтеу | B47: - | C47: - | D47: - | E47: - | F47: - | G47: Погашение

Sheet табл 12.6
A1: 12.6-кесте | E1: Таблица 12.6
A2: ЖАМБЫЛ ОБЛЫСЫ | E2: ИСПОЛНЕНИЕ БЮДЖЕТА
A3: БЮДЖЕТІНІҢ АТҚАРЫЛУЫ | E3: ЖАМБЫЛСКАЯ ОБЛАСТЬ
A4: (млн.теңге) | E4: (млн. тенге)
A5: Атауы | B5: 2022 ж. есеп/ 2022 г. отчет | C5: 2023 ж. есеп/ 2023 г. отчет | D5: 2024 ж. есеп/ 2024 г. отчет | F5: 2025 ж. қантар-ақпан есеп/январь-феврал отчет 2025 г. | G5: Наименование
D6: жылдық/ годовой | E6: қантар-ақпан/январь-феврал
A7: 1 | B7: 2 | C7: 3 | D7: 4 | E7: 5 | F7: 6 | G7: 7
A8: I. КІРІСТЕР | B8: 557710.35 | C8: 647650.25 | D8: 701413.92 | E8: 90677.07 | F8: 110193.38 | G8: I. ДОХОДЫ
A9: Салықтық түсімдер_x000D_ оның iшiнде: | B9: 101009.01 | C9: 128310.79 | D9: 152453.16 | E9: 26903.057 | F9: 31128.62 | G9: Налоговые поступления,_x000D_ в том числе:
A10: корпорациялық табыс салығы | B10: 10857.684 | C10: 11965.332 | D10: 17174.038 | E10: 2575.2784 | F10: 2973.1588 | G10: корпоративный подоходный налог
A11: жеке табыс салығы | B11: 35472.602 | C11: 46482.26 | D11: 59716.78 | E11: 9895.1132 | F11: 12329.997 | G11: индивидуальный подоходный налог
A12: әлеуметтік салық | B12: 26573.441 | C12: 33811.337 | D12: 39604.881 | E12: 7027.7507 | F12: 8169.9983 | G12: социальный налог
A13: акциздер | B13: 3767.0016 | C13: 3309.4974 | D13: 3204.864 | E13: 701.96058 | F13: 356.94576 | G13: акцизы
A14: Салықтық емес түсімдер | B14: 6391.289 | C14: 11502.799 | D14: 15521.033 | E14: 1529.7126 | F14: 1567.3532 | G14: Неналоговые поступления
A15: Негізгі капиталды сатудан түсетін түсімдер | B15: 11956.832 | C15: 10922.824 | D15: 11602.388 | E15: 2478.2824 | F15: 2424.4299 | G15: Поступления от продажи основного капитала
A16: Трансферттердің түсімдері | B16: 438353.22 | C16: 496913.84 | D16: 521837.33 | E16: 59766.018 | F16: 75072.978 | G16: Поступления трансфертов
A17: II. ШЫҒЫНДАР | B17: 557540.98 | C17: 630861.77 | D17: 727944.33 | E17: 74227.861 | F17: 97654.944 | G17: II. ЗАТРАТЫ
A18: 1. Жалпы сипаттағы мемлекеттiк қызметтер | B18: 19965.486 | C18: 27013.526 | D18: 28305.006 | E18: 3640.9759 | F18: 3939.1955 | G18: 1. Государственные услуги общего характера
A19: 2. Қорғаныс | B19: 1238.2558 | C19: 1863.5947 | D19: 2279.1128 | E19: 69.42174 | F19: 571.08265 | G19: 2. Оборона
... A37: Қаржылық активтерді сатып алу | B37: 1540.566 | C37: 1147.061 | D37: 1540.7038 | E37: 156.6 | F37: 50 | G37: Приобретение финансовых активов
A38: Мемлекеттің қаржы активтерін сатудан түсетін түсімдер | B38: 0.49544 | G38: Поступления от продажи финансовых активов государства
A39: V. БЮДЖЕТ ТАПШЫЛЫҒЫ (ПРОФИЦИТІ) | B39: -7805.1251 | C39: -10370.017 | D39: -40655.204 | E39: 16510.199 | F39: 12845.793 | G39: V. ДЕФИЦИТ (ПРОФИЦИТ) БЮДЖЕТА
A41: VII. БЮДЖЕТТІҢ ТАПШЫЛЫҒЫН ҚАРЖЫЛАНДЫРУ (ПРОФИЦИТТІ ПАЙДАЛАНУ | B41: 7805.1251 | C41: 10370.017 | D41: -40655.204 | E41: -16510.199 | F41: -12845.793 | G41: VII. ФИНАНСИРОВАНИЕ ДЕФИЦИТА (ИСПОЛЬЗОВАНИЕ ПРОФИЦИТА) БЮДЖЕТА
A42: Ішкі | B42: -27361.525 | C42: -97791.222 | D42: 241677.71 | E42: -138938.68 | F42: -12845.793 | G42: Внутреннее
A43: Түсімдер | B43: -12063.136 | C43: -78965.845 | D43: 269955.92 | E43: -133558.34 | F43: -12616.407 | G43: Поступление
A44: Өтеу | B44: 15298.389 | C44: 18825.377 | D44: 28278.215 | E44: 5380.3374 | F44: 229.38636 | G44: Погашение
A45: Сыртқы | B45: - | C45: - | D45: - | E45: - | F45: - | G45: Внешнее
A46: Түсімдер | B46: - | C46: - | D46: - | E46: - | F46: - | G46: Поступление
A47: Өтеу | B47: - | C47: - | D47: - | E47: - | F47: - | G47: Погашение

Sheet табл 12.7
A1: 12.7-кесте | E1: Таблица 12.7
A2: БАТЫС ҚАЗАҚСТАН ОБЛЫСЫ | E2: ИСПОЛНЕНИЕ БЮДЖЕТА
A3: БЮДЖЕТІНІҢ АТҚАРЫЛУЫ | E3: ЗАП-КАЗАХСТАНСКАЯ ОБЛАСТЬ
A4: (млн.теңге) | E4: (млн. тенге)
A5: Атауы | B5: 2022 ж. есеп/ 2022 г. отчет | C5: 2023 ж. есеп/ 2023 г. отчет | D5: 2024 ж. есеп/ 2024 г. отчет | F5: 2025 ж. қантар-ақпан есеп/январь-феврал отчет 2025 г. | G5: Наименование
D6: жылдық/ годовой | E6: қантар-ақпан/январь-феврал
A7: 1 | B7: 2 | C7: 3 | D7: 4 | E7: 5 | F7: 6 | G7: 7
A8: I. КІРІСТЕР | B8: 355921.06 | C8: 453047.34 | D8: 532073.16 | E8: 71358.499 | F8: 72556.47 | G8: I. ДОХОДЫ
A9: Салықтық түсімдер_x000D_ оның iшiнде: | B9: 136040.88 | C9: 176101.88 | D9: 197849.71 | E9: 36410.929 | F9: 40641.627 | G9: Налоговые поступления,_x000D_ в том числе:
A10: корпорациялық табыс салығы | B10: 17876.508 | C10: 23819.677 | D10: 29745.342 | E10: 4042.4814 | F10: 4632.2132 | G10: корпоративный подоходный налог
A11: жеке табыс салығы | B11: 46152.443 | C11: 60446.744 | D11: 71402.108 | E11: 12873.723 | F11: 14375.772 | G11: индивидуальный подоходный налог
A12: әлеуметтік салық | B12: 58464.761 | C12: 65791.879 | D12: 73256 | E12: 15208.292 | F12: 16805.623 | G12: социальный налог
A13: акциздер | B13: 1784.5321 | C13: 4116.8709 | D13: 2316.8132 | E13: 615.60515 | F13: 176.80767 | G13: акцизы
A14: Салықтық емес түсімдер | B14: 4223.8187 | C14: 5184.1237 | D14: 6731.9796 | E14: 1145.0465 | F14: 1180.6572 | G14: Неналоговые поступления
A15: Негізгі капиталды сатудан түсетін түсімдер | B15: 7882.4974 | C15: 8859.4531 | D15: 6142.5363 | E15: 1797.6448 | F15: 2750.32 | G15: Поступления от продажи основного капитала
A16: Трансферттердің түсімдері | B16: 207773.86 | C16: 262901.88 | D16: 321348.93 | E16: 32004.879 | F16: 27983.866 | G16: Поступления трансфертов
A17: II. ШЫҒЫНДАР | B17: 340221.25 | C17: 445141.74 | D17: 559071.76 | E17: 59490.634 | F17: 57640.094 | G17: II. ЗАТРАТЫ
A18: 1. Жалпы сипаттағы мемлекеттiк қызметтер | B18: 16648.76 | C18: 23456.157 | D18: 42350.09 | E18: 4961.6581 | F18: 3788.3373 | G18: 1. Государственные услуги общего характера
A19: 2. Қорғаныс | B19: 1120.9243 | C19: 2958.5653 | D19: 3981.6445 | E19: 59.472368 | F19: 67.92796 | G19: 2. Оборона
... A35: Бюджеттік кредиттерді өтеу | B35: 5275.0286 | C35: 3136.1149 | D35: 5811.1896 | E35: 366.22595 | F35: 1067.3689 | G35: Погашение бюджетных кредитов
A36: IV. ҚАРЖЫ АКТИВТЕРІМЕН ОПЕРАЦИЯЛАР БОЙЫНША САЛЬДО - ҚАРЖЫ АК | C36: 12.583 | D36: 2001.398 | E36: 0 | G36: IV. САЛЬДО ПО ОПЕРАЦИЯМ С ФИНАНСОВЫМИ АКТИВАМИ
A37: Қаржылық активтерді сатып алу | C37: 12.583 | D37: 2001.398 | E37: 0 | G37: Приобретение финансовых активов
A38: V. БЮДЖЕТ ТАПШЫЛЫҒЫ (ПРОФИЦИТІ) | B38: 14658.841 | C38: -5596.7209 | D38: -37075.479 | E38: 11969.232 | F38: 15983.745 | G38: V. ДЕФИЦИТ (ПРОФИЦИТ) БЮДЖЕТА
A40: VII. БЮДЖЕТТІҢ ТАПШЫЛЫҒЫН ҚАРЖЫЛАНДЫРУ (ПРОФИЦИТТІ ПАЙДАЛАНУ | B40: -14658.841 | C40: 5596.7209 | D40: -37075.479 | E40: -11969.232 | F40: -15983.745 | G40: VII. ФИНАНСИРОВАНИЕ ДЕФИЦИТА (ИСПОЛЬЗОВАНИЕ ПРОФИЦИТА) БЮДЖЕТА
A41: Ішкі | B41: -80854.731 | C41: -126662.63 | D41: 232779.58 | E41: -142704.35 | F41: -15983.745 | G41: Внутреннее
A42: Түсімдер | B42: -62360.325 | C42: -119750.59 | D42: 242914.29 | E42: -142620.13 | F42: -15230.435 | G42: Поступление
A43: Өтеу | B43: 18494.406 | C43: 6912.0418 | D43: 10134.71 | E43: 84.2216 | F43: 753.3096 | G43: Погашение
A44: Сыртқы | B44: - | C44: - | D44: - | E44: - | F44: - | G44: Внешнее
A45: Түсімдер | B45: - | C45: - | D45: - | E45: - | F45: - | G45: Поступление
A46: Өтеу | B46: - | C46: - | D46: - | E46: - | F46: - | G46: Погашение

Sheet табл 12.8
A1: 12.8-кесте | E1: Таблица 12.8
A2: ҚАРАҒАНДЫ ОБЛЫСЫ | E2: ИСПОЛНЕНИЕ БЮДЖЕТА
A3: БЮДЖЕТІНІҢ АТҚАРЫЛУЫ | E3: КАРАГАНДИНСКАЯ ОБЛАСТЬ
A4: (млн.теңге) | E4: (млн. тенге)
A5: Атауы | B5: 2022 ж. есеп/ 2022 г. отчет | C5: 2023 ж. есеп/ 2023 г. отчет | D5: 2024 ж. есеп/ 2024 г. отчет | F5: 2025 ж. қантар-ақпан есеп/январь-феврал отчет 2025 г. | G5: Наименование
D6: жылдық/ годовой | E6: қантар-ақпан/январь-феврал
A7: 1 | B7: 2 | C7: 3 | D7: 4 | E7: 5 | F7: 6 | G7: 7
A8: I. КІРІСТЕР | B8: 601163.66 | C8: 686571.15 | D8: 782542.05 | E8: 115877.97 | F8: 107976.67 | G8: I. ДОХОДЫ
A9: Салықтық түсімдер_x000D_ оның iшiнде: | B9: 276736.66 | C9: 279296.66 | D9: 347457.48 | E9: 60383.106 | F9: 61548.925 | G9: Налоговые поступления,_x000D_ в том числе:
A10: корпорациялық табыс салығы | B10: 41790.778 | C10: 50643.141 | D10: 65372.599 | E10: 9560.2522 | F10: 10528.026 | G10: корпоративный подоходный налог
A11: жеке табыс салығы | B11: 97720.215 | C11: 100657.78 | D11: 130633.83 | E11: 24514.089 | F11: 24094.26 | G11: индивидуальный подоходный налог
A12: әлеуметтік салық | B12: 69413.028 | C12: 70479.115 | D12: 85429.921 | E12: 17073.787 | F12: 16057.142 | G12: социальный налог
A13: акциздер | B13: 8175.2935 | C13: 8092.5258 | D13: 7686.1147 | E13: 1120.9906 | F13: 1110.9105 | G13: акцизы
A14: Салықтық емес түсімдер | B14: 8253.7204 | C14: 11211.452 | D14: 27590.047 | E14: 1455.1507 | F14: 1651.4738 | G14: Неналоговые поступления
A15: Негізгі капиталды сатудан түсетін түсімдер | B15: 8386.6656 | C15: 3103.0047 | D15: 4608.7489 | E15: 479.95928 | F15: 940.70702 | G15: Поступления от продажи основного капитала
A16: Трансферттердің түсімдері | B16: 307786.61 | C16: 392960.03 | D16: 402885.77 | E16: 53559.751 | F16: 43835.562 | G16: Поступления трансфертов
A17: II. ШЫҒЫНДАР | B17: 541666.71 | C17: 673296.69 | D17: 795649.24 | E17: 66546.203 | F17: 75099.508 | G17: II. ЗАТРАТЫ
A18: 1. Жалпы сипаттағы мемлекеттiк қызметтер | B18: 20749.235 | C18: 28618.703 | D18: 34271.162 | E18: 3863.2145 | F18: 5596.3805 | G18: 1. Государственные услуги общего характера
A19: 2. Қорғаныс | B19: 2672.9403 | C19: 2604.8186 | D19: 3295.2285 | E19: 93.543091 | F19: 109.40435 | G19: 2. Оборона
... A43: Түсімдер | B43: -423413.49 | C43: -63641.709 | D43: 43180.261 | E43: -560481.31 | F43: -33033.545 | G43: Поступление
A44: Өтеу | B44: 10718.722 | C44: 5043.5343 | D44: 8113.2071 | E44: 2465 | F44: - | G44: Погашение
A45: Сыртқы | B45: - | C45: - | D45: - | E45: - | F45: - | G45: Внешнее
A46: Түсімдер | B46: - | C46: - | D46: - | E46: - | F46: - | G46: Поступление
A47: Өтеу | B47: - | C47: - | D47: - | E47: - | F47: - | G47: Погашение

Sheet табл 12.9
A1: 12.9-кесте | E1: Таблица 12.9
A2: ҚЫЗЫЛОРДА ОБЛЫСЫ | E2: ИСПОЛНЕНИЕ БЮДЖЕТА
A3: БЮДЖЕТІНІҢ АТҚАРЫЛУЫ | E3: КЫЗЫЛОРДИНСКАЯ ОБЛАСТЬ
A4: (млн.теңге) | E4: (млн. тенге)
A5: Атауы | B5: 2022 ж. есеп/ 2022 г. отчет | C5: 2023 ж. есеп/ 2023 г. отчет | D5: 2024 ж. есеп/ 2024 г. отчет | F5: 2025 ж. қантар-ақпан есеп/январь-феврал отчет 2025 г. | G5: Наименование
D6: жылдық/ годовой | E6: қантар-ақпан/январь-феврал
A7: 1 | B7: 2 | C7: 3 | D7: 4 | E7: 5 | F7: 6 | G7: 7
A8: I. КІРІСТЕР | B8: 417735.97 | C8: 597172.6 | D8: 688375.1 | E8: 90537.352 | F8: 102587.68 | G8: I. ДОХОДЫ
A9: Салықтық түсімдер_x000D_ оның iшiнде: | B9: 68176.779 | C9: 89965.953 | D9: 113891.83 | E9: 19266.391 | F9: 23711.681 | G9: Налоговые поступления,_x000D_ в том числе:
A10: корпорациялық табыс салығы | B10: 7293.8047 | C10: 8720.5044 | D10: 16592.943 | E10: 1603.8783 | F10: 3133.1407 | G10: корпоративный подоходный налог
A11: жеке табыс салығы | B11: 26007.383 | C11: 34223.426 | D11: 44987.131 | E11: 8082.4845 | F11: 9600.4927 | G11: индивидуальный подоходный налог
A12: әлеуметтік салық | B12: 19323.765 | C12: 25039.27 | D12: 30129.397 | E12: 5666.6427 | F12: 6412.4189 | G12: социальный налог
A13: акциздер | B13: 127.02314 | C13: 139.68694 | D13: 116.04345 | E13: 16.428325 | F13: 18.321217 | G13: акцизы
A14: Салықтық емес түсімдер | B14: 5589.3801 | C14: 10570.979 | D14: 33610.595 | E14: 1234.3695 | F14: 4437.3543 | G14: Неналоговые поступления
A15: Негізгі капиталды сатудан түсетін түсімдер | B15: 5075.3512 | C15: 9002.805 | D15: 10672.773 | E15: 1787.4146 | F15: 2025.0757 | G15: Поступления от продажи основного капитала
A16: Трансферттердің түсімдері | B16: 338894.46 | C16: 487632.86 | D16: 530199.9 | E16: 68249.177 | F16: 72413.566 | G16: Поступления трансфертов
A17: II. ШЫҒЫНДАР | B17: 415462.88 | C17: 569744.49 | D17: 707644.21 | E17: 70278.458 | F17: 82120.152 | G17: II. ЗАТРАТЫ
A18: 1. Жалпы сипаттағы мемлекеттiк қызметтер | B18: 19825.775 | C18: 21548.543 | D18: 25338.796 | E18: 3575.9333 | F18: 4480.2435 | G18: 1. Государственные услуги общего характера
A19: 2. Қорғаныс | B19: 1595.6792 | C19: 1831.1092 | D19: 2739.7235 | E19: 60.662564 | F19: 73.964216 | G19: 2. Оборона
... A36: IV. ҚАРЖЫ АКТИВТЕРІМЕН ОПЕРАЦИЯЛАР БОЙЫНША САЛЬДО - ҚАРЖЫ АК | B36: 4357.5615 | C36: 11286.891 | D36: 7307.6519 | E36: 444.30656 | F36: -2.522405 | G36: IV. САЛЬДО ПО ОПЕРАЦИЯМ С ФИНАНСОВЫМИ АКТИВАМИ
A37: Қаржылық активтерді сатып алу | B37: 4357.5615 | C37: 11297.835 | D37: 7312.6936 | E37: 447.952 | G37: Приобретение финансовых активов
A38: Мемлекеттің қаржы активтерін сатудан түсетін түсімдер | C38: 10.944182 | D38: 5.041745 | E38: 3.645436 | F38: 2.522405 | G38: Поступления от продажи финансовых активов государства
A39: V. БЮДЖЕТ ТАПШЫЛЫҒЫ (ПРОФИЦИТІ) | B39: -7332.7874 | C39: 8840.5622 | D39: -35564.174 | E39: 20351.613 | F39: 21002.341 | G39: V. ДЕФИЦИТ (ПРОФИЦИТ) БЮДЖЕТА
A41: VII. БЮДЖЕТТІҢ ТАПШЫЛЫҒЫН ҚАРЖЫЛАНДЫРУ (ПРОФИЦИТТІ ПАЙДАЛАНУ | B41: 7332.7874 | C41: -8840.5622 | D41: -35564.174 | E41: -20351.613 | F41: -21002.341 | G41: VII. ФИНАНСИРОВАНИЕ ДЕФИЦИТА (ИСПОЛЬЗОВАНИЕ ПРОФИЦИТА) БЮДЖЕТА
A42: Ішкі | B42: 75339.843 | C42: -160335.33 | D42: 86560.111 | E42: -231481.73 | F42: -21002.341 | G42: Внутреннее
A43: Түсімдер | B43: 84754.964 | C43: -149731.8 | D43: 98509.642 | E43: -231271.5 | F43: -20674.884 | G43: Поступление
A44: Өтеу | B44: 9415.1203 | C44: 10603.525 | D44: 11949.531 | E44: 210.23189 | F44: 327.45684 | G44: Погашение
A45: Сыртқы | B45: -1516.9375 | C45: -1880.877 | D45: -868.7564 | E45: -868.7564 | F45: - | G45: Внешнее
A46: Түсімдер | B46: - | C46: - | D46: - | E46: - | F46: - | G46: Поступление
A47: Өтеу | B47: 1516.9375 | C47: 1880.877 | D47: 868.7564 | E47: 868.7564 | F47: - | G47: Погашение

Sheet табл 12.10
A1: 12.10-кесте | E1: Таблица 12.10
A2: ҚОСТАНАЙ ОБЛЫСЫ | E2: ИСПОЛНЕНИЕ БЮДЖЕТА
A3: БЮДЖЕТІНІҢ АТҚАРЫЛУЫ | E3: КОСТАНАЙСКАЯ ОБЛАСТЬ
A4: (млн.теңге) | E4: (млн. тенге)
A5: Атауы | B5: 2022 ж. есеп/ 2022 г. отчет | C5: 2023 ж. есеп/ 2023 г. отчет | D5: 2024 ж. есеп/ 2024 г. отчет | F5: 2025 ж. қантар-ақпан есеп/январь-феврал отчет 2025 г. | G5: Наименование
D6: жылдық/ годовой | E6: қантар-ақпан/январь-феврал
A7: 1 | B7: 2 | C7: 3 | D7: 4 | E7: 5 | F7: 6 | G7: 7
A8: I. КІРІСТЕР | B8: 438229 | C8: 604311.98 | D8: 628629.96 | E8: 109044.09 | F8: 95316.417 | G8: I. ДОХОДЫ
A9: Салықтық түсімдер_x000D_ оның iшiнде: | B9: 144076.63 | C9: 174857.99 | D9: 205358.32 | E9: 37736.864 | F9: 42918.724 | G9: Налоговые поступления,_x000D_ в том числе:
A10: корпорациялық табыс салығы | B10: 33859.442 | C10: 33911.561 | D10: 37426.524 | E10: 5478.988 | F10: 6144.2061 | G10: корпоративный подоходный налог
A11: жеке табыс салығы | B11: 47237.783 | C11: 62045.659 | D11: 79538.501 | E11: 14571.228 | F11: 17435.641 | G11: индивидуальный подоходный налог
A12: әлеуметтік салық | B12: 32217.986 | C12: 40145.801 | D12: 48992.711 | E12: 10097.92 | F12: 10915.551 | G12: социальный налог
A13: акциздер | B13: 5054.0913 | C13: 5085.7443 | D13: 4367.686 | E13: 383.25625 | F13: 386.24401 | G13: акцизы
A14: Салықтық емес түсімдер | B14: 5914.2177 | C14: 6220.1607 | D14: 11769.215 | E14: 3633.0832 | F14: 1794.6177 | G14: Неналоговые поступления
A15: Негізгі капиталды сатудан түсетін түсімдер | B15: 5657.074 | C15: 5656.0616 | D15: 9621.5046 | E15: 2446.8073 | F15: 1452.5351 | G15: Поступления от продажи основного капитала
A16: Трансферттердің түсімдері | B16: 282581.07 | C16: 417577.77 | D16: 401880.92 | E16: 65227.338 | F16: 49150.541 | G16: Поступления трансфертов
A17: II. ШЫҒЫНДАР | B17: 421205.17 | C17: 547560.7 | D17: 628666.42 | E17: 64018.045 | F17: 67242.13 | G17: II. ЗАТРАТЫ
A18: 1. Жалпы сипаттағы мемлекеттiк қызметтер | B18: 20142.484 | C18: 30915.334 | D18: 40995.492 | E18: 4059.8066 | F18: 4244.0469 | G18: 1. Государственные услуги общего характера
A19: 2. Қорғаныс | B19: 872.68626 | C19: 1571.8601 | D19: 2531.2785 | E19: 42.590726 | F19: 70.832999 | G19: 2. Оборона
... A44: Өтеу | B44: 9230.309 | C44: 13617.529 | D44: 11793.154 | E44: 22.782337 | F44: 24.606699 | G44: Погашение
A45: Сыртқы | B45: - | C45: - | D45: - | E45: - | F45: - | G45: Внешнее
A46: Түсімдер | B46: - | C46: - | D46: - | E46: - | F46: - | G46: Поступление
A47: Өтеу | B47: - | C47: - | D47: - | E47: - | F47: - | G47: Погашение

Sheet табл 12.11
A1: 12.11-кесте | E1: Таблица 12.11
A2: МАҢҒЫСТАУ ОБЛЫСЫ | E2: ИСПОЛНЕНИЕ БЮДЖЕТА
A3: БЮДЖЕТІНІҢ АТҚАРЫЛУЫ | E3: МАНГИСТАУСКАЯ ОБЛАСТЬ
A4: (млн.теңге) | E4: (млн. тенге)
A5: Атауы | B5: 2022 ж. есеп/ 2022 г. отчет | C5: 2023 ж. есеп/ 2023 г. отчет | D5: 2024 ж. есеп/ 2024 г. отчет | F5: 2025 ж. қантар-ақпан есеп/январь-феврал отчет 2025 г. | G5: Наименование
D6: жылдық/ годовой | E6: қантар-ақпан/январь-феврал
A7: 1 | B7: 2 | C7: 3 | D7: 4 | E7: 5 | F7: 6 | G7: 7
A8: I. КІРІСТЕР | B8: 351894.12 | C8: 475001.67 | D8: 565387.99 | E8: 79074.443 | F8: 115589.02 | G8: I. ДОХОДЫ
A9: Салықтық түсімдер_x000D_ оның iшiнде: | B9: 201132.45 | C9: 249915.93 | D9: 290147.77 | E9: 54746.404 | F9: 58522.243 | G9: Налоговые поступления,_x000D_ в том числе:
A10: корпорациялық табыс салығы | B10: 29409.688 | C10: 30124.379 | D10: 31655.206 | E10: 4269.9485 | F10: 4261.2311 | G10: корпоративный подоходный налог
A11: жеке табыс салығы | B11: 75641.827 | C11: 95760.861 | D11: 117448.69 | E11: 21628.513 | F11: 24436.675 | G11: индивидуальный подоходный налог
A12: әлеуметтік салық | B12: 57287.788 | C12: 72326.61 | D12: 85395.26 | E12: 16867.633 | F12: 18632.621 | G12: социальный налог
A13: акциздер | B13: 619.41999 | C13: 1636.9414 | D13: 1512.377 | E13: 223.2459 | F13: 9.9335975 | G13: акцизы
A14: Салықтық емес түсімдер | B14: 6596.3625 | C14: 8955.6703 | D14: 11116.334 | E14: 1117.469 | F14: 33384.445 | G14: Неналоговые поступления
A15: Негізгі капиталды сатудан түсетін түсімдер | B15: 5934.8791 | C15: 6033.2791 | D15: 4729.1387 | E15: 895.49285 | F15: 450.78732 | G15: Поступления от продажи основного капитала
A16: Трансферттердің түсімдері | B16: 138230.43 | C16: 210096.79 | D16: 259394.75 | E16: 22315.078 | F16: 23231.541 | G16: Поступления трансфертов
A17: II. ШЫҒЫНДАР | B17: 335696.2 | C17: 445032.94 | D17: 548979.79 | E17: 41861.199 | F17: 56127.317 | G17: II. ЗАТРАТЫ
A18: 1. Жалпы сипаттағы мемлекеттiк қызметтер | B18: 9629.0065 | C18: 13009.328 | D18: 19808.839 | E18: 1595.4002 | F18: 1955.6025 | G18: 1. Государственные услуги общего характера
A19: 2. Қорғаныс | B19: 1420.4398 | C19: 2131.3234 | D19: 3018.473 | E19: 57.936898 | F19: 412.73409 | G19: 2. Оборона
... A37: Қаржылық активтерді сатып алу | B37: 892.767 | C37: 3678.269 | D37: 2831.235 | E37: 170 | F37: 1633.332 | G37: Приобретение финансовых активов
A38: Мемлекеттің қаржы активтерін сатудан түсетін түсімдер | C38: 36.150285 | G38: Поступления от продажи финансовых активов государства
A39: V. БЮДЖЕТ ТАПШЫЛЫҒЫ (ПРОФИЦИТІ) | B39: 9420.301 | C39: 24445.137 | D39: 10865.029 | E39: 37206.654 | F39: 58065.794 | G39: V. ДЕФИЦИТ (ПРОФИЦИТ) БЮДЖЕТА
A41: VII. БЮДЖЕТТІҢ ТАПШЫЛЫҒЫН ҚАРЖЫЛАНДЫРУ (ПРОФИЦИТТІ ПАЙДАЛАНУ | B41: -9420.301 | C41: -24445.137 | D41: 10865.029 | E41: -37206.654 | F41: -58065.794 | G41: VII. ФИНАНСИРОВАНИЕ ДЕФИЦИТА (ИСПОЛЬЗОВАНИЕ ПРОФИЦИТА) БЮДЖЕТА
A42: Ішкі | B42: -70614.803 | C42: -312630.52 | D42: -244298.81 | E42: -445996.4 | F42: -58065.794 | G42: Внутреннее
A43: Түсімдер | B43: -59262.314 | C43: -311173.63 | D43: -238722.45 | E43: -445952.45 | F43: -57936.264 | G43: Поступление
A44: Өтеу | B44: 11352.488 | C44: 1456.89 | D44: 5576.3587 | E44: 43.949572 | F44: 129.52995 | G44: Погашение
A45: Сыртқы | B45: - | C45: - | D45: - | E45: - | F45: - | G45: Внешнее
A46: Түсімдер | B46: - | C46: - | D46: - | E46: - | F46: - | G46: Поступление
A47: Өтеу | B47: - | C47: - | D47: - | E47: - | F47: - | G47: Погашение

Sheet табл 12.12
A1: 12.12-кесте | E1: Таблица 12.12
A2: ПАВЛОДАР ОБЛЫСЫ | E2: ИСПОЛНЕНИЕ БЮДЖЕТА
A3: БЮДЖЕТІНІҢ АТҚАРЫЛУЫ | E3: ПАВЛОДАРСКАЯ ОБЛАСТЬ
A4: (млн.теңге) | E4: (млн. тенге)
A5: Атауы | B5: 2022 ж. есеп/ 2022 г. отчет | C5: 2023 ж. есеп/ 2023 г. отчет | D5: 2024 ж. есеп/ 2024 г. отчет | F5: 2025 ж. қантар-ақпан есеп/январь-феврал отчет 2025 г. | G5: Наименование
D6: жылдық/ годовой | E6: қантар-ақпан/январь-феврал
A7: 1 | B7: 2 | C7: 3 | D7: 4 | E7: 5 | F7: 6 | G7: 7
A8: I. КІРІСТЕР | B8: 457265.76 | C8: 530607.87 | D8: 568290.97 | E8: 86475.843 | F8: 91545.458 | G8: I. ДОХОДЫ
A9: Салықтық түсімдер_x000D_ оның iшiнде: | B9: 257861.33 | C9: 311139.96 | D9: 355688.78 | E9: 60644.698 | F9: 67905.265 | G9: Налоговые поступления,_x000D_ в том числе:
A10: корпорациялық табыс салығы | B10: 23499.142 | C10: 24425.448 | D10: 34139.694 | E10: 3859.6228 | F10: 4749.3521 | G10: корпоративный подоходный налог
A11: жеке табыс салығы | B11: 52114.956 | C11: 67868.655 | D11: 86404.401 | E11: 16074.866 | F11: 18267.505 | G11: индивидуальный подоходный налог
A12: әлеуметтік салық | B12: 37181.825 | C12: 47871.635 | D12: 58092.974 | E12: 11453.983 | F12: 12974.62 | G12: социальный налог
A13: акциздер | B13: 107719.1 | C13: 125534.48 | D13: 129598.29 | E13: 19646.381 | F13: 22647.049 | G13: акцизы
A14: Салықтық емес түсімдер | B14: 4151.6239 | C14: 4507.2143 | D14: 6402.786 | E14: 906.54506 | F14: 1498.7788 | G14: Неналоговые поступления
A15: Негізгі капиталды сатудан түсетін түсімдер | B15: 8068.3621 | C15: 7729.2877 | D15: 7851.1996 | E15: 1191.9205 | F15: 679.1871 | G15: Поступления от продажи основного капитала
A16: Трансферттердің түсімдері | B16: 187184.45 | C16: 207231.4 | D16: 198348.21 | E16: 23732.679 | F16: 21462.227 | G16: Поступления трансфертов
A17: II. ШЫҒЫНДАР | B17: 457710.46 | C17: 528208.21 | D17: 579464.48 | E17: 64638.817 | F17: 77987.393 | G17: II. ЗАТРАТЫ
A18: 1. Жалпы сипаттағы мемлекеттiк қызметтер | B18: 20029.081 | C18: 42863.349 | D18: 33133.36 | E18: 3708.5743 | F18: 5873.1215 | G18: 1. Государственные услуги общего характера
A19: 2. Қорғаныс | B19: 1538.3453 | C19: 1786.6605 | D19: 2384.4454 | E19: 130.0712 | F19: 161.06086 | G19: 2. Оборона
... A37: Қаржылық активтерді сатып алу | B37: 1757.762 | C37: 844.11634 | D37: 1272.8383 | E37: 179.729 | F37: 70.681 | G37: Приобретение финансовых активов
A38: Мемлекеттің қаржы активтерін сатудан түсетін түсімдер | B38: 102.91243 | C38: 2.557065 | D38: 48.849596 | F38: 3.105596 | G38: Поступления от продажи финансовых активов государства
A39: V. БЮДЖЕТ ТАПШЫЛЫҒЫ (ПРОФИЦИТІ) | B39: -2130.5122 | C39: -10426.094 | D39: -19278.523 | E39: 21800.397 | F39: 13651.357 | G39: V. ДЕФИЦИТ (ПРОФИЦИТ) БЮДЖЕТА
A41: VII. БЮДЖЕТТІҢ ТАПШЫЛЫҒЫН ҚАРЖЫЛАНДЫРУ (ПРОФИЦИТТІ ПАЙДАЛАНУ | B41: 2130.5122 | C41: 10426.094 | D41: -19278.523 | E41: -21800.397 | F41: -13651.357 | G41: VII. ФИНАНСИРОВАНИЕ ДЕФИЦИТА (ИСПОЛЬЗОВАНИЕ ПРОФИЦИТА) БЮДЖЕТА
A42: Ішкі | B42: 85648.617 | C42: 9464.0863 | D42: 47257.462 | E42: -261604.76 | F42: -13651.357 | G42: Внутреннее
A43: Түсімдер | B43: 98733.745 | C43: 17349.601 | D43: 55012.88 | E43: -261604.76 | F43: -13651.357 | G43: Поступление
A44: Өтеу | B44: 13085.128 | C44: 7885.5148 | D44: 7755.4174 | E44: - | F44: - | G44: Погашение
A45: Сыртқы | B45: - | C45: - | D45: - | E45: - | F45: - | G45: Внешнее
A46: Түсімдер | B46: - | C46: - | D46: - | E46: - | F46: - | G46: Поступление
A47: Өтеу | B47: - | C47: - | D47: - | E47: - | F47: - | G47: Погашение

Sheet табл 12.13
A1: 12.13-кесте | E1: Таблица 12.13
A2: СОЛТҮСТІК-ҚАЗАҚСТАН ОБЛЫСЫ | E2: ИСПОЛНЕНИЕ БЮДЖЕТА
A3: БЮДЖЕТІНІҢ АТҚАРЫЛУЫ | E3: СЕВ-КАЗАХСТАНСКАЯ ОБЛАСТЬ
A4: (млн.теңге) | E4: (млн. тенге)
A5: Атауы | B5: 2022 ж. есеп/ 2022 г. отчет | C5: 2023 ж. есеп/ 2023 г. отчет | D5: 2024 ж. есеп/ 2024 г. отчет | F5: 2025 ж. қантар-ақпан есеп/январь-феврал отчет 2025 г. | G5: Наименование
D6: жылдық/ годовой | E6: қантар-ақпан/январь-феврал
A7: 1 | B7: 2 | C7: 3 | D7: 4 | E7: 5 | F7: 6 | G7: 7
A8: I. КІРІСТЕР | B8: 411923.16 | C8: 479286.16 | D8: 499744.12 | E8: 59655.998 | F8: 82207.171 | G8: I. ДОХОДЫ
A9: Салықтық түсімдер_x000D_ оның iшiнде: | B9: 86449.968 | C9: 104168.43 | D9: 114911.18 | E9: 19981.699 | F9: 22025.779 | G9: Налоговые поступления,_x000D_ в том числе:
A10: корпорациялық табыс салығы | B10: 14246.799 | C10: 19981.616 | D10: 20968.836 | E10: 3402.3839 | F10: 3224.4108 | G10: корпоративный подоходный налог
A11: жеке табыс салығы | B11: 26590.562 | C11: 33665.851 | D11: 42183.254 | E11: 6838.795 | F11: 8043.7124 | G11: индивидуальный подоходный налог
A12: әлеуметтік салық | B12: 16721.482 | C12: 20700.577 | D12: 24710.833 | E12: 4636.6828 | F12: 5287.4107 | G12: социальный налог
A13: акциздер | B13: 16863.605 | C13: 13585.507 | D13: 11347.819 | E13: 2169.3774 | F13: 2235.4755 | G13: акцизы
A14: Салықтық емес түсімдер | B14: 3517.6964 | C14: 4418.0267 | D14: 5764.0759 | E14: 657.2643 | F14: 1061.4741 | G14: Неналоговые поступления
A15: Негізгі капиталды сатудан түсетін түсімдер | B15: 6843.2221 | C15: 11077.734 | D15: 6402.5728 | E15: 500.08262 | F15: 1916.1397 | G15: Поступления от продажи основного капитала
A16: Трансферттердің түсімдері | B16: 315112.27 | C16: 359621.97 | D16: 372666.29 | E16: 38516.952 | F16: 57203.778 | G16: Поступления трансфертов
A17: II. ШЫҒЫНДАР | B17: 378633.97 | C17: 456049.77 | D17: 519516.5 | E17: 52523.866 | F17: 67226.874 | G17: II. ЗАТРАТЫ
A18: 1. Жалпы сипаттағы мемлекеттiк қызметтер | B18: 15791.163 | C18: 21153.388 | D18: 46477.998 | E18: 3222.0559 | F18: 4259.1355 | G18: 1. Государственные услуги общего характера
A19: 2. Қорғаныс | B19: 853.0642 | C19: 1551.1442 | D19: 2113.6186 | E19: 89.306217 | F19: 102.10293 | G19: 2. Оборона
... A35: Бюджеттік кредиттерді өтеу | B35: 2156.3395 | C35: 2437.6831 | D35: 4274.9727 | E35: 825.50099 | F35: 1088.347 | G35: Погашение бюджетных кредитов
A36: IV. ҚАРЖЫ АКТИВТЕРІМЕН ОПЕРАЦИЯЛАР БОЙЫНША САЛЬДО - ҚАРЖЫ АК | B36: 29973.455 | C36: 7499.9987 | D36: 33.974 | G36: IV. САЛЬДО ПО ОПЕРАЦИЯМ С ФИНАНСОВЫМИ АКТИВАМИ
A37: Қаржылық активтерді сатып алу | B37: 29975.55 | C37: 7500 | D37: 35 | G37: Приобретение финансовых активов
A38: Мемлекеттің қаржы активтерін сатудан түсетін түсімдер | B38: 2.094767 | C38: 0.001336 | D38: 1.026 | G38: Поступления от продажи финансовых активов государства
A39: V. БЮДЖЕТ ТАПШЫЛЫҒЫ (ПРОФИЦИТІ) | B39: -1028.2882 | C39: -2878.5917 | D39: -23552.591 | E39: 7957.6333 | F39: 15468.644 | G39: V. ДЕФИЦИТ (ПРОФИЦИТ) БЮДЖЕТА
A41: VII. БЮДЖЕТТІҢ ТАПШЫЛЫҒЫН ҚАРЖЫЛАНДЫРУ (ПРОФИЦИТТІ ПАЙДАЛАНУ | B41: 1028.2882 | C41: 2878.5917 | D41: -23552.591 | E41: -7957.6333 | F41: -15468.644 | G41: VII. ФИНАНСИРОВАНИЕ ДЕФИЦИТА (ИСПОЛЬЗОВАНИЕ ПРОФИЦИТА) БЮДЖЕТА
A42: Ішкі | B42: 1085.8274 | C42: -63363.316 | D42: 244902.68 | E42: -92309.871 | F42: -15468.644 | G42: Внутреннее
A43: Түсімдер | B43: 12720.555 | C43: -48522.388 | D43: 256392.58 | E43: -92020.623 | F43: -14706.879 | G43: Поступление
A44: Өтеу | B44: 11634.728 | C44: 14840.928 | D44: 11489.901 | E44: 289.248 | F44: 761.76488 | G44: Погашение
A45: Сыртқы | B45: - | C45: - | D45: - | E45: - | F45: - | G45: Внешнее
A46: Түсімдер | B46: - | C46: - | D46: - | E46: - | F46: - | G46: Поступление
A47: Өтеу | B47: - | C47: - | D47: - | E47: - | F47: - | G47: Погашение

Sheet табл 12.14
A1: 12.14-кесте | E1: Таблица 12.14
A2: ТҮРКІСТАН ОБЛЫСЫ | E2: ИСПОЛНЕНИЕ БЮДЖЕТА
A3: БЮДЖЕТІНІҢ АТҚАРЫЛУЫ | E3: ТУРКЕСТАНСКАЯ ОБЛАСТЬ
A4: (млн.теңге) | E4: (млн. тенге)
A5: Атауы | B5: 2022 ж. есеп/ 2022 г. отчет | C5: 2023 ж. есеп/ 2023 г. отчет | D5: 2024 ж. есеп/ 2024 г. отчет | F5: 2025 ж. қантар-ақпан есеп/январь-феврал отчет 2025 г. | G5: Наименование
D6: жылдық/ годовой | E6: қантар-ақпан/январь-феврал
A7: 1 | B7: 2 | C7: 3 | D7: 4 | E7: 5 | F7: 6 | G7: 7
A8: I. КІРІСТЕР | B8: 1093249.8 | C8: 1355385.2 | D8: 1482111.7 | E8: 193814.69 | F8: 215042.37 | G8: I. ДОХОДЫ
A9: Салықтық түсімдер_x000D_ оның iшiнде: | B9: 112612.55 | C9: 149133.74 | D9: 192225.51 | E9: 28349.916 | F9: 38491.681 | G9: Налоговые поступления,_x000D_ в том числе:
A10: корпорациялық табыс салығы | B10: 10090.392 | C10: 12501.811 | D10: 29399.857 | E10: 2281.914 | F10: 4509.4632 | G10: корпоративный подоходный налог
A11: жеке табыс салығы | B11: 46292.272 | C11: 59251.623 | D11: 76377.383 | E11: 11523.375 | F11: 16409.789 | G11: индивидуальный подоходный налог
A12: әлеуметтік салық | B12: 35788.861 | C12: 45981.778 | D12: 52625.318 | E12: 9044.4272 | F12: 11220.801 | G12: социальный налог
A13: акциздер | B13: 427.36189 | C13: 412.31388 | D13: 402.20076 | E13: 59.566495 | F13: 58.97581 | G13: акцизы
A14: Салықтық емес түсімдер | B14: 12995.992 | C14: 16833.17 | D14: 37569.665 | E14: 8637.6013 | F14: 4683.4241 | G14: Неналоговые поступления
A15: Негізгі капиталды сатудан түсетін түсімдер | B15: 38422.814 | C15: 19654.299 | D15: 23284.113 | E15: 5966.8578 | F15: 1404.5398 | G15: Поступления от продажи основного капитала
A16: Трансферттердің түсімдері | B16: 929218.4 | C16: 1169764 | D16: 1229032.5 | E16: 150860.32 | F16: 170462.72 | G16: Поступления трансфертов
A17: II. ШЫҒЫНДАР | B17: 1091950.3 | C17: 1324232.9 | D17: 1469273.5 | E17: 147560.26 | F17: 183281.91 | G17: II. ЗАТРАТЫ
A18: 1. Жалпы сипаттағы мемлекеттiк қызметтер | B18: 30411.011 | C18: 37613.034 | D18: 41735.89 | E18: 6231.9098 | F18: 6378.9325 | G18: 1. Государственные услуги общего характера
A19: 2. Қорғаныс | B19: 1834.4717 | C19: 7115.7448 | D19: 4702.653 | E19: 1081.347 | F19: 1060.0418 | G19: 2. Оборона
... A37: Қаржылық активтерді сатып алу | B37: 203.733 | C37: 1302.731 | D37: 6018.6537 | E37: 0 | F37: 0 | G37: Приобретение финансовых активов
A38: Мемлекеттің қаржы активтерін сатудан түсетін түсімдер | B38: 48.706972 | C38: 145.06179 | D38: 23.477661 | F38: 0.5 | G38: Поступления от продажи финансовых активов государства
A39: V. БЮДЖЕТ ТАПШЫЛЫҒЫ (ПРОФИЦИТІ) | B39: -6263.5892 | C39: 2411.4449 | D39: -4255.5784 | E39: 46459.188 | F39: 34481.997 | G39: V. ДЕФИЦИТ (ПРОФИЦИТ) БЮДЖЕТА
A41: VII. БЮДЖЕТТІҢ ТАПШЫЛЫҒЫН ҚАРЖЫЛАНДЫРУ (ПРОФИЦИТТІ ПАЙДАЛАНУ | B41: 6263.5892 | C41: -2411.4449 | D41: -4255.5784 | E41: -46459.188 | F41: -34481.997 | G41: VII. ФИНАНСИРОВАНИЕ ДЕФИЦИТА (ИСПОЛЬЗОВАНИЕ ПРОФИЦИТА) БЮДЖЕТА
A42: Ішкі | B42: 9077.9158 | C42: -76270.707 | D42: -84384.103 | E42: -289295.4 | F42: -34481.997 | G42: Внутреннее
A43: Түсімдер | B43: 35997.279 | C43: -24168.026 | D43: -35494.078 | E43: -264912.23 | F43: -32134.973 | G43: Поступление
A44: Өтеу | B44: 26919.364 | C44: 52102.681 | D44: 48890.025 | E44: 24383.169 | F44: 2347.0233 | G44: Погашение
A45: Сыртқы | B45: - | C45: - | D45: - | E45: - | F45: - | G45: Внешнее
A46: Түсімдер | B46: - | C46: - | D46: - | E46: - | F46: - | G46: Поступление
A47: Өтеу | B47: - | C47: - | D47: - | E47: - | F47: - | G47: Погашение

Sheet табл 12.15.
A1: 12.15-кесте | E1: Таблица 12.15
A2: ШЫМКЕНТ Қ. | E2: ИСПОЛНЕНИЕ БЮДЖЕТА
A3: БЮДЖЕТІНІҢ АТҚАРЫЛУЫ | E3: Г.ШЫМКЕНТ
A4: (млн.теңге) | E4: (млн. тенге)
A5: Атауы | B5: 2022 ж. есеп/ 2022 г. отчет | C5: 2023 ж. есеп/ 2023 г. отчет | D5: 2024 ж. есеп/ 2024 г. отчет | F5: 2025 ж. қантар-ақпан есеп/январь-феврал отчет 2025 г. | G5: Наименование
D6: жылдық/ годовой | E6: қантар-ақпан/январь-феврал
A7: 1 | B7: 2 | C7: 3 | D7: 4 | E7: 5 | F7: 6 | G7: 7
A8: I. КІРІСТЕР | B8: 594277.32 | C8: 627061.85 | D8: 735887.74 | E8: 106295.82 | F8: 127720.5 | G8: I. ДОХОДЫ
A9: Салықтық түсімдер_x000D_ оның iшiнде: | B9: 245644.64 | C9: 305471.98 | D9: 370511.82 | E9: 60634.436 | F9: 67126.602 | G9: Налоговые поступления,_x000D_ в том числе:
A10: корпорациялық табыс салығы | B10: 25315.737 | C10: 29134.129 | D10: 41909.805 | E10: 4557.5767 | F10: 6263.0999 | G10: корпоративный подоходный налог
A11: жеке табыс салығы | B11: 41223.421 | C11: 55307.321 | D11: 80327.448 | E11: 14689.192 | F11: 19424.235 | G11: индивидуальный подоходный налог
A12: әлеуметтік салық | B12: 28610.328 | C12: 38666.348 | D12: 50978.411 | E12: 10288.178 | F12: 11818.115 | G12: социальный налог
A13: акциздер | B13: 128275.7 | C13: 140181.27 | D13: 148639.15 | E13: 24887.568 | F13: 22782.976 | G13: акцизы
A14: Салықтық емес түсімдер | B14: 11701.14 | C14: 12877.295 | D14: 20094.627 | E14: 1851.7671 | F14: 2358.6425 | G14: Неналоговые поступления
A15: Негізгі капиталды сатудан түсетін түсімдер | B15: 23217.94 | C15: 24378.713 | D15: 31129.909 | E15: 7487.6543 | F15: 3614.0021 | G15: Поступления от продажи основного капитала
A16: Трансферттердің түсімдері | B16: 313713.6 | C16: 284333.86 | D16: 314151.39 | E16: 36321.962 | F16: 54621.257 | G16: Поступления трансфертов
A17: II. ШЫҒЫНДАР | B17: 561567.31 | C17: 621600.2 | D17: 741031.51 | E17: 62868.214 | F17: 97739.583 | G17: II. ЗАТРАТЫ
A18: 1. Жалпы сипаттағы мемлекеттiк қызметтер | B18: 5134.2192 | C18: 6097.5574 | D18: 14228.974 | E18: 1718.5774 | F18: 2009.6357 | G18: 1. Государственные услуги общего характера
A19: 2. Қорғаныс | B19: 2589.1297 | C19: 4312.2946 | D19: 8394.1274 | E19: 553.76983 | F19: 359.84567 | G19: 2. Оборона
... A25: 8. Мәдениет, спорт, туризм және ақпараттық кеңістiк | B25: 32058.71 | C25: 38798.724 | D25: 33030.379 | E25: 3159.2848 | F25: 5257.4862 | G25: 8. Культура, спорт, туризм и информационное пространство
A26: 9. Отын-энергетика кешенi және жер қойнауын пайдалану | B26: 9004.1981 | C26: 6818.9773 | D26: 11930.668 | E26: - | F26: - | G26: 9. Топливно-энергетический комплекс и недропользование
A27: 10. Ауыл, су, орман, балық шаруашылығы, ерекше қорғалатын табиғи аумақтар, қоршаған ортаны және жануарлар дүниесін қорғау, жер қатынастары | B27: 16732.933 | C27: 14391.974 | D27: 22106.441 | E27: 926.6463 | F27: 1172.1757 | G27: 10. Сельское, водное, лесное, рыбное хозяйство, особо охраняемые природные территории, охрана окружающей среды и животного мира, земельные отношения
A28: 11. Өнеркәсіп, сәулет, қала құрылысы және құрылыс қызметі | B28: 1022.1711 | C28: 1607.4513 | D28: 5766.676 | E28: 418.31199 | F28: 615.45092 | G28: 11. Промышленность, архитектурная, градостроительная и строительная деятельность
A29: 12. Көлiк және коммуникация | B29: 59629.675 | C29: 72269.961 | D29: 92570.19 | E29: 3665.7187 | F29: 7714.7179 | G29: 12. Транспорт и коммуникации
A30: 13. Басқалар | B30: 16340.678 | C30: 31453.46 | D30: 31472.966 | E30: 5282.4154 | F30: 4538.5509 | G30: 13. Прочие
A31: 14. Борышқа қызмет көрсету | B31: 4783.745 | C31: 4364.2538 | D31: 3715.2608 | E31: 9.68815 | F31: 202.11308 | G31: 14. Обслуживание долга
A32: 15. Трансферттер | B32: 64436.864 | C32: 1024.3202 | D32: 60.359268 | E32: 53.973268 | F32: 310.18455 | G32: 15. Трансферты
A33: III. ТАЗА БЮДЖЕТТІК КРЕДИТ БЕРУ | B33: -209.00727 | C33: 3595.6154 | D33: 24346.933 | E33: -38.436531 | F33: -246.66792 | G33: III. ЧИСТОЕ БЮДЖЕТНОЕ КРЕДИТОВАНИЕ
A34: Бюджеттік кредиттер | B34: 400 | C34: 4305 | D34: 24715.997 | E34: 0 | F34: 0 | G34: Бюджетные кредиты
A35: Бюджеттік кредиттерді өтеу | B35: 609.00727 | C35: 709.3846 | D35: 369.06413 | E35: 38.436531 | F35: 246.66792 | G35: Погашение бюджетных кредитов
A36: IV. ҚАРЖЫ АКТИВТЕРІМЕН ОПЕРАЦИЯЛАР БОЙЫНША САЛЬДО - ҚАРЖЫ АК | B36: 417.10246 | C36: 1040.141 | D36: 4546.9162 | E36: -20.379941 | G36: IV. САЛЬДО ПО ОПЕРАЦИЯМ С ФИНАНСОВЫМИ АКТИВАМИ
A37: Қаржылық активтерді сатып алу | B37: 462.073 | C37: 1040.141 | D37: 4650.2915 | G37: Приобретение финансовых активов
A38: Мемлекеттің қаржы активтерін сатудан түсетін түсімдер | B38: 44.970536 | D38: 103.37533 | E38: 20.379941 | G38: Поступления от продажи финансовых активов государства
A39: V. БЮДЖЕТ ТАПШЫЛЫҒЫ (ПРОФИЦИТІ) | B39: 32501.917 | C39: 825.89571 | D39: -34037.623 | E39: 43486.421 | F39: 30227.588 | G39: V. ДЕФИЦИТ (ПРОФИЦИТ) БЮДЖЕТА
A41: VII. БЮДЖЕТТІҢ ТАПШЫЛЫҒЫН ҚАРЖЫЛАНДЫРУ (ПРОФИЦИТТІ ПАЙДАЛАНУ | B41: -32501.917 | C41: -825.89571 | D41: -34037.623 | E41: -43486.421 | F41: -30227.588 | G41: VII. ФИНАНСИРОВАНИЕ ДЕФИЦИТА (ИСПОЛЬЗОВАНИЕ ПРОФИЦИТА) БЮДЖЕТА
A42: Ішкі | B42: -65751.323 | C42: 53721.326 | D42: -11866.888 | E42: -521639.06 | F42: -30227.588 | G42: Внутреннее
A43: Түсімдер | B43: -26231.055 | C43: 76211.623 | D43: -2021.0519 | E43: -521621.06 | F43: -30209.588 | G43: Поступление
A44: Өтеу | B44: 39520.268 | C44: 22490.297 | D44: 9845.836 | E44: 18 | F44: 18 | G44: Погашение
A45: Сыртқы | B45: - | C45: - | D45: - | E45: - | F45: - | G45: Внешнее
A46: Түсімдер | B46: - | C46: - | D46: - | E46: - | F46: - | G46: Поступление
A47: Өтеу | B47: - | C47: - | D47: - | E47: - | F47: - | G47: Погашение

Sheet табл 12.16
A1: 12.16-кесте | E1: Таблица 12.16
A2: АЛМАТЫ Қ. | E2: ИСПОЛНЕНИЕ БЮДЖЕТА
A3: БЮДЖЕТІНІҢ АТҚАРЫЛУЫ | E3: Г.АЛМАТЫ
A4: (млн.теңге) | E4: (млн. тенге)
A5: Атауы | B5: 2022 ж. есеп/ 2022 г. отчет | C5: 2023 ж. есеп/ 2023 г. отчет | D5: 2024 ж. есеп/ 2024 г. отчет | F5: 2025 ж. қантар-ақпан есеп/январь-феврал отчет 2025 г. | G5: Наименование
D6: жылдық/ годовой | E6: қантар-ақпан/январь-феврал
A7: 1 | B7: 2 | C7: 3 | D7: 4 | E7: 5 | F7: 6 | G7: 7
A8: I. КІРІСТЕР | B8: 1399237.9 | C8: 1637208.5 | D8: 1968721 | E8: 289909.37 | F8: 351801.08 | G8: I. ДОХОДЫ
A9: Салықтық түсімдер_x000D_ оның iшiнде: | B9: 1122101.8 | C9: 1458171.8 | D9: 1810913.8 | E9: 279261.08 | F9: 331120.91 | G9: Налоговые поступления,_x000D_ в том числе:
A10: корпорациялық табыс салығы | B10: 441667.45 | C10: 480314.07 | D10: 632526.82 | E10: 81477.168 | F10: 93337.134 | G10: корпоративный подоходный налог
A11: жеке табыс салығы | B11: 376430.03 | C11: 550653.94 | D11: 663170.95 | E11: 109705.08 | F11: 137135.35 | G11: индивидуальный подоходный налог
A12: әлеуметтік салық | B12: 207296.3 | C12: 283392.46 | D12: 353665.14 | E12: 65105.144 | F12: 76395.858 | G12: социальный налог
A13: акциздер | B13: 22972.399 | C13: 24182.211 | D13: 20738.486 | E13: 3121.1472 | F13: 2816.5759 | G13: акцизы
A14: Салықтық емес түсімдер | B14: 16584.992 | C14: 28489.614 | D14: 53614.391 | E14: 6639.0367 | F14: 10365.028 | G14: Неналоговые поступления
A15: Негізгі капиталды сатудан түсетін түсімдер | B15: 36457.864 | C15: 24703.233 | D15: 9841.7819 | E15: 1570.7667 | F15: 2003.6625 | G15: Поступления от продажи основного капитала
A16: Трансферттердің түсімдері | B16: 224093.22 | C16: 125843.88 | D16: 94351.102 | E16: 2438.489 | F16: 8311.475 | G16: Поступления трансфертов
A17: II. ШЫҒЫНДАР | B17: 1101542.2 | C17: 1397412.5 | D17: 1591047.9 | E17: 126673.31 | F17: 264417.51 | G17: II. ЗАТРАТЫ
A18: 1. Жалпы сипаттағы мемлекеттiк қызметтер | B18: 13202.9 | C18: 25740.582 | D18: 26609.068 | E18: 1654.8357 | F18: 3257.0661 | G18: 1. Государственные услуги общего характера
A19: 2. Қорғаныс | B19: 8598.6902 | C19: 17949.3 | D19: 13685.076 | E19: 39.732987 | F19: 1339.6444 | G19: 2. Оборона
... A44: Өтеу | B44: 54597.504 | C44: 1697.1099 | D44: 15850.324 | E44: 14 | F44: 14 | G44: Погашение
A45: Сыртқы | B45: - | C45: - | D45: - | E45: - | F45: - | G45: Внешнее
A46: Түсімдер | B46: - | C46: - | D46: - | E46: - | F46: - | G46: Поступление
A47: Өтеу | B47: - | C47: - | D47: - | E47: - | F47: - | G47: Погашение

Sheet табл 12.17
A1: 12.17-кесте | E1: Таблица 12.17
A2: АСТАНА Қ. | E2: ИСПОЛНЕНИЕ БЮДЖЕТА
A3: БЮДЖЕТІНІҢ АТҚАРЫЛУЫ | E3: Г.АСТАНА
A4: (млн.теңге) | E4: (млн. тенге)
A5: Атауы | B5: 2022 ж. есеп/ 2022 г. отчет | C5: 2023 ж. есеп/ 2023 г. отчет | D5: 2024 ж. есеп/ 2024 г. отчет | F5: 2025 ж. қантар-ақпан есеп/январь-феврал отчет 2025 г. | G5: Наименование
D6: жылдық/ годовой | E6: қантар-ақпан/январь-феврал
A7: 1 | B7: 2 | C7: 3 | D7: 4 | E7: 5 | F7: 6 | G7: 7
A8: I. КІРІСТЕР | B8: 898608.87 | C8: 1214113.6 | D8: 1362235.7 | E8: 172189.02 | F8: 247657.51 | G8: I. ДОХОДЫ
A9: Салықтық түсімдер_x000D_ оның iшiнде: | B9: 556603.65 | C9: 740597.87 | D9: 999235.25 | E9: 154234.6 | F9: 187626.78 | G9: Налоговые поступления,_x000D_ в том числе:
A10: корпорациялық табыс салығы | B10: 174626.78 | C10: 213956.37 | D10: 345278.42 | E10: 39506.701 | F10: 48385.428 | G10: корпоративный подоходный налог
A11: жеке табыс салығы | B11: 193983.18 | C11: 274609.96 | D11: 345535.64 | E11: 59006.248 | F11: 72939.434 | G11: индивидуальный подоходный налог
A12: әлеуметтік салық | B12: 130486.4 | C12: 172818.42 | D12: 217507.87 | E12: 41026.082 | F12: 50107.813 | G12: социальный налог
A13: акциздер | B13: 335.26185 | C13: 494.4745 | D13: 398.92685 | E13: 105.45896 | F13: 101.46813 | G13: акцизы
A14: Салықтық емес түсімдер | B14: 19576.334 | C14: 21947.539 | D14: 72224.371 | E14: 3188.921 | F14: 9530.2935 | G14: Неналоговые поступления
A15: Негізгі капиталды сатудан түсетін түсімдер | B15: 26325.768 | C15: 13395.537 | D15: 16189.97 | E15: 4608.9929 | F15: 1232.671 | G15: Поступления от продажи основного капитала
A16: Трансферттердің түсімдері | B16: 296103.12 | C16: 438172.65 | D16: 274586.08 | E16: 10156.508 | F16: 49267.762 | G16: Поступления трансфертов
A17: II. ШЫҒЫНДАР | B17: 856289.05 | C17: 1104676.1 | D17: 1274128.6 | E17: 112161.74 | F17: 156093.2 | G17: II. ЗАТРАТЫ
A18: 1. Жалпы сипаттағы мемлекеттiк қызметтер | B18: 40014.73 | C18: 24279.956 | D18: 39994.935 | E18: 7341.1477 | F18: 1985.6364 | G18: 1. Государственные услуги общего характера
A19: 2. Қорғаныс | B19: 4167.4934 | C19: 4020.8667 | D19: 5256.4435 | E19: 332.32696 | F19: 319.1292 | G19: 2. Оборона
... A37: Қаржылық активтерді сатып алу | B37: 19195.808 | C37: 116663.06 | D37: 47690.034 | E37: 4475.4131 | F37: 43764.939 | G37: Приобретение финансовых активов
A38: Мемлекеттің қаржы активтерін сатудан түсетін түсімдер | B38: 32.4101 | C38: 59.56885 | D38: 0.39444 | E38: 0.110713 | G38: Поступления от продажи финансовых активов государства
A39: V. БЮДЖЕТ ТАПШЫЛЫҒЫ (ПРОФИЦИТІ) | B39: -9614.7864 | C39: -10078.596 | D39: 40222.557 | E39: 56104.183 | F39: 43894.807 | G39: V. ДЕФИЦИТ (ПРОФИЦИТ) БЮДЖЕТА
A41: VII. БЮДЖЕТТІҢ ТАПШЫЛЫҒЫН ҚАРЖЫЛАНДЫРУ (ПРОФИЦИТТІ ПАЙДАЛАНУ | B41: 9614.7864 | C41: 10078.596 | D41: 40222.557 | E41: -56104.183 | F41: -43894.807 | G41: VII. ФИНАНСИРОВАНИЕ ДЕФИЦИТА (ИСПОЛЬЗОВАНИЕ ПРОФИЦИТА) БЮДЖЕТА
A42: Ішкі | B42: 192902.28 | C42: 207074.39 | D42: -678096.76 | E42: -535088.17 | F42: -43894.807 | G42: Внутреннее
A43: Түсімдер | B43: 232117.65 | C43: 222464.5 | D43: -640900.98 | E43: -522527.98 | F43: -43826.807 | G43: Поступление
A44: Өтеу | B44: 39215.369 | C44: 15390.112 | D44: 37195.777 | E44: 12560.184 | F44: 68 | G44: Погашение
A45: Сыртқы | B45: - | C45: - | D45: - | E45: - | F45: - | G45: Внешнее
A46: Түсімдер | B46: - | C46: - | D46: - | E46: - | F46: - | G46: Поступление
A47: Өтеу | B47: - | C47: - | D47: - | E47: - | F47: - | G47: Погашение

Sheet табл 12.18
A1: 12.18-кесте | E1: Таблица 12.18
A2: ЖЕТІСУ ОБЛЫСЫ | E2: ИСПОЛНЕНИЕ БЮДЖЕТА
A3: БЮДЖЕТІНІҢ АТҚАРЫЛУЫ | E3: ОБЛАСТЬ ЖЕТІСУ
A4: (млн.теңге) | E4: (млн. тенге)
A5: Атауы | B5: 2022 ж. есеп/ 2022 г. отчет | C5: 2023 ж. есеп/ 2023 г. отчет | D5: 2024 ж. есеп/ 2024 г. отчет | F5: 2025 ж. қантар-ақпан есеп/январь-феврал отчет 2025 г. | G5: Наименование
D6: жылдық/ годовой | E6: қантар-ақпан/январь-феврал
A7: 1 | B7: 2 | C7: 3 | D7: 4 | E7: 5 | F7: 6 | G7: 7
A8: I. КІРІСТЕР | B8: 314563.64 | C8: 463421.37 | D8: 542203.66 | E8: 56892.79 | F8: 65844.552 | G8: I. ДОХОДЫ
A9: Салықтық түсімдер_x000D_ оның iшiнде: | B9: 18067.345 | C9: 66904.461 | D9: 87798.583 | E9: 14403.614 | F9: 17389.199 | G9: Налоговые поступления,_x000D_ в том числе:
A10: корпорациялық табыс салығы | B10: 2806.2266 | C10: 9017.648 | D10: 13383.169 | E10: 1571.7128 | F10: 2001.9187 | G10: корпоративный подоходный налог
A11: жеке табыс салығы | B11: 7258.0591 | C11: 25930.316 | D11: 34956.565 | E11: 5911.8573 | F11: 7447.8425 | G11: индивидуальный подоходный налог
A12: әлеуметтік салық | B12: 5466.8729 | C12: 18598.439 | D12: 23298.185 | E12: 4191.6056 | F12: 5019.6021 | G12: социальный налог
A13: акциздер | B13: 35.103894 | C13: 108.67661 | D13: 115.49381 | E13: 16.569197 | F13: 18.483963 | G13: акцизы
A14: Салықтық емес түсімдер | B14: 811.24923 | C14: 7011.9315 | D14: 15570.046 | E14: 710.03295 | F14: 638.46023 | G14: Неналоговые поступления
A15: Негізгі капиталды сатудан түсетін түсімдер | B15: 1516.0592 | C15: 1881.3507 | D15: 14651.2 | E15: 3527.7538 | F15: 1288.8971 | G15: Поступления от продажи основного капитала
A16: Трансферттердің түсімдері | B16: 294168.99 | C16: 387623.63 | D16: 424183.83 | E16: 38251.389 | F16: 46527.995 | G16: Поступления трансфертов
A17: II. ШЫҒЫНДАР | B17: 333888.75 | C17: 468267.8 | D17: 529861.03 | E17: 49304.04 | F17: 61553.075 | G17: II. ЗАТРАТЫ
A18: 1. Жалпы сипаттағы мемлекеттiк қызметтер | B18: 15467.947 | C18: 21805.231 | D18: 21189.219 | E18: 2550.1593 | F18: 3023.7296 | G18: 1. Государственные услуги общего характера
A19: 2. Қорғаныс | B19: 857.189 | C19: 2597.8495 | D19: 4147.4281 | E19: 57.973763 | F19: 94.112809 | G19: 2. Оборона
... A37: Қаржылық активтерді сатып алу | B37: 229 | C37: 1369.6586 | D37: 2879.5543 | E37: 215 | F37: 75.895 | G37: Приобретение финансовых активов
A38: Мемлекеттің қаржы активтерін сатудан түсетін түсімдер | C38: 139.67744 | D38: 16.454256 | G38: Поступления от продажи финансовых активов государства
A39: V. БЮДЖЕТ ТАПШЫЛЫҒЫ (ПРОФИЦИТІ) | B39: -22710.45 | C39: -15200.423 | D39: -1835.6411 | E39: 7467.7618 | F39: 4588.3999 | G39: V. ДЕФИЦИТ (ПРОФИЦИТ) БЮДЖЕТА
A41: VII. БЮДЖЕТТІҢ ТАПШЫЛЫҒЫН ҚАРЖЫЛАНДЫРУ (ПРОФИЦИТТІ ПАЙДАЛАНУ | B41: 22710.45 | C41: 15200.423 | D41: -1835.6411 | E41: -7467.7618 | F41: -4588.3999 | G41: VII. ФИНАНСИРОВАНИЕ ДЕФИЦИТА (ИСПОЛЬЗОВАНИЕ ПРОФИЦИТА) БЮДЖЕТА
A42: Ішкі | B42: 249468.62 | C42: 105211.69 | D42: -202290.09 | E42: -27021.151 | F42: -4588.3999 | G42: Внутреннее
A43: Түсімдер | B43: 255500.31 | C43: 112586.44 | D43: -190675.47 | E43: -21330.97 | F43: -4058.8961 | G43: Поступление
A44: Өтеу | B44: 6031.6945 | C44: 7374.7509 | D44: 11614.621 | E44: 5690.181 | F44: 529.50375 | G44: Погашение
A45: Сыртқы | B45: - | C45: - | D45: - | E45: - | F45: - | G45: Внешнее
A46: Түсімдер | B46: - | C46: - | D46: - | E46: - | F46: - | G46: Поступление
A47: Өтеу | B47: - | C47: - | D47: - | E47: - | F47: - | G47: Погашение

Sheet табл 12.19
A1: 12.19-кесте | E1: Таблица 12.19
A2: АБАЙ ОБЛЫСЫ | E2: ИСПОЛНЕНИЕ БЮДЖЕТА
A3: БЮДЖЕТІНІҢ АТҚАРЫЛУЫ | E3: ОБЛАСТЬ АБАЙ
A4: (млн.теңге) | E4: (млн. тенге)
A5: Атауы | B5: 2022 ж. есеп/ 2022 г. отчет | C5: 2023 ж. есеп/ 2023 г. отчет | D5: 2024 ж. есеп/ 2024 г. отчет | F5: 2025 ж. қантар-ақпан есеп/январь-феврал отчет 2025 г. | G5: Наименование
D6: жылдық/ годовой | E6: қантар-ақпан/январь-феврал
A7: 1 | B7: 2 | C7: 3 | D7: 4 | E7: 5 | F7: 6 | G7: 7
A8: I. КІРІСТЕР | B8: 123963.96 | C8: 406297.42 | D8: 436986.27 | E8: 51944.572 | F8: 58616.931 | G8: I. ДОХОДЫ
A9: Салықтық түсімдер_x000D_ оның iшiнде: | B9: 23640.793 | C9: 96670.78 | D9: 120573.62 | E9: 20469.123 | F9: 23436.488 | G9: Налоговые поступления,_x000D_ в том числе:
A10: корпорациялық табыс салығы | B10: 3442.4366 | C10: 10602.802 | D10: 15174.453 | E10: 1917.3003 | F10: 2205.9221 | G10: корпоративный подоходный налог
A11: жеке табыс салығы | B11: 8475.622 | C11: 35508.593 | D11: 47635.001 | E11: 8319.4828 | F11: 9220.5258 | G11: индивидуальный подоходный налог
A12: әлеуметтік салық | B12: 6413.9815 | C12: 25133.408 | D12: 31334.967 | E12: 5518.5763 | F12: 6210.799 | G12: социальный налог
A13: акциздер | B13: 47.402816 | C13: 120.5248 | D13: 136.75735 | E13: 19.438542 | F13: 27.719488 | G13: акцизы
A14: Салықтық емес түсімдер | B14: 1403.9666 | C14: 5854.4088 | D14: 7963.6674 | E14: 788.91741 | F14: 822.21649 | G14: Неналоговые поступления
A15: Негізгі капиталды сатудан түсетін түсімдер | B15: 1877.6062 | C15: 9525.8628 | D15: 7036.9998 | E15: 657.13303 | F15: 2309.3127 | G15: Поступления от продажи основного капитала
A16: Трансферттердің түсімдері | B16: 97041.596 | C16: 294246.37 | D16: 301411.98 | E16: 30029.399 | F16: 32048.914 | G16: Поступления трансфертов
A17: II. ШЫҒЫНДАР | B17: 241281 | C17: 400475.3 | D17: 450819.22 | E17: 41029.548 | F17: 46052.123 | G17: II. ЗАТРАТЫ
A18: 1. Жалпы сипаттағы мемлекеттiк қызметтер | B18: 13142.849 | C18: 18110.235 | D18: 18833.812 | E18: 2188.9012 | F18: 2845.4233 | G18: 1. Государственные услуги общего характера
A19: 2. Қорғаныс | B19: 454.4762 | C19: 1514.0761 | D19: 2981.9366 | E19: 100.82927 | F19: 92.503098 | G19: 2. Оборона
... A37: Қаржылық активтерді сатып алу | B37: 20.0976 | C37: 1138.5577 | D37: 439.7482 | E37: 0 | F37: 0 | G37: Приобретение финансовых активов
A38: Мемлекеттің қаржы активтерін сатудан түсетін түсімдер | B38: 6.58692 | C38: 11.111278 | D38: 5.707039 | G38: Поступления от продажи финансовых активов государства
A39: V. БЮДЖЕТ ТАПШЫЛЫҒЫ (ПРОФИЦИТІ) | B39: -120429.75 | C39: -1273.3862 | D39: -25745.844 | E39: 10972.007 | F39: 12643.466 | G39: V. ДЕФИЦИТ (ПРОФИЦИТ) БЮДЖЕТА
A41: VII. БЮДЖЕТТІҢ ТАПШЫЛЫҒЫН ҚАРЖЫЛАНДЫРУ (ПРОФИЦИТТІ ПАЙДАЛАНУ | B41: 120429.75 | C41: 1273.3862 | D41: -25745.844 | E41: -10972.007 | F41: -12643.466 | G41: VII. ФИНАНСИРОВАНИЕ ДЕФИЦИТА (ИСПОЛЬЗОВАНИЕ ПРОФИЦИТА) БЮДЖЕТА
A42: Ішкі | B42: 1403591.2 | C42: -13422.418 | D42: 66813.71 | E42: -131539.47 | F42: -12643.466 | G42: Внутреннее
A43: Түсімдер | B43: 1410351.7 | C43: -4225.5401 | D43: 78615.675 | E43: -131528.33 | F43: -12643.466 | G43: Поступление
A44: Өтеу | B44: 6760.4604 | C44: 9196.8776 | D44: 11801.966 | E44: 11.142884 | F44: - | G44: Погашение
A45: Сыртқы | B45: - | C45: - | D45: - | E45: - | F45: - | G45: Внешнее
A46: Түсімдер | B46: - | C46: - | D46: - | E46: - | F46: - | G46: Поступление
A47: Өтеу | B47: - | C47: - | D47: - | E47: - | F47: - | G47: Погашение

Sheet табл 12.20
A1: 12.20-кесте | E1: Таблица 12.20
A2: ҰЛЫТАУ ОБЛЫСЫ | E2: ИСПОЛНЕНИЕ БЮДЖЕТА
A3: БЮДЖЕТІНІҢ АТҚАРЫЛУЫ | E3: ОБЛАСТЬ УЛЫТАУ
A4: (млн.теңге) | E4: (млн. тенге)
A5: Атауы | B5: 2022 ж. есеп/ 2022 г. отчет | C5: 2023 ж. есеп/ 2023 г. отчет | D5: 2024 ж. есеп/ 2024 г. отчет | F5: 2025 ж. қантар-ақпан есеп/январь-феврал отчет 2025 г. | G5: Наименование
D6: жылдық/ годовой | E6: қантар-ақпан/январь-феврал
A7: 1 | B7: 2 | C7: 3 | D7: 4 | E7: 5 | F7: 6 | G7: 7
A8: I. КІРІСТЕР | B8: 69867.744 | C8: 169203.26 | D8: 182521.75 | E8: 28782.748 | F8: 33370.558 | G8: I. ДОХОДЫ
A9: Салықтық түсімдер_x000D_ оның iшiнде: | B9: 29082.263 | C9: 88623.044 | D9: 101434.1 | E9: 22244.074 | F9: 22114.81 | G9: Налоговые поступления,_x000D_ в том числе:
A10: корпорациялық табыс салығы | B10: 1033.0279 | C10: 3437.64 | D10: 3853.4637 | E10: 584.62901 | F10: 589.43537 | G10: корпоративный подоходный налог
A11: жеке табыс салығы | B11: 15216.672 | C11: 35167.663 | D11: 42259.528 | E11: 9598.1403 | F11: 8729.7673 | G11: индивидуальный подоходный налог
A12: әлеуметтік салық | B12: 7006.6025 | C12: 26713.417 | D12: 30448.408 | E12: 7064.0385 | F12: 6692.9836 | G12: социальный налог
A13: акциздер | B13: 10.406807 | C13: 31.923543 | D13: 34.491962 | E13: 6.0514873 | F13: 5.7342009 | G13: акцизы
A14: Салықтық емес түсімдер | B14: 701.8482 | C14: 1846.7391 | D14: 4476.532 | E14: 169.29435 | F14: 419.26286 | G14: Неналоговые поступления
A15: Негізгі капиталды сатудан түсетін түсімдер | B15: 388.8179 | C15: 836.04433 | D15: 573.04005 | E15: 47.515419 | F15: 385.86388 | G15: Поступления от продажи основного капитала
A16: Трансферттердің түсімдері | B16: 39694.814 | C16: 77897.437 | D16: 76038.08 | E16: 6321.864 | F16: 10450.621 | G16: Поступления трансфертов
A17: II. ШЫҒЫНДАР | B17: 104669.26 | C17: 173439.18 | D17: 190573.16 | E17: 16526.345 | F17: 16378.076 | G17: II. ЗАТРАТЫ
A18: 1. Жалпы сипаттағы мемлекеттiк қызметтер | B18: 9909.0703 | C18: 10297.274 | D18: 11032.221 | E18: 1254.5472 | F18: 1437.8135 | G18: 1. Государственные услуги общего характера
A19: 2. Қорғаныс | B19: 268.0898 | C19: 928.85161 | D19: 1060.7158 | E19: 56.335575 | F19: 12.049261 | G19: 2. Оборона
... A25: 8. Мәдениет, спорт, туризм және ақпараттық кеңістiк | B25: 5405.7242 | C25: 11072.391 | D25: 14249.226 | E25: 1026.9212 | F25: 1526.7491 | G25: 8. Культура, спорт, туризм и информационное пространство
A26: 9. Отын-энергетика кешенi және жер қойнауын пайдалану | B26: 2580.7009 | C26: 2111.9183 | D26: 1617.3985 | E26: - | F26: 217.419 | G26: 9. Топливно-энергетический комплекс и недропользование
A27: 10. Ауыл, су, орман, балық шаруашылығы, ерекше қорғалатын табиғи аумақтар, қоршаған ортаны және жануарлар дүниесін қорғау, жер қатынастары | B27: 2423.5281 | C27: 8623.1917 | D27: 6251.668 | E27: 548.39447 | F27: 507.36003 | G27: 10. Сельское, водное, лесное, рыбное хозяйство, особо охраняемые природные территории, охрана окружающей среды и животного мира, земельные отношения
A28: 11. Өнеркәсіп, сәулет, қала құрылысы және құрылыс қызметі | B28: 894.39662 | C28: 1225.5944 | D28: 6674.6113 | E28: 62.357601 | F28: 67.196415 | G28: 11. Промышленность, архитектурная, градостроительная и строительная деятельность
A29: 12. Көлiк және коммуникация | B29: 10316.818 | C29: 15331.074 | D29: 15063.926 | E29: 1412.2321 | F29: 1039.633 | G29: 12. Транспорт и коммуникации
A30: 13. Басқалар | B30: 1638.8779 | C30: 6545.8687 | D30: 6062.656 | E30: 400 | F30: 1250.1674 | G30: 13. Прочие
A31: 14. Борышқа қызмет көрсету | B31: 814.0187 | C31: 813.04393 | D31: 804.37548 | E31: 0.00575 | F31: 0.0345 | G31: 14. Обслуживание долга
A32: 15. Трансферттер | B32: 4251.929 | C32: 1346.4662 | D32: 2046.2773 | E32: 1727.7743 | F32: 198.54662 | G32: 15. Трансферты
A33: III. ТАЗА БЮДЖЕТТІК КРЕДИТ БЕРУ | B33: 761.96129 | C33: 4807.962 | D33: 3901.1676 | E33: -20.31406 | F33: -83.166506 | G33: III. ЧИСТОЕ БЮДЖЕТНОЕ КРЕДИТОВАНИЕ
A34: Бюджеттік кредиттер | B34: 805.26827 | C34: 4932.1192 | D34: 4143.1314 | E34: 0 | F34: 0 | G34: Бюджетные кредиты
A35: Бюджеттік кредиттерді өтеу | B35: 43.306982 | C35: 124.1571 | D35: 241.9638 | E35: 20.31406 | F35: 83.166506 | G35: Погашение бюджетных кредитов
A36: IV. ҚАРЖЫ АКТИВТЕРІМЕН ОПЕРАЦИЯЛАР БОЙЫНША САЛЬДО - ҚАРЖЫ АК | B36: 605.2533 | C36: 600 | G36: IV. САЛЬДО ПО ОПЕРАЦИЯМ С ФИНАНСОВЫМИ АКТИВАМИ
A37: Қаржылық активтерді сатып алу | B37: 605.2533 | C37: 600 | G37: Приобретение финансовых активов
A38: V. БЮДЖЕТ ТАПШЫЛЫҒЫ (ПРОФИЦИТІ) | B38: -36168.732 | C38: -9643.875 | D38: -11952.578 | E38: 12276.717 | F38: 17075.648 | G38: V. ДЕФИЦИТ (ПРОФИЦИТ) БЮДЖЕТА
A40: VII. БЮДЖЕТТІҢ ТАПШЫЛЫҒЫН ҚАРЖЫЛАНДЫРУ (ПРОФИЦИТТІ ПАЙДАЛАНУ | B40: 36168.732 | C40: 9643.875 | D40: -11952.578 | E40: -12276.717 | F40: -17075.648 | G40: VII. ФИНАНСИРОВАНИЕ ДЕФИЦИТА (ИСПОЛЬЗОВАНИЕ ПРОФИЦИТА) БЮДЖЕТА
A41: Ішкі | B41: 434411.53 | C41: 27104.05 | D41: 46198.148 | E41: -147090.36 | F41: -17075.648 | G41: Внутреннее
A42: Түсімдер | B42: 435253.89 | C42: 27814.732 | D42: 48671.376 | E42: -147069.43 | F42: -17075.648 | G42: Поступление
A43: Өтеу | B43: 842.36092 | C43: 710.68167 | D43: 2473.2288 | E43: 20.93135 | F43: - | G43: Погашение
A44: Сыртқы | B44: - | C44: - | D44: - | E44: - | F44: - | G44: Внешнее
A45: Түсімдер | B45: - | C45: - | D45: - | E45: - | F45: - | G45: Поступление
A46: Өтеу | B46: - | C46: - | D46: - | E46: - | F46: - | G46: Погашение

Sheet табл 13
B2: Отчет об исполнении консолидированного бюджета
B3: на 1 марта 2025 года
B4: Периодичность: месячная
B5: Единица измерения: тыс.тг
B7: Коды бюджетной классификации | C7: Наименование | E7: Скорректированный бюджет | F7: Исполнение | G7: % исполнение
B8: 1 | C8: 2 | E8: 3 | F8: 4 | G8: 5
C9: I. ДОХОДЫ | E9: 2.8270874e+10 | F9: 4.5551955e+09 | G9: 16.11268
C10: НАЛОГОВЫЕ ПОСТУПЛЕНИЯ | E10: 2.7471284e+10 | F10: 4.2464875e+09 | G10: 15.457914
B11: 1 | C11: Налоговые поступления | E11: 2.7471284e+10 | F11: 4.2464875e+09 | G11: 15.457914
C12: НЕНАЛОГОВЫЕ ПОСТУПЛЕНИЯ | E12: 5.3419782e+08 | F12: 2.7938427e+08 | G12: 52.299777
B13: 2 | C13: Неналоговые поступления | E13: 5.3419782e+08 | F13: 2.7938427e+08 | G13: 52.299777
C14: ПОСТУПЛЕНИЯ ОТ ПРОДАЖИ ОСНОВНОГО КАПИТАЛА | E14: 265392020 | F14: 29323730 | G14: 11.049213
B15: 3 | C15: Поступления от продажи основного капитала | E15: 265392020 | F15: 29323730 | G15: 11.049213
C16: ПОСТУПЛЕНИЯ ТРАНСФЕРТОВ | E16: 0 | F16: 0
B17: 4 | C17: Поступления трансфертов | E17: 0 | F17: 0
C18: II. ИНВЕСТИЦИОННЫЕ ДОХОДЫ ОТ УПРАВЛЕНИЯ НАЦИОНАЛЬНЫМ ФОНДОМ | E18: 888700000 | F18: 0 | G18: 0
C19: III. ИНЫЕ ПОСТУПЛЕНИЯ И ДОХОДЫ, НЕ ЗАПРЕЩЕННЫЕ ЗАКОНОДАТЕЛЬСТВОМ РЕСПУБЛИКИ КАЗАХСТАН | E19: 0 | F19: 0 | G19: 0
C20: IV. ПОСТУПЛЕНИЯ В ГФСС | E20: 1072924400 | F20: 144623447 | G20: 13.47937
C21: V. ПОСТУПЛЕНИЯ В ФСМС | E21: 1156892414 | F21: 1.8960222e+08 | G21: 16.388924
C22: VI. ЗАТРАТЫ | E22: 2.9869222e+10 | F22: 4.0412348e+09 | G22: 13.529762
B23: 1 | C23: Государственные услуги общего характера | E23: 1.5640777e+09 | F23: 2.8549339e+08 | G23: 18.253147
B24: 2 | C24: Оборона | E24: 1342503280 | F24: 92355081 | G24: 6.8793188
B25: 3 | C25: Общественный порядок, безопасность, правовая, судебная, уголовно-исполнительная деятельность | E25: 1744672149 | F25: 2.0219487e+08 | G25: 11.589276
B26: 4 | C26: Образование | E26: 6.9466257e+09 | F26: 9.2806096e+08 | G26: 13.359881
B27: 5 | C27: Здравоохранение | E27: 663637735 | F27: 49977412 | G27: 7.5308274
B28: 6 | C28: Социальная помощь и социальное обеспечение | E28: 6.9586948e+09 | F28: 1.0867593e+09 | G28: 15.617287
B29: 7 | C29: Жилищно-коммунальное хозяйство | E29: 1.9790637e+09 | F29: 1.6045178e+08 | G29: 8.1074592
B30: 8 | C30: Культура, спорт, туризм и информационное пространство | E30: 1.1051361e+09 | F30: 1.5317314e+08 | G30: 13.860116
B31: 9 | C31: Топливно-энергетический комплекс и недропользование | E31: 3.0320493e+08 | F31: 38083380 | G31: 12.560277
B32: 10 | C32: Сельское, водное, лесное, рыбное хозяйство, особо охраняемые природные территории, охрана окружающей среды и животного мира, земельные отношения | E32: 1282349346 | F32: 1.847878e+08 | G32: 14.410098
B33: 11 | C33: Промышленность, архитектурная, градостроительная и строительная деятельность | E33: 71470033 | F33: 5823824.8 | G33: 8.1486247
B34: 12 | C34: Транспорт и коммуникации | E34: 2.1560748e+09 | F34: 2.2510804e+08 | G34: 10.440641
... B36: 14 | C36: Обслуживание долга | E36: 2554145555 | F36: 5.3222477e+08 | G36: 20.837684
B37: 15 | C37: Трансферты | E37: 0 | F37: 0
C38: VII. ВЫПЛАТЫ С КСН ФКП | E38: 0 | F38: 31271.5
C39: VIII. ПОКРЫТИЕ РАСХОДОВ, СВЯЗАННЫХ С УПРАВЛЕНИЕМ НАЦИОНАЛЬНЫМ ФОНДОМ И ПРОВЕДЕНИЕМ ЕЖЕГОДНОГО ВНЕШНЕГО АУДИТА | E39: 84100000 | F39: 778187.6 | G39: 0.92531225
C40: IX. РАСХОДЫ ГФСС | E40: 1041227798 | F40: 226089872 | G40: 21.713776
C41: X. РАСХОДЫ ФСМС | E41: 3266018411 | F41: 5.1970851e+08 | G41: 15.912602
C42: XI. РАСХОДЫ ФПИО | E42: 0 | F42: 0
C43: XII. РАСХОДЫ СГФ | E43: 0 | F43: 17326634
C44: XIII. ЧИСТОЕ БЮДЖЕТНОЕ КРЕДИТОВАНИЕ | E44: 3.248828e+08 | F44: 12537673
C45: БЮДЖЕТНЫЕ КРЕДИТЫ | E45: 594996126 | F45: 25137485 | G45: 4.2248149
B46: 6 | C46: Социальная помощь и социальное обеспечение | E46: 471525 | F46: 18084.8 | G46: 3.8353852
B47: 7 | C47: Жилищно-коммунальное хозяйство | E47: 53858928 | F47: 4019400 | G47: 7.4628296
B48: 10 | C48: Сельское, водное, лесное, рыбное хозяйство, особо охраняемые природные территории, охрана окружающей среды и животного мира, земельные отношения | E48: 4.1882992e+08 | F48: 21100000 | G48: 5.0378445
B49: 11 | C49: Промышленность, архитектурная, градостроительная и строительная деятельность | E49: 30000000 | F49: 0 | G49: 0
B50: 12 | C50: Транспорт и коммуникации
B51: 13 | C51: Прочие | E51: 26355750 | F51: 0 | G51: 0
C52: ПОГАШЕНИЕ БЮДЖЕТНЫХ КРЕДИТОВ | E52: 2.7011333e+08 | F52: 12599811 | G52: 4.6646389
B53: 5 | C53: Погашение бюджетных кредитов | E53: 2.7011333e+08 | F53: 12599811 | G53: 4.6646389
C54: XIV. САЛЬДО ПО ОПЕРАЦИЯМ С ФИНАНСОВЫМИ АКТИВАМИ | E54: 471725235 | F54: 68073492
C55: ПРИОБРЕТЕНИЕ ФИНАНСОВЫХ АКТИВОВ | E55: 472923335 | F55: 68246713 | G55: 14.43082
B56: 1 | C56: Государственные услуги общего характера | E56: 15874081 | F56: 76745.48 | G56: 0.48346408
B57: 7 | C57: Жилищно-коммунальное хозяйство | E57: 373000 | F57: 0 | G57: 0
B58: 10 | C58: Сельское, водное, лесное, рыбное хозяйство, особо охраняемые природные территории, охрана окружающей среды и животного мира, земельные отношения | E58: 30000000 | F58: 0 | G58: 0
B59: 11 | C59: Промышленность, архитектурная, градостроительная и строительная деятельность
B60: 12 | C60: Транспорт и коммуникации | E60: 361016045 | F60: 40000000 | G60: 11.07984
B61: 13 | C61: Прочие | E61: 64642990 | F61: 28169968 | G61: 43.577761
C62: ПОСТУПЛЕНИЯ ОТ ПРОДАЖИ ФИНАНСОВЫХ АКТИВОВ ГОСУДАРСТВА | E62: 1198100 | F62: 173221.29 | G62: 14.458
B63: 6 | C63: Поступления от продажи финансовых активов государства | E63: 1198100 | F63: 173221.29 | G63: 14.458
C64: XV. ДЕФИЦИТ (ПРОФИЦИТ) БЮДЖЕТА | E64: -3.667786e+09 | F64: 3640732
C65: XVI. НЕНЕФТЯНОЙ ДЕФИЦИТ (ПРОФИЦИТ) БЮДЖЕТА | E65: -5.317486e+09 | F65: -1.149908e+08
C66: XVII. ФИНАНСИРОВАНИЕ ДЕФИЦИТА (ИСПОЛЬЗОВАНИЕ ПРОФИЦИТА) БЮДЖЕТА | E66: 3.667786e+09 | F66: -3640732
