Workbook
Name \E: #REF!
Name \E: #REF!
Name \E: #REF!
Name \E: #REF!
Name \E: #REF!
Name _____________________MS798: #REF!
Name _____________________MS798: #REF!
Name _____________________tab1: #REF!
Name _____________________tab2: #REF!
Name _____________________tab6798: #REF!
Name ____________________MS798: #REF!
Name ____________________tab1: #REF!
Name ____________________tab2: #REF!
Name ____________________tab6798: #REF!
Name ___________________MS798: #REF!
Name ___________________tab1: #REF!
Name ___________________tab2: #REF!
Name ___________________tab6798: #REF!
Name __________________MS798: #REF!
Name __________________tab1: #REF!
Name __________________tab2: #REF!
Name __________________tab6798: #REF!
Name _________________MS798: #REF!
Name _________________prt1: #N/A
Name _________________prt2: #N/A
Name _________________prt3: #N/A
Name _________________prt4: #N/A
Name _________________prt5: #N/A
Name _________________prt6: #N/A
Name _________________prt7: #N/A
Name _________________prt8: #N/A
Name _________________tab1: #REF!
Name _________________tab2: #REF!
Name _________________tab6798: #REF!
Name ________________MS798: #REF!
Name ________________prt1: #N/A
Name ________________prt2: #N/A
Name ________________prt3: #N/A
Name ________________prt4: #N/A
Name ________________prt5: #N/A
Name ________________prt6: #N/A
Name ________________prt7: #N/A
Name ________________prt8: #N/A
Name ________________tab1: #REF!
Name ________________tab2: #REF!
Name ________________tab6798: #REF!
Name _______________MS798: #REF!
Name _______________prt1: #N/A
Name _______________prt2: #N/A
Name _______________prt3: #N/A
Name _______________prt4: #N/A
Name _______________prt5: #N/A
Name _______________prt6: #N/A
Name _______________prt7: #N/A
Name _______________prt8: #N/A
Name _______________tab1: #REF!
Name _______________tab2: #REF!
Name _______________tab6798: #REF!
Name ______________MS798: #REF!
Name ______________prt1: #N/A

Sheet табл 1
A1: 1-кесте | J1: Таблица 1
A3: НЕГІЗГІ МАКРОЭКОНОМИКАЛЫҚ ИНДИКАТОРЛАР/
A4: ОСНОВНЫЕ МАКРОЭКОНОМИЧЕСКИЕ ИНДИКАТОРЫ
A6: Атауы | B6: 2019 жыл/ 2019 год | C6: 2020 жыл/ 2020 год | D6: 2021 жыл/ 2021 год | E6: 2022 жыл/ 2022 год | F6: 2023 жыл/ 2023 год | G6: 2024 жыл/ 2024 год | H6: 2025 жыл/ 2025 год | I6: 2026 ж. 1 сәуірдегі есеп/ отчет на 1 апреля 2026 г. | J6: Наименование
A7: 1 | B7: 2 | C7: 3 | D7: 4 | E7: 5 | F7: 6 | G7: 7 | H7: 8 | I7: 9 | J7: 10
A8: Жалпы ішкi өнiм, млрд. теңге | B8: 69532.626 | C8: 70649 | D8: 83951.587 | E8: 65487.797 | F8: 120561.1 | G8: 84962.621 | H8: 99724.898 | I8: 159583.75 | J8: Валовой внутренний продукт, млрд.тенге январь-декабрь 2025 года (предварительные данные)
A9: өткен жылдың тиiстi кезеңiндегi нақты есептеудегi %-бен | B9: 104.5 | C9: 97.5 | D9: 103.3 | E9: 103 | F9: 105.1 | G9: 104.1 | H9: 106.3 | I9: 106.5 | J9: в % к соответствующему периоду предыдущего года
A10: Өнеркәсiп өнiмiнiң көлемi, млрд. теңге | B10: 29380.342 | C10: 26743.4 | D10: 37047.6 | E10: 4157.4 | F10: 46401.716 | G10: 50124.86 | H10: 61560.646 | I10: 15177.195 | J10: Объем промышленного производства, млрд.тенге (январь-март 2026г.)
A11: өткен жылдың тиiстi кезеңiне %-бен | B11: 104.1 | C11: 99.3 | D11: 103.8 | E11: 97.2 | F11: 104.3 | G11: 102.8 | H11: 107.5 | I11: 104.3 | J11: % март 2026г. к марту 2025г.
A12: Мембюджетке кірістер, млрд. теңге | B12: 12758.479 | C12: 14521.191 | D12: 15847.431 | E12: 20248.101 | F12: 24917.246 | G12: ='[46]табл 2 '!C8/1000 -> 27132.165 | H12: ='[47]табл 2 '!C8/1000 -> 29871.048 | I12: ='табл 2 '!C8/1000 -> 7244.8717 | J12: Доходы в госбюджет, млрд.тенге
A13: ЖIӨ-ге %-бен | B13: 18.502241 | C13: 20.535071 | D13: =D12/D8*100 -> 18.876869 | E13: =E12/E8*100 -> 30.918891 | G13: =G12/G8*100 -> 31.934237 | H13: =H12/H8*100 -> 29.95345 | I13: =I12/I8*100 -> 4.5398556 | J13: в % к ВВП
A14: Мембюджеттен шығындар, млрд. теңге | B14: 13535.581 | C14: 16725.097 | D14: 17951.888 | E14: 21532.543 | F14: 26760 | G14: ='[46]табл 2 '!C18/1000 -> 30318.236 | H14: ='[47]табл 2 '!C18/1000 -> 33442.829 | I14: ='табл 2 '!C19/1000 -> 7624.3219 | J14: Затраты из госбюджета, млрд. тенге
A15: ЖIӨ-ге %-бен | B15: 19.629188 | C15: 23.651714 | D15: =D14/D8*100 -> 21.38362 | E15: =E14/E8*100 -> 32.880238 | F15: 35.421743 | G15: =G14/G8*100 -> 35.684206 | H15: =H14/H8*100 -> 33.535084 | I15: =I14/I8*100 -> 4.7776305 | J15: в % к ВВП
A16: Таза бюджеттік кредит беру, млрд. теңге | B16: 262.88084 | C16: 261.98101 | D16: 267.33754 | E16: 592.68034 | F16: 466.44174 | G16: ='[46]табл 2 '!C34/1000 -> 198.40855 | H16: ='[47]табл 3'!E34/1000 -> 286.23027 | I16: ='табл 2 '!C35 -> -46558.897 | J16: Чистое бюджетное кредитование, млрд. тенге
A17: ЖIӨ-ге %-бен | B17: 0.38122761 | C17: 0.37047917 | D17: =D16/D8*100 -> 0.31844251 | E17: =E16/E8*100 -> 0.9050241 | F17: 0.61742075 | G17: =G16/G8*100 -> 0.23352452 | H17: =H16/H8*100 -> 0.28701987 | I17: =I16/I8*100 -> -29.175212 | J17: в % к ВВП
A18: Қаржылық активтермен болатын операциялар бойынша сальдо, млрд. теңге | B18: 245.32373 | C18: 340.26326 | D18: 163.01136 | E18: 292.00158 | F18: 501.9047 | G18: ='[46]табл 2 '!C37/1000 -> 201.56181 | H18: ='[47]табл 3'!E37/1000 -> 525.85985 | I18: ='табл 2 '!C38 -> 59247.785 | J18: Сальдо по операциям с финансовыми активами, млрд.тенге
A19: ЖIӨ-ге %-бен | B19: 0.35576643 | C19: 0.48118163 | D19: =D18/D8*100 -> 0.19417306 | E19: =E18/E8*100 -> 0.44588701 | F19: 0.66436244 | G19: =G18/G8*100 -> 0.23723586 | H19: =H18/H8*100 -> 0.52731049 | I19: =I18/I8*100 -> 37.126453 | J19: в % к ВВП
A20: Мембюджеттiң тапшылығы (-) / профицитi (+), млрд. теңге | B20: -1285.3067 | C20: -2806.1502 | D20: -2534.8062 | E20: -2169.1247 | F20: -2811.1006 | G20: ='[46]табл 2 '!C40/1000 -> -3586.0419 | H20: ='[47]табл 3'!E40/1000 -> -4383.8711 | I20: ='табл 2 '!C41 -> -392139.05 | J20: Дефицит (-) / профицит (+) госбюджета, млрд.тенге
A21: ЖIӨ-ге %-бен | B21: -1.8639412 | C21: -3.9683036 | D21: =D20/D8*100 -> -3.0193666 | E21: =E20/E8*100 -> -3.3122579 | F21: -3.7210045 | G21: =G20/G8*100 -> -4.2207288 | H21: =H20/H8*100 -> -4.3959645 | I21: =I20/I8*100 -> -245.72618 | J21: в % к ВВП
A22: Тұтыну бағаларының индексі өткен жылдың айына, %-бен | B22: 105.4 | C22: 107.5 | D22: 108.4 | E22: 120.3 | F22: 109.5 | G22: 108.9 | H22: 112.2 | I22: 117.7 | J22: Индекс потребительских цен март 2026
A23: орташа есеппен өткен жылдың тиiстi кезеңiндегi кезге арналған, %-бен | B23: 105.3 | C23: 106.8 | D23: 108 | E23: 115 | G23: 108.6 | H23: 103.9 | I23: 111 | J23: в % март 2026г. к марту 2025г.
A24: Орташа айлық атаулы жалақы 1 қызметкердың, теңге | B24: 186815 | C24: 220848 | D24: 268051 | E24: 303055 | F24: 350542 | G24: 390328 | H24: 429368 | I24: 473158 | J24: Среднемесячная номинальная заработная плата 1 работника, тенге (4 квартал 2025г.)
A25: өткен жылдың тиiстi кезеңiне %-бен | B25: 114.8 | C25: 104.4 | D25: 115.3 | E25: 112.2 | F25: 116.9 | G25: 111.3 | H25: 110 | I25: 108.8 | J25: в % к соответствующему периоду предыдущего года
A26: Экспорт, млн. АҚШ долл. | B26: 58065.6 | C26: 46 949,7 2 | D26: 54549.5 | E26: ____ | F26: 71274.7 | G26: 73884.5 | H26: 71135.7 | I26: 12036.8 | J26: Экспорт, млн. долл. США (январь -февраль2026г.)
A27: Импорт, млн. АҚШ долл. | B27: 39709.3 | C27: 38 081,4 2 | D27: 36825.9 | E27: ____ | F27: 54643.5 | G27: 53590.3 | H27: 57666.9 | I27: 9642.7 | J27: Импорт, млн. долл. США (январь -февраль2026г.)
A28: Сауда балансының сальдосы, млн. АҚШ долл. | B28: 18356.3 | C28: 8969 | D28: 17723.6 | E28: ____ | F28: 16631.2 | G28: =G26-G27 -> 20294.2 | H28: =H26-H27 -> 13468.8 | I28: =I26-I27 -> 2394.1 | J28: Сальдо торгового баланса, млн. долл. США
A29: Теңгенiң АҚШ долларына қарағандағы ресми айырбас бағамы: | J29: Официальный обменный курс тенге к доллару США:
A30: кезеңнiң аяғындағы | B30: 381.18 | C30: 420.71 | D30: 433.83 | E30: 459.92 | F30: 448.17 | G30: 525.11 | H30: 521.59 | I30: 481.54 | J30: на конец периода
A31: кезең бойынша орташа | B31: 382.75 | C31: 412.95 | D31: 433.66 | E31: 460.48 | F31: 451.28 | G31: 469.44 | H31: 502.57 | I31: 489.31 | J31: в среднем за март 2026 года
A33: Ақпарат көзi: / Источник:
A34: Қазақстан Республикасының Қаржы министрлiгi / Министерство финансов Республики Казахстан.
A35: Ұлттық статистика бюросы Қазақстан Республикасының Стратегиялық жоспарлау және реформалар агенттігі / Бюро национальной статистики Агентства по стратегическому планированию и реформам Республики Казахстан
A36: Қазақстан Республикасының Ұлттық Банкi / Национальный Банк Республики Казахстан.
A37: Ескерту: / Примечание:
A38: 1 - Ұлттық статистика бюросы Қазақстан Республикасының Стратегиялық жоспарлау және реформалар агенттігінің деректері бойынша /Объем ВВП по отчетным данным Бюро национальной статистики Агентства по стратегическому планированию и реформам Республики Казахстан
A39: 2 - Ұлттық статистика бюросы Қазақстан Республикасының Стратегиялық жоспарлау және реформалар агенттігінің деректері бойынша /По данным Бюро национальной статистики Агентства по стратегическому планированию и реформам Республики Казахстан
A40: 3 - Ұлттық статистика бюросы Қазақстан Республикасының Стратегиялық жоспарлау және реформалар агенттігінің деректері бойынша /По данным Бюро национальной статистики Агентства по стратегическому планированию и реформам Республики Казахстан

Sheet табл 2 
A1: 2-кесте | F1: Таблица - 2
A2: МЕМЛЕКЕТТІК ЖӘНЕ РЕСПУБЛИКАЛЫҚ | F2: СРАВНИТЕЛЬНЫЙ АНАЛИЗ ИСПОЛНЕНИЯ
A3: БЮДЖЕТТЕР АТҚАРЫЛУЫНЫҢ САЛЫСТЫРМА ТАЛДАУЫ | F3: ГОСУДАРСТВЕННОГО И РЕСПУБЛИКАНСКОГО БЮДЖЕТОВ
A5: Атауы | B5: Мемлекеттік бюджет / Государственный бюджет | F5: Республикалық бюджет / Республиканский бюджет | J5: Наименование
B6: 2026 жылға түзету енгізілген бюджет (млн. теңге)/ скорректированный бюджет на 2026 год (млн.тенге) | C6: 2026 жылғы қаңтар-наурыз атқарылуы (млн. теңге)/ исполнение за январь-март 2026 года (млн.тенге) | D6: бір жылға түзету енгізілген бюджеттің атқарылу %-ы/% исполнения к скорректированному бюджету на год | E6: 2025 ж. қаңтар-наурыз %-бен 2026 ж. қаңтар-наурызға/ 2026 г. январь-март в % к январю-марту 2025 г. | F6: 2026 жылға түзету енгізілген бюджет (млн. теңге)/ скорректированный бюджет на 2026 год (млн.тенге) | G6: 2026 жылғы қаңтар-наурыз атқарылуы (млн. теңге)/ исполнение за январь-март 2026 года (млн.тенге) | H6: бір жылға түзету енгізілген бюджеттің атқарылу %-ы/% исполнения к скорректированному бюджету на год | I6: 2025 ж. қаңтар-наурыз %-бен 2026 ж. қаңтар-наурызға/ 2026 г. январь-март в % к январю-марту 2025 г.
A7: 1 | B7: 2 | C7: 3 | D7: 4 | E7: 5 | F7: 6 | G7: 7 | H7: 8 | I7: 9 | J7: 10
A8: I. КІРІСТЕР | B8: 32504897 | C8: 7244871.7 | D8: 22.288555 | E8: 104.02858 | F8: 22889278 | G8: 5206986.9 | H8: 22.748585 | I8: 104.70859 | J8: I. ДОХОДЫ
A9: Салықтық түсімдер оның iшiнде: | B9: 28790353 | C9: 6198135.7 | D9: 21.528515 | E9: 119.87766 | F9: 18886019 | G9: 4077555.7 | H9: 21.59034 | I9: 131.65246 | J9: Налоговые поступления, в том числе:
A10: корпоративтік табыс салығы | B10: 7044250.8 | C10: 1495129.4 | D10: 21.224818 | E10: 107.4044 | F10: 5184046.5 | G10: 1191464.1 | H10: 22.983283 | I10: 116.92737 | J10: корпоративный подоходный налог
A11: жеке табыс салығы | B11: 3336636.6 | C11: 748169.79 | D11: 22.422873 | E11: 107.24885 | F11: 0 | G11: 0 | H11: 0 | I11: 0 | J11: индивидуальный подоходный налог
A12: әлеуметтік салық | B12: 2086356.7 | C12: 495812.63 | D12: 23.764519 | E12: 103.79842 | F12: 0 | G12: 0 | H12: 0 | I12: 0 | J12: социальный налог
A13: қосылған құн салығы | B13: 10013329 | C13: 1962484.6 | D13: 19.598723 | E13: 148.60224 | F13: 10013329 | G13: 1962484.6 | H13: 19.598723 | I13: 148.60224 | J13: налог на добавленную стоимость
A14: акциздер | B14: 1518521.3 | C14: 264607.33 | D14: 17.425329 | E14: 127.36115 | F14: 151773.43 | G14: 22064.597 | H14: 14.537852 | I14: 77.70416 | J14: акцизы
A15: Салықтық емес түсімдер | B15: 474019.55 | C15: 166839.26 | D15: 35.196704 | E15: 55.7378 | F15: 330736.78 | G15: 79068.8 | H15: 23.906867 | I15: 42.364301 | J15: Неналоговые поступления
A16: Негізгі капиталды сатудан түсетін түсімдер | B16: 271855.25 | C16: 36272.211 | D16: 13.342472 | E16: 81.33471 | F16: 2200 | G16: 257.17471 | H16: 11.68976 | I16: 15.617841 | J16: Поступления от продажи основного капитала
A17: Арнаулы түсімдер | B17: 198668.4 | C17: 43624.591 | D17: 21.958495 | E17: 3.00859 | F17: 20375.447 | G17: 2550.3603 | H17: 12.516831 | I17: - | J17: Специальные поступления
A18: Трансферттердің түсімдері | B18: 2770000 | C18: 800000 | D18: 28.880866 | F18: 3649947.1 | G18: 1047554.9 | H18: 28.700551 | I18: 62.265166 | J18: Поступление трансфертов
A19: II. ШЫҒЫНДАР | B19: 35810377 | C19: 7624321.9 | D19: 21.290817 | E19: 113.32613 | F19: 26275678 | G19: 5944897.9 | H19: 22.625098 | I19: 107.56403 | J19: II. ЗАТРАТЫ
A20: 1. Жалпы сипаттағы мемлекеттiк қызметтер | B20: 1761767 | C20: 391736.99 | D20: 22.235459 | E20: 99.58133 | F20: 1266365.4 | G20: 257675.37 | H20: 20.347632 | I20: 96.29092 | J20: 1. Государственные услуги общего характера
A21: 2. Қорғаныс | B21: 1529356.8 | C21: 282791.73 | D21: 18.490893 | E21: 182.48215 | F21: 1427833.2 | G21: 273330.38 | H21: 19.143019 | I21: 201.35676 | J21: 2. Оборона
A22: 3. Қоғамдық тәртіп, қауіпсіздік, құқықтық, сот, қылмыстық-атқару қызметі | B22: 1980261 | C22: 394276.06 | D22: 19.910307 | E22: 120.44573 | F22: 1502936.1 | G22: 305692.9 | H22: 20.339714 | I22: 120.76439 | J22: 3. Общественный порядок, безопасность, правовая, судебная, уголовно-исполнительная деятельность
A23: 4. Бiлiм беру | B23: 6978621.7 | C23: 1462774.4 | D23: 20.960792 | E23: 102.71087 | F23: 812571.93 | G23: 145944.51 | H23: 17.960812 | I23: 56.59529 | J23: 4. Образование
A24: 5. Денсаулық сақтау | B24: 3128524.6 | C24: 439222.66 | D24: 14.039291 | E24: 92.06388 | F24: 2731840.1 | G24: 382998.58 | H24: 14.019802 | I24: 88.4968 | J24: 5. Здравоохранение
A25: 6. Әлеуметтiк көмек және әлеуметтiк қамсыздандыру | B25: 7653082.2 | C25: 1838744.7 | D25: 24.026198 | E25: 112.51673 | F25: 6833009.5 | G25: 1700333.6 | H25: 24.884111 | I25: 113.12967 | J25: 6. Социальная помощь и социальное обеспечение
A26: 7. Тұрғын үй-коммуналдық шаруашылық | B26: 2271344.1 | C26: 377772.47 | D26: 16.632111 | E26: 131.40469 | F26: 95156.925 | G26: 14367.408 | H26: 15.098647 | I26: 61.70006 | J26: 7. Жилищно-коммунальное хозяйство
A27: 8. Мәдениет, спорт, туризм және ақпараттық кеңістiк | B27: 1175531.6 | C27: 238952.07 | D27: 20.32715 | E27: 101.27409 | F27: 236604.46 | G27: 51056.23 | H27: 21.578726 | I27: 89.60663 | J27: 8. Культура, спорт, туризм и информационное пространство
A28: 9. Отын-энергетика кешенi және жер қойнауын пайдалану | B28: 276947.51 | C28: 43645.822 | D28: 15.759601 | E28: 74.00988 | F28: 128415.45 | G28: 15089.131 | H28: 11.750246 | I28: 178.85383 | J28: 9. Топливно-энергетический комплекс и недропользование
A29: 10. Ауыл, су, орман, балық шаруашылығы, ерекше қорғалатын табиғи аумақтар, қоршаған ортаны және жануарлар дүниесін қорғау, жер қатынастары | B29: 1651669.9 | C29: 415305.46 | D29: 25.144581 | E29: 142.32139 | F29: 718055.7 | G29: 68362.497 | H29: 9.5205005 | I29: 115.65692 | J29: 10. Сельское, водное, лесное, рыбное хозяйство, особо охраняемые природные территории, охрана окружающей среды и животного мира, земельные отношения
A30: 11. Өнеркәсіп, сәулет, қала құрылысы және құрылыс қызметі | B30: 81101.556 | C30: 13460.093 | D30: 16.59659 | E30: 126.35317 | F30: 29050.311 | G30: 1561.0769 | H30: 5.3737011 | I30: 603.2137 | J30: 11. Промышленность, архитектурная, градостроительная и строительная деятельность
... A33: 14. Борышқа қызмет көрсету | B33: 3580609.6 | C33: 1194904.9 | D33: 33.37155 | E33: 121.6795 | F33: 3471233.6 | G33: 1189710.4 | H33: 34.273417 | I33: 121.58427 | J33: 14. Обслуживание долга
F34: 5171567.8 | G34: 1315998.3 | H34: 25.446795 | I34: 102.75823 | J34: 15. Трансферты
A35: III. ТАЗА БЮДЖЕТТІК КРЕДИТ БЕРУ | B35: 1019786.5 | C35: -46558.897 | D35: -4.5655534 | E35: -195.4366 | F35: 858213.36 | G35: -43530.656 | H35: -5.0722417 | I35: -138.54762 | J35: III. ЧИСТОЕ БЮДЖЕТНОЕ КРЕДИТОВАНИЕ
A36: Бюджеттік кредиттер | B36: 1288684 | C36: 16100 | D36: 1.2493365 | E36: 30.95572 | F36: 1104500 | G36: 11000 | H36: 0.99592576 | I36: 27.5 | J36: Бюджетные кредиты
A37: Бюджеттік кредиттерді өтеу | B37: 268897.54 | C37: 62658.897 | D37: 23.302145 | E37: 222.29908 | F37: 246286.64 | G37: 54530.656 | H37: 22.141135 | I37: 200.71017 | J37: Погашение бюджетных кредитов
A38: IV. ҚАРЖЫ АКТИВТЕРІМЕН ОПЕРАЦИЯЛАР БОЙЫНША САЛЬДО - ҚАРЖЫ АК | B38: 542286.29 | C38: 59247.785 | D38: 10.925555 | E38: 43.97826 | F38: 350436.62 | G38: 5124.5272 | H38: 1.4623264 | I38: 6677.3017 | J38: IV. САЛЬДО ПО ОПЕРАЦИЯМ С ФИНАНСОВЫМИ АКТИВАМИ
A39: Қаржылық активтерді сатып алу | B39: 542402.89 | C39: 59758.902 | D39: 11.017438 | E39: 44.28622 | F39: 350436.62 | G39: 5124.5272 | H39: 1.4623264 | I39: 6677.3017 | J39: Приобретение финансовых активов
A40: Мемлекеттің қаржы активтерін сатудан түсетін түсімдер | B40: 116.6 | C40: 511.11659 | D40: 438.35042 | E40: 235.23255 | F40: 0 | G40: 0 | H40: 0 | I40: - | J40: Поступления от продажи финансовых активов государства
A41: V. БЮДЖЕТ ТАПШЫЛЫҒЫ (ПРОФИЦИТІ) | B41: -4867553.5 | C41: -392139.05 | D41: 8.0561836 | E41: -502.7736 | F41: -4595050.1 | G41: -699504.86 | H41: 15.223008 | I41: -124.97694 | J41: V. ДЕФИЦИТ (ПРОФИЦИТ) БЮДЖЕТА
A42: VI. БЮДЖЕТТІҢ МҰНАЙҒА ҚАТЫСТЫ ЕМЕС ТАПШЫЛЫҒЫ (ПРОФИЦИТІ) | B42: -9332073.5 | C42: -1425218.3 | D42: 15.272257 | E42: -87.56585 | F42: -9059570.1 | G42: -1732584.1 | H42: 19.124352 | I42: -76.48371 | J42: VI. НЕНЕФТЯНОЙ ДЕФИЦИТ (ПРОФИЦИТ) БЮДЖЕТА

Sheet табл 3
A1: 3-кесте | E1: Таблица 3
A2: МЕМЛЕКЕТТІК БЮДЖЕТТІҢ АТҚАРЫЛУЫ | E2: ИСПОЛНЕНИЕ ГОСУДАРСТВЕННОГО БЮДЖЕТА
A3: (млн.теңге) | E3: (млн. тенге)
A5: Атауы | B5: 2023 ж. есеп/ 2023 г. отчет | C5: 2024 ж. есеп/ 2024 г. отчет | D5: 2025 ж. есеп/ 2025 г. отчет | F5: 2026 ж. қантар-наурыз есеп/январь-март отчет 2026 г. | G5: Наименование
D6: жылдық/ годовой | E6: қантар-наурыз/январь-март
A7: 1 | B7: 2 | C7: 3 | D7: 4 | E7: 5 | F7: 6 | G7: 7
A8: I. КІРІСТЕР | B8: 24917246 | C8: 27132165 | D8: 29871048 | E8: 6964309.1 | F8: 7244871.7 | G8: I. ДОХОДЫ
A9: Салықтық түсімдер_x000D_ оның iшiнде: | B9: 18912204 | C9: 19700517 | D9: 23188179 | E9: 5170384.1 | F9: 6198135.7 | G9: Налоговые поступления,_x000D_ в том числе:
A10: корпоративтік табыс салығы | B10: 5045696.1 | C10: 5213291.4 | D10: 6322629 | E10: 1392056 | F10: 1495129.4 | G10: корпоративный подоходный налог
A11: жеке табыс салығы | B11: 1992384.9 | C11: 2451640 | D11: 2859192.4 | E11: 697601.66 | F11: 748169.79 | G11: индивидуальный подоходный налог
A12: әлеуметтік салық | B12: 1321272.8 | C12: 1579329.4 | D12: 1866744.5 | E12: 477668.78 | F12: 495812.63 | G12: социальный налог
A13: қосылған құн салығы | B13: 5674110.6 | C13: 5179378.1 | D13: 6111842.3 | E13: 1320629.2 | F13: 1962484.6 | G13: налог на добавленную стоимость
A14: акциздер | B14: 840215.7 | C14: 844909.98 | D14: 1039998.8 | E14: 207761.42 | F14: 264607.33 | G14: акцизы
A15: Салықтық емес түсімдер | B15: 1822932.9 | C15: 1630378.8 | D15: 1248358.7 | E15: 299328.74 | F15: 166839.26 | G15: Неналоговые поступления
A16: Негізгі капиталды сатудан түсетін түсімдер | B16: 182108.73 | C16: 201680.05 | D16: 184510.46 | E16: 44596.227 | F16: 36272.211 | G16: Поступления от продажи основного капитала
A17: Арнаулы түсімдер | B17: 0 | C17: 0 | D17: 0 | E17: 0 | F17: 43624.591 | G17: Специальные поступления
A18: Трансферттердің түсімдері | B18: 4000000 | C18: 6006003.1 | D18: 5250000 | E18: 1450000 | F18: 800000 | G18: Поступления трансфертов
A19: II. ШЫҒЫНДАР | B19: 26760000 | C19: 30318236 | D19: 33442829 | E19: 6727770.3 | F19: 7624321.9 | G19: II. ЗАТРАТЫ
... A42: VII. БЮДЖЕТТІҢ ТАПШЫЛЫҒЫН ҚАРЖЫЛАНДЫРУ (ПРОФИЦИТТІ ПАЙДАЛАНУ | B42: 2811100.6 | C42: 3586041.9 | D42: 4383871.1 | E42: -77995.154 | F42: 392139.05 | G42: VII. ФИНАНСИРОВАНИЕ ДЕФИЦИТА (ИСПОЛЬЗОВАНИЕ ПРОФИЦИТА) БЮДЖЕТА
A43: Ішкі | B43: 3221830.7 | C43: 3293971.1 | D43: 3860967 | E43: -702.52207 | F43: =F44-F45 -> 776687.86 | G43: Внутреннее
A44: Түсімдер | B44: 5179541.7 | C44: 5785457.6 | D44: 6463366.7 | E44: 760827.71 | F44: 1471137.2 | G44: Поступление
A45: Өтеу | B45: 1957711 | C45: 2491486.6 | D45: 2602399.7 | E45: 761530.23 | F45: 694449.36 | G45: Погашение
A46: Сыртқы | B46: -410730.11 | C46: 292070.8 | D46: 522904.09 | E46: -77292.632 | F46: =F47-F48 -> -90125.682 | G46: Внешнее
A47: Түсімдер | B47: 251872.16 | C47: 1447223.5 | D47: 2231117.1 | E47: 68267.654 | F47: 31.4 | G47: Поступление
A48: Өтеу | B48: 662602.27 | C48: 1155152.7 | D48: 1708213 | E48: 145560.29 | F48: 90157.082 | G48: Погашение

Sheet табл 4
A1: 4-кесте | G1: Таблица 4
A3: МЕМЛЕКЕТТІК БЮДЖЕТКЕ ТҮСІМДЕР/_x000D_ ПОСТУПЛЕНИЯ В ГОСУДАРСТВЕННЫЙ БЮДЖЕТ
A5: (млн.теңге) | G5: (млн.тенге)
A7: Санаты/ Категория | B7: Сыныбы/ Класс | C7: Сыныпшасы/ Подкласс | D7: Ерешелігі/ Специфика | E7: Атауы | F7: 2026 ж. қаңтар-наурыз есеп/_x000D_ январь-март отчет 2026 г. | G7: Наименование
A8: 1 | B8: 2 | C8: 3 | D8: 4 | E8: 5 | F8: 6 | G8: 7
E9: ТҮСІМДЕР | F9: 7308041.7 | G9: ПОСТУПЛЕНИЯ
E10: оның ішінде: | G10: в том числе:
E11: КІРІСТЕР | F11: 7244871.7 | G11: ДОХОДЫ
A12: 1 | B12: L01 Класс дохода | C12: L01 Подкласс дохода | D12: L01 Специфика дохода | E12: Салықтық түсімдер | F12: 6198135.7 | G12: Налоговые поступления
A13: L01 Категория дохода | B13: 01 | C13: L01 Подкласс дохода | D13: L01 Специфика дохода | E13: Табыс салығы | F13: 2243299.2 | G13: Подоходный налог
A14: L01 Категория дохода | B14: L01 Класс дохода | C14: 1 | D14: L01 Специфика дохода | E14: Корпоративтік табыс салығы | F14: 1495129.4 | G14: Корпоративный подоходный налог
A15: 1 | B15: 01 | C15: 1 | D15: 10 | E15: Мұнай секторы ұйымдарынан түсетін түсімдерді қоспағанда, ірі кәсіпкерлік субъектілерінен – заңды тұлғалардан алынатын корпоративтік табыс салығы | F15: 1191464.1 | G15: Корпоративный подоходный налог с юридических лиц – субъектов крупного предпринимательства, за исключением поступлений от организаций нефтяного сектора
D16: 11 | E16: Ірі кәсіпкерлік субъектілерінен және мұнай секторы ұйымдарынан түсетін түсімдерді қоспағанда, заңды тұлғалардан алынатын корпоративтік табыс салығы | F16: 303665.29 | G16: Корпоративный подоходный налог с юридических лиц, за исключением поступлений от субъектов крупного предпринимательства и организаций нефтяного сектора
A17: L01 Категория дохода | B17: L01 Класс дохода | C17: 2 | D17: L01 Специфика дохода | E17: Жеке табыс салығы | F17: 748169.79 | G17: Индивидуальный подоходный налог
C18: 2 | D18: 01 | E18: Төлем көзінен салық салынатын табыстардан ұсталатын жеке табыс салығы | F18: 517883.11 | G18: Индивидуальный подоходный налог с доходов, облагаемых у источника выплаты
D19: 02 | E19: Төлем көзінен салық салынбайтын табыстардан ұсталатын жеке табыс салығы | F19: 223667.4 | G19: Индивидуальный подоходный налог с доходов, не облагаемых у источника выплаты
D20: 05 | E20: Төлем көзінен салық салынбайтын шетелдік азаматтар табыстарынан ұсталатын жеке табыс салығы | F20: 6619.2768 | G20: Индивидуальный подоходный налог с доходов иностранных граждан, не облагаемых у источника выплаты
A21: L01 Категория дохода | B21: 03 | C21: L01 Подкласс дохода | D21: L01 Специфика дохода | E21: Әлеуметтiк салық | F21: 495812.63 | G21: Социальный налог
A22: L01 Категория дохода | B22: L01 Класс дохода | C22: 1 | D22: L01 Специфика дохода | E22: Әлеуметтік салық | F22: 495812.63 | G22: Социальный налог
B23: 03 | C23: 1 | D23: 01 | E23: Әлеуметтік салық | F23: 495812.63 | G23: Социальный налог
A24: L01 Категория дохода | B24: 04 | C24: L01 Подкласс дохода | D24: L01 Специфика дохода | E24: Меншiкке салынатын салықтар | F24: 233748.66 | G24: Hалоги на собственность
A25: L01 Категория дохода | B25: L01 Класс дохода | C25: 1 | D25: L01 Специфика дохода | E25: Мүлiкке салынатын салықтар | F25: 143953.61 | G25: Налоги на имущество
B26: 04 | C26: 1 | D26: 01 | E26: Заңды тұлғалардың және жеке кәсіпкерлердің мүлкіне салынатын салық | F26: 142532.66 | G26: Налог на имущество юридических лиц и индивидуальных предпринимателей
D27: 02 | E27: Жеке тұлғалардың мүлкiне салынатын салық | F27: 1420.9471 | G27: Hалог на имущество физических лиц
A28: L01 Категория дохода | B28: L01 Класс дохода | C28: 3 | D28: L01 Специфика дохода | E28: Жер салығы | F28: 2375.4006 | G28: Земельный налог
C29: 3 | D29: 02 | E29: Жер салығы | F29: 2375.4006 | G29: Земельный налог
A30: L01 Категория дохода | B30: L01 Класс дохода | C30: 4 | D30: L01 Специфика дохода | E30: Көлiк құралдарына салынатын салық | F30: 85612.676 | G30: Налог на транспортные средства
C31: 4 | D31: 01 | E31: Заңды тұлғалардан көлік құралы салығы | F31: 713.62502 | G31: Hалог на транспортные средства с юридических лиц
D32: 02 | E32: Жеке тұлғалардан көлік құралы салығы | F32: 84899.051 | G32: Hалог на транспортные средства с физических лиц
A33: L01 Категория дохода | B33: L01 Класс дохода | C33: 5 | D33: L01 Специфика дохода | E33: Бірыңғай жер салығы | F33: 1806.98 | G33: Единый земельный налог
C34: 5 | D34: 01 | E34: Бірыңғай жер салығы | F34: 1806.98 | G34: Единый земельный налог
A35: L01 Категория дохода | B35: 05 | C35: L01 Подкласс дохода | D35: L01 Специфика дохода | E35: Тауарларға, жұмыстарға және көрсетілетін қызметтерге салынатын iшкi салықтар | F35: 2671619.1 | G35: Внутренние налоги на товары, работы и услуги
A36: L01 Категория дохода | B36: L01 Класс дохода | C36: 1 | D36: L01 Специфика дохода | E36: Қосылған құн салығы | F36: 1962484.6 | G36: Налог на добавленную стоимость
B37: 05 | C37: 1 | D37: 01 | E37: Қазақстан Республикасының аумағында өндiрiлген тауарларға, орындалған жұмыстарға және көрсетілген қызметтерге салынатынқосылған құн салығы | F37: 1001413.9 | G37: Hалог на добавленную стоимость на произведенные товары, выполненные работы и оказанные услуги на территории Республики Казахстан
D38: 02 | E38: Ресей Федерациясы және Беларусь Республикасының аумағынан импортталатын тауарларға салынатын қосылған құн салығынан басқа, Қазақстан Республикасының аумағына импортталатын тауарларға салынатын қосылған құн салығы | F38: 510847.07 | G38: Hалог на добавленную стоимость на товары, импортируемые на территорию Республики Казахстан, кроме налога на добавленнуюстоимость на товары, импортируемые с территории Российской Федерации и Республики Беларусь
D39: 04 | E39: Резидент емес үшін қосылған құн салығы | F39: 79955.742 | G39: Налог на добавленную стоимость за нерезидента
D40: 14 | E40: Салық төлеушінің бұрын бюджеттен қайтарылған және салықтықтексеру жүргізу барысында қайтарылуы расталмаған қосылған құн салығының асып кеткен сомасын аударуы (қайтаруы), өсімпұл сомасын аударуы | F40: 2270.2665 | G40: Перечисление (возврат) налогоплательщиком суммы превышения налога на добавленную стоимость, ранее возвращенной из бюджета и не подтвержденной к возврату при проведении налоговой проверки, перечисление суммы пени
D41: 15 | E41: Еуразиялық экономикалық одаққа мүше мемлекеттер аумағынан импортталған тауарларға қосылған құн салығы | F41: 348904.06 | G41: Налог на добавленную стоимость на товары, импортированные стерритории государств-членов Евразийского экономического союза
D42: 16 | E42: Тауарлармен электрондық сауданы жүзеге асыру, жеке тұлғаларға электрондық нысанда қызметтер көрсету кезінде шетелдік компаниялардан түсетін қосылған құн салығы | F42: 19093.575 | G42: Налог на добавленную стоимость с иностранных интернет компаний при осуществлении электронной торговли товарами, оказании услуг в электронной форме физическим лицам
A43: L01 Категория дохода | B43: L01 Класс дохода | C43: 2 | D43: L01 Специфика дохода | E43: Акциздер | F43: 264607.33 | G43: Акцизы
C44: 2 | D44: 74 | E44: Қазақстан Республикасының аумағында өндірілген спирттiң және (немесе) шарап материалының, алкоголь өнімдерінің барлық түрлерi | F44: 33174.603 | G44: Все виды спирта и (или) виноматериала, алкогольной продукции, произведенных на территории Республики Казахстан
D45: 75 | E45: Қазақстан Республикасының аумағында өндірілген темекі өнімдері, жеңiл автомобильдер (мүгедектігі бар адамдарға арнайы жасалған қолмен басқарылатын немесе қолмен басқаруға бейімделген автомобильдерден басқа) | F45: 67508.185 | G45: Табачные изделия, легковые автомобили (кроме автомобилей с ручным управлением или адаптером ручного управления, специально предназначенных для лиц с инвалидностью), произведенные на территории Республики Казахстан
D46: 76 | E46: Қазақстан Республикасының аумағына Еуразиялық экономикалық одағына мүше мемлекеттердің аумағынан әкелінетін темекі өнімдері | F46: 1395.6727 | G46: Табачные изделия, ввозимые на территорию Республики Казахстан с территории государств-членов Евразийского экономического союза
D47: 77 | E47: Қазақстан Республикасының аумағына Еуразиялық экономикалық одағына мүше мемлекеттердің аумағынан әкелінетін спирттiң және (немесе) шарап материалының, алкоголь өнімдерінің барлық түрлерi | F47: 2899.1659 | G47: Все виды спирта и (или) виноматериала, алкогольной продукции, ввозимых на территорию Республики Казахстан с территории государств-членов Евразийского экономического союза
D48: 78 | E48: Қазақстан Республикасының аумағына Еуразиялық экономикалық одағына мүше мемлекеттердің аумағынан әкелінетін акцизделетін өнімнің өзге түрлері | F48: 75.67803 | G48: Прочие виды подакцизной продукции, ввозимой на территорию Республики Казахстан с территории государств-членов Евразийского экономического союза
D49: 79 | E49: Қазақстан Республикасы аумағына Еуразиялық экономикалық одағына мүше мемлекеттердің аумағынан әкелінетін бензин (авиациялықты қоспағанда) және дизель отыны | F49: 4754.7208 | G49: Бензин (за исключением авиационного) и дизельное топливо, ввозимых на территорию Республики Казахстан с территории государств-членов Евразийского экономического союза
D50: 80 | E50: Еуразиялық экономикалық одағына мүше болып табылмайтын мемлекеттердің аумағынан әкелінетін, Қазақстан Республикасының аумағына импортталатын спирттің және (немесе) шарап материалының, алкоголь өнімдерінің барлық түрлері | F50: 3612.5414 | G50: Все виды спирта и (или) виноматериала, алкогольной продукции, импортируемых на территорию Республики Казахстан с территории государств, не являющихся членами Евразийского экономического союза
D51: 81 | E51: Еуразиялық экономикалық одағына мүше болып табылмайтын мемлекеттердің аумағынан әкелінетін, Қазақстан Республикасының аумағына импортталатын темекі өнімдері | F51: 8085.2433 | G51: Табачные изделия, импортируемые на территорию Республики Казахстан с территории государств, не являющихся членами Евразийского экономического союза
D52: 82 | E52: Еуразиялық экономикалық одағына мүше болып табылмайтын мемлекеттердің аумағынан әкелінетін, Қазақстан Республикасының аумағына импортталатын акцизделетін өнімдердің өзге түрлері | F52: 1215.2615 | G52: Прочие виды подакцизных продукций, импортируемые на территорию Республики Казахстан с территории государств, не являющихся членами Евразийского экономического союза
D53: 83 | E53: Еуразиялық экономикалық одағына мүше болып табылмайтын мемлекеттер аумағынан әкелінетін, Қазақстан Республикасының аумағына импортталатын бензин (авиациялықты қоспағанда) және дизель отыны | F53: 26.31368 | G53: Бензин (за исключением авиационного) и дизельное топливо, импортируемых на территорию Республики Казахстан с территориигосударств, не являющихся членами Евразийского экономического союза
D54: 84 | E54: Қазақстан Республикасының аумағында өндірілген және асырылған бензин (авиациялық бензинді қоспағанда), дизель отыны, газохол, бензанол, мұнай еріткіш, жеңіл көмірсутектер қоспасы және экологиялық отыны | F54: 141859.94 | G54: Бензин (за исключением авиационного) и дизельное топливо, газохол, бензанол, нефрас, смесь легких углеводородов и экологическое топливо, произведенных и реализованных на территории Республики Казахстан
A55: L01 Категория дохода | B55: L01 Класс дохода | C55: 3 | D55: L01 Специфика дохода | E55: Табиғи және басқа да ресурстарды пайдаланғаны үшiн түсетiн түсiмдер | F55: 414074.34 | G55: Поступления за использование природных и других ресурсов
C56: 3 | D56: 01 | E56: Қалааралық және (немесе) халықаралық телефон байланысын, сондай-ақ ұялы байланысты бергені үшін төлемақы | F56: 3205.7626 | G56: Плата за предоставление междугородной и (или) международнойтелефонной связи, а также сотовой связи
D57: 02 | E57: Мұнай секторы ұйымдарынан түсетін түсімдерді қоспағанда, үстеме пайдаға салынатын салық | F57: 165.032 | G57: Налог на сверхприбыль, за исключением поступлений от организаций нефтяного сектора
D58: 03 | E58: Жерүсті көздерінің су ресурстарын пайдаланғаны үшін төлемақы | F58: 589.29062 | G58: Плата за пользование водными ресурсами поверхностных источников
D59: 04 | E59: Орманды пайдаланғаны үшiн төлемақы | F59: 487.21807 | G59: Плата за лесные пользования
D60: 05 | E60: Мұнай секторы ұйымдарынан түсетін түсімдерді қоспағанда, бонустар | F60: 504.2923 | G60: Бонусы, за исключением поступлений от организаций нефтяногосектора
D61: 06 | E61: Кең таралған пайдалы қазбаларды, жерасты суларын, емдік балшықтарды және мұнай секторы ұйымдарынан түсетін түсімдерді қоспағанда, пайдалы қазбаларды өндіру салығы | F61: 386218.62 | G61: Налог на добычу полезных ископаемых, за исключением общераспространенных полезных ископаемых, подземных вод, лечебных грязей и поступлений от организаций нефтяного сектора
D62: 07 | E62: Мұнай секторы ұйымдарынан түсетін түсімдерді қоспағанда, экспортқа рента салығы | F62: 325.41666 | G62: Рентный налог на экспорт, за исключением поступлений от организаций нефтяного сектора
D63: 08 | E63: Мұнай секторы ұйымдарынан түсетін түсімдерді қоспағанда, жасалған келісімшарттар бойынша өнімді бөлу жөніндегі Қазақстан Республикасының үлесі | F63: 0.001 | G63: Доля Республики Казахстан по разделу продукции по заключенным контрактам, за исключением поступлений от организаций нефтяного сектора
D64: 09 | E64: Радиожиілік спектрін пайдаланғаны үшін төлем | F64: 569.28463 | G64: Плата за использование радиочастотного спектра
D65: 10 | E65: Мұнай секторы ұйымдарынан түсетін түсімдерді қоспағанда, кең таралған пайдалы қазбаларға, жерасты суларына және емдік балшықтарға салынатын пайдалы қазбаларды өндіру салығы | F65: 16.227648 | G65: Налог на добычу полезных ископаемых на общераспространенныеполезные ископаемые, подземные воды и лечебные грязи, за исключением поступлений от организаций нефтяного сектора
D66: 11 | E66: Жануарлар дүниесін пайдаланғаны үшін төлемақы | F66: 635.27471 | G66: Плата за пользование животным миром
D67: 12 | E67: Мұнай секторы ұйымдарынан түсетін түсімдерді қоспағанда, өнімді бөлу туралы келісімшарт бойынша қызметті жүзеге асыратын жер қойнауын пайдаланушының қосымша төлемі және баламалы салық | F67: -0.051695 | G67: Дополнительный платеж недропользователя, осуществляющего деятельность по контракту о разделе продукции, и альтернативный налог, за исключением поступлений от организаций нефтяногосектора
D68: 15 | E68: Жер учаскелерін пайдаланғаны үшін төлемақы | F68: 12773.378 | G68: Плата за пользование земельными участками
... D71: 19 | E71: Тарихи шығындарды өтеу бойынша төлем | F71: 3150.0336 | G71: Платеж по возмещению исторических затрат
A72: L01 Категория дохода | B72: L01 Класс дохода | C72: 4 | D72: L01 Специфика дохода | E72: Кәсiпкерлiк және кәсiби қызметтi жүргiзгенi үшiн алынатын алымдар | F72: 26794.932 | G72: Сборы за ведение предпринимательской и профессиональной деятельности
C73: 4 | D73: 02 | E73: Жекелеген қызмет түрлерімен айналысу құқығы үшін алым (жекелеген қызмет түрлерімен айналысуға арналған лицензияларды бергені үшін алым) | F73: 1554.8249 | G73: Сбор за право занятия отдельными видами деятельности (сборза выдачу лицензий на занятие отдельными видами деятельности)
D74: 06 | E74: Автокөлік құралдарының Қазақстан Республикасының аумағымен жүріп өткені үшін алым | F74: 4557.5953 | G74: Сбор за проезд автотранспортных средств по территории Республики Казахстан
D75: 13 | E75: Телевизия және радио хабарларын тарату ұйымдарына радиожиілік спектрін пайдалануға рұқсат бергені үшін алым | F75: 4.174625 | G75: Сбор за выдачу разрешения на использование радиочастотного спектра телевизионным и радиовещательным организациям
D76: 24 | E76: Сыртқы (көрнекі) жарнаманы республикалық маңызы бар қаладағы, астанадағы үй-жайлардың шегінен тыс ашық кеңістікте, республикалық маңызы бар қала, астана аумағы арқылы өтетін жалпыға ортақ пайдаланылатын автомобиль жолдарының бөлінген белдеуінде орналастырғаны үшін төлемақы | F76: 3303.8092 | G76: Плата за размещение наружной (визуальной) рекламы на открытом пространстве за пределами помещений в городе республиканского значения, столице, в полосе отвода автомобильных дорог общего пользования, проходящих через территории города республиканского значения, столицы
D77: 25 | E77: Облыстық маңызы бар қаладағы үй-жайлардан тыс ашық кеңістікте, облыстық маңызы бар қаланың аумағы арқылы өтетін жалпығаортақ пайдаланылатын автомобиль жолдарының бөлінген белдеуінде сыртқы (көрнекі) жарнаманы орналастырғаны үшін төлемақы | F77: 544.82477 | G77: Плата за размещение наружной (визуальной) рекламы на открытом пространстве за пределами помещений в городе областного значения, в полосе отвода автомобильных дорог общего пользования, проходящих через территорию города областного значения
D78: 28 | E78: Республикалық бюджетке төленетін тіркелгені үшін алым | F78: 24.66019 | G78: Регистрационный сбор, зачисляемый в республиканский бюджет
D79: 29 | E79: Жергілікті бюджетке төленетін тіркелгені үшін алым | F79: 13868.453 | G79: Регистрационный сбор, зачисляемый в местный бюджет
D80: 30 | E80: Аудандық маңызы бар қаладағы, ауылдағы, кенттегі үй- үй-жайлардың шегінен тыс ашық кеңістікте және аудандық маңызы бар қаланың, ауылдың, кенттің, ауылдық округтің аумақтары арқылыөтетін жалпыға ортақ пайдаланылатын автомобиль жолдарының бөлiнген белдеуiнде, сондай-ақ елді мекендерден тыс жердегі үй-жайлардың шегінен тыс ашық кеңістікте және жалпыға ортақ пайдаланылатын автомобиль жолдарының бөлінген белдеуінен тыс ж | F80: 93.728351 | G80: Плата за размещение наружной (визуальной) рекламы на открытом пространстве за пределами помещений в городе районного значения, селе, поселке и в полосе отвода автомобильных дорог общего пользования, проходящих через территории города районного значения, села, поселка, сельского округа, а также на открытом пространстве за пределами помещений вне населенных пунктов и вне полосы отвода автомобильных дорог общего пользов
D81: 31 | E81: Микроқаржы ұйымдарын есептік тіркеуден өткізгені және оларды микроқаржы ұйымдарының тізіліміне енгізгені үшін алым | F81: 0.01966 | G81: Сбор за прохождение учетной регистрации микрофинансовых организаций и включение их в реестр микрофинансовых организаций
D82: 32 | E82: Банк және сақтандыру нарықтарына қатысушылар үшін рұқсат беру құжаттарын, келісім бергені үшін алым | F82: 5.356925 | G82: Сбор за выдачу разрешительных документов, согласия для участников банковского и страхового рынков
D83: 33 | E83: Қазақстан Республикасына шетелдік жұмыс күшін тартуға рұқсатты бергені немесе ұзартқаны үшін алым | F83: 2020.2099 | G83: Сбор за выдачу или продление разрешения на привлечение иностранной рабочей силы в Республику Казахстан
D84: 34 | E84: Жекелеген қызмет түрлерімен айналысуға арналған лицензияларды пайдаланғаны үшін төлемақы | F84: 817.27505 | G84: Плата за пользование лицензиями на занятие отдельными видами деятельности
D85: 36 | E85: "Астана" халықаралық қаржы орталығының инвестициялық резиденті болып табылатын шетелдіктің немесе азаматтығы жоқ адамның резиденттігін растайтын құжатты бергені үшін алы | F85: 0 | G85: Сбор за выдачу документа, подтверждающего резидентство иностранца или лица без гражданства, являющегося инвестиционным резидентом Международного финансового центра "Астана"
A86: L01 Категория дохода | B86: L01 Класс дохода | C86: 5 | D86: L01 Специфика дохода | E86: Ойын бизнесіне салық | F86: 3657.8618 | G86: Налог на игорный бизнес
C87: 5 | D87: 01 | E87: Ойын бизнесі салығы | F87: 3657.8618 | G87: Налог на игорный бизнес
A88: L01 Категория дохода | B88: 06 | C88: L01 Подкласс дохода | D88: L01 Специфика дохода | E88: Халықаралық сауда мен сыртқы операцияларға салынатын салықтар | F88: 378715.06 | G88: Hалоги на международную торговлю и внешние операции
A89: L01 Категория дохода | B89: L01 Класс дохода | C89: 1 | D89: L01 Специфика дохода | E89: Кедендік төлемдер | F89: 360761.32 | G89: Таможенные платежи
B90: 06 | C90: 1 | D90: 01 | E90: Еуразиялық экономикалық одақ туралы шартқа сәйкес төленген әкелінетін кедендік баждары (баламалы қолданылатын өзге де баждар, салықтар мен алымдар) | F90: 10096.544 | G90: Ввозные таможенные пошлины (иные пошлины, налоги и сборы, имеющие эквивалентное действие), уплаченные в соответствии с Договором о Евразийском экономическом союзе
D91: 02 | E91: Әкетілетін тауарларға салынатын кедендік баждар | F91: 3094.3162 | G91: Таможенные пошлины на вывозимые товары
D92: 04 | E92: Кеден бажының бірыңғай ставкасын қолданумен жеке тұлғалардан өндіріп алынатын жеке пайдалануына әкелінетін тауарларға салынатын кеден баждары, салықтары | F92: 960.96553 | G92: Таможенные пошлины, налоги на ввозимые физическими лицами товары для личного пользования с применением единых ставок таможенных пошлин, налогов
D93: 05 | E93: Әкелінетін тауарларға жиынтық кедендік төлем | F93: 372.95291 | G93: Совокупный таможенный платеж на ввозимые товары
D94: 06 | E94: Ресей Федерациясымен бөлінген кедендік баж | F94: 93162.517 | G94: Таможенные пошлины, распределенные Российской Федерацией
D95: 07 | E95: Беларусь Республикасымен бөлінген кедендік баж | F95: 6245.7698 | G95: Таможенные пошлины, распределенные Республикой Беларусь
D96: 10 | E96: Мұнайға салынатын кедендік әкету бажы | F96: 233079.25 | G96: Вывозные таможенные пошлины на сырую нефть
D97: 11 | E97: Мұнайдан өндірілген тауарларға салынатын кедендік әкету бажы | F97: 3280.9341 | G97: Вывозные таможенные пошлины на товары, выработанные из нефти
D98: 12 | E98: Кеден одағында кедендік әкелу баждарын (баламалы қолданысы бар өзге де баждарды, салықтар мен алымдарды) есепке жатқызужәне бөлу тәртібін белгілеу және қолдану туралы келісім күшіне енгенге дейін төлеу жөніндегі міндеті туындаған әкелінетін тауарларға және (немесе) әкелінетін кедендік баждарға арналған кедендік баждар, сондай-ақ жер қойнауын пайдалану саласындағы келісімшарттар шеңберінде, оның ішінде Қазақстан Респ | F98: 391.13478 | G98: Таможенные пошлины на ввозимые товары и (или) ввозные таможенные пошлины, обязанность по уплате которых возникла до вступления в силу Соглашения об установлении и применении в таможенном союзе порядка зачисления и распределения ввозных таможенных пошлин (иных пошлин, налогов и сборов, имеющих эквивалентное действие), а также таможенные пошлины на товары ввозимые в рамках контрактов в сфере недропользования, в том чис
D99: 13 | E99: Армения Республикасымен бөлінген кедендік баждар | F99: 2260.4821 | G99: Таможенные пошлины, распределенные Республикой Армения
D100: 17 | E100: Қырғыз Республикасы бөлген кедендік баждар | F100: 3351.0686 | G100: Таможенные пошлины, распределенные Кыргызской Республикой
D101: 19 | E101: Алдағы кедендік баждарды, кедендік алымдарды, салықтарды, арнайы, демпингке қарсы, өтемақы баждарын төлеу есебіне, сондай-ақ кедендік баждарды, салықтарды арнайы, демпингке қарсы,өтемақы баждарын төлеу жөніндегі міндеттің орындалуын қамтамасыз ету ретінде Еуразиялық экономикалық одақтың және Қазақстан Республикасының кеден заңнамасына сәйкес енгізілетін аванстық төлемдер | F101: 4465.3795 | G101: Авансовые платежи, вносимые в соответствии с таможенным законодательством Евразийского экономического союза и Республики Казахстан, в счет уплаты предстоящих таможенных платежей, налогов, специальных, антидемпинговых, компенсационных пошлин, а также в качестве обеспечения исполнения обязанности по уплате таможенных пошлин, налогов, специальных, антидемпинговых, компенсационных пошлин
A102: L01 Категория дохода | B102: L01 Класс дохода | C102: 2 | D102: L01 Специфика дохода | E102: Халықаралық сауда мен операцияларға салынатын басқа да салықтар | F102: 17953.742 | G102: Прочие налоги на международную торговлю и операции
C103: 2 | D103: 01 | E103: Қазақстан Республикасының кеден заңнамасына сәйкес төленетін кедендік алымдар | F103: 14678.89 | G103: Таможенные сборы, уплачиваемые в соответствии с таможенным законодательством Республики Казахстан
D104: 02 | E104: Еуразиялық экономикалық одақ туралы шартқа сәйкес төленген арнайы, демпингке қарсы, өтемақы баждары | F104: 289.54694 | G104: Специальные, антидемпинговые, компенсационные пошлины, уплаченные в соответствии с Договором о Евразийском экономическом союзе
D105: 05 | E105: Беларусь Республикасынан түсетін арнайы, демпингке қарсы, өтемақы баждары | F105: 113.86232 | G105: Специальные, антидемпинговые, компенсационные пошлины, поступившие от Республики Беларусь
...

Sheet табл 5
B2: Кесте 5 | D2: Таблица 5
B3: ШЫҒЫСТАРДЫҢ ВЕДОМСТВОЛЫҚ | D3: ИСПОЛНЕНИЕ ГОСУДАРСТВЕННОГО БЮДЖЕТА
B4: СЫНЫПТАМАСЫ БОЙЫНША | D4: ПО ВЕДОМСТВЕННОЙ
B5: МЕМЛЕКЕТТІК БЮДЖЕТТІҢ АТҚАРАЛУЫ | D5: КЛАССИФИКАЦИИ РАСХОДОВ
B6: (млн. теңге) | D6: (млн. тенге)
B8: Бағдарламалард_x000D_ ың_x000D_ əкімшісі/_x000D_ Администратор_x000D_ программ | C8: Атауы | D8: 2026 ж. қаңтар-наурыз есеп/_x000D_ январь-март 2026 г. | E8: Наименование
B9: 1 | C9: 2 | D9: 3 | E9: 4
C10: БАРЛЫҒЫ | D10: 7700180.8 | E10: ВСЕГО
B11: 101 | C11: Қазақстан Республикасы Президентінің Әкімшілігі | D11: 4643.5489 | E11: Администрация Президента Республики Казахстан
B12: 106 | C12: Адам құқықтары жөніндегі ұлттық орталық | D12: 409.75887 | E12: Национальный центр по правам человека
B13: 107 | C13: Қазақстан Республикасы Жоғары Сот Кеңесінің Аппараты | D13: 528.87079 | E13: Аппарат Высшего Судебного Совета Республики Казахстан
B14: 109 | C14: Қазақстан Республикасы Үкіметінің Аппараты | D14: 1984.2749 | E14: Аппарат Правительства Республики Казахстан
B15: 110 | C15: Облыс мәслихатының аппараты | D15: 829.31184 | E15: Аппарат маслихата области
B16: 111 | C16: Республикалық маңызы бар қала, астана мәслихатының аппараты | D16: 182.24979 | E16: Аппарат маслихата города республиканского значения, столицы
B17: 112 | C17: Аудан (облыстық маңызы бар қала) мәслихатының аппараты | D17: 3681.9797 | E17: Аппарат маслихата района (города областного значения)
B18: 120 | C18: Облыс әкімінің аппараты | D18: 12927.662 | E18: Аппарат акима области
B19: 121 | C19: Республикалық маңызы бар қала, астана әкімінің аппараты | D19: 3030.3003 | E19: Аппарат акима города республиканского значения, столицы
B20: 122 | C20: Аудан (облыстық маңызы бар қала) әкімінің аппараты | D20: 24264.041 | E20: Аппарат акима района (города областного значения)
B21: 123 | C21: Қаладағы аудан әкімінің аппараты | D21: 69868.709 | E21: Аппарат акима района в городе
B22: 124 | C22: Аудандық маңызы бар қала, ауыл, кент, ауылдық округ әкімінің аппараты | D22: 65733.222 | E22: Аппарат акима города районного значения, села, поселка, сельского округа
... B220: 821 | C220: Ауданның (облыстық маңызы бар қаланың) қоғамдық даму бөлімі | D220: 248.08332 | E220: Отдел общественного развития района (города областного значения)

Sheet табл 6
A1: 6-кесте | D1: Таблица 6
A2: ШЫҒЫНДАРДЫҢ ЭКОНОМИКАЛЫҚ ЖІКТЕМЕСІ | D2: ИСПОЛНЕНИЕ ГОСУДАРСТВЕННОГО БЮДЖЕТА ПО
A3: БОЙЫНША МЕМЛЕКЕТТІК БЮДЖЕТТІК ОРЫНДАЛУЫ | D3: ЭКОНОМИЧЕСКОЙ КЛАССИФИКАЦИИ РАСХОДОВ
A4: (млн.теңге) | D4: (млн.тенге)
A5: Cанаты/_x000D_ Категория | B5: Iшкi сыныбы/_x000D_ Подкласс | C5: Атауы | D5: 2026 ж. қаңтар-наурыз/январь-март отчет 2026 г. | E5: Наименование
A7: 1 | B7: 2 | C7: 3 | D7: 4 | E7: 5
C8: БАРЛЫҒЫ | D8: 7700180.8 | E8: ВСЕГО
A9: 1 | C9: Ағымдағы шығындар | D9: 7021942.8 | E9: Текущие затраты
A10: 1 | B10: 110 | C10: Жалақы | D10: 1084871 | E10: Заработная плата
B11: 120 | C11: Жұмыс берушілердің жарналары | D11: 110810.27 | E11: Взносы работодателей
B12: 130 | C12: Қазақстан Республикасының заңнамалық актілеріне сәйкес азаматтардың жекелеген санаттарына жалақы төлеу және жарналар аудару | D12: 40685.621 | E12: Выплата заработной платы отдельным категориям граждан и отчисления взносов в соответствии с законодательными актами Республики Казахстан
B13: 140 | C13: Қорлар сатып алу | D13: 74025.478 | E13: Приобретение запасов
B14: 150 | C14: Қызметтер мен жұмыстарды сатып алу | D14: 954951.45 | E14: Приобретение услуг и работ
B15: 160 | C15: Басқа да ағымдағы шығындар | D15: 783079.48 | E15: Другие текущие затраты
B16: 210 | C16: Ішкі қарыздар бойынша сыйақы төлемдері | D16: 1136239.4 | E16: Выплаты вознаграждений по внутренним займам
B17: 220 | C17: Сыртқы заемдар бойынша сыйақылар төлеу | D17: 58665.529 | E17: Выплаты вознаграждений по внешним займам
B18: 310 | C18: Бюджеттік субсидиялар | D18: 545344.01 | E18: Бюджетные субсидии
B19: 320 | C19: Жеке тұлғаларға берілетін трансферттер | D19: 1881213.8 | E19: Трансферты физическим лицам
B20: 340 | C20: Шетелге берiлетiн ағымдағы трансферттер | D20: 5118.3126 | E20: Текущие трансферты за границу
B21: 360 | C21: Нысаналы жарна | D21: 346273.94 | E21: Целевой взнос
B22: 370 | D22: 664.5558
A23: 2 | C23: Күрделі шығындар | D23: 545937.99 | E23: Капитальные затраты
A24: 2 | B24: 410 | C24: Негiзгi құралдарды, материалдық емес және биологиялық активтерді сатып алу | D24: 145651.73 | E24: Приобретение основных средств, нематериальных и биологических активов
B25: 420 | C25: Негізгі қаражатты күрделі жөндеу | D25: 37836.851 | E25: Капитальный ремонт основных средств
B26: 430 | C26: Дамуға бағытталған күрделі шығындар | D26: 362449.41 | E26: Капитальные затраты, направленные на развитие
A27: 3 | C27: Бюджеттік кредиттер | D27: 16100 | E27: Бюджетные кредиты
A28: 3 | B28: 510 | C28: Ішкі бюджеттік кредиттер | D28: 16100 | E28: Внутренние бюджетные кредиты
A29: 4 | C29: Қаржы активтерін сатып алу | D29: 59758.902 | E29: Приобретение финансовых активов
A30: 4 | B30: 610 | C30: Қаржы активтерін сатып алу | D30: 59663.505 | E30: Приобретение финансовых активов
B31: 620 | C31: Елден тысқары жерлерден қаржы активтерін сатып алу | D31: 95.397215 | E31: Приобретение финансовых активов за пределами страны
A32: 6 | C32: Мемлекеттік-жекешелік әріптестік жобалар бойынша мемлекеттік міндеттемелерді орындау | D32: 56441.098 | E32: Выполнение государственных обязательств по проектам государственно-частного партнерства
A33: 6 | B33: 810 | C33: Мемлекеттік концессиялық міндеттемелерді орындау | D33: 56441.098 | E33: Выполнение государственных концессионных обязательств

Sheet табл 7
A1: 7-кесте | E1: Таблица 7
A2: РЕСПУБЛИКАЛЫҚ БЮДЖЕТТІҢ АТҚАРЫЛУЫ | E2: ИСПОЛНЕНИЕ РЕСПУБЛИКАНСКОГО БЮДЖЕТА
A3: (млн.теңге) | E3: (млн. тенге)
A5: Атауы | B5: 2023 ж. есеп/ 2023 г. отчет | C5: 2024 ж. есеп/ 2024 г. отчет | D5: 2025 ж. есеп/ 2025 г. отчет | F5: 2026 ж. қантар-наурыз есеп/январь-март отчет 2026 г. | G5: Наименование
D6: жылдық/ годовой | E6: қантар-наурыз/январь-март
A7: 1 | B7: 2 | C7: 3 | D7: 4 | E7: 5 | F7: 6 | G7: 7
A8: I. КІРІСТЕР | B8: 19037979 | C8: 19624012 | D8: 21090148 | E8: 4980046.4 | F8: 5206986.9 | G8: I. ДОХОДЫ
A9: Салықтық түсімдер_x000D_ оның iшiнде: | B9: 12912428 | C9: 12307810 | D9: 14463081 | E9: 3101409.8 | F9: 4077555.7 | G9: Налоговые поступления,_x000D_ в том числе:
A10: корпоративтік табыс салығы | B10: 3889594.5 | C10: 3653190.8 | D10: 4532987.5 | E10: 1018977.9 | F10: 1191464.1 | G10: корпоративный подоходный налог
A11: қосылған құн салығы | B11: 5674110.6 | C11: 5179378.1 | D11: 6111842.3 | E11: 1320629.2 | F11: 1962484.6 | G11: налог на добавленную стоимость
A12: акциздер | B12: 161890.43 | C12: 125189.66 | D12: 117407.4 | E12: 28395.647 | F12: 22064.597 | G12: акцизы
A13: Салықтық емес түсімдер | B13: 1617610.1 | C13: 1201438.2 | D13: 823130.62 | E13: 194580.7 | F13: 79068.8 | G13: Неналоговые поступления
A14: Негізгі капиталды сатудан түсетін түсімдер | B14: 735.69631 | C14: 6170.4309 | D14: 12039.586 | E14: 1646.6727 | F14: 257.17471 | G14: Поступления от продажи основного капитала
A15: Арнаулы түсімдер | B15: 0 | C15: 0 | D15: 0 | E15: 0 | F15: 2550.3603 | G15: Специальные поступления
A16: Трансферттердің түсімдері | B16: 4507205 | C16: 6108593.6 | D16: 5791896.9 | E16: 1682409.3 | F16: 1047554.9 | G16: Поступления трансфертов
A17: II. ШЫҒЫНДАР | B17: 21547819 | C17: 23106552 | D17: 24958709 | E17: 5526845.7 | F17: 5944897.9 | G17: II. ЗАТРАТЫ
A18: 1. Жалпы сипаттағы мемлекеттiк қызметтер | B18: 1137687.2 | C18: 1293447.3 | D18: 1334753.4 | E18: 267600.91 | F18: 257675.37 | G18: 1. Государственные услуги общего характера
A19: 2. Қорғаныс | B19: 1100070.9 | C19: 1038491.2 | D19: 1149535.1 | E19: 135744.33 | F19: 273330.38 | G19: 2. Оборона
... A40: VII. БЮДЖЕТТІҢ ТАПШЫЛЫҒЫН ҚАРЖЫЛАНДЫРУ (ПРОФИЦИТТІ ПАЙДАЛАНУ | B40: 3120850.3 | C40: 3648890.5 | D40: 4065222.9 | E40: 559707.13 | F40: 699504.86 | G40: VII. ФИНАНСИРОВАНИЕ ДЕФИЦИТА (ИСПОЛЬЗОВАНИЕ ПРОФИЦИТА) БЮДЖЕТА
A41: Ішкі | B41: 3529699.5 | C41: 3355950.9 | D41: 3542318.8 | E41: 636999.76 | F41: =F42-F43 -> 797920.22 | G41: Внутреннее
A42: Түсімдер | B42: 5318608.1 | C42: 5643320.3 | D42: 6027050.7 | E42: 1393030 | F42: 1437866.7 | G42: Поступление
A43: Өтеу | B43: 1788908.6 | C43: 2287369.4 | D43: 2484731.9 | E43: 756030.23 | F43: 639946.51 | G43: Погашение
A44: Сыртқы | B44: -408849.23 | C44: 292939.56 | D44: 522904.09 | E44: -77292.632 | F44: =F45-F46 -> -90125.682 | G44: Внешнее
A45: Түсімдер | B45: 251872.16 | C45: 1447223.5 | D45: 2231117.1 | E45: 68267.654 | F45: 31.4 | G45: Поступление
A46: Өтеу | B46: 660721.39 | C46: 1154283.9 | D46: 1708213 | E46: 145560.29 | F46: 90157.082 | G46: Погашение

Sheet табл 8 (дох)
B2: 8-кесте | H2: Таблица 8
F3: РЕСПУБЛИКАЛЫҚ БЮДЖЕТТІҢ АТҚАРЫЛУЫ/ ИСПОЛНЕНИЕ РЕСПУБЛИКАНСКОГО БЮДЖЕТА
B4: (млн.теңге) | H4: (млн.тенге)
B5: Санаты/ Категория | C5: Сыныбы/ Класс | D5: Сыныпшасы/ Подкласс | E5: Ерешелігі/ Специфика | F5: Атауы | G5: 2026 ж. қаңтар-наурыз есеп/_x000D_ январь-март отчет 2026 г. | H5: Наименование
B6: 1 | C6: 2 | D6: 3 | E6: 4 | F6: 5 | G6: 6 | H6: 7
F7: ТҮСІМДЕР | G7: 5261517.6 | H7: ПОСТУПЛЕНИЯ
F8: оның ішінде: | H8: в том числе:
F9: КІРІСТЕР | G9: 5206986.9 | H9: ДОХОДЫ
B10: 1 | F10: Салықтық түсімдер | G10: 4077555.7 | H10: Налоговые поступления
C11: 01 | F11: Табыс салығы | G11: 1191464.1 | H11: Подоходный налог
D12: 1 | F12: Корпоративтік табыс салығы | G12: 1191464.1 | H12: Корпоративный подоходный налог
B13: 1 | C13: 01 | D13: 1 | E13: 10 | F13: Мұнай секторы ұйымдарынан түсетін түсімдерді қоспағанда, ірі кәсіпкерлік субъектілерінен – заңды тұлғалардан алынатын корпоративтік табыс салығы | G13: 1191464.1 | H13: Корпоративный подоходный налог с юридических лиц – субъектов крупного предпринимательства, за исключением поступлений от организаций нефтяного сектора
C14: 05 | F14: Тауарларға, жұмыстарға және көрсетілетін қызметтерге салынатын iшкi салықтар | G14: 2375567.6 | H14: Внутренние налоги на товары, работы и услуги
D15: 1 | F15: Қосылған құн салығы | G15: 1962484.6 | H15: Налог на добавленную стоимость
C16: 05 | D16: 1 | E16: 01 | F16: Қазақстан Республикасының аумағында өндiрiлген тауарларға, орындалған жұмыстарға және көрсетілген қызметтерге салынатынқосылған құн салығы | G16: 1001413.9 | H16: Hалог на добавленную стоимость на произведенные товары, выполненные работы и оказанные услуги на территории Республики Казахстан
E17: 02 | F17: Ресей Федерациясы және Беларусь Республикасының аумағынан импортталатын тауарларға салынатын қосылған құн салығынан басқа, Қазақстан Республикасының аумағына импортталатын тауарларға салынатын қосылған құн салығы | G17: 510847.07 | H17: Hалог на добавленную стоимость на товары, импортируемые на территорию Республики Казахстан, кроме налога на добавленнуюстоимость на товары, импортируемые с территории Российской Федерации и Республики Беларусь
E18: 04 | F18: Резидент емес үшін қосылған құн салығы | G18: 79955.742 | H18: Налог на добавленную стоимость за нерезидента
E19: 14 | F19: Салық төлеушінің бұрын бюджеттен қайтарылған және салықтықтексеру жүргізу барысында қайтарылуы расталмаған қосылған құн салығының асып кеткен сомасын аударуы (қайтаруы), өсімпұл сомасын аударуы | G19: 2270.2665 | H19: Перечисление (возврат) налогоплательщиком суммы превышения налога на добавленную стоимость, ранее возвращенной из бюджета и не подтвержденной к возврату при проведении налоговой проверки, перечисление суммы пени
E20: 15 | F20: Еуразиялық экономикалық одаққа мүше мемлекеттер аумағынан импортталған тауарларға қосылған құн салығы | G20: 348904.06 | H20: Налог на добавленную стоимость на товары, импортированные стерритории государств-членов Евразийского экономического союза
E21: 16 | F21: Тауарлармен электрондық сауданы жүзеге асыру, жеке тұлғаларға электрондық нысанда қызметтер көрсету кезінде шетелдік компаниялардан түсетін қосылған құн салығы | G21: 19093.575 | H21: Налог на добавленную стоимость с иностранных интернет компаний при осуществлении электронной торговли товарами, оказании услуг в электронной форме физическим лицам
D22: 2 | F22: Акциздер | G22: 22064.597 | H22: Акцизы
D23: 2 | E23: 76 | F23: Қазақстан Республикасының аумағына Еуразиялық экономикалық одағына мүше мемлекеттердің аумағынан әкелінетін темекі өнімдері | G23: 1395.6727 | H23: Табачные изделия, ввозимые на территорию Республики Казахстан с территории государств-членов Евразийского экономического союза
E24: 77 | F24: Қазақстан Республикасының аумағына Еуразиялық экономикалық одағына мүше мемлекеттердің аумағынан әкелінетін спирттiң және (немесе) шарап материалының, алкоголь өнімдерінің барлық түрлерi | G24: 2899.1659 | H24: Все виды спирта и (или) виноматериала, алкогольной продукции, ввозимых на территорию Республики Казахстан с территории государств-членов Евразийского экономического союза
E25: 78 | F25: Қазақстан Республикасының аумағына Еуразиялық экономикалық одағына мүше мемлекеттердің аумағынан әкелінетін акцизделетін өнімнің өзге түрлері | G25: 75.67803 | H25: Прочие виды подакцизной продукции, ввозимой на территорию Республики Казахстан с территории государств-членов Евразийского экономического союза
E26: 79 | F26: Қазақстан Республикасы аумағына Еуразиялық экономикалық одағына мүше мемлекеттердің аумағынан әкелінетін бензин (авиациялықты қоспағанда) және дизель отыны | G26: 4754.7208 | H26: Бензин (за исключением авиационного) и дизельное топливо, ввозимых на территорию Республики Казахстан с территории государств-членов Евразийского экономического союза
E27: 80 | F27: Еуразиялық экономикалық одағына мүше болып табылмайтын мемлекеттердің аумағынан әкелінетін, Қазақстан Республикасының аумағына импортталатын спирттің және (немесе) шарап материалының, алкоголь өнімдерінің барлық түрлері | G27: 3612.5414 | H27: Все виды спирта и (или) виноматериала, алкогольной продукции, импортируемых на территорию Республики Казахстан с территории государств, не являющихся членами Евразийского экономического союза
E28: 81 | F28: Еуразиялық экономикалық одағына мүше болып табылмайтын мемлекеттердің аумағынан әкелінетін, Қазақстан Республикасының аумағына импортталатын темекі өнімдері | G28: 8085.2433 | H28: Табачные изделия, импортируемые на территорию Республики Казахстан с территории государств, не являющихся членами Евразийского экономического союза
E29: 82 | F29: Еуразиялық экономикалық одағына мүше болып табылмайтын мемлекеттердің аумағынан әкелінетін, Қазақстан Республикасының аумағына импортталатын акцизделетін өнімдердің өзге түрлері | G29: 1215.2615 | H29: Прочие виды подакцизных продукций, импортируемые на территорию Республики Казахстан с территории государств, не являющихся членами Евразийского экономического союза
E30: 83 | F30: Еуразиялық экономикалық одағына мүше болып табылмайтын мемлекеттер аумағынан әкелінетін, Қазақстан Республикасының аумағына импортталатын бензин (авиациялықты қоспағанда) және дизель отыны | G30: 26.31368 | H30: Бензин (за исключением авиационного) и дизельное топливо, импортируемых на территорию Республики Казахстан с территориигосударств, не являющихся членами Евразийского экономического союза
D31: 3 | F31: Табиғи және басқа да ресурстарды пайдаланғаны үшiн түсетiн түсiмдер | G31: 390988.36 | H31: Поступления за использование природных и других ресурсов
D32: 3 | E32: 01 | F32: Қалааралық және (немесе) халықаралық телефон байланысын, сондай-ақ ұялы байланысты бергені үшін төлемақы | G32: 3205.7626 | H32: Плата за предоставление междугородной и (или) международнойтелефонной связи, а также сотовой связи
E33: 02 | F33: Мұнай секторы ұйымдарынан түсетін түсімдерді қоспағанда, үстеме пайдаға салынатын салық | G33: 165.032 | H33: Налог на сверхприбыль, за исключением поступлений от организаций нефтяного сектора
E34: 05 | F34: Мұнай секторы ұйымдарынан түсетін түсімдерді қоспағанда, бонустар | G34: 504.2923 | H34: Бонусы, за исключением поступлений от организаций нефтяногосектора
E35: 06 | F35: Кең таралған пайдалы қазбаларды, жерасты суларын, емдік балшықтарды және мұнай секторы ұйымдарынан түсетін түсімдерді қоспағанда, пайдалы қазбаларды өндіру салығы | G35: 386218.62 | H35: Налог на добычу полезных ископаемых, за исключением общераспространенных полезных ископаемых, подземных вод, лечебных грязей и поступлений от организаций нефтяного сектора
E36: 07 | F36: Мұнай секторы ұйымдарынан түсетін түсімдерді қоспағанда, экспортқа рента салығы | G36: 325.41666 | H36: Рентный налог на экспорт, за исключением поступлений от организаций нефтяного сектора
E37: 08 | F37: Мұнай секторы ұйымдарынан түсетін түсімдерді қоспағанда, жасалған келісімшарттар бойынша өнімді бөлу жөніндегі Қазақстан Республикасының үлесі | G37: 0.001 | H37: Доля Республики Казахстан по разделу продукции по заключенным контрактам, за исключением поступлений от организаций нефтяного сектора
E38: 09 | F38: Радиожиілік спектрін пайдаланғаны үшін төлем | G38: 569.28463 | H38: Плата за использование радиочастотного спектра
E39: 12 | F39: Мұнай секторы ұйымдарынан түсетін түсімдерді қоспағанда, өнімді бөлу туралы келісімшарт бойынша қызметті жүзеге асыратын жер қойнауын пайдаланушының қосымша төлемі және баламалы салық | G39: -0.051695 | H39: Дополнительный платеж недропользователя, осуществляющего деятельность по контракту о разделе продукции, и альтернативный налог, за исключением поступлений от организаций нефтяногосектора
D40: 4 | F40: Кәсiпкерлiк және кәсiби қызметтi жүргiзгенi үшiн алынатын алымдар | G40: 30.036775 | H40: Сборы за ведение предпринимательской и профессиональной деятельности
D41: 4 | E41: 28 | F41: Республикалық бюджетке төленетін тіркелгені үшін алым | G41: 24.66019 | H41: Регистрационный сбор, зачисляемый в республиканский бюджет
E42: 31 | F42: Микроқаржы ұйымдарын есептік тіркеуден өткізгені және оларды микроқаржы ұйымдарының тізіліміне енгізгені үшін алым | G42: 0.01966 | H42: Сбор за прохождение учетной регистрации микрофинансовых организаций и включение их в реестр микрофинансовых организаций
E43: 32 | F43: Банк және сақтандыру нарықтарына қатысушылар үшін рұқсат беру құжаттарын, келісім бергені үшін алым | G43: 5.356925 | H43: Сбор за выдачу разрешительных документов, согласия для участников банковского и страхового рынков
E44: 36 | F44: "Астана" халықаралық қаржы орталығының инвестициялық резиденті болып табылатын шетелдіктің немесе азаматтығы жоқ адамның резиденттігін растайтын құжатты бергені үшін алы | G44: 0 | H44: Сбор за выдачу документа, подтверждающего резидентство иностранца или лица без гражданства, являющегося инвестиционным резидентом Международного финансового центра "Астана"
C45: 06 | F45: Халықаралық сауда мен сыртқы операцияларға салынатын салықтар | G45: 378715.06 | H45: Hалоги на международную торговлю и внешние операции
D46: 1 | F46: Кедендік төлемдер | G46: 360761.32 | H46: Таможенные платежи
C47: 06 | D47: 1 | E47: 01 | F47: Еуразиялық экономикалық одақ туралы шартқа сәйкес төленген әкелінетін кедендік баждары (баламалы қолданылатын өзге де баждар, салықтар мен алымдар) | G47: 10096.544 | H47: Ввозные таможенные пошлины (иные пошлины, налоги и сборы, имеющие эквивалентное действие), уплаченные в соответствии с Договором о Евразийском экономическом союзе
E48: 02 | F48: Әкетілетін тауарларға салынатын кедендік баждар | G48: 3094.3162 | H48: Таможенные пошлины на вывозимые товары
E49: 04 | F49: Кеден бажының бірыңғай ставкасын қолданумен жеке тұлғалардан өндіріп алынатын жеке пайдалануына әкелінетін тауарларға салынатын кеден баждары, салықтары | G49: 960.96553 | H49: Таможенные пошлины, налоги на ввозимые физическими лицами товары для личного пользования с применением единых ставок таможенных пошлин, налогов
E50: 05 | F50: Әкелінетін тауарларға жиынтық кедендік төлем | G50: 372.95291 | H50: Совокупный таможенный платеж на ввозимые товары
E51: 06 | F51: Ресей Федерациясымен бөлінген кедендік баж | G51: 93162.517 | H51: Таможенные пошлины, распределенные Российской Федерацией
E52: 07 | F52: Беларусь Республикасымен бөлінген кедендік баж | G52: 6245.7698 | H52: Таможенные пошлины, распределенные Республикой Беларусь
E53: 10 | F53: Мұнайға салынатын кедендік әкету бажы | G53: 233079.25 | H53: Вывозные таможенные пошлины на сырую нефть
E54: 11 | F54: Мұнайдан өндірілген тауарларға салынатын кедендік әкету бажы | G54: 3280.9341 | H54: Вывозные таможенные пошлины на товары, выработанные из нефти
E55: 12 | F55: Кеден одағында кедендік әкелу баждарын (баламалы қолданысы бар өзге де баждарды, салықтар мен алымдарды) есепке жатқызужәне бөлу тәртібін белгілеу және қолдану туралы келісім күшіне енгенге дейін төлеу жөніндегі міндеті туындаған әкелінеті | G55: 391.13478 | H55: Таможенные пошлины на ввозимые товары и (или) ввозные таможенные пошлины, обязанность по уплате которых возникла до вступления в силу Соглашения об установлении и применении в таможенном союзе порядка зачисления и распределения ввозных тамо
E56: 13 | F56: Армения Республикасымен бөлінген кедендік баждар | G56: 2260.4821 | H56: Таможенные пошлины, распределенные Республикой Армения
E57: 17 | F57: Қырғыз Республикасы бөлген кедендік баждар | G57: 3351.0686 | H57: Таможенные пошлины, распределенные Кыргызской Республикой
E58: 19 | F58: Алдағы кедендік баждарды, кедендік алымдарды, салықтарды, арнайы, демпингке қарсы, өтемақы баждарын төлеу есебіне, сондай-ақ кедендік баждарды, салықтарды арнайы, демпингке қарсы,өтемақы баждарын төлеу жөніндегі міндеттің орындалуын қамтам | G58: 4465.3795 | H58: Авансовые платежи, вносимые в соответствии с таможенным законодательством Евразийского экономического союза и Республики Казахстан, в счет уплаты предстоящих таможенных платежей, налогов, специальных, антидемпинговых, компенсационных пошлин
D59: 2 | F59: Халықаралық сауда мен операцияларға салынатын басқа да салықтар | G59: 17953.742 | H59: Прочие налоги на международную торговлю и операции
D60: 2 | E60: 01 | F60: Қазақстан Республикасының кеден заңнамасына сәйкес төленетін кедендік алымдар | G60: 14678.89 | H60: Таможенные сборы, уплачиваемые в соответствии с таможенным законодательством Республики Казахстан
E61: 02 | F61: Еуразиялық экономикалық одақ туралы шартқа сәйкес төленген арнайы, демпингке қарсы, өтемақы баждары | G61: 289.54694 | H61: Специальные, антидемпинговые, компенсационные пошлины, уплаченные в соответствии с Договором о Евразийском экономическом союзе
E62: 05 | F62: Беларусь Республикасынан түсетін арнайы, демпингке қарсы, өтемақы баждары | G62: 113.86232 | H62: Специальные, антидемпинговые, компенсационные пошлины, поступившие от Республики Беларусь
E63: 06 | F63: Ресей Федерациясынан түсетін арнайы, демпингке қарсы, өтемақы баждары | G63: 2800.419 | H63: Специальные, антидемпинговые, компенсационные пошлины, поступившие от Российской Федерации
E64: 08 | F64: Бөлуге жатпайтын арнайы, демпингке қарсы, өтемақы баждары | G64: -0.050409 | H64: Специальные, антидемпинговые, компенсационные пошлины, не подлежащие распределению
E65: 09 | F65: Армения Республикасынан түсетін арнайы, демпингке қарсы, өтемақы баждары | G65: 34.145592 | H65: Специальные, антидемпинговые, компенсационные пошлины, поступившие от Республики Армения
E66: 11 | F66: Қырғыз Республикасынан түскен арнайы, демпингке қарсы, өтемақы баждары | G66: 36.928759 | H66: Специальные, антидемпинговые, компенсационные пошлины, поступившие от Кыргызской Республики
C67: 07 | F67: Басқа да салықтар | G67: 130716.27 | H67: Прочие налоги
D68: 1 | F68: Басқа да салықтар | G68: 130716.27 | H68: Прочие налоги
C69: 07 | D69: 1 | E69: 09 | F69: Республикалық бюджетке түсетін өзге де салық түсiмдері | G69: 130716.27 | H69: Прочие налоговые поступления в республиканский бюджет
C70: 08 | F70: Заңдық маңызы бар әрекеттерді жасағаны және (немесе) оған уәкілеттігі бар мемлекеттік органдар немесе лауазымды адамдар құжаттар бергені үшін алынатын міндетті төлемдер | G70: 1092.6641 | H70: Обязательные платежи, взимаемые за совершение юридически значимых действий и (или) выдачу документов уполномоченными нато государственными органами или должностными лицами
D71: 1 | F71: Мемлекеттік баж | G71: 1092.6641 | H71: Государственная пошлина
C72: 08 | D72: 1 | E72: 01 | F72: Консулдық алым | G72: 1092.6641 | H72: Консульский сбор
B73: 2 | F73: Салықтық емес түсiмдер | G73: 79068.8 | H73: Неналоговые поступления
C74: 01 | F74: Мемлекеттік меншіктен түсетін кірістер | G74: 58776.842 | H74: Доходы от государственной собственности
D75: 1 | F75: Мемлекеттік кәсіпорындардың таза кірісі бөлігінің түсімдері | G75: 224.23185 | H75: Поступления части чистого дохода государственных предприятий
B76: 2 | C76: 01 | D76: 1 | E76: 01 | F76: Республикалық мемлекеттік кәсіпорындардың таза кірісі бөлігінің түсімдері | G76: 224.23185 | H76: Поступления части чистого дохода республиканских государственных предприятий
D77: 3 | F77: Мемлекет меншігіндегі акциялардың мемлекеттік пакеттеріне дивидендтер | G77: 27674.679 | H77: Дивиденды на государственные пакеты акций, находящиеся в государственной собственности
D78: 3 | E78: 01 | F78: Республикалық меншігіндегі акциялардың мемлекеттік пакеттеріне дивидендтер | G78: 27674.679 | H78: Дивиденды на государственные пакеты акций, находящиеся в республиканской собственности
D79: 4 | F79: Мемлекет меншігіндегі заңды тұлғалардағы қатысу үлесіне кірістер | G79: 54.393074 | H79: Доходы на доли участия в юридических лицах, находящиеся в государственной собственности
D80: 4 | E80: 01 | F80: Республикалық меншігіндегі заңды тулғаларға қатысу үлесіне кірістер | G80: 54.393074 | H80: Доходы на доли участия в юридических лицах, находящиеся в республиканской собственности
D81: 5 | F81: Мемлекет меншігіндегі мүлікті жалға беруден түсетін кірістер | G81: 15052.265 | H81: Доходы от аренды имущества, находящегося в государственнойсобственности
D82: 5 | E82: 01 | F82: Республикалық меншіктегі мүлікті жалға беруден түсетін кірістер | G82: 1278.3054 | H82: Доходы от аренды имущества, находящегося в республиканской собственности
E83: 02 | F83: Әскери полигондарды пайдаланғаны үшін жалгерлік төлемнен түсетін түсімдер | G83: 0 | H83: Поступления арендной платы за пользование военными полигонами
E84: 03 | F84: «Байқоныр» кешенін пайдаланғаны үшін жалгерлік төлемнен түсетін түсімдер | G84: 13773.959 | H84: Поступления арендной платы за пользование комплексом «Байконур»
D85: 6 | F85: Бюджет қаражатын банк шоттарына орналастырғаны үшін сыйақылар | G85: 3039.2818 | H85: Вознаграждения за размещение бюджетных средств на банковских счетах
D86: 6 | E86: 01 | F86: Қазақстан Республикасы Үкіметінің Қазақстан Республикасы Ұлттық банкіндегі депозиттері бойынша және бірыңғай қазынашылық шоттағы ақшаның күн сайынғы қалдығына сыйақылар | G86: 1145.1754 | H86: Вознаграждения по депозитам Правительства Республики Казахстан в Национальном Банке Республики Казахстан и на ежедневный остаток денег на едином казначейском счете
E87: 04 | F87: Квазимемлекеттік сектор субъектілерінің уақытша бос бюджет қаражатын қаржы құралдарына орналастырудан алынған сыйақылар | G87: 1894.1063 | H87: Вознаграждения, полученные от размещения в финансовые инструменты временно свободных бюджетных средств cубъектами квазигосударственного сектора
D88: 7 | F88: Мемлекеттік бюджеттен берілген кредиттер бойынша сыйақылар | G88: 271.92103 | H88: Вознаграждения по кредитам, выданным из государственного бюджета
D89: 7 | E89: 01 | F89: Облыстардың, республикалық маңызы бар қаланың, астананың жергілікті атқарушы органдарына ішкі көздер есебінен республикалық бюджеттен берілген бюджеттік кредиттер бойынша сыйақылар | G89: 61.026436 | H89: Вознаграждения по бюджетным кредитам, выданным из республиканского бюджета за счет внутренних источников местным исполнительным органам областей, города республиканского значения,столицы
E90: 02 | F90: Облыстардың, республикалық маңызы бар қаланың, астананың жергілікті атқарушы органдарына үкіметтік сыртқы қарыздар қаражаты есебінен республикалық бюджеттен берілген бюджеттік кредиттер бойынша сыйақылар | G90: 32.557179 | H90: Вознаграждения по бюджетным кредитам, выданным из республиканского бюджета за счет средств правительственных внешних займов местным исполнительным органам областей, города республиканского значения, столицы
E91: 04 | F91: Мамандандырылған ұйымдарға ішкі көздер есебінен республикалық бюджеттен берілген бюджеттік кредиттер бойынша сыйақылар | G91: 178.05872 | H91: Вознаграждения по бюджетным кредитам, выданным из республиканского бюджета за счет внутренних источников специализированным организациям
E92: 10 | F92: Заңды тұлғаларға үкіметтік сыртқы қарыздар қаражаты есебінен республикалық бюджеттен 2005 жылға дейін берілген бюджеттік кредиттер бойынша сыйақылар | G92: 0.2787 | H92: Вознаграждения по бюджетным кредитам, выданным из республиканского бюджета до 2005 года за счет средств правительственных внешних займов юридическим лицам
D93: 9 | F93: Мемлекет меншігінен түсетін басқа да кірістер | G93: 12460.071 | H93: Прочие доходы от государственной собственности
D94: 9 | E94: 01 | F94: Ауыл шаруашылығы және орман алқаптарын ауыл және орман шаруашылықтарын жүргізуге байланысты емес мақсаттарға пайдалану үшін алған кезде ауыл шаруашылығы және орман шаруашылығы өндірістерінің шығасыларын өтеуден түсетін түсімдер | G94: 866.02636 | H94: Поступления от возмещения потерь сельскохозяйственного и лесохозяйственного производства при изъятии сельскохозяйственных и лесных угодий для использования их в целях, не связанных с ведением сельского и лесного хозяйства
E95: 03 | F95: Жер қойнауы туралы ақпаратты пайдалануға берілгені үшін ақы | G95: 0.0004 | H95: Плата за предоставление в пользование информации о недрах
E96: 05 | F96: Қару-жарақты және әскери техниканы сатудан түсетін кірістер | G96: 1243.3735 | H96: Доходы от продажи вооружения и военной техники
E97: 06 | F97: Арнаулы мемлекеттік қорға түсетін түсімдерді қоспағанда, тәркіленген мүлікті, белгіленген тәртіппен республикалық меншікке өтеусіз өткен мүлікті, оның ішінде кедендік бас тарту режимінде мемлекеттің пайдасына ресімделген тауарлар мен көлік | G97: 5712.8384 | H97: Поступления от реализации конфискованного имущества, имущества, безвозмездно перешедшего в установленном порядке в республиканскую собственность, в том числе товаров и транспортных средств, оформленных в таможенном режиме отказа в пользу го
E98: 09 | F98: Республикалық меншігіне жататын жер учаскелері бойынша сервитут үшін төлемақы | G98: 14.949594 | H98: Плата за сервитут по земельным участкам, находящихся в республиканской собственности
E99: 11 | F99: Қазақстан Республикасының Мемлекеттік шекарасы арқылы автомобиль көлігі құралдарын, жүктер мен тауарларды өткізу, сондай-ақ олардың электрондық кезек бойынша өтуі үшін төлемақы | G99: 4622.8827 | H99: Плата за пропуск через Государственную границу Республики Казахстан автомобильных транспортных средств, грузов и товаров, а также их прохождение по электронной очереди
C100: 02 | F100: Мемлекеттік бюджеттен қаржыландырылатын мемлекеттік мекемелердің тауарларды (жұмыстарды, көрсетілетін қызметтерді) өткізуінен түсетін түсімдер | G100: 2416.1051 | H100: Поступления от реализации товаров (работ, услуг) государственными учреждениями, финансируемыми из государственного бюджета
D101: 1 | F101: Мемлекеттік бюджеттен қаржыландырылатын мемлекеттік мекемелердің тауарларды (жұмыстарды, көрсетілетін қызметтерді) өткізуінен түсетін түсімдер | G101: 2416.1051 | H101: Поступления от реализации товаров (работ, услуг) государственными учреждениями, финансируемыми из государственного бюджета
...

Sheet табл 8 (расх)
G2: (млн. тенге)
A3: (млн.теңге)
A5: Санаты/ Категория | B5: Сыныбы/ Класс | C5: Сыныпшасы/ Подкласс | D5: Ерешелігі/ Специфика | E5: Атауы | F5: 2026 қаңтар-наурыз есеп/_x000D_ январь-март отчет 2026г. | G5: Наименование
A6: 1 | B6: 2 | C6: 3 | D6: 4 | E6: 5 | F6: 6 | G6: 7
E7: ШЫҒЫСТАР | F7: 5961022.5 | G7: РАСХОДЫ
E8: оның ішінде: | G8: в том числе:
E9: II. ШЫҒЫНДАР | F9: 5944897.9 | G9: II. ЗАТРАТЫ
A10: 01 | E10: Жалпы сипаттағы мемлекеттiк қызметтер | F10: 257675.37 | G10: Государственные услуги общего характера
B11: 1 | E11: Мемлекеттiк басқарудың жалпы функцияларын орындайтын өкiлдi, атқарушы және басқа органдар | F11: 69920.031 | G11: Представительные, исполнительные и другие органы, выполняющие общие функции государственного управления
C12: 101 | E12: Қазақстан Республикасы Президентінің Әкімшілігі | F12: 4643.5489 | G12: Администрация Президента Республики Казахстан
A13: 01 | B13: 1 | C13: 101 | D13: 001 | E13: Мемлекет басшысының қызметін қамтамасыз ету | F13: 4643.5489 | G13: Обеспечение деятельности Главы государства
C14: 106 | E14: Адам құқықтары жөніндегі ұлттық орталық | F14: 409.75887 | G14: Национальный центр по правам человека
C15: 106 | D15: 001 | E15: Адамның және азаматтың құқықтары мен бостандықтарының сақталуын қадағалау жөніндегі көрсетілетін қызметтер | F15: 409.75887 | G15: Услуги по наблюдению за соблюдением прав и свобод человека и гражданина
C16: 107 | E16: Қазақстан Республикасы Жоғары Сот Кеңесінің Аппараты | F16: 333.45298 | G16: Аппарат Высшего Судебного Совета Республики Казахстан
C17: 107 | D17: 001 | E17: Қазақстан Республикасы Жоғары Сот Кеңесінің қызметін қамтамасыз ету жөніндегі көрсетілетін қызметтер | F17: 333.45298 | G17: Услуги по обеспечению деятельности Высшего Судебного СоветаРеспублики Казахстан
C18: 109 | E18: Қазақстан Республикасы Үкіметінің Аппараты | F18: 1359.3539 | G18: Аппарат Правительства Республики Казахстан
C19: 109 | D19: 001 | E19: Қазақстан Республикасы Премьер-Министрінің қызметін қамтамасыз ету жөніндегі көрсетілетін қызметтер | F19: 1359.3539 | G19: Услуги по обеспечению деятельности Премьер-Министра Республики Казахстан
C20: 626 | E20: Қазақстан Республикасының Стратегиялық жоспарлау және реформалар агенттігі | F20: 6115.7632 | G20: Агентство по стратегическому планированию и реформам Республики Казахстан
C21: 626 | D21: 001 | E21: Реформаларды қалыптастыруға және тиімді іске асыруға жәрдемдесу жөніндегі көрсетілетін қызметтер, стратегиялық жоспарлау, мемлекеттік статистикалық қызмет салаларында мемлекеттік саясатты жүзеге асыру, мемлекеттік басқару жүйесі мен квазиме | F21: 6115.7632 | G21: Услуги по содействию в формировании и эффективной реализации реформ, осуществление государственной политики в сферах стратегического планирования, государственной статистической деятельности, участие в совершенствовании системы государствен
D22: 101 | E22: Өкілдiк шығындарға арналған қаражат есебiнен іс-шаралар өткізу | F22: 0 | G22: Проведение мероприятий за счет средств на представительскиезатраты
C23: 637 | E23: Қазақстан Республикасы Конституциялық Сотының Аппараты | F23: 487.15759 | G23: Аппарат Конституционного Суда Республики Казахстан
C24: 637 | D24: 001 | E24: Республика аумағында Қазақстан Республикасы Конституциясының үстемдігін қамтамасыз ету | F24: 487.15759 | G24: Обеспечение верховенства Конституции Республики Казахстан на территории Республики
C25: 690 | E25: Қазақстан Республикасының Орталық сайлау комиссиясы | F25: 18349.906 | G25: Центральная избирательная комиссия Республики Казахстан
C26: 690 | D26: 001 | E26: Сайлау өткізуді ұйымдастыру | F26: 303.9859 | G26: Организация проведения выборов
D27: 002 | E27: Сайлау өткізу | F27: 1017.0606 | G27: Проведение выборов
D28: 101 | E28: Өкілдiк шығындарға арналған қаражат есебiнен іс-шаралар өткізу | F28: 0 | G28: Проведение мероприятий за счет средств на представительскиезатраты
D29: 109 | E29: Қазақстан Республикасы Үкіметінің шұғыл шығындарға арналғанрезервінің есебінен ағымды іс-шаралар өткізу | F29: 17028.859 | G29: Проведение текущих мероприятий за счет резерва Правительства Республики Казахстан на неотложные затраты
C30: 693 | E30: Материалдық-техникалық қамтамасыз ету басқармасы | F30: 7300.5389 | G30: Управление материально-технического обеспечения
C31: 693 | D31: 001 | E31: Қазақстан Республикасы Парламентінің қызметін қамтамасыз ету жөніндегі көрсетілетін қызметтер | F31: 7300.5389 | G31: Услуги по обеспечению деятельности Парламента Республики Казахстан
C32: 694 | E32: Қазақстан Республикасы Президентiнiң Іс Басқармасы | F32: 30920.551 | G32: Управление Делами Президента Республики Казахстан
C33: 694 | D33: 001 | E33: Қазақстан Республикасы Президенті Іс Басқармасының мемлекеттік функциялары мен өкілеттіктерін жүзеге асыруды қамтамасызету жөніндегі көрсетілетін қызметтер | F33: 25804.727 | G33: Услуги по обеспечению осуществления государственных функцийи полномочий Управления Делами Президента Республики Казахстан
D34: 009 | E34: Қазақстан Республикасы Президенттік орталығының қызметін қамтамасыз ету жөніндегі көрсетілетін қызметтер | F34: 342.28471 | G34: Услуги по обеспечению деятельности Президентского центра Республики Казахстан
D35: 167 | E35: Қазақстан Республикасы Президентінің бастамаларына арналғанрезервінің есебінен бюджеттік инвестициялық жобаларды іске асыру | F35: 4773.5392 | G35: Реализация бюджетных инвестиционных проектов за счет резерва на инициативы Президента Республики Казахстан
B36: 2 | E36: Қаржылық қызмет | F36: 1322.5499 | G36: Финансовая деятельность
C37: 217 | E37: Қазақстан Республикасының Қаржы министрлігі | F37: 23.96876 | G37: Министерство финансов Республики Казахстан
B38: 2 | C38: 217 | D38: 002 | E38: Халықаралық қаржы ұйымдары қаржыландыратын инвестициялық жобалардың аудитiн жүзеге асыру | F38: 0 | G38: Осуществление аудита инвестиционных проектов, финансируемыхмеждународными финансовыми организациями
D39: 094 | E39: Мемлекеттік активтерді басқару | F39: 23.96876 | G39: Управление государственными активами
C40: 406 | E40: Қазақстан Республикасының Жоғары аудиторлық палатасы | F40: 1298.5811 | G40: Высшая аудиторская палата Республики Казахстан
C41: 406 | D41: 001 | E41: Қазақстан Республикасы Жоғары аудиторлық палатасының қызметін қамтамасыз ету жөніндегі көрсетілетін қызметтер | F41: 1298.5811 | G41: Услуги по обеспечению деятельности Высшей аудиторской палаты Республики Казахстан
B42: 3 | E42: Сыртқы саяси қызмет | F42: 32796.713 | G42: Внешнеполитическая деятельность
C43: 204 | E43: Қазақстан Республикасының Сыртқы iстер министрлiгi | F43: 32796.713 | G43: Министерство иностранных дел Республики Казахстан
B44: 3 | C44: 204 | D44: 001 | E44: Сыртқы саяси қызметті үйлестіру жөніндегі көрсетілетін қызметтер | F44: 27189.097 | G44: Услуги по координации внешнеполитической деятельности
D45: 005 | E45: Шетелдік іссапарлар | F45: 1074.3286 | G45: Заграничные командировки
D46: 008 | E46: Шетелдегі дипломатиялық өкілдіктердің арнайы, инженерлік-техникалық және нақты қорғалуын қамтамасыз ету | F46: 54.259979 | G46: Обеспечение специальной, инженерно-технической и физическойзащиты дипломатических представительств за рубежом
D47: 013 | E47: Халықаралық ұйымдарда, Тәуелсіз Мемлекеттер Достастығының жарғылық және басқа органдарында Қазақстан Республикасының мүдделерін білдіру | F47: 80.100571 | G47: Представление интересов Республики Казахстан в международных организациях, уставных и других органах Содружества Независимых Государств
D48: 017 | E48: Қазақстан Республикасының халықаралық ұйымдарға, өзге де халықаралық және басқа органдарға қатысуы | F48: 4138.628 | G48: Участие Республики Казахстан в международных организациях, иных международных и прочих органах
D49: 019 | E49: Ақпараттық-имидждік саясаттың іске асырылуын қамтамасыз ету | F49: 93.768741 | G49: Обеспечение реализации информационно-имиджевой политики
D50: 100 | E50: Қазақстан Республикасы Үкіметінің төтенше резерві есебінен ағымды іс-шаралар өткізу | F50: 49.733 | G50: Проведение текущих мероприятий за счет чрезвычайного резерва Правительства Республики Казахстан
D51: 101 | E51: Өкілдiк шығындарға арналған қаражат есебiнен іс-шаралар өткізу | F51: 21.582978 | G51: Проведение мероприятий за счет средств на представительскиезатраты
D52: 109 | E52: Қазақстан Республикасы Үкіметінің шұғыл шығындарға арналғанрезервінің есебінен ағымды іс-шаралар өткізу | F52: 95.214273 | G52: Проведение текущих мероприятий за счет резерва Правительства Республики Казахстан на неотложные затраты
D53: 164 | E53: Қазақстанның Экономикалық ынтымақтастық және даму ұйымымен ынтымақтастығы шеңберінде Қазақстанның Экономикалық ынтымақтастық және даму ұйымының бастамалары мен құралдарына қатысуын қамтамасыз ету | F53: 0 | G53: Обеспечение участия Казахстана в инициативах и инструментахОрганизации экономического сотрудничества и развития в рамках сотрудничества Казахстана с Организацией экономического сотрудничества и развития
C54: 207 | E54: Қазақстан Республикасының Экология және табиғи ресурстар министрлігі | F54: 0 | G54: Министерство экологии и природных ресурсов Республики Казахстан
C55: 207 | D55: 164 | E55: Қазақстанның Экономикалық ынтымақтастық және даму ұйымымен ынтымақтастығы шеңберінде Қазақстанның Экономикалық ынтымақтастық және даму ұйымының бастамалары мен құралдарына қатысуын қамтамасыз ету | F55: 0 | G55: Обеспечение участия Казахстана в инициативах и инструментахОрганизации экономического сотрудничества и развития в рамках сотрудничества Казахстана с Организацией экономического сотрудничества и развития
C56: 217 | E56: Қазақстан Республикасының Қаржы министрлігі | F56: 0 | G56: Министерство финансов Республики Казахстан
C57: 217 | D57: 164 | E57: Қазақстанның Экономикалық ынтымақтастық және даму ұйымымен ынтымақтастығы шеңберінде Қазақстанның Экономикалық ынтымақтастық және даму ұйымының бастамалары мен құралдарына қатысуын қамтамасыз ету | F57: 0 | G57: Обеспечение участия Казахстана в инициативах и инструментахОрганизации экономического сотрудничества и развития в рамках сотрудничества Казахстана с Организацией экономического сотрудничества и развития
C58: 224 | E58: Қазақстан Республикасының Оқу-ағарту министрлігі | F58: 0 | G58: Министерство просвещения Республики Казахстан
C59: 224 | D59: 164 | E59: Қазақстанның Экономикалық ынтымақтастық және даму ұйымымен ынтымақтастығы шеңберінде Қазақстанның Экономикалық ынтымақтастық және даму ұйымының бастамалары мен құралдарына қатысуын қамтамасыз ету | F59: 0 | G59: Обеспечение участия Казахстана в инициативах и инструментахОрганизации экономического сотрудничества и развития в рамках сотрудничества Казахстана с Организацией экономического сотрудничества и развития
C60: 227 | E60: Қазақстан Республикасының Ғылым және жоғары білім министрлігі | F60: 0 | G60: Министерство науки и высшего образования Республики Казахстан
C61: 227 | D61: 164 | E61: Қазақстанның Экономикалық ынтымақтастық және даму ұйымымен ынтымақтастығы шеңберінде Қазақстанның Экономикалық ынтымақтастық және даму ұйымының бастамалары мен құралдарына қатысуын қамтамасыз ету | F61: 0 | G61: Обеспечение участия Казахстана в инициативах и инструментахОрганизации экономического сотрудничества и развития в рамках сотрудничества Казахстана с Организацией экономического сотрудничества и развития
C62: 228 | E62: Қазақстан Республикасының Көлік министрлігі | F62: 0 | G62: Министерство транспорта Республики Казахстан
C63: 228 | D63: 164 | E63: Қазақстанның Экономикалық ынтымақтастық және даму ұйымымен ынтымақтастығы шеңберінде Қазақстанның Экономикалық ынтымақтастық және даму ұйымының бастамалары мен құралдарына қатысуын қамтамасыз ету | F63: 0 | G63: Обеспечение участия Казахстана в инициативах и инструментахОрганизации экономического сотрудничества и развития в рамках сотрудничества Казахстана с Организацией экономического сотрудничества и развития
C64: 229 | E64: Қазақстан Республикасының Өнеркәсіп және құрылыс министрлігі | F64: 0 | G64: Министерство промышленности и строительства Республики Казахстан
C65: 229 | D65: 164 | E65: Қазақстанның Экономикалық ынтымақтастық және даму ұйымымен ынтымақтастығы шеңберінде Қазақстанның Экономикалық ынтымақтастық және даму ұйымының бастамалары мен құралдарына қатысуын қамтамасыз ету | F65: 0 | G65: Обеспечение участия Казахстана в инициативах и инструментахОрганизации экономического сотрудничества и развития в рамках сотрудничества Казахстана с Организацией экономического сотрудничества и развития
C66: 243 | E66: Қазақстан Республикасының Ұлттық экономика министрлігі | F66: 0 | G66: Министерство национальной экономики Республики Казахстан
C67: 243 | D67: 057 | E67: Қазақстанның Экономикалық ынтымақтастық және даму ұйымымен ынтымақтастығы шеңберінде Қазақстанның Экономикалық ынтымақтастық және даму ұйымының бастамалары мен құралдарына қатысуы | F67: 0 | G67: Участие Казахстана в инициативах и инструментах Организацииэкономического сотрудничества и развития в рамках сотрудничества Казахстана с Организацией экономического сотрудничества и развития
D68: 096 | E68: Қазақстан Республикасы мен Экономикалық ынтымақтастық және даму ұйымының арасындағы ынтымақтастық шеңберінде Қазақстан Республикасының әлеуметтік-экономикалық жағдайына зерттеулержүргізу | F68: 0 | G68: Проведение исследования социально-экономического положения Республики Казахстан в рамках сотрудничества между Республикой Казахстан и Организацией экономического сотрудничества и развития
D69: 159 | E69: Қазақстан Республикасы мен Экономикалық ынтымақтастық және даму ұйымының арасындағы ынтымақтастық шеңберінде Қазақстан Республикасының әлеуметтік-экономикалық жағдайына зерттеулержүргізуді қамтамасыз ету | F69: 0 | G69: Обеспечение проведения исследований социально-экономического положения Республики Казахстан в рамках сотрудничества между Республикой Казахстан и Организацией экономического сотрудничества и развития
D70: 164 | E70: Қазақстанның Экономикалық ынтымақтастық және даму ұйымымен ынтымақтастығы шеңберінде Қазақстанның Экономикалық ынтымақтастық және даму ұйымының бастамалары мен құралдарына қатысуын қамтамасыз ету | F70: 0 | G70: Обеспечение участия Казахстана в инициативах и инструментахОрганизации экономического сотрудничества и развития в рамках сотрудничества Казахстана с Организацией экономического сотрудничества и развития
C71: 626 | E71: Қазақстан Республикасының Стратегиялық жоспарлау және реформалар агенттігі | F71: 0 | G71: Агентство по стратегическому планированию и реформам Республики Казахстан
C72: 626 | D72: 164 | E72: Қазақстанның Экономикалық ынтымақтастық және даму ұйымымен ынтымақтастығы шеңберінде Қазақстанның Экономикалық ынтымақтастық және даму ұйымының бастамалары мен құралдарына қатысуын қамтамасыз ету | F72: 0 | G72: Обеспечение участия Казахстана в инициативах и инструментахОрганизации экономического сотрудничества и развития в рамках сотрудничества Казахстана с Организацией экономического сотрудничества и развития
C73: 627 | E73: Қазақстан Республикасының Бәсекелестікті қорғау және дамытуагенттігі | F73: 0 | G73: Агентство по защите и развитию конкуренции Республики Казахстан
C74: 627 | D74: 164 | E74: Қазақстанның Экономикалық ынтымақтастық және даму ұйымымен ынтымақтастығы шеңберінде Қазақстанның Экономикалық ынтымақтастық және даму ұйымының бастамалары мен құралдарына қатысуын қамтамасыз ету | F74: 0 | G74: Обеспечение участия Казахстана в инициативах и инструментахОрганизации экономического сотрудничества и развития в рамках сотрудничества Казахстана с Организацией экономического сотрудничества и развития
B75: 4 | E75: Iргелi ғылыми зерттеулер | F75: 26001.141 | G75: Фундаментальные научные исследования
C76: 207 | E76: Қазақстан Республикасының Экология және табиғи ресурстар министрлігі | F76: 539.8529 | G76: Министерство экологии и природных ресурсов Республики Казахстан
B77: 4 | C77: 207 | D77: 131 | E77: Ғылыми және (немесе) ғылыми-техникалық қызмет субъектілерінбазалық қаржыландыруды қамтамасыз ету | F77: 539.8529 | G77: Обеспечение базового финансирования субъектов научной и (или) научно-технической деятельности
C78: 208 | E78: Қазақстан Республикасының Қорғаныс министрлігі | F78: 11.422 | G78: Министерство обороны Республики Казахстан
C79: 208 | D79: 131 | E79: Ғылыми және (немесе) ғылыми-техникалық қызмет субъектілерінбазалық қаржыландыруды қамтамасыз ету | F79: 11.422 | G79: Обеспечение базового финансирования субъектов научной и (или) научно-технической деятельности
C80: 212 | E80: Қазақстан Республикасының Ауыл шаруашылығы министрлiгi | F80: 1317.352 | G80: Министерство сельского хозяйства Республики Казахстан
C81: 212 | D81: 131 | E81: Ғылыми және (немесе) ғылыми-техникалық қызмет субъектілерінбазалық қаржыландыруды қамтамасыз ету | F81: 1317.352 | G81: Обеспечение базового финансирования субъектов научной и (или) научно-технической деятельности
C82: 213 | E82: Қазақстан Республикасының Еңбек және халықты әлеуметтiк қорғау министрлiгi | F82: 0 | G82: Министерство труда и социальной защиты населения РеспубликиКазахстан
C83: 213 | D83: 131 | E83: Ғылыми және (немесе) ғылыми-техникалық қызмет субъектілерінбазалық қаржыландыруды қамтамасыз ету | F83: 0 | G83: Обеспечение базового финансирования субъектов научной и (или) научно-технической деятельности
C84: 223 | E84: Қазақстан Республикасының Жасанды интеллект және цифрлық даму министрлігі | F84: 61.1643 | G84: Министерство искусственного интеллекта и цифрового развитияРеспублики Казахстан
C85: 223 | D85: 131 | E85: Ғылыми және (немесе) ғылыми-техникалық қызмет субъектілерінбазалық қаржыландыруды қамтамасыз ету | F85: 61.1643 | G85: Обеспечение базового финансирования субъектов научной и (или) научно-технической деятельности
C86: 224 | E86: Қазақстан Республикасының Оқу-ағарту министрлігі | F86: 0 | G86: Министерство просвещения Республики Казахстан
C87: 224 | D87: 131 | E87: Ғылыми және (немесе) ғылыми-техникалық қызмет субъектілерінбазалық қаржыландыруды қамтамасыз ету | F87: 0 | G87: Обеспечение базового финансирования субъектов научной и (или) научно-технической деятельности
C88: 226 | E88: Қазақстан Республикасының Денсаулық сақтау министрлігі | F88: 634.0545 | G88: Министерство здравоохранения Республики Казахстан
C89: 226 | D89: 131 | E89: Ғылыми және (немесе) ғылыми-техникалық қызмет субъектілерінбазалық қаржыландыруды қамтамасыз ету | F89: 634.0545 | G89: Обеспечение базового финансирования субъектов научной и (или) научно-технической деятельности
C90: 227 | E90: Қазақстан Республикасының Ғылым және жоғары білім министрлігі | F90: 23066.139 | G90: Министерство науки и высшего образования Республики Казахстан
C91: 227 | D91: 130 | E91: Ғылыми және (немесе) ғылыми-техникалық қызмет субъектілерінбазалық қаржыландыру | F91: 0 | G91: Базовое финансирование субъектов научной и (или) научно-технической деятельности
D92: 131 | E92: Ғылыми және (немесе) ғылыми-техникалық қызмет субъектілерінбазалық қаржыландыруды қамтамасыз ету | F92: 1130.3003 | G92: Обеспечение базового финансирования субъектов научной и (или) научно-технической деятельности
D93: 217 | E93: Ғылымды дамыту | F93: 21935.839 | G93: Развитие науки
C94: 228 | E94: Қазақстан Республикасының Көлік министрлігі | F94: 12.6 | G94: Министерство транспорта Республики Казахстан
C95: 228 | D95: 131 | E95: Ғылыми және (немесе) ғылыми-техникалық қызмет субъектілерінбазалық қаржыландыруды қамтамасыз ету | F95: 12.6 | G95: Обеспечение базового финансирования субъектов научной и (или) научно-технической деятельности
C96: 229 | E96: Қазақстан Республикасының Өнеркәсіп және құрылыс министрлігі | F96: 280.48974 | G96: Министерство промышленности и строительства Республики Казахстан
C97: 229 | D97: 131 | E97: Ғылыми және (немесе) ғылыми-техникалық қызмет субъектілерінбазалық қаржыландыруды қамтамасыз ету | F97: 280.48974 | G97: Обеспечение базового финансирования субъектов научной и (или) научно-технической деятельности
C98: 629 | E98: Қазақстан Республикасының Атом энергиясы жөніндегі агенттігі | F98: 21.5286 | G98: Агентство Республики Казахстан по атомной энергии
C99: 629 | D99: 131 | E99: Ғылыми және (немесе) ғылыми-техникалық қызмет субъектілерінбазалық қаржыландыруды қамтамасыз ету | F99: 21.5286 | G99: Обеспечение базового финансирования субъектов научной и (или) научно-технической деятельности
C100: 652 | E100: Қазақстан Республикасының Су ресурстары және ирригация министрлігі | F100: 56.538 | G100: Министерство водных ресурсов и ирригации Республики Казахстан
C101: 652 | D101: 131 | E101: Ғылыми және (немесе) ғылыми-техникалық қызмет субъектілерінбазалық қаржыландыруды қамтамасыз ету | F101: 56.538 | G101: Обеспечение базового финансирования субъектов научной и (или) научно-технической деятельности
B102: 5 | E102: Жоспарлау және статистикалық қызмет | F102: 642.01911 | G102: Планирование и статистическая деятельность
...

Sheet табл 9
B2: Кесте 9 | D2: Таблица 9
B3: ШЫҒЫСТАРДЫҢ ВЕДОМСТВОЛЫҚ | D3: ИСПОЛНЕНИЕ РЕСПУБЛИКАНСКОГО БЮДЖЕТА
B4: СЫНЫПТАМАСЫ БОЙЫНША | D4: ПО ВЕДОМСТВЕННОЙ
B5: РЕСПУБЛИКАЛЫҚ БЮДЖЕТТІҢ АТҚАРАЛУЫ | D5: КЛАССИФИКАЦИИ РАСХОДОВ
B6: (млн. теңге) | D6: (млн. тенге)
B8: Бағдарламалард_x000D_ ың_x000D_ əкімшісі/_x000D_ Администратор_x000D_ программ | C8: Атауы | D8: 2026 ж. қаңтар-наурыз есеп/_x000D_ январь-март 2026 г. | E8: Наименование
B9: 1 | C9: 2 | D9: 3 | E9: 4
C10: БАРЛЫҒЫ | D10: 5961022.5 | E10: ВСЕГО
B11: 101 | C11: Қазақстан Республикасы Президентінің Әкімшілігі | D11: 4643.5489 | E11: Администрация Президента Республики Казахстан
B12: 106 | C12: Адам құқықтары жөніндегі ұлттық орталық | D12: 409.75887 | E12: Национальный центр по правам человека
B13: 107 | C13: Қазақстан Республикасы Жоғары Сот Кеңесінің Аппараты | D13: 528.87079 | E13: Аппарат Высшего Судебного Совета Республики Казахстан
B14: 109 | C14: Қазақстан Республикасы Үкіметінің Аппараты | D14: 1984.2749 | E14: Аппарат Правительства Республики Казахстан
B15: 201 | C15: Қазақстан Республикасының Ішкі істер министрлігі | D15: 161631.72 | E15: Министерство внутренних дел Республики Казахстан
B16: 202 | C16: Қазақстан Республикасының Төтенше жағдайлар министрлiгi | D16: 42444.363 | E16: Министерство по чрезвычайным ситуациям Республики Казахстан
B17: 204 | C17: Қазақстан Республикасының Сыртқы iстер министрлiгi | D17: 32969.213 | E17: Министерство иностранных дел Республики Казахстан
B18: 207 | C18: Қазақстан Республикасының Экология және табиғи ресурстар министрлігі | D18: 22649.737 | E18: Министерство экологии и природных ресурсов Республики Казахстан
B19: 208 | C19: Қазақстан Республикасының Қорғаныс министрлігі | D19: 235759.49 | E19: Министерство обороны Республики Казахстан
B20: 211 | C20: Қазақстан Республикасының Сауда және интеграция министрлігі | D20: 2772.5892 | E20: Министерство торговли и интеграции Республики Казахстан
B21: 212 | C21: Қазақстан Республикасының Ауыл шаруашылығы министрлiгi | D21: 47197.44 | E21: Министерство сельского хозяйства Республики Казахстан
B22: 213 | C22: Қазақстан Республикасының Еңбек және халықты әлеуметтiк қорғау министрлiгi | D22: 1700333.6 | E22: Министерство труда и социальной защиты населения РеспубликиКазахстан
... B49: 694 | C49: Қазақстан Республикасы Президентiнiң Іс Басқармасы | D49: 61974.585 | E49: Управление Делами Президента Республики Казахстан

Sheet табл 10
A1: 10-кесте ШЫҒЫНДАРДЫҢ ЭКОНОМИКАЛЫҚ ЖІКТЕМЕСІ БОЙЫНША РЕСПУБЛИКАЛЫҚ БЮДЖЕТТІК ОРЫНДАЛУЫ (млн.теңге) | E1: Таблица 10 ИСПОЛНЕНИЕ РЕСПУБЛИКАНСКОГО БЮДЖЕТА ПО ЭКОНОМИЧЕСКОЙ КЛАССИФИКАЦИИ РАСХОДОВ (млн. тенге)
A3: Cанаты/_x000D_ Категория | B3: Iшкi сыныбы/_x000D_ Подкласс | C3: Ерекшелiгi/_x000D_ Специфика | D3: Атауы | F3: 2026 ж. қаңтар-наурыз/_x000D_ январь-март отчет 2026 г. | G3: Наименование
A4: 1 | B4: 2 | C4: 3 | D4: 4 | F4: 5 | G4: 6
D5: БАРЛЫҒЫ | F5: 5961022.5 | G5: ВСЕГО
A6: 1 | D6: Ағымдағы шығындар | F6: 5830837 | G6: Текущие затраты
A7: L01 Категория расходов | B7: 110 | D7: Жалақы | F7: 246566.97 | G7: Заработная плата
A8: 1 | B8: 110 | C8: 111 | D8: Еңбекке ақы төлеу | F8: 170041.76 | G8: Оплата труда
A9: 1 | C9: 112 | D9: Қосымша ақшалай төлемдер | F9: 47697.562 | G9: Дополнительные денежные выплаты
A10: 1 | C10: 113 | D10: Өтемақы төлемдері | F10: 25768.431 | G10: Компенсационные выплаты
A11: 1 | C11: 114 | D11: Міндетті кәсіптік зейнетақы жарналары | F11: 52.251932 | G11: Обязательные профессиональные пенсионные взносы
A12: 1 | C12: 116 | D12: Жұмыс берушілердің міндетті зейнетақы жарналары | F12: 3006.9655 | G12: Обязательные пенсионные взносы работодателей
A13: L01 Категория расходов | B13: 120 | D13: Жұмыс берушілердің жарналары | F13: 16472.743 | G13: Взносы работодателей
A14: 1 | B14: 120 | C14: 121 | D14: Әлеуметтік салық | F14: 6212.7379 | G14: Социальный налог
A15: 1 | C15: 122 | D15: Мемлекеттiк әлеуметтiк сақтандыру қорына әлеуметтiк аударымдар | F15: 7105.153 | G15: Социальные отчисления в Государственный фонд социального страхования
A16: 1 | C16: 123 | D16: Мiндеттi сақтандыру жарналары | F16: 123.01729 | G16: Взносы на обязательное страхование
A17: 1 | C17: 124 | D17: Міндетті әлеуметтік медициналық сақтандыруға аударымдар | F17: 3031.8344 | G17: Отчисления на обязательное социальное медицинское страхование
A18: L01 Категория расходов | B18: 130 | D18: Қазақстан Республикасының заңнамалық актілеріне сәйкес азаматтардың жекелеген санаттарына жалақы төлеу және жарналар аудару | F18: 13403.187 | G18: Выплата заработной платы отдельным категориям граждан и отчисления взносов в соответствии с законодательными актами Республики Казахстан
A19: 1 | B19: 130 | C19: 131 | D19: Техникалық персоналдың және келісімшарттық қызметшілердің еңбегіне ақы төлеу | F19: 11786.284 | G19: Оплата труда технического персонала и контрактных служащих
A20: 1 | C20: 134 | D20: Алқа билерге сыйақылар төлеу | F20: 68.33862 | G20: Выплата вознаграждений присяжным заседателям
A21: 1 | C21: 135 | D21: Техникалық персонал және келісімшарттық қызметшілер бойыншажұмыс берушілердің жарналары | F21: 1448.0689 | G21: Взносы работодателей по техническому персоналу и контрактным служащим
A22: 1 | C22: 136 | D22: Техникалық персоналдың және келісімшарттық қызметшілердің ел ішіндегі іссапарлары мен қызметтiк жол жүрулері | F22: 94.836212 | G22: Командировки и служебные разъезды внутри страны технического персонала и контрактных служащих
A23: 1 | C23: 137 | D23: Алқабилердің іссапарлық шығыстары | F23: 5.65915 | G23: Командировочные расходы присяжных заседателей
A24: L01 Категория расходов | B24: 140 | D24: Қорлар сатып алу | F24: 25661.437 | G24: Приобретение запасов
A25: 1 | B25: 140 | C25: 141 | D25: Азық-түлiк өнiмдерiн сатып алу | F25: 16090.1 | G25: Приобретение продуктов питания
A26: 1 | C26: 142 | D26: Дәрілік заттар және медициналық мақсаттағы өзге де бұйымдарды сатып алу | F26: 161.39185 | G26: Приобретение лекарственных средств и прочих изделий медицинского назначения
A27: 1 | C27: 143 | D27: Заттай мүлiктердi, басқа да киім нысанын және арнаулы киім-кешектер сатып алу, тiгу және жөндеу | F27: 4291.9556 | G27: Приобретение, пошив и ремонт предметов вещевого имущества идругого форменного и специального обмундирования
A28: 1 | C28: 144 | D28: Отын, жанар-жағар май материалдарын сатып алу | F28: 2457.2463 | G28: Приобретение топлива, горюче-смазочных материалов
A29: 1 | C29: 149 | D29: Өзге де қорларды сатып алу | F29: 2660.7429 | G29: Приобретение прочих запасов
A30: L01 Категория расходов | B30: 150 | D30: Қызметтер мен жұмыстарды сатып алу | F30: 272791.64 | G30: Приобретение услуг и работ
A31: 1 | B31: 150 | C31: 151 | D31: Коммуналдық қызметтерге ақы төлеу | F31: 11806.892 | G31: Оплата коммунальных услуг
A32: 1 | C32: 152 | D32: Байланыс қызметтерiне ақы төлеу | F32: 776.91337 | G32: Оплата услуг связи
A33: 1 | C33: 153 | D33: Көлiктiк қызмет көрсетулерге ақы төлеу | F33: 2033.2311 | G33: Оплата транспортных услуг
A34: 1 | C34: 154 | D34: Зерттеулер бойынша қызметтерге ақы төлеу | F34: 29040.34 | G34: Оплата услуг по исследованиям
A35: 1 | C35: 155 | D35: Мемлекеттiк әлеуметтiк тапсырыс шеңберiнде көрсетілетін қызметтерге ақы төлеу | F35: 105 | G35: Оплата услуг в рамках государственного социального заказа
A36: 1 | C36: 156 | D36: Консалтингтік қызметтерге ақы төлеу | F36: 26.532 | G36: Оплата консалтинговых услуг
A37: 1 | C37: 157 | D37: Форумдар, семинарлар, конференциялар өткізуге және имидждік іс-шараларға арналған қызметтерге ақы төлеу | F37: 0.51249981 | G37: Оплата услуг на проведение форумов, семинаров, конференций и на имиджевые мероприятия
A38: 1 | C38: 158 | D38: Ақпараттандыру саласындағы жұмыстар мен қызметтерге ақы төлеу | F38: 2914.4953 | G38: Оплата работ и услуг в сфере информатизации
A39: 1 | C39: 159 | D39: Өзге де қызметтер мен жұмыстарға ақы төлеу | F39: 226087.72 | G39: Оплата прочих услуг и работ
A40: L01 Категория расходов | B40: 160 | D40: Басқа да ағымдағы шығындар | F40: 574291.34 | G40: Другие текущие затраты
A41: 1 | B41: 160 | C41: 161 | D41: Ел iшiндегi iссапарлар мен қызметтiк сапарлар | F41: 4080.5963 | G41: Командировки и служебные разъезды внутри страны
A42: 1 | C42: 162 | D42: Елден тыс жерлерге iссапарлар мен қызметтiк сапарлар | F42: 1789.0856 | G42: Командировки и служебные разъезды за пределы страны
A43: 1 | C43: 164 | D43: Шетелдегi стипендиаттардың оқуына ақы төлеу | F43: 11100 | G43: Оплата обучения стипендиатов за рубежом
A44: 1 | C44: 165 | D44: Атқарушылық құжаттарының, сот актiлерiнiң орындалуы | F44: 354.3661 | G44: Исполнение исполнительных документов, судебных актов
A45: 1 | C45: 166 | D45: Сайлауға және саяси партиялардың қызметіне арналған шығыстар | F45: 4197 | G45: Расходы на выборы и деятельность политических партий
A46: 1 | C46: 167 | D46: Ерекше шығындар | F46: 389372.13 | G46: Особые затраты
A47: 1 | C47: 168 | D47: Айыппұлдар, тұрақсыздық айыбы және басқа төлемдер | F47: 113.52624 | G47: Штрафы, неустойка и другие платежи
A48: 1 | C48: 169 | D48: Өзге де ағымдағы шығындар | F48: 163284.64 | G48: Прочие текущие затраты
A49: L01 Категория расходов | B49: 210 | D49: Ішкі қарыздар бойынша сыйақы төлемдері | F49: 1131044.9 | G49: Выплаты вознаграждений по внутренним займам
A50: 1 | B50: 210 | C50: 211 | D50: Қазақстан Республикасы Үкіметінің ішкі қарыздары бойынша сыйақыларды төлеу | F50: 1131044.9 | G50: Выплаты вознаграждений по внутренним займам Правительства Республики Казахстан
A51: L01 Категория расходов | B51: 220 | D51: Сыртқы заемдар бойынша сыйақылар төлеу | F51: 58665.529 | G51: Выплаты вознаграждений по внешним займам
A52: 1 | B52: 220 | C52: 221 | D52: Қазақстан Республикасы Үкіметінің сыртқы қарыздары бойынша сыйақы төлемдері | F52: 58665.529 | G52: Выплаты вознаграждений по внешним займам Правительства Республики Казахстан
A53: L01 Категория расходов | B53: 310 | D53: Бюджеттік субсидиялар | F53: 35310.839 | G53: Бюджетные субсидии
A54: 1 | B54: 310 | C54: 311 | D54: Мемлекеттік кәсіпорындарға субсидиялар | F54: 5601.4094 | G54: Субсидии государственным предприятиям
A55: 1 | C55: 312 | D55: Мемлекеттік кәсіпорындар болып табылмайтын заңды тұлғаларғасубсидиялар | F55: 29709.43 | G55: Субсидии юридическим лицам, не являющимися государственнымипредприятиями
A56: L01 Категория расходов | B56: 320 | D56: Жеке тұлғаларға берілетін трансферттер | F56: 1789264.7 | G56: Трансферты физическим лицам
A57: 1 | B57: 320 | C57: 321 | D57: Құқық қорғау, арнаулы мемлекеттік органдардың, азаматтық қорғау органдарының қызметкерлеріне және әскери қызметшілерге төленетін тұрғын үй т | F57: 34061.859 | G57: Жилищные выплаты сотрудникам правоохранительных, специальных государственных органов, органов гражданской защиты и военнослужащим
A58: 1 | C58: 322 | D58: Жеке тұлғаларға берiлетiн трансферттер | F58: 455979.28 | G58: Трансферты физическим лицам
A59: 1 | C59: 323 | D59: Зейнетақылар | F59: 1240814.1 | G59: Пенсии
A60: 1 | C60: 324 | D60: Стипендиялар | F60: 58409.431 | G60: Стипендии
A61: L01 Категория расходов | B61: 330 | D61: Мемлекеттiк басқарудың басқа деңгейлерiне берiлетiн ағымдағытрансферттер | F61: 1316380.9 | G61: Текущие трансферты другим уровням государственного управления
A62: 1 | B62: 330 | C62: 331 | D62: Субвенциялар | F62: 1315998.3 | G62: Субвенции
A63: 1 | C63: 339 | D63: Мемлекеттiк басқарудың басқа деңгейлерiне берiлетiн ағымдағы трансферттер | F63: 382.628 | G63: Текущие трансферты другим уровням государственного управления
A64: L01 Категория расходов | B64: 340 | D64: Шетелге берiлетiн ағымдағы трансферттер | F64: 5118.3126 | G64: Текущие трансферты за границу
A65: 1 | B65: 340 | C65: 341 | D65: Шетелдегi ұйымдарға ағымдағы трансферттер | F65: 5118.3126 | G65: Текущие трансферты за границу
A66: L01 Категория расходов | B66: 360 | D66: Нысаналы жарна | F66: 345200 | G66: Целевой взнос
A67: 1 | B67: 360 | C67: 361 | D67: Заңды тұлғаларға берілетін трансферттер | F67: 345200 | G67: Трансферты юридическим лицам
A68: L01 Категория расходов | B68: 370 | F68: 664.5558
A69: 1 | B69: 370 | C69: 371 | D69: Білім беру гранты | F69: 664.5558 | G69: Образовательный грант
A70: 2 | D70: Күрделі шығындар | F70: 84218.423 | G70: Капитальные затраты
A71: L01 Категория расходов | B71: 410 | D71: Негiзгi құралдарды, материалдық емес және биологиялық активтерді сатып алу | F71: 2839.1167 | G71: Приобретение основных средств, нематериальных и биологических активов
A72: 2 | B72: 410 | C72: 414 | D72: Машиналар, жабдықтар, өндірістік және шаруашылық мүккамал құралдарын сатып алу | F72: 40.433514 | G72: Приобретение машин, оборудования, инструментов, производственного и хозяйственного инвентаря
A73: 2 | C73: 418 | D73: Мемлекеттік кәсіпорындарды материалдық-техникалық жарақтандыру | F73: 2798.6832 | G73: Материально-техническое оснащение государственных предприятий
A74: L01 Категория расходов | B74: 420 | D74: Негізгі қаражатты күрделі жөндеу | F74: 835.09354 | G74: Капитальный ремонт основных средств
A75: 2 | B75: 420 | C75: 421 | D75: Жайларды, ғимараттарды, құрылыстарды беру қондырғыларын күрделі жөндеу | F75: 835.09354 | G75: Капитальный ремонт помещений, зданий, сооружений, передаточных устройств
A76: L01 Категория расходов | B76: 430 | D76: Дамуға бағытталған күрделі шығындар | F76: 28306.831 | G76: Капитальные затраты, направленные на развитие
A77: 2 | B77: 430 | C77: 431 | D77: Жаңа объектілерді салу және қолдағы объектілерді реконструкциялау | F77: 27732.353 | G77: Строительство новых объектов и реконструкция имеющихся объектов
A78: 2 | C78: 434 | D78: Ақпараттық жүйелерді құру, енгізу және дамыту | F78: 320.05394 | G78: Создание, внедрение и развитие информационных систем
A79: 2 | C79: 435 | D79: Мемлекеттік кәсіпорындардың жаңа объектілерін салу және қолдағы бар объектілерін реконструкциялау | F79: 254.425 | G79: Строительство новых объектов и реконструкция имеющихся объектов государственных предприятий
A80: L01 Категория расходов | B80: 440 | D80: Дамуға арналған нысаналы трансферттер | F80: 52237.381 | G80: Целевые трансферты на развитие
A81: 2 | B81: 440 | C81: 441 | D81: Мемлекеттік басқарудың басқа деңгейлерін дамытуға арналған нысаналы трансферттер | F81: 52237.381 | G81: Целевые трансферты на развитие другим уровням государственного управления
A82: 3 | D82: Бюджеттік кредиттер | F82: 11000 | G82: Бюджетные кредиты
A83: L01 Категория расходов | B83: 510 | D83: Ішкі бюджеттік кредиттер | F83: 11000 | G83: Внутренние бюджетные кредиты
A84: 3 | B84: 510 | C84: 511 | D84: Бюджеттік инвестициялық жобаларды іске асыруға арналған бюджеттік кредиттерді қоспағанда, жергілікті атқарушы органдарға бюджеттік кредиттер | F84: 11000 | G84: Бюджетные кредиты местным исполнительным органам, за исключением бюджетных кредитов на реализацию бюджетных инвестиционных проектов
A85: 4 | D85: Қаржы активтерін сатып алу | F85: 5124.5272 | G85: Приобретение финансовых активов
A86: L01 Категория расходов | B86: 610 | D86: Қаржы активтерін сатып алу | F86: 5029.13 | G86: Приобретение финансовых активов
A87: 4 | B87: 610 | C87: 612 | D87: Квазимемлекеттік сектордың жарғылық капиталын қалыптастыру және ұлғайту | F87: 5029.13 | G87: Формирование и увеличение уставных капиталов субъектов квазигосударственного сектора
A88: L01 Категория расходов | B88: 620 | D88: Елден тысқары жерлерден қаржы активтерін сатып алу | F88: 95.397215 | G88: Приобретение финансовых активов за пределами страны
A89: 4 | B89: 620 | C89: 621 | D89: Халқаралық ұйымдардың акцияларын сатып алу | F89: 95.397215 | G89: Приобретение акций международных организаций
A90: 6 | D90: Мемлекеттік-жекешелік әріптестік жобалар бойынша мемлекеттік міндеттемелерді орындау | F90: 29842.509 | G90: Выполнение государственных обязательств по проектам государственно-частного партнерства
A91: L01 Категория расходов | B91: 810 | D91: Мемлекеттік концессиялық міндеттемелерді орындау | F91: 29842.509 | G91: Выполнение государственных концессионных обязательств
A92: 6 | B92: 810 | C92: 812 | D92: Мемлекеттік-жекешелік әріптестік жобалар бойынша инвестициялық шығындарды өтеу бойынша мемлекеттік міндеттемелерді орындау | F92: 7796.6605 | G92: Выполнение государственных обязательств по компенсации инвестиционных затрат по проектам государственно-частного партнерства
A93: 6 | C93: 813 | D93: Мемлекеттік-жекешелік әріптестік жобалар бойынша операциялық (пайдалану) шығындарды өтеу бойынша мемлекеттік міндеттемелерді орындау | F93: 414.2305 | G93: Выполнение государственных обязательств по компенсации операционных (эксплуатационных) затрат по проектам государственно-частного п
A94: 6 | C94: 814 | D94: Мемлекеттік-жекешелік әріптестік объектісін басқаруды жүзеге асырғаны үшін сыйақы төлемі бойынша мемлекеттік міндеттемелерді орындау | F94: 21631.618 | G94: Выполнение государственных обязательств по выплате вознаграждений за осуществление управления объектом государственно-частного парт

Sheet таб 11
A1: 11-кесте ШЫҒЫНДАРДЫҢ ЭКОНОМИКАЛЫҚ ЖІКТЕМЕСІ БОЙЫНША ЖЕРГІЛІКТІ БЮДЖЕТТІК ОРЫНДАЛУЫ (млн.теңге) | E1: Таблица 11 ИСПОЛНЕНИЕ МЕСТНОГО БЮДЖЕТА ПО ЭКОНОМИЧЕСКОЙ КЛАССИФИКАЦИИ РАСХОДОВ (млн. тенге)
A3: Cанаты/_x000D_ Категория | B3: Iшкi сыныбы/_x000D_ Подкласс | C3: Ерекшелiгi/_x000D_ Специфика | D3: Атауы | F3: 2026 ж. қаңтар-наурыз/_x000D_ январь-март отчет 2026 г. | G3: Наименование
A4: 1 | B4: 2 | C4: 3 | D4: 4 | F4: 5 | G4: 6
D5: БАРЛЫҒЫ | F5: 3370292.4 | G5: ВСЕГО
A6: 1 | D6: Ағымдағы шығындар | F6: 2759002.4 | G6: Текущие затраты
A7: L01 Категория расходов | B7: 110 | D7: Жалақы | F7: 838304.01 | G7: Заработная плата
A8: 1 | B8: 110 | C8: 111 | D8: Еңбекке ақы төлеу | F8: 763218.64 | G8: Оплата труда
A9: 1 | C9: 112 | D9: Қосымша ақшалай төлемдер | F9: 39280.724 | G9: Дополнительные денежные выплаты
A10: 1 | C10: 113 | D10: Өтемақы төлемдері | F10: 17850.939 | G10: Компенсационные выплаты
A11: 1 | C11: 114 | D11: Міндетті кәсіптік зейнетақы жарналары | F11: 3.4572914 | G11: Обязательные профессиональные пенсионные взносы
A12: 1 | C12: 116 | D12: Жұмыс берушілердің міндетті зейнетақы жарналары | F12: 17950.242 | G12: Обязательные пенсионные взносы работодателей
A13: L01 Категория расходов | B13: 120 | D13: Жұмыс берушілердің жарналары | F13: 94337.523 | G13: Взносы работодателей
A14: 1 | B14: 120 | C14: 121 | D14: Әлеуметтік салық | F14: 40323.582 | G14: Социальный налог
A15: 1 | C15: 122 | D15: Мемлекеттiк әлеуметтiк сақтандыру қорына әлеуметтiк аударымдар | F15: 33519.534 | G15: Социальные отчисления в Государственный фонд социального страхования
A16: 1 | C16: 123 | D16: Мiндеттi сақтандыру жарналары | F16: 259.1736 | G16: Взносы на обязательное страхование
A17: 1 | C17: 124 | D17: Міндетті әлеуметтік медициналық сақтандыруға аударымдар | F17: 20235.233 | G17: Отчисления на обязательное социальное медицинское страхование
A18: L01 Категория расходов | B18: 130 | D18: Қазақстан Республикасының заңнамалық актілеріне сәйкес азаматтардың жекелеген санаттарына жалақы төлеу және жарналар аудару | F18: 27282.434 | G18: Выплата заработной платы отдельным категориям граждан и отчисления взносов в соответствии с законодательными актами Республики Казахстан
A19: 1 | B19: 130 | C19: 131 | D19: Техникалық персоналдың және келісімшарттық қызметшілердің еңбегіне ақы төлеу | F19: 23589.966 | G19: Оплата труда технического персонала и контрактных служащих
A20: 1 | C20: 133 | D20: Негізгі жұмыс орны бойынша мәслихат депутаттарына орташа жалақыны өтеу | F20: 0.04 | G20: Возмещение средней заработной платы депутатам маслихата по их основному месту работы
A21: 1 | C21: 135 | D21: Техникалық персонал және келісімшарттық қызметшілер бойыншажұмыс берушілердің жарналары | F21: 3181.3405 | G21: Взносы работодателей по техническому персоналу и контрактным служащим
A22: 1 | C22: 136 | D22: Техникалық персоналдың және келісімшарттық қызметшілердің ел ішіндегі іссапарлары мен қызметтiк жол жүрулері | F22: 511.08772 | G22: Командировки и служебные разъезды внутри страны технического персонала и контрактных служащих
A23: L01 Категория расходов | B23: 140 | D23: Қорлар сатып алу | F23: 48364.041 | G23: Приобретение запасов
A24: 1 | B24: 140 | C24: 141 | D24: Азық-түлiк өнiмдерiн сатып алу | F24: 8239.3683 | G24: Приобретение продуктов питания
A25: 1 | C25: 142 | D25: Дәрілік заттар және медициналық мақсаттағы өзге де бұйымдарды сатып алу | F25: 15134.493 | G25: Приобретение лекарственных средств и прочих изделий медицинского назначения
A26: 1 | C26: 143 | D26: Заттай мүлiктердi, басқа да киім нысанын және арнаулы киім-кешектер сатып алу, тiгу және жөндеу | F26: 540.57051 | G26: Приобретение, пошив и ремонт предметов вещевого имущества идругого форменного и специального обмундирования
A27: 1 | C27: 144 | D27: Отын, жанар-жағар май материалдарын сатып алу | F27: 13479.119 | G27: Приобретение топлива, горюче-смазочных материалов
A28: 1 | C28: 149 | D28: Өзге де қорларды сатып алу | F28: 10970.491 | G28: Приобретение прочих запасов
A29: L01 Категория расходов | B29: 150 | D29: Қызметтер мен жұмыстарды сатып алу | F29: 682159.81 | G29: Приобретение услуг и работ
A30: 1 | B30: 150 | C30: 151 | D30: Коммуналдық қызметтерге ақы төлеу | F30: 70108.089 | G30: Оплата коммунальных услуг
A31: 1 | C31: 152 | D31: Байланыс қызметтерiне ақы төлеу | F31: 5043.4821 | G31: Оплата услуг связи
A32: 1 | C32: 153 | D32: Көлiктiк қызмет көрсетулерге ақы төлеу | F32: 3332.4956 | G32: Оплата транспортных услуг
A33: 1 | C33: 154 | D33: Зерттеулер бойынша қызметтерге ақы төлеу | F33: 33.764867 | G33: Оплата услуг по исследованиям
A34: 1 | C34: 155 | D34: Мемлекеттiк әлеуметтiк тапсырыс шеңберiнде көрсетілетін қызметтерге ақы төлеу | F34: 8846.8578 | G34: Оплата услуг в рамках государственного социального заказа
A35: 1 | C35: 157 | D35: Форумдар, семинарлар, конференциялар өткізуге және имидждік іс-шараларға арналған қызметтерге ақы төлеу | F35: 343.97413 | G35: Оплата услуг на проведение форумов, семинаров, конференций и на имиджевые мероприятия
A36: 1 | C36: 158 | D36: Ақпараттандыру саласындағы жұмыстар мен қызметтерге ақы төлеу | F36: 6644.2949 | G36: Оплата работ и услуг в сфере информатизации
A37: 1 | C37: 159 | D37: Өзге де қызметтер мен жұмыстарға ақы төлеу | F37: 587806.85 | G37: Оплата прочих услуг и работ
A38: L01 Категория расходов | B38: 160 | D38: Басқа да ағымдағы шығындар | F38: 208788.14 | G38: Другие текущие затраты
A39: 1 | B39: 160 | C39: 161 | D39: Ел iшiндегi iссапарлар мен қызметтiк сапарлар | F39: 7854.1228 | G39: Командировки и служебные разъезды внутри страны
A40: 1 | C40: 162 | D40: Елден тыс жерлерге iссапарлар мен қызметтiк сапарлар | F40: 1290.1065 | G40: Командировки и служебные разъезды за пределы страны
A41: 1 | C41: 163 | D41: Жалпыға бiрдей мiндеттi орта бiлiм қорының шығындары | F41: 21743.444 | G41: Затраты Фонда всеобщего обязательного среднего образования
A42: 1 | C42: 165 | D42: Атқарушылық құжаттарының, сот актiлерiнiң орындалуы | F42: 8877.7527 | G42: Исполнение исполнительных документов, судебных актов
A43: 1 | C43: 166 | D43: Сайлауға және саяси партиялардың қызметіне арналған шығыстар | F43: 51.859755 | G43: Расходы на выборы и деятельность политических партий
A44: 1 | C44: 168 | D44: Айыппұлдар, тұрақсыздық айыбы және басқа төлемдер | F44: 833.62931 | G44: Штрафы, неустойка и другие платежи
A45: 1 | C45: 169 | D45: Өзге де ағымдағы шығындар | F45: 168137.22 | G45: Прочие текущие затраты
A46: L01 Категория расходов | B46: 210 | D46: Ішкі қарыздар бойынша сыйақы төлемдері | F46: 5288.1292 | G46: Выплаты вознаграждений по внутренним займам
A47: 1 | B47: 210 | C47: 212 | D47: Жоғары тұрған бюджеттен жергiлiктi атқарушы органдар алған қарыздар бойынша сыйақы төлемдері | F47: 93.583658 | G47: Выплаты вознаграждений по займам, полученным из вышестоящего бюджета местными исполнительными органами
A48: 1 | C48: 213 | D48: Ішкі қарыздары бойынша сыйақыларды төлеу | F48: 5194.5456 | G48: Выплаты вознаграждений по внутренним займам местных исполнительных органов
A49: L01 Категория расходов | B49: 310 | D49: Бюджеттік субсидиялар | F49: 510033.17 | G49: Бюджетные субсидии
A50: 1 | B50: 310 | C50: 311 | D50: Мемлекеттік кәсіпорындарға субсидиялар | F50: 80237.599 | G50: Субсидии государственным предприятиям
A51: 1 | C51: 312 | D51: Мемлекеттік кәсіпорындар болып табылмайтын заңды тұлғаларғасубсидиялар | F51: 383694.29 | G51: Субсидии юридическим лицам, не являющимися государственнымипредприятиями
A52: 1 | C52: 313 | D52: Жеке тұлғаларға субсидиялар | F52: 46101.282 | G52: Субсидии физическим лицам
A53: L01 Категория расходов | B53: 320 | D53: Жеке тұлғаларға берілетін трансферттер | F53: 91949.108 | G53: Трансферты физическим лицам
A54: 1 | B54: 320 | C54: 321 | D54: Құқық қорғау, арнаулы мемлекеттік органдардың, азаматтық қорғау органдарының қызметкерлеріне және әскери қызметшілерге төленетін тұрғын үй т | F54: 12157.267 | G54: Жилищные выплаты сотрудникам правоохранительных, специальных государственных органов, органов гражданской защиты и военнослужащим
A55: 1 | C55: 322 | D55: Жеке тұлғаларға берiлетiн трансферттер | F55: 58665.523 | G55: Трансферты физическим лицам
A56: 1 | C56: 324 | D56: Стипендиялар | F56: 21126.318 | G56: Стипендии
A57: L01 Категория расходов | B57: 330 | D57: Мемлекеттiк басқарудың басқа деңгейлерiне берiлетiн ағымдағытрансферттер | F57: 227254.53 | G57: Текущие трансферты другим уровням государственного управления
A58: 1 | B58: 330 | C58: 332 | D58: Бюджеттiк алып қоюлар | F58: 222550.67 | G58: Бюджетные изъятия
A59: 1 | C59: 336 | D59: Бюджет заңнамасымен қарастырылған жағдайларда жалпы сипаттағы трансферттерды қайтару | F59: 214.439 | G59: Возврат трансфертов общего характера в случаях, предусмотренных бюджетным законодательством
A60: 1 | C60: 338 | D60: Нысаналы трансферттерді қайтару | F60: 4489.4197 | G60: Возврат целевых трансфертов
A61: L01 Категория расходов | B61: 350 | D61: Өзге де ағымдағы трансферттер | F61: 24167.606 | G61: Прочие текущие трансферты
A62: 1 | B62: 350 | C62: 352 | D62: Қазақстан Республикасының Ұлттық қорынан тартылған қаражаттың бір бөлігін қайтару | F62: 20300.397 | G62: Возврат части средств, привлеченных из Национального фонда Республики Казахстан
A63: 1 | C63: 359 | D63: Өзге де ағымдағы трансферттер | F63: 3867.209 | G63: Прочие текущие трансферты
A64: L01 Категория расходов | B64: 360 | D64: Нысаналы жарна | F64: 1073.9445 | G64: Целевой взнос
A65: 1 | B65: 360 | C65: 361 | D65: Заңды тұлғаларға берілетін трансферттер | F65: 1073.9445 | G65: Трансферты юридическим лицам
A66: 2 | D66: Күрделі шығындар | F66: 513956.95 | G66: Капитальные затраты
A67: L01 Категория расходов | B67: 410 | D67: Негiзгi құралдарды, материалдық емес және биологиялық активтерді сатып алу | F67: 142812.61 | G67: Приобретение основных средств, нематериальных и биологических активов
A68: 2 | B68: 410 | C68: 411 | D68: Жер сатып алу | F68: 31246.85 | G68: Приобретение земли
A69: 2 | C69: 412 | D69: Үй-жайлар, ғимараттар мен құрылыстарды, беру қондырғыларын сатып алу | F69: 85087.766 | G69: Приобретение помещений, зданий, сооружений, передаточных устройств
A70: 2 | C70: 413 | D70: Көлік құралдарын сатып алу | F70: 3305.0692 | G70: Приобретение транспортных средств
A71: 2 | C71: 414 | D71: Машиналар, жабдықтар, өндірістік және шаруашылық мүккамал құралдарын сатып алу | F71: 13713.044 | G71: Приобретение машин, оборудования, инструментов, производственного и хозяйственного инвентаря
A72: 2 | C72: 416 | D72: Материалдық емес активтерді сатып алу | F72: 86.600446 | G72: Приобретение нематериальных активов
A73: 2 | C73: 417 | D73: Биологиялық активтерді сатып алу | F73: 16.032 | G73: Приобретение биологических активов
A74: 2 | C74: 418 | D74: Мемлекеттік кәсіпорындарды материалдық-техникалық жарақтандыру | F74: 7957.0994 | G74: Материально-техническое оснащение государственных предприятий
A75: 2 | C75: 419 | D75: Өзге де негізгі құралдарды сатып алу | F75: 1400.1531 | G75: Приобретение прочих основных средств
A76: L01 Категория расходов | B76: 420 | D76: Негізгі қаражатты күрделі жөндеу | F76: 37001.758 | G76: Капитальный ремонт основных средств
A77: 2 | B77: 420 | C77: 421 | D77: Жайларды, ғимараттарды, құрылыстарды беру қондырғыларын күрделі жөндеу | F77: 17778.464 | G77: Капитальный ремонт помещений, зданий, сооружений, передаточных устройств
A78: 2 | C78: 422 | D78: Жолдарды күрделі жөндеу | F78: 10396.729 | G78: Капитальный ремонт дорог
A79: 2 | C79: 423 | D79: Мемлекеттiк кәсiпорындардың жайларын, ғимараттарын, құрылыстарын күрделі жөндеу | F79: 8225.4226 | G79: Капитальный ремонт помещений, зданий, сооружений государственных предприятий
A80: 2 | C80: 429 | D80: Өзге де негізгі қаражатты күрделі жөндеу | F80: 601.14218 | G80: Капитальный ремонт прочих основных средств
A81: L01 Категория расходов | B81: 430 | D81: Дамуға бағытталған күрделі шығындар | F81: 334142.57 | G81: Капитальные затраты, направленные на развитие
A82: 2 | B82: 430 | C82: 431 | D82: Жаңа объектілерді салу және қолдағы объектілерді реконструкциялау | F82: 282424.73 | G82: Строительство новых объектов и реконструкция имеющихся объектов
A83: 2 | C83: 432 | D83: Жолдар салу | F83: 51717.848 | G83: Строительство дорог
A84: 3 | D84: Бюджеттік кредиттер | F84: 16100 | G84: Бюджетные кредиты
A85: L01 Категория расходов | B85: 510 | D85: Ішкі бюджеттік кредиттер | F85: 16100 | G85: Внутренние бюджетные кредиты
A86: 3 | B86: 510 | C86: 513 | D86: Мамандандырылған ұйымдарға бюджеттік кредиттер | F86: 14100 | G86: Бюджетные кредиты специализированным организациям
A87: 3 | C87: 519 | D87: Өзге де ішкі бюджеттік кредиттер | F87: 2000 | G87: Прочие внутренние бюджетные кредиты
A88: 4 | D88: Қаржы активтерін сатып алу | F88: 54634.375 | G88: Приобретение финансовых активов
A89: L01 Категория расходов | B89: 610 | D89: Қаржы активтерін сатып алу | F89: 54634.375 | G89: Приобретение финансовых активов
A90: 4 | B90: 610 | C90: 612 | D90: Квазимемлекеттік сектордың жарғылық капиталын қалыптастыру және ұлғайту | F90: 54634.375 | G90: Формирование и увеличение уставных капиталов субъектов квазигосударственного сектора
A91: 6 | D91: Мемлекеттік-жекешелік әріптестік жобалар бойынша мемлекеттік міндеттемелерді орындау | F91: 26598.589 | G91: Выполнение государственных обязательств по проектам государственно-частного партнерства
A92: L01 Категория расходов | B92: 810 | D92: Мемлекеттік концессиялық міндеттемелерді орындау | F92: 26598.589 | G92: Выполнение государственных концессионных обязательств
A93: 6 | B93: 810 | C93: 812 | D93: Мемлекеттік-жекешелік әріптестік жобалар бойынша инвестициялық шығындарды өтеу бойынша мемлекеттік міндеттемелерді орындау | F93: 4668.5866 | G93: Выполнение государственных обязательств по компенсации инвестиционных затрат по проектам государственно-частного партнерства
A94: 6 | C94: 813 | D94: Мемлекеттік-жекешелік әріптестік жобалар бойынша операциялық (пайдалану) шығындарды өтеу бойынша мемлекеттік міндеттемелерді орындау | F94: 9992.26 | G94: Выполнение государственных обязательств по компенсации операционных (эксплуатационных) затрат по проектам государственно-частного п
A95: 6 | C95: 814 | D95: Мемлекеттік-жекешелік әріптестік объектісін басқаруды жүзеге асырғаны үшін сыйақы төлемі бойынша мемлекеттік міндеттемелерді орындау | F95: 1728.1262 | G95: Выполнение государственных обязательств по выплате вознаграждений за осуществление управления объектом государственно-частного парт
A96: 6 | C96: 815 | D96: Мемлекеттік-жекешелік әріптестік жобалар бойынша өзге де төлемдер бойынша мемлекеттік міндеттемелерді орындау | F96: 10209.616 | G96: Выполнение государственных обязательств по прочим выплатам по проектам государственно-частного партнерства

Sheet табл 12
A1: 12-кесте | E1: Таблица 12
A2: ЖЕРГІЛІКТІ БЮДЖЕТТЕРДІҢ АТҚАРЫЛУЫ | E2: ИСПОЛНЕНИЕ МЕСТНЫХ БЮДЖЕТОВ
A3: (млн.теңге) | E3: (млн. тенге)
A5: Атауы | B5: 2023 ж. есеп/ 2023 г. отчет | C5: 2024 ж. есеп/ 2024 г. отчет | D5: 2025 ж. есеп/ 2025 г. отчет | F5: 2026 ж. қантар-наурыз есеп/январь-март отчет 2026 г. | G5: Наименование
D6: жылдық/ годовой | E6: қантар-наурыз/январь-март
A7: 1 | B7: 2 | C7: 3 | D7: 4 | E7: 5 | F7: 6 | G7: 7
A8: I. КІРІСТЕР | B8: 13552443 | C8: 15346311 | D8: 17039799 | E8: 3758865.8 | F8: 3658018.8 | G8: I. ДОХОДЫ
A9: Салықтық түсімдер_x000D_ оның iшiнде: | B9: 5999776.2 | C9: 7392707.2 | D9: 8725097.5 | E9: 2068974.3 | F9: 2120580 | G9: Налоговые поступления,_x000D_ в том числе:
A10: корпоративтік табыс салығы | B10: 1156101.6 | C10: 1560100.6 | D10: 1789641.5 | E10: 373078.02 | F10: 303665.29 | G10: корпоративный подоходный налог
A11: жеке табыс салығы | B11: 1992384.9 | C11: 2451640 | D11: 2859192.4 | E11: 697601.66 | F11: 748169.79 | G11: индивидуальный подоходный налог
A12: әлеуметтік салық | B12: 1321272.8 | C12: 1579329.4 | D12: 1866744.5 | E12: 477668.78 | F12: 495812.63 | G12: социальный налог
A13: акциздер | B13: 678325.27 | C13: 719720.32 | D13: 922591.39 | E13: 179365.77 | F13: 242542.73 | G13: акцизы
A14: Салықтық емес түсімдер | B14: 205639.7 | C14: 429128.27 | D14: 425962.39 | E14: 104809.97 | F14: 87864.041 | G14: Неналоговые поступления
A15: Негізгі капиталды сатудан түсетін түсімдер | B15: 181373.04 | C15: 195509.62 | D15: 172470.88 | E15: 42949.555 | F15: 36015.036 | G15: Поступления от продажи основного капитала
A16: Арнаулы түсімдер | B16: 0 | C16: 0 | D16: 0 | E16: 0 | F16: 41074.23 | G16: Специальные поступления
A17: Трансферттердің түсімдері | B17: 7165654.2 | C17: 7329228.8 | D17: 7716267.9 | E17: 1542131.9 | F17: 1372485.5 | G17: Поступления трансфертов
A18: II. ШЫҒЫНДАР | B18: 12885357 | C18: 15049842 | D18: 16743019 | E18: 2975527.6 | F18: 3299558 | G18: II. ЗАТРАТЫ
A19: 1. Жалпы сипаттағы мемлекеттiк қызметтер | B19: 498739.23 | C19: 626197.96 | D19: 629385.65 | E19: 125783.06 | F19: 134061.62 | G19: 1. Государственные услуги общего характера
... A42: VII. БЮДЖЕТТІҢ ТАПШЫЛЫҒЫН ҚАРЖЫЛАНДЫРУ (ПРОФИЦИТТІ ПАЙДАЛАНУ | B42: -119017.05 | C42: 8428.4121 | D42: 406359.47 | E42: -662131.25 | F42: -348192.62 | G42: VII. ФИНАНСИРОВАНИЕ ДЕФИЦИТА (ИСПОЛЬЗОВАНИЕ ПРОФИЦИТА) БЮДЖЕТА
A43: Ішкі | B43: -117136.18 | C43: 9297.3391 | D43: 406359.47 | E43: -662131.25 | F43: =F44-F45 -> -76183.767 | G43: Внутреннее
A44: Түсімдер | B44: 111991.8 | C44: 305965.81 | D44: 643108.9 | E44: -632202.44 | F44: 44270.499 | G44: Поступление
A45: Өтеу | B45: 229127.97 | C45: 296668.47 | D45: 236749.43 | E45: 29928.811 | F45: 120454.27 | G45: Погашение
A46: Сыртқы | B46: -1880.877 | C46: -868.7564 | D46: - | E46: - | F46: - | G46: Внешнее
A47: Түсімдер | B47: - | C47: - | D47: - | E47: - | F47: - | G47: Поступление
A48: Өтеу | B48: 1880.877 | C48: 868.7564 | D48: - | E48: - | F48: - | G48: Погашение

Sheet табл 12.1
A1: 12.1-кесте | E1: Таблица 12.1
A2: АҚМОЛА ОБЛЫСЫ | E2: ИСПОЛНЕНИЕ БЮДЖЕТА
A3: БЮДЖЕТІНІҢ АТҚАРЫЛУЫ | E3: АКМОЛИНСКАЯ ОБЛАСТЬ
A4: (млн.теңге) | E4: (млн. тенге)
A5: Атауы | B5: 2023 ж. есеп/ 2023 г. отчет | C5: 2024 ж. есеп/ 2024 г. отчет | D5: 2025 ж. есеп/ 2025 г. отчет | F5: 2026 ж. қантар-наурыз есеп/январь-март отчет 2026 г. | G5: Наименование
D6: жылдық/ годовой | E6: қантар-наурыз/январь-март
A7: 1 | B7: 2 | C7: 3 | D7: 4 | E7: 5 | F7: 6 | G7: 7
A8: I. КІРІСТЕР | B8: 630074.59 | C8: 707086.76 | D8: 714825.41 | E8: 155237.8 | F8: 165873.73 | G8: I. ДОХОДЫ
A9: Салықтық түсімдер_x000D_ оның iшiнде: | B9: 166838.2 | C9: 193200.14 | D9: 220429.75 | E9: 51484.631 | F9: 59860.349 | G9: Налоговые поступления,_x000D_ в том числе:
A10: корпоративтік табыс салығы | B10: 26898.106 | C10: 29578.991 | D10: 33713.57 | E10: 6332.1002 | F10: 8068.2586 | G10: корпоративный подоходный налог
A11: жеке табыс салығы | B11: 57696.794 | C11: 70347.91 | D11: 81501.176 | E11: 19072.168 | F11: 22246.898 | G11: индивидуальный подоходный налог
A12: әлеуметтік салық | B12: 36673.221 | C12: 43624.91 | D12: 51909.543 | E12: 12380.556 | F12: 13628.907 | G12: социальный налог
A13: акциздер | B13: 18706.909 | C13: 21122.258 | D13: 21806.271 | E13: 4768.8622 | F13: 6062.4668 | G13: акцизы
A14: Салықтық емес түсімдер | B14: 10031.309 | C14: 17228.574 | D14: 21042.885 | E14: 1778.0495 | F14: 2986.3084 | G14: Неналоговые поступления
A15: Негізгі капиталды сатудан түсетін түсімдер | B15: 4230.2271 | C15: 6929.2453 | D15: 12047.529 | E15: 3210.9098 | F15: 1179.5584 | G15: Поступления от продажи основного капитала
A16: Арнаулы түсімдер | B16: 448974.85 | C16: 489728.81 | D16: 461305.25 | E16: 98764.21 | F16: 944.88971 | G16: Специальные поступления
A17: Трансферттердің түсімдері | F17: 100902.63 | G17: Поступления трансфертов
A18: II. ШЫҒЫНДАР | B18: 629557.51 | C18: 718203.43 | D18: 719434.09 | E18: 138302.51 | F18: 155602.46 | G18: II. ЗАТРАТЫ
A19: 1. Жалпы сипаттағы мемлекеттiк қызметтер | B19: 34057.909 | C19: 38754.396 | D19: 38988.923 | E19: 7948.061 | F19: 7741.7885 | G19: 1. Государственные услуги общего характера
A20: 2. Қорғаныс | B20: 7702.9187 | C20: 8416.1057 | D20: 9647.3974 | E20: 2439.7311 | F20: 1992.3438 | G20: 2. Оборона
A21: 3. Қоғамдық тәртіп, қауіпсіздік, құқықтық, сот, қылмыстық-атқару қызметі | B21: 13521.217 | C21: 15030.734 | D21: 18517.408 | E21: 3649.3845 | F21: 3784.7235 | G21: 3. Общественный порядок, безопасность, правовая, судебная, уголовно-исполнительная деятельность
A22: 4. Бiлiм беру | B22: 257095.51 | C22: 289232.92 | D22: 268580.06 | E22: 41627.188 | F22: 43503.643 | G22: 4. Образование
A23: 5. Денсаулық сақтау | B23: 12735.368 | C23: 21949.104 | D23: 14702.57 | E23: 2103.1132 | F23: 457.39604 | G23: 5. Здравоохранение
A24: 6. Әлеуметтiк көмек және әлеуметтiк қамсыздандыру | B24: 21242.731 | C24: 23444.199 | D24: 26035.823 | E24: 4575.9154 | F24: 5044.9002 | G24: 6. Социальная помощь и социальное обеспечение
A25: 7. Тұрғын үй-коммуналдық шаруашылық | B25: 68458.009 | C25: 97123.859 | D25: 88608.939 | E25: 9630.2164 | F25: 8741.7267 | G25: 7. Жилищно-коммунальное хозяйство
A26: 8. Мәдениет, спорт, туризм және ақпараттық кеңістiк | B26: 29880.074 | C26: 33275.452 | D26: 37462.662 | E26: 8067.2172 | F26: 8344.3324 | G26: 8. Культура, спорт, туризм и информационное пространство
A27: 9. Отын-энергетика кешенi және жер қойнауын пайдалану | B27: 16086.269 | C27: 23333.857 | D27: 32249.588 | E27: 7836.0009 | F27: 5051.4435 | G27: 9. Топливно-энергетический комплекс и недропользование
A28: 10. Ауыл, су, орман, балық шаруашылығы, ерекше қорғалатын табиғи аумақтар, қоршаған ортаны және жануарлар дүниесін қорғау, жер қатынастары | B28: 65206.49 | C28: 56705.92 | D28: 81299.501 | E28: 39239.519 | F28: 56872.506 | G28: 10. Сельское, водное, лесное, рыбное хозяйство, особо охраняемые природные территории, охрана окружающей среды и животного мира, земельные отношения
A29: 11. Өнеркәсіп, сәулет, қала құрылысы және құрылыс қызметі | B29: 2126.0672 | C29: 8407.1109 | D29: 2844.0734 | E29: 333.36249 | F29: 1641.8165 | G29: 11. Промышленность, архитектурная, градостроительная и строительная деятельность
... A42: VII. БЮДЖЕТТІҢ ТАПШЫЛЫҒЫН ҚАРЖЫЛАНДЫРУ (ПРОФИЦИТТІ ПАЙДАЛАНУ | B42: 13984.598 | C42: 12519.931 | D42: -8541.767 | E42: -18811.289 | F42: -11336.644 | G42: VII. ФИНАНСИРОВАНИЕ ДЕФИЦИТА (ИСПОЛЬЗОВАНИЕ ПРОФИЦИТА) БЮДЖЕТА
A43: Ішкі | B43: -28337.013 | C43: 15222.376 | D43: 90929.786 | E43: -204637.33 | F43: =F44-F45 -> -2130.6304 | G43: Внутреннее
A44: Түсімдер | B44: -22220.166 | C44: 26195.917 | D44: 103628.81 | E44: -202719.32 | F44: 2000 | G44: Поступление
A45: Өтеу | B45: 6116.8467 | C45: 10973.542 | D45: 12699.028 | E45: 1918.0129 | F45: 4130.6304 | G45: Погашение
A46: Сыртқы | B46: - | C46: - | D46: - | E46: - | F46: - | G46: Внешнее
A47: Түсімдер | B47: - | C47: - | D47: - | E47: - | F47: - | G47: Поступление
A48: Өтеу | B48: - | C48: - | D48: - | E48: - | F48: - | G48: Погашение

Sheet табл 12.2
A1: 12.2-кесте | E1: Таблица 12.2
A2: АҚТОБЕ ОБЛЫСЫ | E2: ИСПОЛНЕНИЕ БЮДЖЕТА
A3: БЮДЖЕТІНІҢ АТҚАРЫЛУЫ | E3: АКТЮБИНСКАЯ ОБЛАСТЬ
A4: (млн.теңге) | E4: (млн. тенге)
A5: Атауы | B5: 2023 ж. есеп/ 2023 г. отчет | C5: 2024 ж. есеп/ 2024 г. отчет | D5: 2025 ж. есеп/ 2025 г. отчет | F5: 2026 ж. қантар-наурыз есеп/январь-март отчет 2026 г. | G5: Наименование
D6: жылдық/ годовой | E6: қантар-наурыз/январь-март
A7: 1 | B7: 2 | C7: 3 | D7: 4 | E7: 5 | F7: 6 | G7: 7
A8: I. КІРІСТЕР | B8: 601085.02 | C8: 676122.67 | D8: 682561.21 | E8: 137715.43 | F8: 128365.2 | G8: I. ДОХОДЫ
A9: Салықтық түсімдер_x000D_ оның iшiнде: | B9: 217147.69 | C9: 258870.07 | D9: 286094.5 | E9: 71248.797 | F9: 73491.157 | G9: Налоговые поступления,_x000D_ в том числе:
A10: корпоративтік табыс салығы | B10: 27092.378 | C10: 35280.087 | D10: 44934.434 | E10: 7838.6602 | F10: 8826.1027 | G10: корпоративный подоходный налог
A11: жеке табыс салығы | B11: 71801.508 | C11: 89575.631 | D11: 99420.477 | E11: 26327.059 | F11: 26140.931 | G11: индивидуальный подоходный налог
A12: әлеуметтік салық | B12: 50661.538 | C12: 60866.559 | D12: 65271.952 | E12: 17543.745 | F12: 19334.733 | G12: социальный налог
A13: акциздер | B13: 12786.271 | C13: 18850.711 | D13: 17633.532 | E13: 3897.4209 | F13: 4691.3417 | G13: акцизы
A14: Салықтық емес түсімдер | B14: 11013.336 | C14: 22063.261 | D14: 21654.327 | E14: 2244.844 | F14: 4188.0312 | G14: Неналоговые поступления
A15: Негізгі капиталды сатудан түсетін түсімдер | B15: 5032.1948 | C15: 6404.1867 | D15: 3527.6792 | E15: 798.28645 | F15: 716.62695 | G15: Поступления от продажи основного капитала
A16: Арнаулы түсімдер | B16: 367891.79 | C16: 388785.15 | D16: 371284.7 | E16: 63423.506 | F16: 3922.4797 | G16: Специальные поступления
A17: Трансферттердің түсімдері | F17: 46046.909 | G17: Поступления трансфертов
A18: II. ШЫҒЫНДАР | B18: 572439.64 | C18: 692559.6 | D18: 726133.96 | E18: 113698.26 | F18: 120366.18 | G18: II. ЗАТРАТЫ
A19: 1. Жалпы сипаттағы мемлекеттiк қызметтер | B19: 38185.996 | C19: 53420.173 | D19: 40421.998 | E19: 8537.1171 | F19: 6577.0496 | G19: 1. Государственные услуги общего характера
A20: 2. Қорғаныс | B20: 3456.9188 | C20: 6083.1211 | D20: 8858.0714 | E20: 805.60031 | F20: 402.53219 | G20: 2. Оборона
A21: 3. Қоғамдық тәртіп, қауіпсіздік, құқықтық, сот, қылмыстық-атқару қызметі | B21: 18072.721 | C21: 18451.926 | D21: 21273.096 | E21: 2745.0888 | F21: 3075.3561 | G21: 3. Общественный порядок, безопасность, правовая, судебная, уголовно-исполнительная деятельность
A22: 4. Бiлiм беру | B22: 247605.08 | C22: 279794.18 | D22: 307216.75 | E22: 59820.669 | F22: 67697.942 | G22: 4. Образование
A23: 5. Денсаулық сақтау | B23: 11352.279 | C23: 14447.43 | D23: 18697.984 | E23: 2857.6675 | F23: 457.12828 | G23: 5. Здравоохранение
A24: 6. Әлеуметтiк көмек және әлеуметтiк қамсыздандыру | B24: 28282.71 | C24: 33494.219 | D24: 35138.302 | E24: 5167.7167 | F24: 4973.0041 | G24: 6. Социальная помощь и социальное обеспечение
A25: 7. Тұрғын үй-коммуналдық шаруашылық | B25: 64363.641 | C25: 79866.245 | D25: 85149.41 | E25: 5505.2272 | F25: 6612.6063 | G25: 7. Жилищно-коммунальное хозяйство
A26: 8. Мәдениет, спорт, туризм және ақпараттық кеңістiк | B26: 30321.585 | C26: 40176.654 | D26: 52984.947 | E26: 9202.1742 | F26: 7643.5882 | G26: 8. Культура, спорт, туризм и информационное пространство
A27: 9. Отын-энергетика кешенi және жер қойнауын пайдалану | B27: 30909.63 | C27: 36334.677 | D27: 9919.8863 | E27: 1044.1082 | F27: 588.26878 | G27: 9. Топливно-энергетический комплекс и недропользование
A28: 10. Ауыл, су, орман, балық шаруашылығы, ерекше қорғалатын табиғи аумақтар, қоршаған ортаны және жануарлар дүниесін қорғау, жер қатынастары | B28: 27698.114 | C28: 26039.748 | D28: 28515.204 | E28: 6424.5411 | F28: 6239.05 | G28: 10. Сельское, водное, лесное, рыбное хозяйство, особо охраняемые природные территории, охрана окружающей среды и животного мира, земельные отношения
A29: 11. Өнеркәсіп, сәулет, қала құрылысы және құрылыс қызметі | B29: 1273.0942 | C29: 9362.7536 | D29: 4387.7314 | E29: 319.47439 | F29: 304.54235 | G29: 11. Промышленность, архитектурная, градостроительная и строительная деятельность
... A38: Қаржылық активтерді сатып алу | B38: 102 | C38: 194.7798 | D38: 892.082 | E38: 114.475 | F38: 138.5245 | G38: Приобретение финансовых активов
A39: Мемлекеттің қаржы активтерін сатудан түсетін түсімдер | F39: 364.352 | G39: Поступления от продажи финансовых активов государства
A40: V. БЮДЖЕТ ТАПШЫЛЫҒЫ (ПРОФИЦИТІ) | B40: 11136.075 | C40: -17543.714 | D40: -48235.745 | E40: 26506.926 | F40: 13249.358 | G40: V. ДЕФИЦИТ (ПРОФИЦИТ) БЮДЖЕТА
A42: VII. БЮДЖЕТТІҢ ТАПШЫЛЫҒЫН ҚАРЖЫЛАНДЫРУ (ПРОФИЦИТТІ ПАЙДАЛАНУ | B42: -11136.075 | C42: 17543.714 | D42: -48235.745 | E42: -26506.926 | F42: -13249.358 | G42: VII. ФИНАНСИРОВАНИЕ ДЕФИЦИТА (ИСПОЛЬЗОВАНИЕ ПРОФИЦИТА) БЮДЖЕТА
A43: Ішкі | B43: -312074.58 | C43: -6027.6511 | D43: 548137.26 | E43: -229450.59 | F43: =F44-F45 -> -6619.014 | G43: Внутреннее
A44: Түсімдер | B44: -301203.36 | C44: 7654.2188 | D44: 558874.71 | E44: -221393.09 | G44: Поступление
A45: Өтеу | B45: 10871.218 | C45: 13681.87 | D45: 10737.449 | E45: 8057.5017 | F45: 6619.014 | G45: Погашение
A46: Сыртқы | B46: - | C46: - | D46: - | E46: - | F46: - | G46: Внешнее
A47: Түсімдер | B47: - | C47: - | D47: - | E47: - | F47: - | G47: Поступление
A48: Өтеу | B48: - | C48: - | D48: - | E48: - | F48: - | G48: Погашение

Sheet табл 12.3
A1: 12.3-кесте | E1: Таблица 12.3
A2: АЛМАТЫ ОБЛЫСЫ | E2: ИСПОЛНЕНИЕ БЮДЖЕТА
A3: БЮДЖЕТІНІҢ АТҚАРЫЛУЫ | E3: АЛМАТИНСКАЯ ОБЛАСТЬ
A4: (млн.теңге) | E4: (млн. тенге)
A5: Атауы | B5: 2023 ж. есеп/ 2023 г. отчет | C5: 2024 ж. есеп/ 2024 г. отчет | D5: 2025 ж. есеп/ 2025 г. отчет | F5: 2026 ж. қантар-наурыз есеп/январь-март отчет 2026 г. | G5: Наименование
D6: жылдық/ годовой | E6: қантар-наурыз/январь-март
A7: 1 | B7: 2 | C7: 3 | D7: 4 | E7: 5 | F7: 6 | G7: 7
A8: I. КІРІСТЕР | B8: 755699.04 | C8: 832469.88 | D8: 945126.85 | E8: 190379.22 | F8: 205148.04 | G8: I. ДОХОДЫ
A9: Салықтық түсімдер_x000D_ оның iшiнде: | B9: 388446.56 | C9: 491276.75 | D9: 596132.41 | E9: 129148.44 | F9: 158620.88 | G9: Налоговые поступления,_x000D_ в том числе:
A10: корпоративтік табыс салығы | B10: 34158.596 | C10: 57113.634 | D10: 71617.514 | E10: 14176.737 | F10: 10339.724 | G10: корпоративный подоходный налог
A11: жеке табыс салығы | B11: 85030.922 | C11: 118580.99 | D11: 120514.16 | E11: 29056.305 | F11: 32353.3 | G11: индивидуальный подоходный налог
A12: әлеуметтік салық | B12: 40395.425 | C12: 54091.398 | D12: 65531.412 | E12: 16903.071 | F12: 18953.832 | G12: социальный налог
A13: акциздер | B13: 199121.45 | C13: 226071.95 | D13: 296091.65 | E13: 54972.73 | F13: 77803.675 | G13: акцизы
A14: Салықтық емес түсімдер | B14: 5738.8874 | C14: 20653.374 | D14: 21231.435 | E14: 3355.0606 | F14: 6115.5639 | G14: Неналоговые поступления
A15: Негізгі капиталды сатудан түсетін түсімдер | B15: 6153.3465 | C15: 8607.4865 | D15: 11238.27 | E15: 2064.2922 | F15: 2975.5133 | G15: Поступления от продажи основного капитала
A16: Арнаулы түсімдер | B16: 355360.25 | C16: 311933.66 | D16: 316524.73 | E16: 55811.435 | F16: 497.15055 | G16: Специальные поступления
A17: Трансферттердің түсімдері | F17: 36938.94 | G17: Поступления трансфертов
A18: II. ШЫҒЫНДАР | B18: 752774.03 | C18: 838922.5 | D18: 958728.51 | E18: 162177.04 | F18: 181221.28 | G18: II. ЗАТРАТЫ
A19: 1. Жалпы сипаттағы мемлекеттiк қызметтер | B19: 26808.017 | C19: 24546.153 | D19: 29034.055 | E19: 6704.9874 | F19: 6182.6219 | G19: 1. Государственные услуги общего характера
A20: 2. Қорғаныс | B20: 2158.7445 | C20: 4038.0936 | D20: 6713.984 | E20: 1124.9098 | F20: 463.77269 | G20: 2. Оборона
A21: 3. Қоғамдық тәртіп, қауіпсіздік, құқықтық, сот, қылмыстық-атқару қызметі | B21: 15326.75 | C21: 17983.839 | D21: 21496.804 | E21: 3150.7744 | F21: 3781.0411 | G21: 3. Общественный порядок, безопасность, правовая, судебная, уголовно-исполнительная деятельность
A22: 4. Бiлiм беру | B22: 390464.79 | C22: 445824.99 | D22: 492945.79 | E22: 91151.678 | F22: 95868.352 | G22: 4. Образование
A23: 5. Денсаулық сақтау | B23: 15553.898 | C23: 29840.06 | D23: 29281.659 | E23: 2222.1797 | F23: 3566.4013 | G23: 5. Здравоохранение
A24: 6. Әлеуметтiк көмек және әлеуметтiк қамсыздандыру | B24: 31531.425 | C24: 32476.342 | D24: 35734.735 | E24: 5349.5872 | F24: 5930.5871 | G24: 6. Социальная помощь и социальное обеспечение
A25: 7. Тұрғын үй-коммуналдық шаруашылық | B25: 84198.428 | C25: 96906.473 | D25: 116898.14 | E25: 9985.7788 | F25: 10528.52 | G25: 7. Жилищно-коммунальное хозяйство
A26: 8. Мәдениет, спорт, туризм және ақпараттық кеңістiк | B26: 27725.789 | C26: 31535.968 | D26: 38179.837 | E26: 8200.4159 | F26: 7845.924 | G26: 8. Культура, спорт, туризм и информационное пространство
A27: 9. Отын-энергетика кешенi және жер қойнауын пайдалану | B27: 8321.7765 | C27: 19540.303 | D27: 22249.333 | E27: 3309.3444 | F27: 2111.7161 | G27: 9. Топливно-энергетический комплекс и недропользование
A28: 10. Ауыл, су, орман, балық шаруашылығы, ерекше қорғалатын табиғи аумақтар, қоршаған ортаны және жануарлар дүниесін қорғау, жер қатынастары | B28: 61103.794 | C28: 49937.026 | D28: 61316.819 | E28: 19558.055 | F28: 27218.442 | G28: 10. Сельское, водное, лесное, рыбное хозяйство, особо охраняемые природные территории, охрана окружающей среды и животного мира, земельные отношения
A29: 11. Өнеркәсіп, сәулет, қала құрылысы және құрылыс қызметі | B29: 5558.4523 | C29: 7829.6847 | D29: 5453.7873 | E29: 973.67409 | F29: 487.05439 | G29: 11. Промышленность, архитектурная, градостроительная и строительная деятельность
... A38: Қаржылық активтерді сатып алу | B38: 7439.182 | C38: 8291.7479 | D38: 6648.0107 | E38: 2550 | F38: 2438.914 | G38: Приобретение финансовых активов
A39: Мемлекеттің қаржы активтерін сатудан түсетін түсімдер | B39: 5.1049999 | D39: 4.946728 | E39: 0.9883215 | G39: Поступления от продажи финансовых активов государства
A40: V. БЮДЖЕТ ТАПШЫЛЫҒЫ (ПРОФИЦИТІ) | B40: -32271.614 | C40: -19347.425 | D40: -27968.214 | E40: 26541.355 | F40: 25393.95 | G40: V. ДЕФИЦИТ (ПРОФИЦИТ) БЮДЖЕТА
A42: VII. БЮДЖЕТТІҢ ТАПШЫЛЫҒЫН ҚАРЖЫЛАНДЫРУ (ПРОФИЦИТТІ ПАЙДАЛАНУ | B42: 32271.614 | C42: 19347.425 | D42: -27968.214 | E42: -26541.355 | F42: -25393.95 | G42: VII. ФИНАНСИРОВАНИЕ ДЕФИЦИТА (ИСПОЛЬЗОВАНИЕ ПРОФИЦИТА) БЮДЖЕТА
A43: Ішкі | B43: 76147.561 | C43: 3774.7945 | D43: 101339.24 | E43: -304172.04 | F43: =F44-F45 -> -3380.7091 | G43: Внутреннее
A44: Түсімдер | B44: 80801.049 | C44: 15303.941 | D44: 111919.04 | E44: -302869.84 | G44: Поступление
A45: Өтеу | B45: 4653.4875 | C45: 11529.146 | D45: 10579.794 | E45: 1302.2014 | F45: 3380.7091 | G45: Погашение
A46: Сыртқы | B46: - | C46: - | D46: - | E46: - | F46: - | G46: Внешнее
A47: Түсімдер | B47: - | C47: - | D47: - | E47: - | F47: - | G47: Поступление
A48: Өтеу | B48: - | C48: - | D48: - | E48: - | F48: - | G48: Погашение

Sheet табл 12.4
A1: 12.4-кесте | E1: Таблица 12.4
A2: АТЫРАУ ОБЛЫСЫ | E2: ИСПОЛНЕНИЕ БЮДЖЕТА
A3: БЮДЖЕТІНІҢ АТҚАРЫЛУЫ | E3: АТЫРАУСКАЯ ОБЛАСТЬ
A4: (млн.теңге) | E4: (млн. тенге)
A5: Атауы | B5: 2023 ж. есеп/ 2023 г. отчет | C5: 2024 ж. есеп/ 2024 г. отчет | D5: 2025 ж. есеп/ 2025 г. отчет | F5: 2026 ж. қантар-наурыз есеп/январь-март отчет 2026 г. | G5: Наименование
D6: жылдық/ годовой | E6: қантар-наурыз/январь-март
A7: 1 | B7: 2 | C7: 3 | D7: 4 | E7: 5 | F7: 6 | G7: 7
A8: I. КІРІСТЕР | B8: 733369.76 | C8: 898777.25 | D8: 970437.13 | E8: 232450.11 | F8: 210715.03 | G8: I. ДОХОДЫ
A9: Салықтық түсімдер_x000D_ оның iшiнде: | B9: 643622.37 | C9: 783514.64 | D9: 891220.75 | E9: 220683.69 | F9: 199449.28 | G9: Налоговые поступления,_x000D_ в том числе:
A10: корпоративтік табыс салығы | B10: 74074.302 | C10: 60322.062 | D10: 62684.029 | E10: 15165.327 | F10: 18999.143 | G10: корпоративный подоходный налог
A11: жеке табыс салығы | B11: 176724.85 | C11: 170721.06 | D11: 159908.09 | E11: 43809.363 | F11: 39314.1 | G11: индивидуальный подоходный налог
A12: әлеуметтік салық | B12: 161262.4 | C12: 161395.59 | D12: 159621.05 | E12: 45115.068 | F12: 40416.551 | G12: социальный налог
A13: акциздер | B13: 120507.84 | C13: 122879.83 | D13: 161080.09 | E13: 34362.786 | F13: 47973.766 | G13: акцизы
A14: Салықтық емес түсімдер | B14: 16168.04 | C14: 32940.563 | D14: 17182.158 | E14: 3075.8527 | F14: 2802.387 | G14: Неналоговые поступления
A15: Негізгі капиталды сатудан түсетін түсімдер | B15: 2333.9873 | C15: 2568.7507 | D15: 2234.6395 | E15: 460.09294 | F15: 474.26516 | G15: Поступления от продажи основного капитала
A16: Арнаулы түсімдер | B16: 71245.364 | C16: 79753.298 | D16: 59799.576 | E16: 8230.482 | F16: 4426.077 | G16: Специальные поступления
A17: Трансферттердің түсімдері | F17: 3563.019 | G17: Поступления трансфертов
A18: II. ШЫҒЫНДАР | B18: 670273.07 | C18: 939255.77 | D18: 947576.92 | E18: 170010.79 | F18: 200621.61 | G18: II. ЗАТРАТЫ
A19: 1. Жалпы сипаттағы мемлекеттiк қызметтер | B19: 18263.609 | C19: 30985.339 | D19: 27972.617 | E19: 5786.5187 | F19: 5544.1423 | G19: 1. Государственные услуги общего характера
A20: 2. Қорғаныс | B20: 3723.3195 | C20: 60454.116 | D20: 43985.302 | E20: 6018.9362 | F20: 289.8064 | G20: 2. Оборона
A21: 3. Қоғамдық тәртіп, қауіпсіздік, құқықтық, сот, қылмыстық-атқару қызметі | B21: 18080.541 | C21: 20679.759 | D21: 23688.209 | E21: 2787.0706 | F21: 3213.3022 | G21: 3. Общественный порядок, безопасность, правовая, судебная, уголовно-исполнительная деятельность
A22: 4. Бiлiм беру | B22: 191891.18 | C22: 240443.04 | D22: 245617.11 | E22: 46336.67 | F22: 58458.532 | G22: 4. Образование
A23: 5. Денсаулық сақтау | B23: 16686.402 | C23: 21006.188 | D23: 22788.913 | E23: 1449.3807 | F23: 8390.6431 | G23: 5. Здравоохранение
A24: 6. Әлеуметтiк көмек және әлеуметтiк қамсыздандыру | B24: 21880.676 | C24: 29713.444 | D24: 33127.179 | E24: 4827.4733 | F24: 4790.4436 | G24: 6. Социальная помощь и социальное обеспечение
A25: 7. Тұрғын үй-коммуналдық шаруашылық | B25: 88240.861 | C25: 163385.74 | D25: 130802.75 | E25: 17829.404 | F25: 30708.635 | G25: 7. Жилищно-коммунальное хозяйство
A26: 8. Мәдениет, спорт, туризм және ақпараттық кеңістiк | B26: 31738.022 | C26: 41275.754 | D26: 58428.444 | E26: 9922.8419 | F26: 18245.673 | G26: 8. Культура, спорт, туризм и информационное пространство
A27: 9. Отын-энергетика кешенi және жер қойнауын пайдалану | B27: 5554.204 | C27: 14919.195 | D27: 15625.634 | E27: 2458.1 | F27: 481.21046 | G27: 9. Топливно-энергетический комплекс и недропользование
A28: 10. Ауыл, су, орман, балық шаруашылығы, ерекше қорғалатын табиғи аумақтар, қоршаған ортаны және жануарлар дүниесін қорғау, жер қатынастары | B28: 15107.141 | C28: 13733.335 | D28: 17572.713 | E28: 2101.8044 | F28: 2521.3326 | G28: 10. Сельское, водное, лесное, рыбное хозяйство, особо охраняемые природные территории, охрана окружающей среды и животного мира, земельные отношения
A29: 11. Өнеркәсіп, сәулет, қала құрылысы және құрылыс қызметі | B29: 1469.3605 | C29: 6668.0098 | D29: 3322.4514 | E29: 240.11153 | F29: 327.67726 | G29: 11. Промышленность, архитектурная, градостроительная и строительная деятельность
... A37: IV. ҚАРЖЫ АКТИВТЕРІМЕН ОПЕРАЦИЯЛАР БОЙЫНША САЛЬДО - ҚАРЖЫ АК | B37: 9896.5255 | C37: 8503.6076 | D37: 11944.051 | E37: 11993.629 | F37: -10.701877 | G37: IV. САЛЬДО ПО ОПЕРАЦИЯМ С ФИНАНСОВЫМИ АКТИВАМИ
A38: Қаржылық активтерді сатып алу | B38: 9953.961 | C38: 8545.6732 | D38: 12000 | E38: 12000 | G38: Приобретение финансовых активов
A39: Мемлекеттің қаржы активтерін сатудан түсетін түсімдер | B39: 57.435537 | C39: 42.065678 | D39: 55.948946 | E39: 6.371214 | F39: 10.701877 | G39: Поступления от продажи финансовых активов государства
A40: V. БЮДЖЕТ ТАПШЫЛЫҒЫ (ПРОФИЦИТІ) | B40: 46715.894 | C40: -57025.507 | D40: 6764.4027 | E40: 50098.114 | F40: 9351.4083 | G40: V. ДЕФИЦИТ (ПРОФИЦИТ) БЮДЖЕТА
A42: VII. БЮДЖЕТТІҢ ТАПШЫЛЫҒЫН ҚАРЖЫЛАНДЫРУ (ПРОФИЦИТТІ ПАЙДАЛАНУ | B42: -46715.894 | C42: 57025.507 | D42: 6764.4027 | E42: -50098.114 | F42: -9351.4083 | G42: VII. ФИНАНСИРОВАНИЕ ДЕФИЦИТА (ИСПОЛЬЗОВАНИЕ ПРОФИЦИТА) БЮДЖЕТА
A43: Ішкі | B43: -471715.14 | C43: 643064.31 | D43: -86366.095 | E43: -593630.87 | F43: =F44-F45 -> -1754.5172 | G43: Внутреннее
A44: Түсімдер | B44: -461025.59 | C44: 652859.24 | D44: -84037.412 | E44: -592944.82 | G44: Поступление
A45: Өтеу | B45: 10689.549 | C45: 9794.9234 | D45: 2328.6832 | E45: 686.04564 | F45: 1754.5172 | G45: Погашение
A46: Сыртқы | B46: - | C46: - | D46: - | E46: - | F46: - | G46: Внешнее
A47: Түсімдер | B47: - | C47: - | D47: - | E47: - | F47: - | G47: Поступление
A48: Өтеу | B48: - | C48: - | D48: - | E48: - | F48: - | G48: Погашение

Sheet табл 12.5
A1: 12.5-кесте | E1: Таблица 12.5
A2: ШЫҒЫС-ҚАЗАҚСТАН ОБЛЫСЫ | E2: ИСПОЛНЕНИЕ БЮДЖЕТА
A3: БЮДЖЕТІНІҢ АТҚАРЫЛУЫ | E3: ВОСТ-КАЗАХСТАНСКАЯ ОБЛАСТЬ
A4: (млн.теңге) | E4: (млн. тенге)
A5: Атауы | B5: 2023 ж. есеп/ 2023 г. отчет | C5: 2024 ж. есеп/ 2024 г. отчет | D5: 2025 ж. есеп/ 2025 г. отчет | F5: 2026 ж. қантар-наурыз есеп/январь-март отчет 2026 г. | G5: Наименование
D6: жылдық/ годовой | E6: қантар-наурыз/январь-март
A7: 1 | B7: 2 | C7: 3 | D7: 4 | E7: 5 | F7: 6 | G7: 7
A8: I. КІРІСТЕР | B8: 485874.5 | C8: 554729.11 | D8: 583888.09 | E8: 120713.61 | F8: 124584.74 | G8: I. ДОХОДЫ
A9: Салықтық түсімдер_x000D_ оның iшiнде: | B9: 164390.14 | C9: 205394.71 | D9: 237485.49 | E9: 58001.898 | F9: 57023.287 | G9: Налоговые поступления,_x000D_ в том числе:
A10: корпоративтік табыс салығы | B10: 31322.068 | C10: 43204.659 | D10: 59220.777 | E10: 13085.055 | F10: 11346.418 | G10: корпоративный подоходный налог
A11: жеке табыс салығы | B11: 63550.133 | C11: 79837.166 | D11: 88780.744 | E11: 21345.845 | F11: 22071.589 | G11: индивидуальный подоходный налог
A12: әлеуметтік салық | B12: 44809.692 | C12: 53880.619 | D12: 60465.79 | E12: 14640.779 | F12: 14696.479 | G12: социальный налог
A13: акциздер | B13: 170.14397 | C13: 180.05535 | D13: 197.25448 | E13: 43.087933 | F13: 59.496183 | G13: акцизы
A14: Салықтық емес түсімдер | B14: 5257.0033 | C14: 6223.1357 | D14: 6456.1827 | E14: 1279.8589 | F14: 1783.5761 | G14: Неналоговые поступления
A15: Негізгі капиталды сатудан түсетін түсімдер | B15: 6863.7925 | C15: 6662.0791 | D15: 5734.8132 | E15: 805.96891 | F15: 1905.5996 | G15: Поступления от продажи основного капитала
A16: Арнаулы түсімдер | B16: 309363.57 | C16: 336555.96 | D16: 334211.6 | E16: 60625.883 | F16: 756.3744 | G16: Специальные поступления
A17: Трансферттердің түсімдері | F17: 63115.899 | G17: Поступления трансфертов
A18: II. ШЫҒЫНДАР | B18: 474312.87 | C18: 547229.27 | D18: 614799.29 | E18: 104584.02 | F18: 127634.29 | G18: II. ЗАТРАТЫ
A19: 1. Жалпы сипаттағы мемлекеттiк қызметтер | B19: 28901.504 | C19: 34187.037 | D19: 28134.426 | E19: 6381.4867 | F19: 7119.3497 | G19: 1. Государственные услуги общего характера
A20: 2. Қорғаныс | B20: 2283.3219 | C20: 4437.5789 | D20: 5502.1421 | E20: 524.18902 | F20: 342.60878 | G20: 2. Оборона
A21: 3. Қоғамдық тәртіп, қауіпсіздік, құқықтық, сот, қылмыстық-атқару қызметі | B21: 12140.89 | C21: 14150.564 | D21: 17587.635 | E21: 3069.4839 | F21: 5004.9351 | G21: 3. Общественный порядок, безопасность, правовая, судебная, уголовно-исполнительная деятельность
A22: 4. Бiлiм беру | B22: 169324.94 | C22: 203640.01 | D22: 218674.33 | E22: 48163.36 | F22: 47992.858 | G22: 4. Образование
A23: 5. Денсаулық сақтау | B23: 24622.294 | C23: 23710.417 | D23: 38696.644 | E23: 2030.9929 | F23: 4092.3873 | G23: 5. Здравоохранение
A24: 6. Әлеуметтiк көмек және әлеуметтiк қамсыздандыру | B24: 26641.538 | C24: 31304.504 | D24: 34309.708 | E24: 5982.1283 | F24: 6341.8688 | G24: 6. Социальная помощь и социальное обеспечение
A25: 7. Тұрғын үй-коммуналдық шаруашылық | B25: 78618.878 | C25: 86947.53 | D25: 112199.73 | E25: 7344.8806 | F25: 10118.666 | G25: 7. Жилищно-коммунальное хозяйство
A26: 8. Мәдениет, спорт, туризм және ақпараттық кеңістiк | B26: 21535.178 | C26: 28722.796 | D26: 37471.012 | E26: 6935.5435 | F26: 9391.6722 | G26: 8. Культура, спорт, туризм и информационное пространство
A27: 9. Отын-энергетика кешенi және жер қойнауын пайдалану | B27: 2178.6665 | C27: 8929.5848 | D27: 7130.5427 | E27: 291.787 | F27: 889.97848 | G27: 9. Топливно-энергетический комплекс и недропользование
A28: 10. Ауыл, су, орман, балық шаруашылығы, ерекше қорғалатын табиғи аумақтар, қоршаған ортаны және жануарлар дүниесін қорғау, жер қатынастары | B28: 41408.764 | C28: 36131.232 | D28: 41027.198 | E28: 8945.6975 | F28: 23651.504 | G28: 10. Сельское, водное, лесное, рыбное хозяйство, особо охраняемые природные территории, охрана окружающей среды и животного мира, земельные отношения
A29: 11. Өнеркәсіп, сәулет, қала құрылысы және құрылыс қызметі | B29: 3339.9956 | C29: 10848.038 | D29: 5332.4821 | E29: 311.64202 | F29: 300.88915 | G29: 11. Промышленность, архитектурная, градостроительная и строительная деятельность
... A42: VII. БЮДЖЕТТІҢ ТАПШЫЛЫҒЫН ҚАРЖЫЛАНДЫРУ (ПРОФИЦИТТІ ПАЙДАЛАНУ | B42: 6543.5716 | C42: 5586.7251 | D42: -38170.05 | E42: -16095.27 | F42: -574.04336 | G42: VII. ФИНАНСИРОВАНИЕ ДЕФИЦИТА (ИСПОЛЬЗОВАНИЕ ПРОФИЦИТА) БЮДЖЕТА
A43: Ішкі | B43: -63401.59 | C43: 77150.073 | D43: -61438.33 | E43: -172025.46 | F43: =F44-F45 -> -3838.7485 | G43: Внутреннее
A44: Түсімдер | B44: -54752.567 | C44: 95076.792 | D44: -50940.789 | E44: -170105.66 | G44: Поступление
A45: Өтеу | B45: 8649.0233 | C45: 17926.718 | D45: 10497.541 | E45: 1919.7986 | F45: 3838.7485 | G45: Погашение
A46: Сыртқы | B46: - | C46: - | D46: - | E46: - | F46: - | G46: Внешнее
A47: Түсімдер | B47: - | C47: - | D47: - | E47: - | F47: - | G47: Поступление
A48: Өтеу | B48: - | C48: - | D48: - | E48: - | F48: - | G48: Погашение

Sheet табл 12.6
A1: 12.6-кесте | E1: Таблица 12.6
A2: ЖАМБЫЛ ОБЛЫСЫ | E2: ИСПОЛНЕНИЕ БЮДЖЕТА
A3: БЮДЖЕТІНІҢ АТҚАРЫЛУЫ | E3: ЖАМБЫЛСКАЯ ОБЛАСТЬ
A4: (млн.теңге) | E4: (млн. тенге)
A5: Атауы | B5: 2023 ж. есеп/ 2023 г. отчет | C5: 2024 ж. есеп/ 2024 г. отчет | D5: 2025 ж. есеп/ 2025 г. отчет | F5: 2026 ж. қантар-наурыз есеп/январь-март отчет 2026 г. | G5: Наименование
D6: жылдық/ годовой | E6: қантар-наурыз/январь-март
A7: 1 | B7: 2 | C7: 3 | D7: 4 | E7: 5 | F7: 6 | G7: 7
A8: I. КІРІСТЕР | B8: 647650.25 | C8: 701413.92 | D8: 774130.45 | E8: 160599.53 | F8: 187946.44 | G8: I. ДОХОДЫ
A9: Салықтық түсімдер_x000D_ оның iшiнде: | B9: 128310.79 | C9: 152453.16 | D9: 179633.21 | E9: 44322.08 | F9: 49123.998 | G9: Налоговые поступления,_x000D_ в том числе:
A10: корпоративтік табыс салығы | B10: 11965.332 | C10: 17174.038 | D10: 20124.099 | E10: 4309.96 | F10: 4462.1509 | G10: корпоративный подоходный налог
A11: жеке табыс салығы | B11: 46482.26 | C11: 59716.78 | D11: 67942.278 | E11: 16523.068 | F11: 18507.543 | G11: индивидуальный подоходный налог
A12: әлеуметтік салық | B12: 33811.337 | C12: 39604.881 | D12: 45604.252 | E12: 11160.091 | F12: 12842.328 | G12: социальный налог
A13: акциздер | B13: 3309.4974 | C13: 3204.864 | D13: 3532.1678 | E13: 617.99216 | F13: 675.40209 | G13: акцизы
A14: Салықтық емес түсімдер | B14: 11502.799 | C14: 15521.033 | D14: 16164.352 | E14: 2444.2466 | F14: 4156.7246 | G14: Неналоговые поступления
A15: Негізгі капиталды сатудан түсетін түсімдер | B15: 10922.824 | C15: 11602.388 | D15: 19365.236 | E15: 4020.702 | F15: 1633.726 | G15: Поступления от продажи основного капитала
A16: Арнаулы түсімдер | B16: 496913.84 | C16: 521837.33 | D16: 558967.65 | E16: 109812.5 | F16: 2631.2904 | G16: Специальные поступления
A17: Трансферттердің түсімдері | F17: 130400.71 | G17: Поступления трансфертов
A18: II. ШЫҒЫНДАР | B18: 630861.77 | C18: 727944.33 | D18: 795668.79 | E18: 152041.44 | F18: 173302.73 | G18: II. ЗАТРАТЫ
A19: 1. Жалпы сипаттағы мемлекеттiк қызметтер | B19: 27013.526 | C19: 28305.006 | D19: 30902.468 | E19: 6850.6555 | F19: 6867.0585 | G19: 1. Государственные услуги общего характера
A20: 2. Қорғаныс | B20: 1863.5947 | C20: 2279.1128 | D20: 4238.3684 | E20: 761.77319 | F20: 323.23699 | G20: 2. Оборона
A21: 3. Қоғамдық тәртіп, қауіпсіздік, құқықтық, сот, қылмыстық-атқару қызметі | B21: 20235.733 | C21: 19922.677 | D21: 21526.855 | E21: 3225.0569 | F21: 3991.0502 | G21: 3. Общественный порядок, безопасность, правовая, судебная, уголовно-исполнительная деятельность
A22: 4. Бiлiм беру | B22: 307399.56 | C22: 343519.77 | D22: 385576.97 | E22: 80111.168 | F22: 95425.554 | G22: 4. Образование
A23: 5. Денсаулық сақтау | B23: 14327.337 | C23: 16331.731 | D23: 19193.858 | E23: 2287.4525 | F23: 2074.1183 | G23: 5. Здравоохранение
A24: 6. Әлеуметтiк көмек және әлеуметтiк қамсыздандыру | B24: 38262.425 | C24: 42022.833 | D24: 45689.938 | E24: 7086.7314 | F24: 6635.7387 | G24: 6. Социальная помощь и социальное обеспечение
A25: 7. Тұрғын үй-коммуналдық шаруашылық | B25: 73878.705 | C25: 116436.95 | D25: 109473.97 | E25: 9667.916 | F25: 12474.092 | G25: 7. Жилищно-коммунальное хозяйство
A26: 8. Мәдениет, спорт, туризм және ақпараттық кеңістiк | B26: 27012.307 | C26: 32318.7 | D26: 37644.364 | E26: 8128.3594 | F26: 9043.0593 | G26: 8. Культура, спорт, туризм и информационное пространство
A27: 9. Отын-энергетика кешенi және жер қойнауын пайдалану | B27: 11856.845 | C27: 14915.715 | D27: 20190.835 | E27: 652.97994 | F27: - | G27: 9. Топливно-энергетический комплекс и недропользование
A28: 10. Ауыл, су, орман, балық шаруашылығы, ерекше қорғалатын табиғи аумақтар, қоршаған ортаны және жануарлар дүниесін қорғау, жер қатынастары | B28: 53394.155 | C28: 48194.806 | D28: 54924.542 | E28: 25492.736 | F28: 26363.781 | G28: 10. Сельское, водное, лесное, рыбное хозяйство, особо охраняемые природные территории, охрана окружающей среды и животного мира, земельные отношения
A29: 11. Өнеркәсіп, сәулет, қала құрылысы және құрылыс қызметі | B29: 4737.6124 | C29: 5353.262 | D29: 7480.8554 | E29: 495.83385 | F29: 362.37415 | G29: 11. Промышленность, архитектурная, градостроительная и строительная деятельность
A30: 12. Көлiк және коммуникация | B30: 23210.084 | C30: 26396.561 | D30: 32851.128 | E30: 3502.0134 | F30: 7255.876 | G30: 12. Транспорт и коммуникации
A31: 13. Басқалар | B31: 21808.831 | C31: 25036.381 | D31: 20197.44 | E31: 1544.3292 | F31: 2023.9265 | G31: 13. Прочие
A32: 14. Борышқа қызмет көрсету | B32: 3680.9677 | C32: 3079.5035 | D32: 3018.462 | E32: 112.60259 | F32: 112.40599 | G32: 14. Обслуживание долга
A33: 15. Трансферттер | B33: 2180.0815 | C33: 3831.3136 | D33: 2758.7401 | E33: 2121.8319 | F33: 350.45521 | G33: 15. Трансферты
A34: III. ТАЗА БЮДЖЕТТІК КРЕДИТ БЕРУ | B34: 26011.438 | C34: 12584.089 | D34: 8279.2726 | E34: -568.01643 | F34: -2350.4475 | G34: III. ЧИСТОЕ БЮДЖЕТНОЕ КРЕДИТОВАНИЕ
A35: Бюджеттік кредиттер | B35: 30229.179 | C35: 19814.045 | D35: 16777.653 | E35: 0 | F35: 0 | G35: Бюджетные кредиты
A36: Бюджеттік кредиттерді өтеу | B36: 4217.7406 | C36: 7229.9555 | D36: 8498.3804 | E36: 568.01643 | F36: 2350.4475 | G36: Погашение бюджетных кредитов
A37: IV. ҚАРЖЫ АКТИВТЕРІМЕН ОПЕРАЦИЯЛАР БОЙЫНША САЛЬДО - ҚАРЖЫ АК | B37: 1147.061 | C37: 1540.7038 | D37: 510.63108 | E37: 292.63108 | F37: -10.805 | G37: IV. САЛЬДО ПО ОПЕРАЦИЯМ С ФИНАНСОВЫМИ АКТИВАМИ
A38: Қаржылық активтерді сатып алу | B38: 1147.061 | C38: 1540.7038 | D38: 510.63108 | E38: 292.63108 | G38: Приобретение финансовых активов
A39: Мемлекеттің қаржы активтерін сатудан түсетін түсімдер | F39: 10.805 | G39: Поступления от продажи финансовых активов государства
A40: V. БЮДЖЕТ ТАПШЫЛЫҒЫ (ПРОФИЦИТІ) | B40: -10370.017 | C40: -40655.204 | D40: -30328.246 | E40: 8833.4744 | F40: 17004.97 | G40: V. ДЕФИЦИТ (ПРОФИЦИТ) БЮДЖЕТА
A42: VII. БЮДЖЕТТІҢ ТАПШЫЛЫҒЫН ҚАРЖЫЛАНДЫРУ (ПРОФИЦИТТІ ПАЙДАЛАНУ | B42: 10370.017 | C42: 40655.204 | D42: -30328.246 | E42: -8833.4744 | F42: -17004.97 | G42: VII. ФИНАНСИРОВАНИЕ ДЕФИЦИТА (ИСПОЛЬЗОВАНИЕ ПРОФИЦИТА) БЮДЖЕТА
A43: Ішкі | B43: -97791.222 | C43: 241677.71 | D43: 33289.077 | E43: -88386.35 | F43: =F44-F45 -> -7110.9975 | G43: Внутреннее
A44: Түсімдер | B44: -78965.845 | C44: 269955.92 | D44: 54443.794 | E44: -86784.956 | G44: Поступление
A45: Өтеу | B45: 18825.377 | C45: 28278.215 | D45: 21154.717 | E45: 1601.3948 | F45: 7110.9975 | G45: Погашение
A46: Сыртқы | B46: - | C46: - | D46: - | E46: - | G46: Внешнее
A47: Түсімдер | B47: - | C47: - | D47: - | E47: - | G47: Поступление
A48: Өтеу | B48: - | C48: - | D48: - | E48: - | F48: - | G48: Погашение

Sheet табл 12.7
A1: 12.7-кесте | E1: Таблица 12.7
A2: БАТЫС ҚАЗАҚСТАН ОБЛЫСЫ | E2: ИСПОЛНЕНИЕ БЮДЖЕТА
A3: БЮДЖЕТІНІҢ АТҚАРЫЛУЫ | E3: ЗАП-КАЗАХСТАНСКАЯ ОБЛАСТЬ
A4: (млн.теңге) | E4: (млн. тенге)
A5: Атауы | B5: 2023 ж. есеп/ 2023 г. отчет | C5: 2024 ж. есеп/ 2024 г. отчет | D5: 2025 ж. есеп/ 2025 г. отчет | F5: 2026 ж. қантар-наурыз есеп/январь-март отчет 2026 г. | G5: Наименование
D6: жылдық/ годовой | E6: қантар-наурыз/январь-март
A7: 1 | B7: 2 | C7: 3 | D7: 4 | E7: 5 | F7: 6 | G7: 7
A8: I. КІРІСТЕР | B8: 453047.34 | C8: 532073.16 | D8: 569567.64 | E8: 117434.01 | F8: 105036.43 | G8: I. ДОХОДЫ
A9: Салықтық түсімдер_x000D_ оның iшiнде: | B9: 176101.88 | C9: 197849.71 | D9: 217938.68 | E9: 59026.301 | F9: 53506.705 | G9: Налоговые поступления,_x000D_ в том числе:
A10: корпоративтік табыс салығы | B10: 23819.677 | C10: 29745.342 | D10: 30969.328 | E10: 7969.4566 | F10: 4885.4772 | G10: корпоративный подоходный налог
A11: жеке табыс салығы | B11: 60446.744 | C11: 71402.108 | D11: 77767.64 | E11: 20159.428 | F11: 19077.756 | G11: индивидуальный подоходный налог
A12: әлеуметтік салық | B12: 65791.879 | C12: 73256 | D12: 77061.318 | E12: 22692.986 | F12: 21271.129 | G12: социальный налог
A13: акциздер | B13: 4116.8709 | C13: 2316.8132 | D13: 3742.845 | E13: 254.12229 | F13: 1209.3928 | G13: акцизы
A14: Салықтық емес түсімдер | B14: 5184.1237 | C14: 6731.9796 | D14: 9633.2014 | E14: 2439.6006 | F14: 1919.5827 | G14: Неналоговые поступления
A15: Негізгі капиталды сатудан түсетін түсімдер | B15: 8859.4531 | C15: 6142.5363 | D15: 12106.013 | E15: 3987.2901 | F15: 1044.71 | G15: Поступления от продажи основного капитала
A16: Арнаулы түсімдер | B16: 262901.88 | C16: 321348.93 | D16: 329889.74 | E16: 51980.82 | F16: 3365.7099 | G16: Специальные поступления
A17: Трансферттердің түсімдері | F17: 45199.724 | G17: Поступления трансфертов
A18: II. ШЫҒЫНДАР | B18: 445141.74 | C18: 559071.76 | D18: 578762.29 | E18: 97288.926 | F18: 95930.536 | G18: II. ЗАТРАТЫ
A19: 1. Жалпы сипаттағы мемлекеттiк қызметтер | B19: 23456.157 | C19: 42350.09 | D19: 36137.943 | E19: 7099.4128 | F19: 6111.6776 | G19: 1. Государственные услуги общего характера
A20: 2. Қорғаныс | B20: 2958.5653 | C20: 3981.6445 | D20: 4000.7543 | E20: 159.61685 | F20: 250.99604 | G20: 2. Оборона
A21: 3. Қоғамдық тәртіп, қауіпсіздік, құқықтық, сот, қылмыстық-атқару қызметі | B21: 15034.757 | C21: 16128.322 | D21: 16154.304 | E21: 2694.5064 | F21: 2678.2719 | G21: 3. Общественный порядок, безопасность, правовая, судебная, уголовно-исполнительная деятельность
A22: 4. Бiлiм беру | B22: 193496.85 | C22: 214041.68 | D22: 233050.27 | E22: 47693.849 | F22: 50001.448 | G22: 4. Образование
A23: 5. Денсаулық сақтау | B23: 16125.634 | C23: 15150.619 | D23: 15486.675 | E23: 2231.5895 | F23: 1369.7387 | G23: 5. Здравоохранение
A24: 6. Әлеуметтiк көмек және әлеуметтiк қамсыздандыру | B24: 24814.384 | C24: 31524.106 | D24: 26426.837 | E24: 4610.0797 | F24: 5009.99 | G24: 6. Социальная помощь и социальное обеспечение
A25: 7. Тұрғын үй-коммуналдық шаруашылық | B25: 46077.505 | C25: 72479.626 | D25: 68904.023 | E25: 3273.7718 | F25: 7031.8516 | G25: 7. Жилищно-коммунальное хозяйство
A26: 8. Мәдениет, спорт, туризм және ақпараттық кеңістiк | B26: 24486.839 | C26: 28783.009 | D26: 38037.312 | E26: 6993.4559 | F26: 7134.5627 | G26: 8. Культура, спорт, туризм и информационное пространство
A27: 9. Отын-энергетика кешенi және жер қойнауын пайдалану | B27: 3881.0404 | C27: 5724.5984 | D27: 4111.237 | E27: 878.141 | F27: - | G27: 9. Топливно-энергетический комплекс и недропользование
A28: 10. Ауыл, су, орман, балық шаруашылығы, ерекше қорғалатын табиғи аумақтар, қоршаған ортаны және жануарлар дүниесін қорғау, жер қатынастары | B28: 28162.505 | C28: 44859.705 | D28: 50717.513 | E28: 9015.0228 | F28: 5250.7339 | G28: 10. Сельское, водное, лесное, рыбное хозяйство, особо охраняемые природные территории, охрана окружающей среды и животного мира, земельные отношения
A29: 11. Өнеркәсіп, сәулет, қала құрылысы және құрылыс қызметі | B29: 1894.329 | C29: 8254.598 | D29: 1458.1904 | E29: 257.54459 | F29: 274.94581 | G29: 11. Промышленность, архитектурная, градостроительная и строительная деятельность
A30: 12. Көлiк және коммуникация | B30: 41557.621 | C30: 53384.791 | D30: 63174.251 | E30: 10047.029 | F30: 6089.8558 | G30: 12. Транспорт и коммуникации
A31: 13. Басқалар | B31: 12712.503 | C31: 18318.993 | D31: 18714.186 | E31: 1980.1113 | F31: 2789.8832 | G31: 13. Прочие
A32: 14. Борышқа қызмет көрсету | B32: 1789.2801 | C32: 1763.5418 | D32: 1955.2655 | E32: 101.35489 | F32: 106.09906 | G32: 14. Обслуживание долга
A33: 15. Трансферттер | B33: 8693.7776 | C33: 2326.4282 | D33: 433.53012 | E33: 253.44142 | F33: 1830.4824 | G33: 15. Трансферты
A34: III. ТАЗА БЮДЖЕТТІК КРЕДИТ БЕРУ | B34: 13489.729 | C34: 8075.4857 | D34: 18988.328 | E34: -1607.9019 | F34: -5149.8605 | G34: III. ЧИСТОЕ БЮДЖЕТНОЕ КРЕДИТОВАНИЕ
A35: Бюджеттік кредиттер | B35: 16625.844 | C35: 13886.675 | D35: 25765.359 | E35: 0 | F35: 0 | G35: Бюджетные кредиты
A36: Бюджеттік кредиттерді өтеу | B36: 3136.1149 | C36: 5811.1896 | D36: 6777.0312 | E36: 1607.9019 | F36: 5149.8605 | G36: Погашение бюджетных кредитов
A37: IV. ҚАРЖЫ АКТИВТЕРІМЕН ОПЕРАЦИЯЛАР БОЙЫНША САЛЬДО - ҚАРЖЫ АК | B37: 12.583 | C37: 2001.398 | D37: 40.07288 | G37: IV. САЛЬДО ПО ОПЕРАЦИЯМ С ФИНАНСОВЫМИ АКТИВАМИ
A38: Қаржылық активтерді сатып алу | B38: 12.583 | C38: 2001.398 | D38: 40.07288 | G38: Приобретение финансовых активов
A39: V. БЮДЖЕТ ТАПШЫЛЫҒЫ (ПРОФИЦИТІ) | B39: -5596.7209 | C39: -37075.479 | D39: -28223.054 | E39: 21752.988 | F39: 14255.756 | G39: V. ДЕФИЦИТ (ПРОФИЦИТ) БЮДЖЕТА
A41: VII. БЮДЖЕТТІҢ ТАПШЫЛЫҒЫН ҚАРЖЫЛАНДЫРУ (ПРОФИЦИТТІ ПАЙДАЛАНУ | B41: 5596.7209 | C41: 37075.479 | D41: -28223.054 | E41: -21752.988 | F41: -14255.756 | G41: VII. ФИНАНСИРОВАНИЕ ДЕФИЦИТА (ИСПОЛЬЗОВАНИЕ ПРОФИЦИТА) БЮДЖЕТА
A42: Ішкі | B42: -126662.63 | C42: 232779.58 | D42: 31971.36 | E42: -246132.27 | F42: =F43-F44 -> 9454.5906 | G42: Внутреннее
A43: Түсімдер | B43: -119750.59 | C43: 242914.29 | D43: 44629.223 | E43: -244777.39 | F43: 13925.693 | G43: Поступление
A44: Өтеу | B44: 6912.0418 | C44: 10134.71 | D44: 12657.863 | E44: 1354.8714 | F44: 4471.1024 | G44: Погашение
A45: Сыртқы | B45: - | C45: - | D45: - | E45: - | F45: - | G45: Внешнее
A46: Түсімдер | B46: - | C46: - | D46: - | E46: - | F46: - | G46: Поступление
A47: Өтеу | B47: - | C47: - | D47: - | E47: - | F47: - | G47: Погашение

Sheet табл 12.8
A1: 12.8-кесте | E1: Таблица 12.8
A2: ҚАРАҒАНДЫ ОБЛЫСЫ | E2: ИСПОЛНЕНИЕ БЮДЖЕТА
A3: БЮДЖЕТІНІҢ АТҚАРЫЛУЫ | E3: КАРАГАНДИНСКАЯ ОБЛАСТЬ
A4: (млн.теңге) | E4: (млн. тенге)
A5: Атауы | B5: 2023 ж. есеп/ 2023 г. отчет | C5: 2024 ж. есеп/ 2024 г. отчет | D5: 2025 ж. есеп/ 2025 г. отчет | F5: 2026 ж. қантар-наурыз есеп/январь-март отчет 2026 г. | G5: Наименование
D6: жылдық/ годовой | E6: қантар-наурыз/январь-март
A7: 1 | B7: 2 | C7: 3 | D7: 4 | E7: 5 | F7: 6 | G7: 7
A8: I. КІРІСТЕР | B8: 686571.15 | C8: 782542.05 | D8: 831509.34 | E8: 190948.05 | F8: 181625.66 | G8: I. ДОХОДЫ
A9: Салықтық түсімдер_x000D_ оның iшiнде: | B9: 279296.66 | C9: 347457.48 | D9: 410446.96 | E9: 105312.81 | F9: 98759.761 | G9: Налоговые поступления,_x000D_ в том числе:
A10: корпоративтік табыс салығы | B10: 50643.141 | C10: 65372.599 | D10: 74607.447 | E10: 15870.929 | F10: 12351.101 | G10: корпоративный подоходный налог
A11: жеке табыс салығы | B11: 100657.78 | C11: 130633.83 | D11: 153920.22 | E11: 40569.975 | F11: 40671.046 | G11: индивидуальный подоходный налог
A12: әлеуметтік салық | B12: 70479.115 | C12: 85429.921 | D12: 103173.56 | E12: 28110.456 | F12: 27808.981 | G12: социальный налог
A13: акциздер | B13: 8092.5258 | C13: 7686.1147 | D13: 8381.385 | E13: 1602.8571 | F13: 1780.4528 | G13: акцизы
A14: Салықтық емес түсімдер | B14: 11211.452 | C14: 27590.047 | D14: 13643.166 | E14: 2623.0424 | F14: 4391.0177 | G14: Неналоговые поступления
A15: Негізгі капиталды сатудан түсетін түсімдер | B15: 3103.0047 | C15: 4608.7489 | D15: 6493.648 | E15: 1301.1234 | F15: 2354.0039 | G15: Поступления от продажи основного капитала
A16: Арнаулы түсімдер | B16: 392960.03 | C16: 402885.77 | D16: 400925.57 | E16: 81711.076 | F16: 7693.0139 | G16: Специальные поступления
A17: Трансферттердің түсімдері | F17: 68427.861 | G17: Поступления трансфертов
A18: II. ШЫҒЫНДАР | B18: 673296.69 | C18: 795649.24 | D18: 841950.34 | E18: 133472.24 | F18: 146887.61 | G18: II. ЗАТРАТЫ
A19: 1. Жалпы сипаттағы мемлекеттiк қызметтер | B19: 28618.703 | C19: 34271.162 | D19: 38635.359 | E19: 8406.9917 | F19: 7915.8158 | G19: 1. Государственные услуги общего характера
A20: 2. Қорғаныс | B20: 2604.8186 | C20: 3295.2285 | D20: 4374.0501 | E20: 418.8868 | F20: 280.07407 | G20: 2. Оборона
A21: 3. Қоғамдық тәртіп, қауіпсіздік, құқықтық, сот, қылмыстық-атқару қызметі | B21: 24020.08 | C21: 25951.122 | D21: 31930.597 | E21: 5883.8226 | F21: 7055.2249 | G21: 3. Общественный порядок, безопасность, правовая, судебная, уголовно-исполнительная деятельность
A22: 4. Бiлiм беру | B22: 249193.9 | C22: 283785.4 | D22: 299368.23 | E22: 48346.479 | F22: 52436.003 | G22: 4. Образование
A23: 5. Денсаулық сақтау | B23: 21247.252 | C23: 22937.215 | D23: 24608.447 | E23: 3333.1349 | F23: 1948.826 | G23: 5. Здравоохранение
A24: 6. Әлеуметтiк көмек және әлеуметтiк қамсыздандыру | B24: 36613.314 | C24: 45895.86 | D24: 53656.787 | E24: 9364.0603 | F24: 9162.0995 | G24: 6. Социальная помощь и социальное обеспечение
A25: 7. Тұрғын үй-коммуналдық шаруашылық | B25: 100549.55 | C25: 136779.83 | D25: 134173.05 | E25: 16509.839 | F25: 14768.709 | G25: 7. Жилищно-коммунальное хозяйство
A26: 8. Мәдениет, спорт, туризм және ақпараттық кеңістiк | B26: 48493.916 | C26: 56361.162 | D26: 65497.019 | E26: 13361.929 | F26: 14314.725 | G26: 8. Культура, спорт, туризм и информационное пространство
A27: 9. Отын-энергетика кешенi және жер қойнауын пайдалану | B27: 11692.767 | C27: 14879.071 | D27: 21584.263 | E27: 3341.5457 | F27: 2765.7296 | G27: 9. Топливно-энергетический комплекс и недропользование
A28: 10. Ауыл, су, орман, балық шаруашылығы, ерекше қорғалатын табиғи аумақтар, қоршаған ортаны және жануарлар дүниесін қорғау, жер қатынастары | B28: 34851.562 | C28: 36319.911 | D28: 41764.84 | E28: 7248.8973 | F28: 14239.398 | G28: 10. Сельское, водное, лесное, рыбное хозяйство, особо охраняемые природные территории, охрана окружающей среды и животного мира, земельные отношения
A29: 11. Өнеркәсіп, сәулет, қала құрылысы және құрылыс қызметі | B29: 2333.2124 | C29: 5501.2256 | D29: 4606.9835 | E29: 669.41029 | F29: 638.17844 | G29: 11. Промышленность, архитектурная, градостроительная и строительная деятельность
... A38: Қаржылық активтерді сатып алу | B38: 6551.8835 | C38: 1358.875 | D38: 3150.579 | E38: 65.5 | F38: 2337.7766 | G38: Приобретение финансовых активов
A39: Мемлекеттің қаржы активтерін сатудан түсетін түсімдер | B39: 15.432563 | C39: 59.587433 | D39: 57.317661 | E39: 1.979661 | G39: Поступления от продажи финансовых активов государства
A40: V. БЮДЖЕТ ТАПШЫЛЫҒЫ (ПРОФИЦИТІ) | B40: 328.55379 | C40: -21951.289 | D40: -31316.885 | E40: 59401.163 | F40: 37689.745 | G40: V. ДЕФИЦИТ (ПРОФИЦИТ) БЮДЖЕТА
A42: VII. БЮДЖЕТТІҢ ТАПШЫЛЫҒЫН ҚАРЖЫЛАНДЫРУ (ПРОФИЦИТТІ ПАЙДАЛАНУ | B42: -328.55379 | C42: 21951.289 | D42: -31316.885 | E42: -59401.163 | F42: -37689.745 | G42: VII. ФИНАНСИРОВАНИЕ ДЕФИЦИТА (ИСПОЛЬЗОВАНИЕ ПРОФИЦИТА) БЮДЖЕТА
A43: Ішкі | B43: -68685.243 | C43: 35067.054 | D43: -22536.849 | E43: -692339.12 | F43: =F44-F45 -> -28.420171 | G43: Внутреннее
A44: Түсімдер | B44: -63641.709 | C44: 43180.261 | D44: -13191.592 | E44: -690477.77 | F44: 5588.249 | G44: Поступление
A45: Өтеу | B45: 5043.5343 | C45: 8113.2071 | D45: 9345.2562 | E45: 1861.3483 | F45: 5616.6692 | G45: Погашение
A46: Сыртқы | B46: - | C46: - | D46: - | E46: - | F46: - | G46: Внешнее
A47: Түсімдер | B47: - | C47: - | D47: - | E47: - | F47: - | G47: Поступление
A48: Өтеу | B48: - | C48: - | D48: - | E48: - | F48: - | G48: Погашение

Sheet табл 12.9
A1: 12.9-кесте | E1: Таблица 12.9
A2: ҚЫЗЫЛОРДА ОБЛЫСЫ | E2: ИСПОЛНЕНИЕ БЮДЖЕТА
A3: БЮДЖЕТІНІҢ АТҚАРЫЛУЫ | E3: КЫЗЫЛОРДИНСКАЯ ОБЛАСТЬ
A4: (млн.теңге) | E4: (млн. тенге)
A5: Атауы | B5: 2023 ж. есеп/ 2023 г. отчет | C5: 2024 ж. есеп/ 2024 г. отчет | D5: 2025 ж. есеп/ 2025 г. отчет | F5: 2026 ж. қантар-наурыз есеп/январь-март отчет 2026 г. | G5: Наименование
D6: жылдық/ годовой | E6: қантар-наурыз/январь-март
A7: 1 | B7: 2 | C7: 3 | D7: 4 | E7: 5 | F7: 6 | G7: 7
A8: I. КІРІСТЕР | B8: 597172.6 | C8: 688375.1 | D8: 743911.02 | E8: 158433.13 | F8: 170680.77 | G8: I. ДОХОДЫ
A9: Салықтық түсімдер_x000D_ оның iшiнде: | B9: 89965.953 | C9: 113891.83 | D9: 133090.37 | E9: 33990.407 | F9: 33269.896 | G9: Налоговые поступления,_x000D_ в том числе:
A10: корпоративтік табыс салығы | B10: 8720.5044 | C10: 16592.943 | D10: 18574.854 | E10: 4510.5607 | F10: 2972.0956 | G10: корпоративный подоходный налог
A11: жеке табыс салығы | B11: 34223.426 | C11: 44987.131 | D11: 52280.763 | E11: 13196.297 | F11: 12586.352 | G11: индивидуальный подоходный налог
A12: әлеуметтік салық | B12: 25039.27 | C12: 30129.397 | D12: 35347.871 | E12: 8999.5997 | F12: 9245.8521 | G12: социальный налог
A13: акциздер | B13: 139.68694 | C13: 116.04345 | D13: 120.13726 | E13: 28.856317 | F13: 28.581168 | G13: акцизы
A14: Салықтық емес түсімдер | B14: 10570.979 | C14: 33610.595 | D14: 24690.941 | E14: 4977.3105 | F14: 2583.4658 | G14: Неналоговые поступления
A15: Негізгі капиталды сатудан түсетін түсімдер | B15: 9002.805 | C15: 10672.773 | D15: 12165.299 | E15: 2502.9426 | F15: 1085.2385 | G15: Поступления от продажи основного капитала
A16: Арнаулы түсімдер | B16: 487632.86 | C16: 530199.9 | D16: 573964.41 | E16: 116962.47 | F16: 364.03378 | G16: Специальные поступления
A17: Трансферттердің түсімдері | F17: 133378.14 | G17: Поступления трансфертов
A18: II. ШЫҒЫНДАР | B18: 569744.49 | C18: 707644.21 | D18: 772137.56 | E18: 131962.18 | F18: 143295.81 | G18: II. ЗАТРАТЫ
A19: 1. Жалпы сипаттағы мемлекеттiк қызметтер | B19: 21548.543 | C19: 25338.796 | D19: 28778.262 | E19: 7222.7608 | F19: 6668.4128 | G19: 1. Государственные услуги общего характера
A20: 2. Қорғаныс | B20: 1831.1092 | C20: 2739.7235 | D20: 2488.6342 | E20: 93.366984 | F20: 164.8546 | G20: 2. Оборона
A21: 3. Қоғамдық тәртіп, қауіпсіздік, құқықтық, сот, қылмыстық-атқару қызметі | B21: 13249.461 | C21: 14963.116 | D21: 20191.141 | E21: 3046.7373 | F21: 4422.346 | G21: 3. Общественный порядок, безопасность, правовая, судебная, уголовно-исполнительная деятельность
A22: 4. Бiлiм беру | B22: 273065.83 | C22: 306256.85 | D22: 324207.37 | E22: 71655.552 | F22: 69092.765 | G22: 4. Образование
A23: 5. Денсаулық сақтау | B23: 20533.648 | C23: 19260.927 | D23: 35591.12 | E23: 1935.072 | F23: 5270.3574 | G23: 5. Здравоохранение
A24: 6. Әлеуметтiк көмек және әлеуметтiк қамсыздандыру | B24: 40226.702 | C24: 45622.76 | D24: 45946.07 | E24: 7018.2932 | F24: 7130.7998 | G24: 6. Социальная помощь и социальное обеспечение
A25: 7. Тұрғын үй-коммуналдық шаруашылық | B25: 73234.737 | C25: 105918.35 | D25: 132176.24 | E25: 10421.745 | F25: 14471.32 | G25: 7. Жилищно-коммунальное хозяйство
A26: 8. Мәдениет, спорт, туризм және ақпараттық кеңістiк | B26: 33001.149 | C26: 46524.956 | D26: 53665.811 | E26: 10798.545 | F26: 9762.393 | G26: 8. Культура, спорт, туризм и информационное пространство
A27: 9. Отын-энергетика кешенi және жер қойнауын пайдалану | B27: 9078.9065 | C27: 35768.358 | D27: 22411.62 | E27: 1261.4217 | F27: 1596.4273 | G27: 9. Топливно-энергетический комплекс и недропользование
A28: 10. Ауыл, су, орман, балық шаруашылығы, ерекше қорғалатын табиғи аумақтар, қоршаған ортаны және жануарлар дүниесін қорғау, жер қатынастары | B28: 26384.756 | C28: 31865.069 | D28: 26503.625 | E28: 5470.338 | F28: 11187.382 | G28: 10. Сельское, водное, лесное, рыбное хозяйство, особо охраняемые природные территории, охрана окружающей среды и животного мира, земельные отношения
A29: 11. Өнеркәсіп, сәулет, қала құрылысы және құрылыс қызметі | B29: 1571.466 | C29: 6653.5481 | D29: 2081.2359 | E29: 320.34 | F29: 418.92228 | G29: 11. Промышленность, архитектурная, градостроительная и строительная деятельность
... A42: VII. БЮДЖЕТТІҢ ТАПШЫЛЫҒЫН ҚАРЖЫЛАНДЫРУ (ПРОФИЦИТТІ ПАЙДАЛАНУ | B42: -8840.5622 | C42: 35564.174 | D42: -30682.434 | E42: -29326.988 | F42: -31649.747 | G42: VII. ФИНАНСИРОВАНИЕ ДЕФИЦИТА (ИСПОЛЬЗОВАНИЕ ПРОФИЦИТА) БЮДЖЕТА
A43: Ішкі | B43: -160335.33 | C43: 86560.111 | D43: 96309.989 | E43: -324315.46 | F43: =F44-F45 -> -16905.723 | G43: Внутреннее
A44: Түсімдер | B44: -149731.8 | C44: 98509.642 | D44: 111063.88 | E44: -321805.6 | F44: 3000 | G44: Поступление
A45: Өтеу | B45: 10603.525 | C45: 11949.531 | D45: 14753.89 | E45: 2509.8548 | F45: 19905.723 | G45: Погашение
A46: Сыртқы | B46: -1880.877 | C46: -868.7564 | D46: - | E46: - | F46: - | G46: Внешнее
A47: Түсімдер | B47: - | C47: - | D47: - | E47: - | F47: - | G47: Поступление
A48: Өтеу | B48: 1880.877 | C48: 868.7564 | D48: - | E48: - | F48: - | G48: Погашение

Sheet табл 12.10
A1: 12.10-кесте | E1: Таблица 12.10
A2: ҚОСТАНАЙ ОБЛЫСЫ | E2: ИСПОЛНЕНИЕ БЮДЖЕТА
A3: БЮДЖЕТІНІҢ АТҚАРЫЛУЫ | E3: КОСТАНАЙСКАЯ ОБЛАСТЬ
A4: (млн.теңге) | E4: (млн. тенге)
A5: Атауы | B5: 2023 ж. есеп/ 2023 г. отчет | C5: 2024 ж. есеп/ 2024 г. отчет | D5: 2025 ж. есеп/ 2025 г. отчет | F5: 2026 ж. қантар-наурыз есеп/январь-март отчет 2026 г. | G5: Наименование
D6: жылдық/ годовой | E6: қантар-наурыз/январь-март
A7: 1 | B7: 2 | C7: 3 | D7: 4 | E7: 5 | F7: 6 | G7: 7
A8: I. КІРІСТЕР | B8: 604311.98 | C8: 628629.96 | D8: 639937.38 | E8: 157849.43 | F8: 179320.27 | G8: I. ДОХОДЫ
A9: Салықтық түсімдер_x000D_ оның iшiнде: | B9: 174857.99 | C9: 205358.32 | D9: 236662.83 | E9: 61175.495 | F9: 59413.189 | G9: Налоговые поступления,_x000D_ в том числе:
A10: корпоративтік табыс салығы | B10: 33911.561 | C10: 37426.524 | D10: 44145.534 | E10: 9574.7895 | F10: 7375.8714 | G10: корпоративный подоходный налог
A11: жеке табыс салығы | B11: 62045.659 | C11: 79538.501 | D11: 94703.71 | E11: 24023.004 | F11: 24987.789 | G11: индивидуальный подоходный налог
A12: әлеуметтік салық | B12: 40145.801 | C12: 48992.711 | D12: 55695.777 | E12: 14747.516 | F12: 16635.915 | G12: социальный налог
A13: акциздер | B13: 5085.7443 | C13: 4367.686 | D13: 5754.3083 | E13: 673.28375 | F13: 893.60605 | G13: акцизы
A14: Салықтық емес түсімдер | B14: 6220.1607 | C14: 11769.215 | D14: 13955.646 | E14: 2459.5812 | F14: 3579.9162 | G14: Неналоговые поступления
A15: Негізгі капиталды сатудан түсетін түсімдер | B15: 5656.0616 | C15: 9621.5046 | D15: 5981.9156 | E15: 1652.5746 | F15: 3443.2123 | G15: Поступления от продажи основного капитала
A16: Арнаулы түсімдер | B16: 417577.77 | C16: 402035.83 | D16: 383336.99 | E16: 92561.779 | F16: 1713.0386 | G16: Специальные поступления
A17: Трансферттердің түсімдері | F17: 111170.91 | G17: Поступления трансфертов
A18: II. ШЫҒЫНДАР | B18: 547560.7 | C18: 628666.42 | D18: 641390.19 | E18: 118315.12 | F18: 147204.22 | G18: II. ЗАТРАТЫ
A19: 1. Жалпы сипаттағы мемлекеттiк қызметтер | B19: 30915.334 | C19: 40995.492 | D19: 31860.825 | E19: 6516.7534 | F19: 7293.5859 | G19: 1. Государственные услуги общего характера
A20: 2. Қорғаныс | B20: 1571.8601 | C20: 2531.2785 | D20: 3496.4035 | E20: 523.12683 | F20: 290.44346 | G20: 2. Оборона
A21: 3. Қоғамдық тәртіп, қауіпсіздік, құқықтық, сот, қылмыстық-атқару қызметі | B21: 14757.978 | C21: 16391.756 | D21: 19786.077 | E21: 3996.78 | F21: 4572.6077 | G21: 3. Общественный порядок, безопасность, правовая, судебная, уголовно-исполнительная деятельность
A22: 4. Бiлiм беру | B22: 198389.64 | C22: 223046.76 | D22: 228950.17 | E22: 46536.935 | F22: 49147.984 | G22: 4. Образование
A23: 5. Денсаулық сақтау | B23: 19552.847 | C23: 13757.408 | D23: 16862.695 | E23: 1853.9146 | F23: 1999.1534 | G23: 5. Здравоохранение
A24: 6. Әлеуметтiк көмек және әлеуметтiк қамсыздандыру | B24: 26793.728 | C24: 30391.651 | D24: 30933.478 | E24: 5342.0146 | F24: 6142.7395 | G24: 6. Социальная помощь и социальное обеспечение
A25: 7. Тұрғын үй-коммуналдық шаруашылық | B25: 71668.302 | C25: 91799.893 | D25: 95651.184 | E25: 12035.353 | F25: 9288.2917 | G25: 7. Жилищно-коммунальное хозяйство
A26: 8. Мәдениет, спорт, туризм және ақпараттық кеңістiк | B26: 27397.203 | C26: 35608.407 | D26: 42139.243 | E26: 7935.8176 | F26: 11627.856 | G26: 8. Культура, спорт, туризм и информационное пространство
A27: 9. Отын-энергетика кешенi және жер қойнауын пайдалану | B27: 8676.6909 | C27: 6865.9827 | D27: 3580.7103 | E27: 528.92874 | F27: 70.455058 | G27: 9. Топливно-энергетический комплекс и недропользование
A28: 10. Ауыл, су, орман, балық шаруашылығы, ерекше қорғалатын табиғи аумақтар, қоршаған ортаны және жануарлар дүниесін қорғау, жер қатынастары | B28: 58015.369 | C28: 55094.368 | D28: 60955.681 | E28: 19593.059 | F28: 39746.898 | G28: 10. Сельское, водное, лесное, рыбное хозяйство, особо охраняемые природные территории, охрана окружающей среды и животного мира, земельные отношения
A29: 11. Өнеркәсіп, сәулет, қала құрылысы және құрылыс қызметі | B29: 6646.0821 | C29: 17379.179 | D29: 9382.2969 | E29: 590.20114 | F29: 692.63255 | G29: 11. Промышленность, архитектурная, градостроительная и строительная деятельность
... A42: VII. БЮДЖЕТТІҢ ТАПШЫЛЫҒЫН ҚАРЖЫЛАНДЫРУ (ПРОФИЦИТТІ ПАЙДАЛАНУ | B42: 8226.7917 | C42: 31832.397 | D42: -26198.718 | E42: -36616.397 | F42: -32623.883 | G42: VII. ФИНАНСИРОВАНИЕ ДЕФИЦИТА (ИСПОЛЬЗОВАНИЕ ПРОФИЦИТА) БЮДЖЕТА
A43: Ішкі | B43: -194.33866 | C43: 223893.46 | D43: -22027.318 | E43: -436280.47 | F43: =F44-F45 -> 704.38564 | G43: Внутреннее
A44: Түсімдер | B44: 13423.19 | C44: 235686.62 | D44: -12947.333 | E44: -435997.17 | F44: 3500 | G44: Поступление
A45: Өтеу | B45: 13617.529 | C45: 11793.154 | D45: 9079.9847 | E45: 283.2993 | F45: 2795.6144 | G45: Погашение
A46: Сыртқы | B46: - | C46: - | D46: - | E46: - | F46: - | G46: Внешнее
A47: Түсімдер | B47: - | C47: - | D47: - | E47: - | F47: - | G47: Поступление
A48: Өтеу | B48: - | C48: - | D48: - | E48: - | F48: - | G48: Погашение

Sheet табл 12.11
A1: 12.11-кесте | E1: Таблица 12.11
A2: МАҢҒЫСТАУ ОБЛЫСЫ | E2: ИСПОЛНЕНИЕ БЮДЖЕТА
A3: БЮДЖЕТІНІҢ АТҚАРЫЛУЫ | E3: МАНГИСТАУСКАЯ ОБЛАСТЬ
A4: (млн.теңге) | E4: (млн. тенге)
A5: Атауы | B5: 2023 ж. есеп/ 2023 г. отчет | C5: 2024 ж. есеп/ 2024 г. отчет | D5: 2025 ж. есеп/ 2025 г. отчет | F5: 2026 ж. қантар-наурыз есеп/январь-март отчет 2026 г. | G5: Наименование
D6: жылдық/ годовой | E6: қантар-наурыз/январь-март
A7: 1 | B7: 2 | C7: 3 | D7: 4 | E7: 5 | F7: 6 | G7: 7
A8: I. КІРІСТЕР | B8: 475001.67 | C8: 565387.99 | D8: 612674.35 | E8: 160470.76 | F8: 104258.12 | G8: I. ДОХОДЫ
A9: Салықтық түсімдер_x000D_ оның iшiнде: | B9: 249915.93 | C9: 290147.77 | D9: 335928.32 | E9: 81092.052 | F9: 74146.738 | G9: Налоговые поступления,_x000D_ в том числе:
A10: корпоративтік табыс салығы | B10: 30124.379 | C10: 31655.206 | D10: 29656.97 | E10: 6967.997 | F10: 5622.509 | G10: корпоративный подоходный налог
A11: жеке табыс салығы | B11: 95760.861 | C11: 117448.69 | D11: 140244.25 | E11: 33193.788 | F11: 29848.79 | G11: индивидуальный подоходный налог
A12: әлеуметтік салық | B12: 72326.61 | C12: 85395.26 | D12: 108716 | E12: 25680.148 | F12: 20900.373 | G12: социальный налог
A13: акциздер | B13: 1636.9414 | C13: 1512.377 | D13: 285.88065 | E13: 14.120932 | F13: 15.663196 | G13: акцизы
A14: Салықтық емес түсімдер | B14: 8955.6703 | C14: 11116.334 | D14: 21632.846 | E14: 34022.018 | F14: 8423.8501 | G14: Неналоговые поступления
A15: Негізгі капиталды сатудан түсетін түсімдер | B15: 6033.2791 | C15: 4729.1387 | D15: 2887.4111 | E15: 823.08746 | F15: 477.78064 | G15: Поступления от продажи основного капитала
A16: Арнаулы түсімдер | B16: 210096.79 | C16: 259394.75 | D16: 252225.77 | E16: 44533.599 | F16: 909.75444 | G16: Специальные поступления
A17: Трансферттердің түсімдері | F17: 20300 | G17: Поступления трансфертов
A18: II. ШЫҒЫНДАР | B18: 445032.94 | C18: 548979.79 | D18: 670272.17 | E18: 97148.609 | F18: 89628.933 | G18: II. ЗАТРАТЫ
A19: 1. Жалпы сипаттағы мемлекеттiк қызметтер | B19: 13009.328 | C19: 19808.839 | D19: 26407.709 | E19: 3541.8093 | F19: 4774.7558 | G19: 1. Государственные услуги общего характера
A20: 2. Қорғаныс | B20: 2131.3234 | C20: 3018.473 | D20: 7430.2806 | E20: 446.00283 | F20: 370.14664 | G20: 2. Оборона
A21: 3. Қоғамдық тәртіп, қауіпсіздік, құқықтық, сот, қылмыстық-атқару қызметі | B21: 17429.294 | C21: 21764.178 | D21: 30707.98 | E21: 2718.3287 | F21: 3553.0803 | G21: 3. Общественный порядок, безопасность, правовая, судебная, уголовно-исполнительная деятельность
A22: 4. Бiлiм беру | B22: 214629.44 | C22: 244071.75 | D22: 290011.89 | E22: 49745.558 | F22: 48646.99 | G22: 4. Образование
A23: 5. Денсаулық сақтау | B23: 14411.04 | C23: 20712.628 | D23: 24296.274 | E23: 2561.493 | F23: 1392.4655 | G23: 5. Здравоохранение
A24: 6. Әлеуметтiк көмек және әлеуметтiк қамсыздандыру | B24: 27934.031 | C24: 32150.225 | D24: 37808.399 | E24: 5434.6858 | F24: 4826.244 | G24: 6. Социальная помощь и социальное обеспечение
A25: 7. Тұрғын үй-коммуналдық шаруашылық | B25: 57417.225 | C25: 91644.451 | D25: 86179.226 | E25: 6935.1887 | F25: 6375.2662 | G25: 7. Жилищно-коммунальное хозяйство
A26: 8. Мәдениет, спорт, туризм және ақпараттық кеңістiк | B26: 20843.476 | C26: 29190.299 | D26: 39523.868 | E26: 7712.2389 | F26: 6802.8097 | G26: 8. Культура, спорт, туризм и информационное пространство
A27: 9. Отын-энергетика кешенi және жер қойнауын пайдалану | B27: 16065.4 | C27: 26065.903 | D27: 41904.786 | E27: 8105.5947 | F27: - | G27: 9. Топливно-энергетический комплекс и недропользование
A28: 10. Ауыл, су, орман, балық шаруашылығы, ерекше қорғалатын табиғи аумақтар, қоршаған ортаны және жануарлар дүниесін қорғау, жер қатынастары | B28: 13536.715 | C28: 6541.2623 | D28: 12157.362 | E28: 2163.8792 | F28: 1944.1327 | G28: 10. Сельское, водное, лесное, рыбное хозяйство, особо охраняемые природные территории, охрана окружающей среды и животного мира, земельные отношения
A29: 11. Өнеркәсіп, сәулет, қала құрылысы және құрылыс қызметі | B29: 5385.3058 | C29: 2645.6561 | D29: 2953.0519 | E29: 259.07538 | F29: 570.98369 | G29: 11. Промышленность, архитектурная, градостроительная и строительная деятельность
A30: 12. Көлiк және коммуникация | B30: 18269.848 | C30: 29139.46 | D30: 46559.914 | E30: 4843.0557 | F30: 4354.9442 | G30: 12. Транспорт и коммуникации
A31: 13. Басқалар | B31: 16669.273 | C31: 16240.398 | D31: 14993.887 | E31: 1660.1302 | F31: 1070.5921 | G31: 13. Прочие
A32: 14. Борышқа қызмет көрсету | B32: 2177.7378 | C32: 2178.6271 | D32: 2210.6332 | E32: 0.64814183 | F32: 0.50671604 | G32: 14. Обслуживание долга
A33: 15. Трансферттер | B33: 5123.4969 | C33: 3807.6327 | D33: 7126.9134 | E33: 1020.9202 | F33: 4946.0152 | G33: 15. Трансферты
A34: III. ТАЗА БЮДЖЕТТІК КРЕДИТ БЕРУ | B34: 1881.482 | C34: 2711.9401 | D34: 4051.8704 | E34: -1067.2229 | F34: -1666.3191 | G34: III. ЧИСТОЕ БЮДЖЕТНОЕ КРЕДИТОВАНИЕ
A35: Бюджеттік кредиттер | B35: 3711.3245 | C35: 5486.4935 | D35: 7473.9088 | E35: 0 | F35: 0 | G35: Бюджетные кредиты
A36: Бюджеттік кредиттерді өтеу | B36: 1829.8424 | C36: 2774.5534 | D36: 3422.0385 | E36: 1067.2229 | F36: 1666.3191 | G36: Погашение бюджетных кредитов
A37: IV. ҚАРЖЫ АКТИВТЕРІМЕН ОПЕРАЦИЯЛАР БОЙЫНША САЛЬДО - ҚАРЖЫ АК | B37: 3642.1187 | C37: 2831.235 | D37: 4182.489 | E37: 1699.998 | F37: 3699.4453 | G37: IV. САЛЬДО ПО ОПЕРАЦИЯМ С ФИНАНСОВЫМИ АКТИВАМИ
A38: Қаржылық активтерді сатып алу | B38: 3678.269 | C38: 2831.235 | D38: 4182.489 | E38: 1699.998 | F38: 3699.4453 | G38: Приобретение финансовых активов
A39: Мемлекеттің қаржы активтерін сатудан түсетін түсімдер | B39: 36.150285 | G39: Поступления от продажи финансовых активов государства
A40: V. БЮДЖЕТ ТАПШЫЛЫҒЫ (ПРОФИЦИТІ) | B40: 24445.137 | C40: 10865.029 | D40: -65832.184 | E40: 62689.373 | F40: 12596.064 | G40: V. ДЕФИЦИТ (ПРОФИЦИТ) БЮДЖЕТА
A42: VII. БЮДЖЕТТІҢ ТАПШЫЛЫҒЫН ҚАРЖЫЛАНДЫРУ (ПРОФИЦИТТІ ПАЙДАЛАНУ | B42: -24445.137 | C42: -10865.029 | D42: -65832.184 | E42: -62689.373 | F42: -12596.064 | G42: VII. ФИНАНСИРОВАНИЕ ДЕФИЦИТА (ИСПОЛЬЗОВАНИЕ ПРОФИЦИТА) БЮДЖЕТА
A43: Ішкі | B43: -312630.52 | C43: -244298.81 | D43: 635568.68 | E43: -737336.01 | F43: =F44-F45 -> -1632.6005 | G43: Внутреннее
A44: Түсімдер | B44: -311173.63 | C44: -238722.45 | D44: 638922.34 | E44: -735978.15 | G44: Поступление
A45: Өтеу | B45: 1456.89 | C45: 5576.3587 | D45: 3353.6608 | E45: 1357.8605 | F45: 1632.6005 | G45: Погашение
A46: Сыртқы | B46: - | C46: - | D46: - | E46: - | F46: - | G46: Внешнее
A47: Түсімдер | B47: - | C47: - | D47: - | E47: - | F47: - | G47: Поступление
A48: Өтеу | B48: - | C48: - | D48: - | E48: - | F48: - | G48: Погашение

Sheet табл 12.12
A1: 12.12-кесте | E1: Таблица 12.12
A2: ПАВЛОДАР ОБЛЫСЫ | E2: ИСПОЛНЕНИЕ БЮДЖЕТА
A3: БЮДЖЕТІНІҢ АТҚАРЫЛУЫ | E3: ПАВЛОДАРСКАЯ ОБЛАСТЬ
A4: (млн.теңге) | E4: (млн. тенге)
A5: Атауы | B5: 2023 ж. есеп/ 2023 г. отчет | C5: 2024 ж. есеп/ 2024 г. отчет | D5: 2025 ж. есеп/ 2025 г. отчет | F5: 2026 ж. қантар-наурыз есеп/январь-март отчет 2026 г. | G5: Наименование
D6: жылдық/ годовой | E6: қантар-наурыз/январь-март
A7: 1 | B7: 2 | C7: 3 | D7: 4 | E7: 5 | F7: 6 | G7: 7
A8: I. КІРІСТЕР | B8: 530607.87 | C8: 568290.97 | D8: 625185.1 | E8: 138518.31 | F8: 130313.12 | G8: I. ДОХОДЫ
A9: Салықтық түсімдер_x000D_ оның iшiнде: | B9: 311139.96 | C9: 355688.78 | D9: 426655.29 | E9: 98893.962 | F9: 112083.44 | G9: Налоговые поступления,_x000D_ в том числе:
A10: корпоративтік табыс салығы | B10: 24425.448 | C10: 34139.694 | D10: 38047.812 | E10: 8093.4799 | F10: 9154.6497 | G10: корпоративный подоходный налог
A11: жеке табыс салығы | B11: 67868.655 | C11: 86404.401 | D11: 99740.05 | E11: 24762.098 | F11: 26887.845 | G11: индивидуальный подоходный налог
A12: әлеуметтік салық | B12: 47871.635 | C12: 58092.974 | D12: 67370.203 | E12: 17367.119 | F12: 18782.629 | G12: социальный налог
A13: акциздер | B13: 125534.48 | C13: 129598.29 | D13: 170870.86 | E13: 34274.785 | F13: 46665.805 | G13: акцизы
A14: Салықтық емес түсімдер | B14: 4507.2143 | C14: 6402.786 | D14: 8874.8603 | E14: 2038.8551 | F14: 2052.603 | G14: Неналоговые поступления
A15: Негізгі капиталды сатудан түсетін түсімдер | B15: 7729.2877 | C15: 7851.1996 | D15: 7717.4319 | E15: 1267.0624 | F15: 1145.975 | G15: Поступления от продажи основного капитала
A16: Арнаулы түсімдер | B16: 207231.4 | C16: 198348.21 | D16: 181937.52 | E16: 36318.434 | F16: 4144.341 | G16: Специальные поступления
A17: Трансферттердің түсімдері | F17: 10886.766 | G17: Поступления трансфертов
A18: II. ШЫҒЫНДАР | B18: 528208.21 | C18: 579464.48 | D18: 625786.68 | E18: 127666.29 | F18: 118772.09 | G18: II. ЗАТРАТЫ
A19: 1. Жалпы сипаттағы мемлекеттiк қызметтер | B19: 42863.349 | C19: 33133.36 | D19: 40195.222 | E19: 9106.64 | F19: 7936.673 | G19: 1. Государственные услуги общего характера
A20: 2. Қорғаныс | B20: 1786.6605 | C20: 2384.4454 | D20: 2457.46 | E20: 281.81597 | F20: 577.96578 | G20: 2. Оборона
A21: 3. Қоғамдық тәртіп, қауіпсіздік, құқықтық, сот, қылмыстық-атқару қызметі | B21: 11681.013 | C21: 15647.561 | D21: 16920.941 | E21: 3521.0285 | F21: 3723.3757 | G21: 3. Общественный порядок, безопасность, правовая, судебная, уголовно-исполнительная деятельность
A22: 4. Бiлiм беру | B22: 194222.74 | C22: 215677.12 | D22: 234655.11 | E22: 54409.896 | F22: 55664.28 | G22: 4. Образование
A23: 5. Денсаулық сақтау | B23: 19116.509 | C23: 19663.761 | D23: 16669.895 | E23: 1792.1395 | F23: 864.24686 | G23: 5. Здравоохранение
A24: 6. Әлеуметтiк көмек және әлеуметтiк қамсыздандыру | B24: 32987.26 | C24: 37999.459 | D24: 41046.306 | E24: 7389.4286 | F24: 7534.6911 | G24: 6. Социальная помощь и социальное обеспечение
A25: 7. Тұрғын үй-коммуналдық шаруашылық | B25: 75776.768 | C25: 81762.786 | D25: 76958.299 | E25: 11685.883 | F25: 7516.8178 | G25: 7. Жилищно-коммунальное хозяйство
A26: 8. Мәдениет, спорт, туризм және ақпараттық кеңістiк | B26: 27131.851 | C26: 33271.652 | D26: 38023.809 | E26: 8159.7193 | F26: 7293.0031 | G26: 8. Культура, спорт, туризм и информационное пространство
A27: 9. Отын-энергетика кешенi және жер қойнауын пайдалану | B27: 2972.2032 | C27: 6483.698 | D27: 16277.751 | E27: 3400.8647 | F27: 4819.082 | G27: 9. Топливно-энергетический комплекс и недропользование
A28: 10. Ауыл, су, орман, балық шаруашылығы, ерекше қорғалатын табиғи аумақтар, қоршаған ортаны және жануарлар дүниесін қорғау, жер қатынастары | B28: 48063.759 | C28: 41732.188 | D28: 49466.197 | E28: 14610.809 | F28: 8964.7226 | G28: 10. Сельское, водное, лесное, рыбное хозяйство, особо охраняемые природные территории, охрана окружающей среды и животного мира, земельные отношения
A29: 11. Өнеркәсіп, сәулет, қала құрылысы және құрылыс қызметі | B29: 5581.309 | C29: 11359.854 | D29: 3816.7288 | E29: 528.20865 | F29: 755.48998 | G29: 11. Промышленность, архитектурная, градостроительная и строительная деятельность
... A42: VII. БЮДЖЕТТІҢ ТАПШЫЛЫҒЫН ҚАРЖЫЛАНДЫРУ (ПРОФИЦИТТІ ПАЙДАЛАНУ | B42: 10426.094 | C42: 19278.523 | D42: -14266.781 | E42: -12127.566 | F42: -13705.037 | G42: VII. ФИНАНСИРОВАНИЕ ДЕФИЦИТА (ИСПОЛЬЗОВАНИЕ ПРОФИЦИТА) БЮДЖЕТА
A43: Ішкі | B43: 9464.0863 | C43: 47257.462 | D43: -107819.11 | E43: -132608.6 | F43: =F44-F45 -> 4856.9167 | G43: Внутреннее
A44: Түсімдер | B44: 17349.601 | C44: 55012.88 | D44: -99135.551 | E44: -131433.85 | F44: 7256.557 | G44: Поступление
A45: Өтеу | B45: 7885.5148 | C45: 7755.4174 | D45: 8683.5566 | E45: 1174.7454 | F45: 2399.6403 | G45: Погашение
A46: Сыртқы | B46: - | C46: - | D46: - | E46: - | F46: - | G46: Внешнее
A47: Түсімдер | B47: - | C47: - | D47: - | E47: - | F47: - | G47: Поступление
A48: Өтеу | B48: - | C48: - | D48: - | E48: - | F48: - | G48: Погашение

Sheet табл 12.13
A1: 12.13-кесте | E1: Таблица 12.13
A2: СОЛТҮСТІК-ҚАЗАҚСТАН ОБЛЫСЫ | E2: ИСПОЛНЕНИЕ БЮДЖЕТА
A3: БЮДЖЕТІНІҢ АТҚАРЫЛУЫ | E3: СЕВ-КАЗАХСТАНСКАЯ ОБЛАСТЬ
A4: (млн.теңге) | E4: (млн. тенге)
A5: Атауы | B5: 2023 ж. есеп/ 2023 г. отчет | C5: 2024 ж. есеп/ 2024 г. отчет | D5: 2025 ж. есеп/ 2025 г. отчет | F5: 2026 ж. қантар-наурыз есеп/январь-март отчет 2026 г. | G5: Наименование
D6: жылдық/ годовой | E6: қантар-наурыз/январь-март
A7: 1 | B7: 2 | C7: 3 | D7: 4 | E7: 5 | F7: 6 | G7: 7
A8: I. КІРІСТЕР | B8: 479286.16 | C8: 499744.12 | D8: 530250.23 | E8: 127948.3 | F8: 145869.33 | G8: I. ДОХОДЫ
A9: Салықтық түсімдер_x000D_ оның iшiнде: | B9: 104168.43 | C9: 114911.18 | D9: 131166.57 | E9: 32895.194 | F9: 33503.353 | G9: Налоговые поступления,_x000D_ в том числе:
A10: корпоративтік табыс салығы | B10: 19981.616 | C10: 20968.836 | D10: 24592.399 | E10: 5491.2401 | F10: 4585.7911 | G10: корпоративный подоходный налог
A11: жеке табыс салығы | B11: 33665.851 | C11: 42183.254 | D11: 48150.638 | E11: 11180.707 | F11: 11975.096 | G11: индивидуальный подоходный налог
A12: әлеуметтік салық | B12: 20700.577 | C12: 24710.833 | D12: 28404.081 | E12: 7219.7719 | F12: 7731.1676 | G12: социальный налог
A13: акциздер | B13: 13585.507 | C13: 11347.819 | D13: 12079.683 | E13: 3161.5841 | F13: 3437.534 | G13: акцизы
A14: Салықтық емес түсімдер | B14: 4418.0267 | C14: 5764.0759 | D14: 7686.3608 | E14: 1848.203 | F14: 3027.0877 | G14: Неналоговые поступления
A15: Негізгі капиталды сатудан түсетін түсімдер | B15: 11077.734 | C15: 6402.5728 | D15: 9118.1715 | E15: 2189.6987 | F15: 1226.0425 | G15: Поступления от продажи основного капитала
A16: Арнаулы түсімдер | B16: 359621.97 | C16: 372666.29 | D16: 382279.13 | E16: 91015.205 | F16: 460.6218 | G16: Специальные поступления
A17: Трансферттердің түсімдері | F17: 107652.22 | G17: Поступления трансфертов
A18: II. ШЫҒЫНДАР | B18: 456049.77 | C18: 519516.5 | D18: 524179.94 | E18: 118372.43 | F18: 144579.65 | G18: II. ЗАТРАТЫ
A19: 1. Жалпы сипаттағы мемлекеттiк қызметтер | B19: 21153.388 | C19: 46477.998 | D19: 38873.107 | E19: 7290.9253 | F19: 7651.4078 | G19: 1. Государственные услуги общего характера
A20: 2. Қорғаныс | B20: 1551.1442 | C20: 2113.6186 | D20: 2513.3636 | E20: 223.63705 | F20: 247.80566 | G20: 2. Оборона
