Workbook
Name \E: #REF!
Name \E: #REF!
Name \E: #REF!
Name \E: #REF!
Name \E: #REF!
Name _____________________MS798: #REF!
Name _____________________MS798: #REF!
Name _____________________tab1: #REF!
Name _____________________tab2: #REF!
Name _____________________tab6798: #REF!
Name ____________________MS798: #REF!
Name ____________________tab1: #REF!
Name ____________________tab2: #REF!
Name ____________________tab6798: #REF!
Name ___________________MS798: #REF!
Name ___________________tab1: #REF!
Name ___________________tab2: #REF!
Name ___________________tab6798: #REF!
Name __________________MS798: #REF!
Name __________________tab1: #REF!
Name __________________tab2: #REF!
Name __________________tab6798: #REF!
Name _________________MS798: #REF!
Name _________________prt1: #N/A
Name _________________prt2: #N/A
Name _________________prt3: #N/A
Name _________________prt4: #N/A
Name _________________prt5: #N/A
Name _________________prt6: #N/A
Name _________________prt7: #N/A
Name _________________prt8: #N/A
Name _________________tab1: #REF!
Name _________________tab2: #REF!
Name _________________tab6798: #REF!
Name ________________MS798: #REF!
Name ________________prt1: #N/A
Name ________________prt2: #N/A
Name ________________prt3: #N/A
Name ________________prt4: #N/A
Name ________________prt5: #N/A
Name ________________prt6: #N/A
Name ________________prt7: #N/A
Name ________________prt8: #N/A
Name ________________tab1: #REF!
Name ________________tab2: #REF!
Name ________________tab6798: #REF!
Name _______________MS798: #REF!
Name _______________prt1: #N/A
Name _______________prt2: #N/A
Name _______________prt3: #N/A
Name _______________prt4: #N/A
Name _______________prt5: #N/A
Name _______________prt6: #N/A
Name _______________prt7: #N/A
Name _______________prt8: #N/A
Name _______________tab1: #REF!
Name _______________tab2: #REF!
Name _______________tab6798: #REF!
Name ______________MS798: #REF!
Name ______________prt1: #N/A

Sheet табл 1
A1: 1-кесте | I1: Таблица 1
A3: НЕГІЗГІ МАКРОЭКОНОМИКАЛЫҚ ИНДИКАТОРЛАР/
A4: ОСНОВНЫЕ МАКРОЭКОНОМИЧЕСКИЕ ИНДИКАТОРЫ
A6: Атауы | B6: 2019 жыл/ 2019 год | C6: 2020 жыл/ 2020 год | D6: 2021 жыл/ 2021 год | E6: 2022 жыл/ 2022 год | F6: 2023 жыл/ 2023 год | G6: 2024 жыл/ 2024 год | H6: 2025 ж. 1 тамыздағы есеп/ отчет на 1 августа 2025 г. | I6: Наименование
A7: 1 | B7: 2 | C7: 3 | D7: 4 | E7: 5 | F7: 6 | G7: 7 | H7: 8 | I7: 9
A8: Жалпы ішкi өнiм, млрд. теңге | B8: 69532.626 | C8: 70649 | D8: 83951.587 | E8: 65487.797 | F8: 120561.1 | G8: 84962.621 | H8: 61361.3 | I8: Валовой внутренний продукт, млрд.тенге январь-июнь 2025 года (предварит. данные)
A9: өткен жылдың тиiстi кезеңiндегi нақты есептеудегi %-бен | B9: 104.5 | C9: 97.5 | D9: 103.3 | E9: 103 | F9: 105.1 | G9: 104.1 | H9: 106.3 | I9: в % к соответствующему периоду предыдущего года
A10: Өнеркәсiп өнiмiнiң көлемi, млрд. теңге | B10: 29380.342 | C10: 26743.4 | D10: 37047.6 | E10: 4157.4 | F10: 46401.716 | G10: 50124.86 | H10: 34204.1 | I10: Объем промышленного производства, млрд.тенге (январь-июль 2025г.)
A11: өткен жылдың тиiстi кезеңiне %-бен | B11: 104.1 | C11: 99.3 | D11: 103.8 | E11: 97.2 | F11: 104.3 | G11: 102.8 | H11: 106.9 | I11: в % к соответствующему периоду предыдущего года
A12: Мембюджетке кірістер, млрд. теңге | B12: 12758.479 | C12: 14521.191 | D12: 15847.431 | E12: 20248.101 | F12: 24917.246 | G12: ='[46]табл 2 '!C8/1000 -> 27132.165 | H12: ='табл 2 '!C8/1000 -> 16361.108 | I12: Доходы в госбюджет, млрд.тенге
A13: ЖIӨ-ге %-бен | B13: 18.502241 | C13: 20.535071 | D13: =D12/D8*100 -> 18.876869 | E13: =E12/E8*100 -> 30.918891 | G13: =G12/G8*100 -> 31.934237 | H13: =H12/H8*100 -> 26.663561 | I13: в % к ВВП
A14: Мембюджеттен шығындар, млрд. теңге | B14: 13535.581 | C14: 16725.097 | D14: 17951.888 | E14: 21532.543 | F14: 26760 | G14: ='[46]табл 2 '!C18/1000 -> 30318.236 | H14: ='табл 2 '!C18/1000 -> 17461.82 | I14: Затраты из госбюджета, млрд. тенге
A15: ЖIӨ-ге %-бен | B15: 19.629188 | C15: 23.651714 | D15: =D14/D8*100 -> 21.38362 | E15: =E14/E8*100 -> 32.880238 | F15: 35.421743 | G15: =G14/G8*100 -> 35.684206 | H15: =H14/H8*100 -> 28.457382 | I15: в % к ВВП
A16: Таза бюджеттік кредит беру, млрд. теңге | B16: 262.88084 | C16: 261.98101 | D16: 267.33754 | E16: 592.68034 | F16: 466.44174 | G16: ='[46]табл 2 '!C34/1000 -> 198.40855 | H16: ='табл 3'!F34/1000 -> 139.28394 | I16: Чистое бюджетное кредитование, млрд. тенге
A17: ЖIӨ-ге %-бен | B17: 0.38122761 | C17: 0.37047917 | D17: =D16/D8*100 -> 0.31844251 | E17: =E16/E8*100 -> 0.9050241 | F17: 0.61742075 | G17: =G16/G8*100 -> 0.23352452 | H17: =H16/H8*100 -> 0.22698987 | I17: в % к ВВП
A18: Қаржылық активтермен болатын операциялар бойынша сальдо, млрд. теңге | B18: 245.32373 | C18: 340.26326 | D18: 163.01136 | E18: 292.00158 | F18: 501.9047 | G18: ='[46]табл 2 '!C37/1000 -> 201.56181 | H18: ='табл 2 '!C37/1000 -> 285.29756 | I18: Сальдо по операциям с финансовыми активами, млрд.тенге
A19: ЖIӨ-ге %-бен | B19: 0.35576643 | C19: 0.48118163 | D19: =D18/D8*100 -> 0.19417306 | E19: =E18/E8*100 -> 0.44588701 | F19: 0.66436244 | G19: =G18/G8*100 -> 0.23723586 | H19: =H18/H8*100 -> 0.46494707 | I19: в % к ВВП
A20: Мембюджеттiң тапшылығы (-) / профицитi (+), млрд. теңге | B20: -1285.3067 | C20: -2806.1502 | D20: -2534.8062 | E20: -2169.1247 | F20: -2811.1006 | G20: ='[46]табл 2 '!C40/1000 -> -3586.0419 | H20: ='табл 3'!F40/1000 -> -1525.2933 | I20: Дефицит (-) / профицит (+) госбюджета, млрд.тенге
A21: ЖIӨ-ге %-бен | B21: -1.8639412 | C21: -3.9683036 | D21: =D20/D8*100 -> -3.0193666 | E21: =E20/E8*100 -> -3.3122579 | F21: -3.7210045 | G21: =G20/G8*100 -> -4.2207288 | H21: =H20/H8*100 -> -2.4857578 | I21: в % к ВВП
A22: Тұтыну бағаларының индексі өткен жылдың айына, %-бен | B22: 105.4 | C22: 107.5 | D22: 108.4 | E22: 120.3 | F22: 109.5 | G22: 108.9 | H22: 112.2 | I22: Индекс потребительских цен к августу предыдущего года, в %
A23: орташа есеппен өткен жылдың тиiстi кезеңiндегi кезге арналған, %-бен | B23: 105.3 | C23: 106.8 | D23: 108 | E23: 115 | G23: 108.6 | H23: 105.7 | I23: в среднем за период к соответствующему периоду предыдущего года, в %
A24: Орташа айлық атаулы жалақы 1 қызметкердың, теңге | B24: 186815 | C24: 220848 | D24: 268051 | E24: 303055 | F24: 350542 | G24: 390328 | H24: 448620 | I24: Среднемесячная номинальная заработная плата 1 работника, тенге (2 квартал 2025г.)
A25: өткен жылдың тиiстi кезеңiне %-бен | B25: 114.8 | C25: 104.4 | D25: 115.3 | E25: 112.2 | F25: 116.9 | G25: 111.3 | H25: 111.3 | I25: в % к соответствующему периоду предыдущего года
A26: Экспорт, млн. АҚШ долл. | B26: 58065.6 | C26: 46 949,7 2 | D26: 54549.5 | E26: ____ | F26: 71274.7 | G26: 73884.5 | H26: 36819.5 | I26: Экспорт, млн. долл. США (январь-июнь 2025г.)
A27: өткен жылдың тиiстi кезеңiне %-бен | B27: 95 | C27: 80.9 | D27: 124.5 | I27: в % к соответствующему периоду предыдущего года
A28: Импорт, млн. АҚШ долл. | B28: 39709.3 | C28: 38 081,4 2 | D28: 36825.9 | E28: ____ | F28: 54643.5 | G28: 53590.3 | H28: 29138.5 | I28: Импорт, млн. долл. США (январь-июнь 2025г.)
A29: өткен жылдың тиiстi кезеңiне %-бен | B29: 118 | C29: 95.9 | D29: 104.2 | I29: в % к соответствующему периоду предыдущего года
A30: Сауда балансының сальдосы, млн. АҚШ долл. | B30: 18356.3 | C30: 8969 | D30: 17723.6 | E30: ____ | F30: 16631.2 | G30: =G26-G28 -> 20294.2 | H30: =H26-H28 -> 7681 | I30: Сальдо торгового баланса, млн. долл. США
A31: Теңгенiң АҚШ долларына қарағандағы ресми айырбас бағамы: | I31: Официальный обменный курс тенге к доллару США:
A32: кезеңнiң аяғындағы | B32: 381.18 | C32: 420.71 | D32: 433.83 | E32: 459.92 | F32: 448.17 | G32: 525.11 | H32: 546.36 | I32: на конец периода
A33: кезең бойынша орташа | B33: 382.75 | C33: 412.95 | D33: 433.66 | E33: 460.48 | F33: 451.28 | G33: 469.44 | H33: 528.81 | I33: в среднем за период январь-июль 2025 года
A35: Ақпарат көзi: / Источник:
A36: Қазақстан Республикасының Қаржы министрлiгi / Министерство финансов Республики Казахстан.
A37: Ұлттық статистика бюросы Қазақстан Республикасының Стратегиялық жоспарлау және реформалар агенттігі / Бюро национальной статистики Агентства по стратегическому планированию и реформам Республики Казахстан
A38: Қазақстан Республикасының Ұлттық Банкi / Национальный Банк Республики Казахстан.
A39: Ескерту: / Примечание:
A40: 1 - Ұлттық статистика бюросы Қазақстан Республикасының Стратегиялық жоспарлау және реформалар агенттігінің деректері бойынша /Объем ВВП по отчетным данным Бюро национальной статистики Агентства по стратегическому планированию и реформам Республики Казахстан
A41: 2 - Ұлттық статистика бюросы Қазақстан Республикасының Стратегиялық жоспарлау және реформалар агенттігінің деректері бойынша /По данным Бюро национальной статистики Агентства по стратегическому планированию и реформам Республики Казахстан
A42: 3 - Ұлттық статистика бюросы Қазақстан Республикасының Стратегиялық жоспарлау және реформалар агенттігінің деректері бойынша /По данным Бюро национальной статистики Агентства по стратегическому планированию и реформам Республики Казахстан

Sheet табл 2 
A1: 2-кесте | F1: Таблица - 2
A2: МЕМЛЕКЕТТІК ЖӘНЕ РЕСПУБЛИКАЛЫҚ | F2: СРАВНИТЕЛЬНЫЙ АНАЛИЗ ИСПОЛНЕНИЯ
A3: БЮДЖЕТТЕР АТҚАРЫЛУЫНЫҢ САЛЫСТЫРМА ТАЛДАУЫ | F3: ГОСУДАРСТВЕННОГО И РЕСПУБЛИКАНСКОГО БЮДЖЕТОВ
A5: Атауы | B5: Мемлекеттік бюджет / Государственный бюджет | F5: Республикалық бюджет / Республиканский бюджет | J5: Наименование
B6: 2025 жылға түзету енгізілген бюджет (млн. теңге)/ скорректированный бюджет на 2025 год (млн.тенге) | C6: 2025 жылғы қаңтар-шілде атқарылуы (млн. теңге)/ исполнение за январь-июль 2025 года (млн.тенге) | D6: бір жылға түзету енгізілген бюджеттің атқарылу %-ы/% исполнения к скорректированному бюджету на год | E6: 2024 ж. қаңтар-шілде %-бен 2025 ж. қаңтар-шілдеге/ 2025 г. январь-июль в % к январю-июлю 2024 г. | F6: 2025 жылға түзету енгізілген бюджет (млн. теңге)/ скорректированный бюджет на 2025 год (млн.тенге) | G6: 2025 жылғы қаңтар-шілде атқарылуы (млн. теңге)/ исполнение за январь-июль 2025 года (млн.тенге) | H6: бір жылға түзету енгізілген бюджеттің атқарылу %-ы/% исполнения к скорректированному бюджету на год | I6: 2024 ж. қаңтар-шілде %-бен 2025 ж. қаңтар-шілдеге/ 2025 г. январь-июль в % к январю-июлю 2024 г.
A7: 1 | B7: 2 | C7: 3 | D7: 4 | E7: 5 | F7: 6 | G7: 7 | H7: 8 | I7: 9 | J7: 10
A8: I. КІРІСТЕР | B8: 29363162 | C8: 16361108 | D8: 55.719843 | E8: 112.60792 | F8: 21392055 | G8: 11543427 | H8: 53.961281 | I8: 112.43755 | J8: I. ДОХОДЫ
A9: Салықтық түсімдер оның iшiнде: | B9: 23065569 | C9: 12073505 | D9: 52.344276 | E9: 117.53547 | F9: 15193344 | G9: 7239542.7 | H9: 47.649436 | I9: 119.29379 | J9: Налоговые поступления, в том числе:
A10: корпорациялық табыс салығы | B10: 6690090.8 | C10: 3277371.7 | D10: 48.988449 | E10: 119.46468 | F10: 5087546.7 | G10: 2237617.7 | H10: 43.982255 | I10: 125.43367 | J10: корпоративный подоходный налог
A11: жеке табыс салығы | B11: 2604126.1 | C11: 1591651.2 | D11: 61.120357 | E11: 113.3821 | F11: 0 | G11: 0 | H11: 0 | I11: 0 | J11: индивидуальный подоходный налог
A12: әлеуметтік салық | B12: 1727455.1 | C12: 1042470.7 | D12: 60.347196 | E12: 117.46983 | F12: 0 | G12: 0 | H12: 0 | I12: 0 | J12: социальный налог
A13: қосылған құн салығы | B13: 6510033 | C13: 3067591.1 | D13: 47.120977 | E13: 122.27757 | F13: 6510033 | G13: 3067591.1 | H13: 47.120977 | I13: 122.27757 | J13: налог на добавленную стоимость
A14: акциздер | B14: 954584.86 | C14: 547340.06 | D14: 57.33802 | E14: 122.28168 | F14: 149702.35 | G14: 68224.961 | H14: 45.573741 | I14: 98.24186 | J14: акцизы
A15: Салықтық емес түсімдер | B15: 736338.75 | C15: 709043.91 | D15: 96.293169 | E15: 61.7369 | F15: 435325.85 | G15: 459781.24 | H15: 105.61772 | I15: 52.432752 | J15: Неналоговые поступления
A16: Негізгі капиталды сатудан түсетін түсімдер | B16: 311254.07 | C16: 103558.82 | D16: 33.271475 | E16: 94.52776 | F16: 5200 | G16: 2062.5326 | H16: 39.664089 | I16: 44.029785 | J16: Поступления от продажи основного капитала
A17: Трансферттердің түсімдері | B17: 5250000 | C17: 3475000 | D17: 66.190476 | E17: 115.87196 | F17: 5758184.9 | G17: 3842040.4 | H17: 66.723116 | I17: 115.8541 | J17: Поступления трансфертов
A18: II. ШЫҒЫНДАР | B18: 33857057 | C18: 17461820 | D18: 51.575125 | E18: 108.96696 | F18: 25193778 | G18: 13382506 | H18: 53.118299 | I18: 103.30965 | J18: II. ЗАТРАТЫ
A19: 1. Жалпы сипаттағы мемлекеттiк қызметтер | B19: 1921415.6 | C19: 893361.5 | D19: 46.494966 | E19: 98.01588 | F19: 1431272.2 | G19: 597063.17 | H19: 41.715558 | I19: 93.05389 | J19: 1. Государственные услуги общего характера
... A32: 14. Борышқа қызмет көрсету | B32: 2550090.2 | C32: 2035215.4 | D32: 79.809547 | E32: 119.06396 | F32: 2497932.3 | G32: 2017823 | H32: 80.77973 | I32: 119.30154 | J32: 14. Обслуживание долга
F33: 5578500.9 | G33: 3358383.8 | H33: 60.202264 | I33: 106.47882 | J33: 15. Трансферты
A34: III. ТАЗА БЮДЖЕТТІК КРЕДИТ БЕРУ | B34: 363161.74 | C34: 139283.94 | D34: 38.353141 | E34: 130.74924 | F34: 252140.98 | G34: 55411.289 | H34: 21.976312 | I34: 78.0273 | J34: III. ЧИСТОЕ БЮДЖЕТНОЕ КРЕДИТОВАНИЕ
A35: Бюджеттік кредиттер | B35: 636968.88 | C35: 281411.46 | D35: 44.179782 | E35: 124.0133 | F35: 510480 | G35: 204000 | H35: 39.962388 | I35: 106.16709 | J35: Бюджетные кредиты
A36: Бюджеттік кредиттерді өтеу | B36: 273807.14 | C36: 142127.53 | D36: 51.907898 | E36: 118.05313 | F36: 258339.02 | G36: 148588.71 | H36: 57.516944 | I36: 122.66406 | J36: Погашение бюджетных кредитов
A37: IV. ҚАРЖЫ АКТИВТЕРІМЕН ОПЕРАЦИЯЛАР БОЙЫНША САЛЬДО - ҚАРЖЫ АК | B37: 525287.43 | C37: 285297.56 | D37: 54.312658 | E37: 207.66876 | F37: 46891.3 | G37: 19155.048 | H37: 40.849897 | I37: 45.14115 | J37: IV. САЛЬДО ПО ОПЕРАЦИЯМ С ФИНАНСОВЫМИ АКТИВАМИ
A38: Қаржылық активтерді сатып алу | B38: 528067.62 | C38: 288193.58 | D38: 54.575129 | E38: 208.87861 | F38: 46891.3 | G38: 19155.048 | H38: 40.849897 | I38: 45.14115 | J38: Приобретение финансовых активов
A39: Мемлекеттің қаржы активтерін сатудан түсетін түсімдер | B39: 2780.189 | C39: 2896.0196 | D39: 104.16628 | E39: 490.24066 | J39: Поступления от продажи финансовых активов государства
A40: V. БЮДЖЕТ ТАПШЫЛЫҒЫ (ПРОФИЦИТІ) | B40: -5382344.4 | C40: -1525293.3 | D40: 28.338827 | E40: -87.68501 | F40: -4100755.3 | G40: -1913645.8 | H40: 46.665691 | I40: -68.32725 | J40: V. ДЕФИЦИТ (ПРОФИЦИТ) БЮДЖЕТА
A41: VI. БЮДЖЕТТІҢ МҰНАЙҒА ҚАТЫСТЫ ЕМЕС ТАПШЫЛЫҒЫ (ПРОФИЦИТІ) | B41: -12282044 | C41: -5881059.7 | D41: 47.883394 | E41: -105.83906 | F41: -11000455 | G41: -6269412.2 | H41: 56.992298 | I41: -94.73562 | J41: VI. НЕНЕФТЯНОЙ ДЕФИЦИТ (ПРОФИЦИТ) БЮДЖЕТА

Sheet табл 3
A1: 3-кесте | E1: Таблица 3
A2: МЕМЛЕКЕТТІК БЮДЖЕТТІҢ АТҚАРЫЛУЫ | E2: ИСПОЛНЕНИЕ ГОСУДАРСТВЕННОГО БЮДЖЕТА
A3: (млн.теңге) | E3: (млн. тенге)
A5: Атауы | B5: 2022 ж. есеп/ 2022 г. отчет | C5: 2023 ж. есеп/ 2023 г. отчет | D5: 2024 ж. есеп/ 2024 г. отчет | F5: 2025 ж. қантар-шілде есеп/январь-июль отчет 2025 г. | G5: Наименование
D6: жылдық/ годовой | E6: қантар-шілде/январь-июль
A7: 1 | B7: 2 | C7: 3 | D7: 4 | E7: 5 | F7: 6 | G7: 7
A8: I. КІРІСТЕР | B8: 20248101 | C8: 24917246 | D8: 27132165 | E8: 14529270 | F8: 16361108 | G8: I. ДОХОДЫ
A9: Салықтық түсімдер_x000D_ оның iшiнде: | B9: 14843311 | C9: 18912204 | D9: 19700517 | E9: 10272223 | F9: 12073505 | G9: Налоговые поступления,_x000D_ в том числе:
A10: корпорациялық табыс салығы | B10: 3962495.8 | C10: 5045696.1 | D10: 5213291.4 | E10: 2743381.2 | F10: 3277371.7 | G10: корпоративный подоходный налог
A11: жеке табыс салығы | B11: 1499712.4 | C11: 1992384.9 | D11: 2451640 | E11: 1403794.1 | F11: 1591651.2 | G11: индивидуальный подоходный налог
A12: әлеуметтік салық | B12: 1035129 | C12: 1321272.8 | D12: 1579329.4 | E12: 887436.98 | F12: 1042470.7 | G12: социальный налог
A13: қосылған құн салығы | B13: 4226358.8 | C13: 5674110.6 | D13: 5179378.1 | E13: 2508711.3 | F13: 3067591.1 | G13: налог на добавленную стоимость
A14: акциздер | B14: 757266.87 | C14: 840215.7 | D14: 844909.98 | E14: 447605.92 | F14: 547340.06 | G14: акцизы
A15: Салықтық емес түсімдер | B15: 584848.01 | C15: 1822932.9 | D15: 1629968 | E15: 1148493 | F15: 709043.91 | G15: Неналоговые поступления
A16: Негізгі капиталды сатудан түсетін түсімдер | B16: 239941.5 | C16: 182108.73 | D16: 201680.05 | E16: 109553.88 | F16: 103558.82 | G16: Поступления от продажи основного капитала
A17: Трансферттердің түсімдері | B17: 4580000 | C17: 4000000 | D17: 5600000 | E17: 2999000 | F17: 3475000 | G17: Поступления трансфертов
A18: II. ШЫҒЫНДАР | B18: 21532543 | C18: 26760000 | D18: 30318236 | E18: 16024875 | F18: 17461820 | G18: II. ЗАТРАТЫ
A19: 1. Жалпы сипаттағы мемлекеттiк қызметтер | B19: 1211805.7 | C19: 1489124.1 | D19: 1766404.2 | E19: 911445.68 | F19: 893361.5 | G19: 1. Государственные услуги общего характера
... A32: 14. Борышқа қызмет көрсету | B32: 1357551.8 | C32: 1865649 | D32: 2232329.2 | E32: 1709346.4 | F32: 2035215.4 | G32: 14. Обслуживание долга
A33: 15. Трансферттер | B33: 140421.01 | C33: - | D33: - | E33: - | F33: - | G33: 15. Трансферты
A34: III. ТАЗА БЮДЖЕТТІК КРЕДИТ БЕРУ | B34: 592680.34 | C34: 466441.74 | D34: 198408.55 | E34: 106527.53 | F34: 139283.94 | G34: III. ЧИСТОЕ БЮДЖЕТНОЕ КРЕДИТОВАНИЕ
A35: Бюджеттік кредиттер | B35: 742434.13 | C35: 712385.4 | D35: 519749.13 | E35: 226920.38 | F35: 281411.46 | G35: Бюджетные кредиты
A36: Бюджеттік кредиттерді өтеу | B36: 149753.78 | C36: 245943.66 | D36: 321340.58 | E36: 120392.85 | F36: 142127.53 | G36: Погашение бюджетных кредитов
A37: IV. ҚАРЖЫ АКТИВТЕРІМЕН ОПЕРАЦИЯЛАР БОЙЫНША САЛЬДО - ҚАРЖЫ АК | B37: 292001.58 | C37: 501904.7 | D37: 201561.81 | E37: 137381.07 | F37: 285297.56 | G37: IV. САЛЬДО ПО ОПЕРАЦИЯМ С ФИНАНСОВЫМИ АКТИВАМИ
A38: Қаржылық активтерді сатып алу | B38: 293189.28 | C38: 503365.1 | D38: 202951.32 | E38: 137971.81 | F38: 288193.58 | G38: Приобретение финансовых активов
A39: Мемлекеттің қаржы активтерін сатудан түсетін түсімдер | B39: 1187.6999 | C39: 1460.4064 | D39: 1389.5083 | E39: 590.73428 | F39: 2896.0196 | G39: Поступления от продажи финансовых активов государства
A40: V. БЮДЖЕТ ТАПШЫЛЫҒЫ (ПРОФИЦИТІ) | B40: -2169124.7 | C40: -2811100.6 | D40: -3586041.9 | E40: -1739514.3 | F40: -1525293.3 | G40: V. ДЕФИЦИТ (ПРОФИЦИТ) БЮДЖЕТА
A41: VI. БЮДЖЕТТІҢ МҰНАЙҒА ҚАТЫСТЫ ЕМЕС ТАПШЫЛЫҒЫ (ПРОФИЦИТІ) | B41: -8370502.3 | C41: -8454245.5 | D41: -10784416 | E41: -5556606.1 | F41: -5881059.7 | G41: VI. НЕНЕФТЯНОЙ ДЕФИЦИТ (ПРОФИЦИТ) БЮДЖЕТА
A42: VII. БЮДЖЕТТІҢ ТАПШЫЛЫҒЫН ҚАРЖЫЛАНДЫРУ (ПРОФИЦИТТІ ПАЙДАЛАНУ | B42: 2169124.7 | C42: 2811100.6 | D42: 3586041.9 | E42: 1739514.3 | F42: 1525293.3 | G42: VII. ФИНАНСИРОВАНИЕ ДЕФИЦИТА (ИСПОЛЬЗОВАНИЕ ПРОФИЦИТА) БЮДЖЕТА
A43: Ішкі | B43: 2312930.2 | C43: 3221830.7 | D43: 3293971.1 | E43: 1882679.8 | F43: 1673301.6 | G43: Внутреннее
A44: Түсімдер | B44: 3925848 | C44: 5179541.7 | D44: 5785457.6 | E44: 3692099.2 | F44: 3477623.5 | G44: Поступление
A45: Өтеу | B45: 1612917.7 | C45: 1957711 | D45: 2491486.6 | E45: 1809419.4 | F45: 1804322 | G45: Погашение
... A48: Өтеу | B48: 209770.89 | C48: 662602.27 | D48: 1155152.7 | E48: 198689.08 | F48: 1527454 | G48: Погашение

Sheet табл 4
A1: 4-кесте | G1: Таблица 4
A3: МЕМЛЕКЕТТІК БЮДЖЕТКЕ ТҮСІМДЕР/_x000D_ ПОСТУПЛЕНИЯ В ГОСУДАРСТВЕННЫЙ БЮДЖЕТ
A5: (млн.теңге) | G5: (млн.тенге)
A7: Санаты/ Категория | B7: Сыныбы/ Класс | C7: Сыныпшасы/ Подкласс | D7: Ерешелігі/ Специфика | E7: Атауы | F7: 2025 ж. қаңтар-шілде есеп/_x000D_ январь-июль отчет 2025 г. | G7: Наименование
A8: 1 | B8: 2 | C8: 3 | D8: 4 | E8: 5 | F8: 6 | G8: 7
E9: ТҮСІМДЕР | F9: 16506131 | G9: ПОСТУПЛЕНИЯ
E10: оның ішінде: | G10: в том числе:
E11: КІРІСТЕР | F11: 16361108 | G11: ДОХОДЫ
A12: 1 | B12: L01 Класс дохода | C12: L01 Подкласс дохода | D12: L01 Специфика дохода | E12: Салықтық түсімдер | F12: 12073505 | G12: Налоговые поступления
A13: L01 Категория дохода | B13: 01 | C13: L01 Подкласс дохода | D13: L01 Специфика дохода | E13: Табыс салығы | F13: 4869022.9 | G13: Подоходный налог
A14: L01 Категория дохода | B14: L01 Класс дохода | C14: 1 | D14: L01 Специфика дохода | E14: Корпорациялық табыс салығы | F14: 3277371.7 | G14: Корпоративный подоходный налог
A15: 1 | B15: 01 | C15: 1 | D15: 10 | E15: Мұнай секторы ұйымдарынан түсетін түсімдерді қоспағанда, ірі кәсіпкерлік субъектілерінен – заңды тұлғалардан алынатын корпоративтік табыс салығы | F15: 2237617.7 | G15: Корпоративный подоходный налог с юридических лиц – субъектов крупного предпринимательства, за исключением поступлений от организаций нефтяного сектора
D16: 11 | E16: Ірі кәсіпкерлік субъектілерінен және мұнай секторы ұйымдарынан түсетін түсімдерді қоспағанда, заңды тұлғалардан алынатын корпоративтік табыс салығы | F16: 1039754 | G16: Корпоративный подоходный налог с юридических лиц, за исключением поступлений от субъектов крупного предпринимательства и организаций нефтяного сектора
A17: L01 Категория дохода | B17: L01 Класс дохода | C17: 2 | D17: L01 Специфика дохода | E17: Жеке табыс салығы | F17: 1591651.2 | G17: Индивидуальный подоходный налог
C18: 2 | D18: 01 | E18: Төлем көзінен салық салынатын табыстардан ұсталатын жеке табыс салығы | F18: 1245048.6 | G18: Индивидуальный подоходный налог с доходов, облагаемых у источника выплаты
D19: 02 | E19: Төлем көзінен салық салынбайтын табыстардан ұсталатын жеке табыс салығы | F19: 334477.07 | G19: Индивидуальный подоходный налог с доходов, не облагаемых у источника выплаты
D20: 05 | E20: Төлем көзінен салық салынбайтын шетелдік азаматтар табыстарынан ұсталатын жеке табыс салығы | F20: 12125.509 | G20: Индивидуальный подоходный налог с доходов иностранных граждан, не облагаемых у источника выплаты
A21: L01 Категория дохода | B21: 03 | C21: L01 Подкласс дохода | D21: L01 Специфика дохода | E21: Әлеуметтiк салық | F21: 1042470.7 | G21: Социальный налог
A22: L01 Категория дохода | B22: L01 Класс дохода | C22: 1 | D22: L01 Специфика дохода | E22: Әлеуметтік салық | F22: 1042470.7 | G22: Социальный налог
B23: 03 | C23: 1 | D23: 01 | E23: Әлеуметтік салық | F23: 1042470.7 | G23: Социальный налог
A24: L01 Категория дохода | B24: 04 | C24: L01 Подкласс дохода | D24: L01 Специфика дохода | E24: Меншiкке салынатын салықтар | F24: 437977.17 | G24: Hалоги на собственность
A25: L01 Категория дохода | B25: L01 Класс дохода | C25: 1 | D25: L01 Специфика дохода | E25: Мүлiкке салынатын салықтар | F25: 305262.29 | G25: Hалоги на имущество
B26: 04 | C26: 1 | D26: 01 | E26: Заңды тұлғалардың және жеке кәсіпкерлердің мүлкіне салынатын салық | F26: 291401.58 | G26: Налог на имущество юридических лиц и индивидуальных предпринимателей
D27: 02 | E27: Жеке тұлғалардың мүлкiне салынатын салық | F27: 13860.717 | G27: Hалог на имущество физических лиц
A28: L01 Категория дохода | B28: L01 Класс дохода | C28: 3 | D28: L01 Специфика дохода | E28: Жер салығы | F28: 10114.546 | G28: Земельный налог
C29: 3 | D29: 02 | E29: Жер салығы | F29: 10114.546 | G29: Земельный налог
A30: L01 Категория дохода | B30: L01 Класс дохода | C30: 4 | D30: L01 Специфика дохода | E30: Көлiк құралдарына салынатын салық | F30: 119327.14 | G30: Hалог на транспортные средства
C31: 4 | D31: 01 | E31: Заңды тұлғалардан көлiк құралдарына салынатын салық | F31: 14703.929 | G31: Hалог на транспортные средства с юридических лиц
D32: 02 | E32: Жеке тұлғалардан көлiк құралдарына салынатын салық | F32: 104623.21 | G32: Hалог на транспортные средства с физических лиц
A33: L01 Категория дохода | B33: L01 Класс дохода | C33: 5 | D33: L01 Специфика дохода | E33: Бірыңғай жер салығы | F33: 3273.1892 | G33: Единый земельный налог
C34: 5 | D34: 01 | E34: Бірыңғай жер салығы | F34: 3273.1892 | G34: Единый земельный налог
A35: L01 Категория дохода | B35: 05 | C35: L01 Подкласс дохода | D35: L01 Специфика дохода | E35: Тауарларға, жұмыстарға және қызметтерге салынатын iшкi салықтар | F35: 4393387.2 | G35: Внутренние налоги на товары, работы и услуги
A36: L01 Категория дохода | B36: L01 Класс дохода | C36: 1 | D36: L01 Специфика дохода | E36: Қосылған құн салығы | F36: 3067591.1 | G36: Налог на добавленную стоимость
B37: 05 | C37: 1 | D37: 01 | E37: Қазақстан Республикасының аумағында өндiрiлген тауарларға, орындалған жұмыстарға және көрсетілген қызметтерге салынатын қосылған құн салығы | F37: 1104662.5 | G37: Hалог на добавленную стоимость на произведенные товары, выполненные работы и оказанные услуги на территории Республики Казахстан
D38: 02 | E38: Ресей Федерациясы және Беларусь Республикасының аумағынан импортталатын тауарларға салынатын қосылған құн салығынан басқа, Қазақстан Республикасының аумағына импортталатын тауарларға салынатын қосылған құн салығы | F38: 1107698.1 | G38: Hалог на добавленную стоимость на товары, импортируемые на территорию Республики Казахстан, кроме налога на добавленнуюстоимость на товары, импортируемые с территории Российской Федерации и Республики Беларусь
D39: 04 | E39: Резидент емес үшін қосылған құн салығы | F39: 122175.14 | G39: Налог на добавленную стоимость за нерезидента
D40: 14 | E40: Салық төлеушінің бұрын бюджеттен қайтарылған және салықтық тексеру жүргізу барысында қайтарылуы расталмаған қосылған құн салығының асып кеткен сомасын аударуы (қайтаруы), өсімпұл сомасын аударуы | F40: 4503.0997 | G40: Перечисление (возврат) налогоплательщиком суммы превышения налога на добавленную стоимость, ранее возвращенной из бюджета и не подтвержденной к возврату при проведении налоговой проверки, перечисление суммы пени
D41: 15 | E41: Еуразиялық экономикалық одаққа мүше мемлекеттер аумағынан импортталған тауарларға қосылған құн салығы | F41: 697884.35 | G41: Налог на добавленную стоимость на товары, импортированные стерритории государств-членов Евразийского экономического союза
D42: 16 | E42: Тауарлармен электрондық сауданы жүзеге асыру, жеке тұлғаларға электрондық нысанда қызметтер көрсету кезінде шетелдік компаниялардан түсетін қосылған құн салығы | F42: 30667.93 | G42: Налог на добавленную стоимость с иностранных интернет компаний при осуществлении электронной торговли товарами, оказании услуг в электронной форме физическим лицам
A43: L01 Категория дохода | B43: L01 Класс дохода | C43: 2 | D43: L01 Специфика дохода | E43: Акциздер | F43: 547340.06 | G43: Акцизы
C44: 2 | D44: 74 | E44: Қазақстан Республикасының аумағында өндірілген спирттiң және (немесе) шарап материалының, алкоголь өнімдерінің барлық түрлерi | F44: 68604.868 | G44: Все виды спирта и (или) виноматериала, алкогольной продукции, произведенных на территории Республики Казахстан
D45: 75 | E45: Қазақстан Республикасының аумағында өндірілген темекі өнімдері, жеңiл автомобильдер (арнайы мүгедектігі бар адамдарға арналған, қолмен басқарылатын немесе қолмен басқару бейімдегіші бар автомобильдерден басқа) | F45: 144640 | G45: Табачные изделия, легковые автомобили (кроме автомобилей с ручным управлением или адаптером ручного управления, специально предназначенных для лиц с инвалидностью), произведенные на территории Республики Казахстан
D46: 76 | E46: Қазақстан Республикасының аумағына Еуразиялық экономикалық одаққа мүше мемлекеттердің аумағынан әкелінетін темекі өнімдері | F46: 7013.0455 | G46: Табачные изделия, ввозимые на территорию Республики Казахстан с территории государств-членов Евразийского экономического союза
D47: 77 | E47: Қазақстан Республикасының аумағына Еуразиялық экономикалық одаққа мүше мемлекеттердің аумағынан әкелінетін спирттiң және (немесе) шарап материалының, алкоголь өнімдерінің барлық түрлерi | F47: 9691.7062 | G47: Все виды спирта и (или) виноматериала, алкогольной продукции, ввозимых на территорию Республики Казахстан с территории государств-членов Евразийского экономического союза
D48: 78 | E48: Қазақстан Республикасының аумағына Еуразиялық экономикалық одаққа мүше мемлекеттердің аумағынан әкелінетін акцизделетінөнімнің өзге түрлері | F48: 10.8828 | G48: Прочие виды подакцизной продукции, ввозимой на территорию Республики Казахстан с территории государств-членов Евразийского экономического союза
D49: 79 | E49: Қазақстан Республикасы аумағына Еуразиялық экономикалық одаққа мүше мемлекеттердің аумағынан әкелінетін бензин (авиациялықты қоспағанда) және дизель отыны | F49: 10633.958 | G49: Бензин (за исключением авиационного) и дизельное топливо, ввозимых на территорию Республики Казахстан с территории государств-членов Евразийского экономического союза
D50: 80 | E50: Еуразиялық экономикалық одаққа мүше болып табылмайтын мемлекеттердің аумағынан әкелінетін, Қазақстан Республикасының аумағына импортталатын спирттің және (немесе) шарап материалының, алкоголь өнімдерінің барлық түрлері | F50: 9132.9916 | G50: Все виды спирта и (или) виноматериала, алкогольной продукции, импортируемых на территорию Республики Казахстан с территории государств, не являющихся членами Евразийского экономического союза
D51: 81 | E51: Еуразиялық экономикалық одаққа мүше болып табылмайтын мемлекеттердің аумағынан әкелінетін, Қазақстан Республикасының аумағына импортталатын темекі өнімдері | F51: 29093.108 | G51: Табачные изделия, импортируемые на территорию Республики Казахстан с территории государств, не являющихся членами Евразийского экономического союза
D52: 82 | E52: Еуразиялық экономикалық одаққа мүше болып табылмайтын мемлекеттердің аумағынан әкелінетін, Қазақстан Республикасының аумағына импортталатын акцизделетін өнімдердің өзге түрлері | F52: 2577.8349 | G52: Прочие виды подакцизных продукций, импортируемые на территорию Республики Казахстан с территории государств, не являющихся членами Евразийского экономического союза
D53: 83 | E53: Еуразиялық экономикалық одаққа мүше болып табылмайтын мемлекеттер аумағынан әкелінетін, Қазақстан Республикасының аумағына импортталатын бензин (авиациялықты қоспағанда) және дизель отыны | F53: 71.434439 | G53: Бензин (за исключением авиационного) и дизельное топливо, импортируемых на территорию Республики Казахстан с территориигосударств, не являющихся членами Евразийского экономического союза
D54: 84 | E54: Қазақстан Республикасының аумағында өндірілген және іске асырылған бензин (авиациялық бензинді қоспағанда), дизель отыны, газохол, бензанол, нефрас, жеңіл көмірсутектер қоспалары және экологиялық отыны | F54: 265870.22 | G54: Бензин (за исключением авиационного) и дизельное топливо, газохол, бензанол, нефрас, смеси легких углеводородов и экологическое топливо, произведенных и реализованных на территории Республики Казахстан
A55: L01 Категория дохода | B55: L01 Класс дохода | C55: 3 | D55: L01 Специфика дохода | E55: Табиғи және басқа да ресурстарды пайдаланғаны үшiн түсетiн түсiмдер | F55: 695554.31 | G55: Поступления за использование природных и других ресурсов
C56: 3 | D56: 01 | E56: Қалааралық және (немесе) халықаралық телефон байланысын, сондай-ақ ұялы байланысты бергені үшін төлемақы | F56: 7793.3647 | G56: Плата за предоставление междугородной и (или) международнойтелефонной связи, а также сотовой связи
D57: 02 | E57: Үстеме пайда салығы, мұнай секторы ұйымдарынан түсетін түсімдерден басқа | F57: 155.32398 | G57: Налог на сверхприбыль, за исключением поступлений от организаций нефтяного сектора
D58: 03 | E58: Жерүсті су көздерінің су ресурстарын пайдаланғаны үшін төлемақы | F58: 901.42549 | G58: Плата за пользование водными ресурсами поверхностных источников
D59: 04 | E59: Орманды пайдаланғаны үшiн төлемақы | F59: 1473.9034 | G59: Плата за лесные пользования
D60: 05 | E60: Бонустар, мұнай секторы ұйымдарынан түсетін түсімдерден басқа | F60: 19546.681 | G60: Бонусы, за исключением поступлений от организаций нефтяногосектора
D61: 06 | E61: Пайдалы қазбаларды өндіруге салынатын салық, мұнай секторы ұйымдарынан түсетін түсімдерден басқа | F61: 536314.47 | G61: Налог на добычу полезных ископаемых, за исключением поступлений от организаций нефтяного сектора
D62: 07 | E62: Мұнай секторы ұйымдарынан түсетін түсімдерді қоспағанда, экспортқа салынатын рента салығы | F62: 1792.9649 | G62: Рентный налог на экспорт, за исключением поступлений от организаций нефтяного сектора
D63: 09 | E63: Радиожиілік спектрін пайдаланғаны үшін төлем | F63: 27556.743 | G63: Плата за использование радиочастотного спектра
D64: 11 | E64: Жануарлар дүниесін пайдаланғаны үшін төлем | F64: 1224.8475 | G64: Плата за пользование животным миром
D65: 12 | E65: Мұнай секторы ұйымдарынан түсетін түсімдерді қоспағанда, өнімді бөлу туралы келісімшарт бойынша қызметін жүзеге асыратын жер қойнауын пайдаланушының қосымша төлемі | F65: 0.01176 | G65: Дополнительный платеж недропользователя, осуществляющего деятельность по контракту о разделе продукции, за исключением поступлений от организаций нефтяного сектора
D66: 13 | E66: Республикалық маңызы бар ерекше қорғалатын табиғи аумақтарды пайдаланғаны үшін төлем | F66: 6.7306857 | G66: Плата за использование особо охраняемых природных территорий республиканского значения
D67: 14 | E67: Жергілікті маңызы бар ерекше қорғалатын табиғи аумақтарды пайдаланғаны үшін төлем | F67: 0.67788117 | G67: Плата за использование особо охраняемых природных территорий местного значения
D68: 15 | E68: Жер учаскелерін пайдаланғаны үшін төлем | F68: 15426.986 | G68: Плата за пользование земельными участками
... D71: 19 | E71: Тарихи шығындарды өтеу бойынша төлемдер | F71: 5950.6029 | G71: Платеж по возмещению исторических затрат
A72: L01 Категория дохода | B72: L01 Класс дохода | C72: 4 | D72: L01 Специфика дохода | E72: Кәсiпкерлiк және кәсiби қызметтi жүргiзгенi үшiн алынатын алымдар | F72: 73987.26 | G72: Сборы за ведение предпринимательской и профессиональной деятельности
C73: 4 | D73: 02 | E73: Жекелеген қызмет түрлерімен айналысу құқығы үшін алым (жекелеген қызмет түрлерімен айналысуға арналған лицензияларды бергені үшін алым) | F73: 3227.5213 | G73: Сбор за право занятия отдельными видами деятельности (сбор за выдачу лицензий на занятие отдельными видами деятельности)
D74: 06 | E74: Автокөлік құралдарының Қазақстан Республикасының аумағымен жүріп өткені үшін алым | F74: 10631.722 | G74: Сбор за проезд автотранспортных средств по территории Республики Казахстан
D75: 13 | E75: Телевизия және радио хабарларын тарату ұйымдарына радиожиілік спектрін пайдалануға рұқсат бергені үшін алым | F75: 2.02498 | G75: Сбор за выдачу разрешения на использование радиочастотного спектра телевизионным и радиовещательным организациям
D76: 19 | E76: Сыртқы (көрнекі) жарнаманы аудандық маңызы бар қалалар, ауылдар, кенттер, ауылдық округтер аумақтары арқылы өтетін республикалық маңызы бар жалпыға ортақ пайдаланылатын автомобиль жолдарының бөлiнген белдеуiндегі жарнаманы тұрақты орналастыру объектілерінде орналастырғаны үшін төлемақыны қоспағанда, сыртқы (көрнекi) жарнаманы республикалық маңызы бар жалпыға ортақ пайдаланылатын автомобиль жолдарының бөлiнген белдеу | F76: 4.5993203 | G76: Плата за размещение наружной (визуальной) рекламы на объектах стационарного размещения рекламы в полосе отвода автомобильных дорог общего пользования республиканского значения, заисключением платы за размещение наружной (визуальной) рекламы на объектах стационарного размещения рекламы в полосе отвода автомобильных дорог общего пользования республиканского значения, проходящих через территории городов районного значе
D77: 20 | E77: Сыртқы (көрнекі) жарнаманы аудандық маңызы бар қалалар, ауылдар, кенттер, ауылдық округтер аумақтары арқылы өтетін облыстық маңызы бар жалпыға ортақ пайдаланылатын автомобиль жолдарының бөлiнген белдеуiндегі жарнаманы тұрақты орналастыру объектілерінде орналастырғаны үшін төлемақыны қоспағанда, сыртқы (көрнекi) жарнаманы облыстық маңызы бар жалпыға ортақ пайдаланылатын автомобиль жолдарының бөлiнген белдеуiндегі жарн | F77: 0.226485 | G77: Плата за размещение наружной (визуальной) рекламы на объектах стационарного размещения рекламы в полосе отвода автомобильных дорог общего пользования областного значения, за исключением платы за размещение наружной (визуальной) рекламы на объектах стационарного размещения рекламы в полосе отвода автомобильных дорог общего пользования областного значения, проходящих через территории городов районного значения, сел, по
D78: 24 | E78: Сыртқы (көрнекі) жарнаманы республикалық маңызы бар қаладағы, астанадағы үй-жайлардың шегінен тыс ашық кеңістікте, республикалық маңызы бар қаланың, астананың аумақтары арқылы өтетін жалпыға ортақ пайдаланылатын автомобиль жолдарының бөлінген белдеуінде орналастырғаны үшін төлемақы | F78: 6088.8271 | G78: Плата за размещение наружной (визуальной) рекламы на открытом пространстве за пределами помещений в городе республиканского значения, столице в полосе отвода автомобильных дорог общего пользования, проходящих через территории города республиканского значения, столицы
D79: 25 | E79: Сыртқы (көрнекі) жарнаманы облыстық маңызы бар қаладағы үй-жайлардың шегінен тыс ашық кеңістікте, облыстық маңызы бар қаланың аумағы арқылы өтетін жалпыға ортақ пайдаланылатын автомобиль жолдарының бөлінген белдеуінде орналастырғаны үшін төлемақы | F79: 1274.7752 | G79: Плата за размещение наружной (визуальной) рекламы на открытом пространстве за пределами помещений в городе областного значения, в полосе отвода автомобильных дорог общего пользования, проходящих через территорию города областного значения
D80: 28 | E80: Республикалық бюджетке төленетін тіркелгені үшін алым | F80: 60.693004 | G80: Регистрационный сбор, зачисляемый в республиканский бюджет
D81: 29 | E81: Жергілікті бюджетке төленетін тіркелгені үшін алым | F81: 42440.192 | G81: Регистрационный сбор, зачисляемый в местный бюджет
D82: 30 | E82: Сыртқы (көрнекі) жарнаманы аудандық маңызы бар қаладағы, ауылдағы, кенттегі үй-жайлардың шегінен тыс ашық кеңістікте және аудандық маңызы бар қаланың, ауылдың, кенттің, ауылдық округтің аумақтары арқылы өтетін жалпыға ортақ пайдаланылатын автомобиль жолдарының бөлінген белдеуінде, сондай-ақ елді мекендерден тыс жердегі үй-жайлардың шегінен тыс ашық кеңістікте және жалпыға ортақ пайдаланылатын автомобиль жолдарының б | F82: 206.28267 | G82: Плата за размещение наружной (визуальной) рекламы на открытом пространстве за пределами помещений в городе районного значения, селе, поселке и в полосе отвода автомобильных дорог общего пользования, проходящих через территории города районного значения, села, поселка, сельского округа, а также на открытом пространстве за пределами помещений вне населенных пунктов и вне полосы отвода автомобильных дорог общего пользов
D83: 31 | E83: Микроқаржы ұйымдарын есептік тіркеуден өткізгені және оларды микроқаржы ұйымдарының тізіліміне енгізгені үшін алым | F83: 0 | G83: Сбор за прохождение учетной регистрации микрофинансовых организаций и включение их в реестр микрофинансовых организаций
D84: 32 | E84: Банк және сақтандыру нарықтарына қатысушылар үшін рұқсат беру құжаттарын, келісім бергені үшін алым | F84: 13.2937 | G84: Сбор за выдачу разрешительных документов, согласия для участников банковского и страхового рынков
D85: 33 | E85: Қазақстан Республикасына шетелдік жұмыс күшін тартуға рұқсатты бергені немесе ұзартқаны үшін алым | F85: 4057.5788 | G85: Сбор за выдачу или продление разрешения на привлечение иностранной рабочей силы в Республику Казахстан
... D88: 36 | E88: "Астана" халықаралық қаржы орталығының инвестициялық резиденті болып табылатын шетелдіктің немесе азаматтығы жоқ адамның резиденттігін растайтын құжаттыбергені үшін алым | F88: 84.4461 | G88: Сбор за выдачу документа, подтверждающего резидентство иностранца или лица без гражданства, являющегося инвестиционным резидентом Международного финансового центра «Астана»
A89: L01 Категория дохода | B89: L01 Класс дохода | C89: 5 | D89: L01 Специфика дохода | E89: Ойын бизнесіне салық | F89: 8914.4564 | G89: Налог на игорный бизнес
C90: 5 | D90: 01 | E90: Ойын бизнесіне салық | F90: 8914.4564 | G90: Налог на игорный бизнес
A91: L01 Категория дохода | B91: 06 | C91: L01 Подкласс дохода | D91: L01 Специфика дохода | E91: Халықаралық сауда мен сыртқы операцияларға салынатын салықтар | F91: 1245535.1 | G91: Hалоги на международную торговлю и внешние операции
A92: L01 Категория дохода | B92: L01 Класс дохода | C92: 1 | D92: L01 Специфика дохода | E92: Кеден төлемдерi | F92: 1199236.9 | G92: Таможенные платежи
B93: 06 | C93: 1 | D93: 01 | E93: Еуразиялық экономикалық одақ туралы шартқа сәйкес төленген әкелінетін кедендік баждары (баламалы қолданылатын өзге де баждар, салықтар мен алымдар) | F93: 33103.859 | G93: Ввозные таможенные пошлины (иные пошлины, налоги и сборы, имеющие эквивалентное действие), уплаченные в соответствии с Договором о Евразийском экономическом союзе
D94: 02 | E94: Әкетілетін тауарларға салынатын кедендік баждар | F94: 6872.649 | G94: Таможенные пошлины на вывозимые товары
D95: 04 | E95: Кеден бажының бірыңғай ставкасын қолданумен жеке тұлғалардан өндіріп алынатын жеке пайдалануына әкелінетін тауарларға салынатын кеден баждары, салықтары | F95: 2207.9504 | G95: Таможенные пошлины, налоги на ввозимые физическими лицами товары для личного пользования с применением единых ставок таможенных пошлин, налогов
D96: 05 | E96: Әкелінетін тауарларға жиынтық кедендік төлем | F96: 280.77526 | G96: Совокупный таможенный платеж на ввозимые товары
D97: 06 | E97: Ресей Федерациясымен бөлінген кедендік баж | F97: 227010.88 | G97: Таможенные пошлины, распределенные Российской Федерацией
D98: 07 | E98: Беларусь Республикасымен бөлінген кедендік баж | F98: 13942.893 | G98: Таможенные пошлины, распределенные Республикой Беларусь
D99: 10 | E99: Мұнайға салынатын кедендік әкету бажы | F99: 880766.44 | G99: Вывозные таможенные пошлины на сырую нефть
D100: 11 | E100: Мұнайдан өндірілген тауарларға салынатын кедендік әкету бажы | F100: 16337.423 | G100: Вывозные таможенные пошлины на товары, выработанные из нефти
D101: 12 | E101: Кеден одағында кедендік әкелу баждарын (баламалы қолданысы бар өзге де баждарды, салықтар мен алымдарды) есепке жатқызужәне бөлу тәртібін белгілеу және қолдану туралы келісім күшіне енгенге дейін төлеу жөніндегі міндеті туындаған әкелінетін тауарларға және (немесе) әкелінетін кедендік баждарға арналған кедендік баждар, сондай-ақ жер қойнауын пайдалану саласындағы келісімшарттар шеңберінде, оның ішінде Қазақстан Респ | F101: 2293.43 | G101: Таможенные пошлины на ввозимые товары и (или) ввозные таможенные пошлины, обязанность по уплате которых возникла до вступления в силу Соглашения об установлении и применении в таможенном союзе порядка зачисления и распределения ввозных таможенных пошлин (иных пошлин, налогов и сборов, имеющих эквивалентное действие), а также таможенные пошлины на товары ввозимые в рамках контрактов в сфере недропользования, в том чис
D102: 13 | E102: Армения Республикасымен бөлінген кедендік баждар | F102: 6447.263 | G102: Таможенные пошлины, распределенные Республикой Армения
D103: 17 | E103: Қырғыз Республикасы бөлген кедендік баждар | F103: 9610.9152 | G103: Таможенные пошлины, распределенные Кыргызской Республикой
D104: 19 | E104: Алдағы кедендік баждарды, кедендік алымдарды, салықтарды, арнайы, демпингке қарсы, өтемақы баждарын төлеу есебіне, сондай-ақ кедендік баждарды, салықтарды арнайы, демпингке қарсы,өтемақы баждарын төлеу жөніндегі міндеттің орындалуын қамтамасыз ету ретінде Еуразиялық экономикалық одақтың және Қазақстан Республикасының кеден заңнамасына сәйкес енгізілетін аванстық төлемдер | F104: 362.44901 | G104: Авансовые платежи, вносимые в соответствии с таможенным законодательством Евразийского экономического союза и Республики Казахстан, в счет уплаты предстоящих таможенных платежей, налогов, специальных, антидемпинговых, компенсационных пошлин, а также в качестве обеспечения исполнения обязанности по уплате таможенных пошлин, налогов, специальных, антидемпинговых, компенсационных пошлин
A105: L01 Категория дохода | B105: L01 Класс дохода | C105: 2 | D105: L01 Специфика дохода | E105: Халықаралық сауда мен операцияларға салынатын басқа да салықтар | F105: 46298.184 | G105: Прочие налоги на международную торговлю и операции
C106: 2 | D106: 01 | E106: Қазақстан Республикасының кеден заңнамасына сәйкес төленетін кедендік алымдар | F106: 39217.424 | G106: Таможенные сборы, уплачиваемые в соответствии с таможенным законодательством Республики Казахстан
D107: 02 | E107: Еуразиялық экономикалық одақ туралы шартқа сәйкес төленген арнайы, демпингке қарсы, өтемақы баждары | F107: 788.32311 | G107: Специальные, антидемпинговые, компенсационные пошлины, уплаченные в соответствии с Договором о Евразийском экономическом союзе
...

Sheet табл 5
B2: Кесте 5 | D2: Таблица 5
B3: ШЫҒЫСТАРДЫҢ ВЕДОМСТВОЛЫҚ | D3: ИСПОЛНЕНИЕ ГОСУДАРСТВЕННОГО БЮДЖЕТА
B4: СЫНЫПТАМАСЫ БОЙЫНША | D4: ПО ВЕДОМСТВЕННОЙ
B5: МЕМЛЕКЕТТІК БЮДЖЕТТІҢ АТҚАРАЛУЫ | D5: КЛАССИФИКАЦИИ РАСХОДОВ
B6: (млн. теңге) | D6: (млн. тенге)
B8: Бағдарламалард_x000D_ ың_x000D_ əкімшісі/_x000D_ Администратор_x000D_ программ | C8: Атауы | D8: 2025 ж. қаңтар-шілде есеп/_x000D_ январь-июль 2025 г. | E8: Наименование
B9: 1 | C9: 2 | D9: 3 | E9: 4
C10: БАРЛЫҒЫ | D10: 18031425 | E10: ВСЕГО
B11: 101 | C11: Қазақстан Республикасы Президентінің Әкімшілігі | D11: 10302.321 | E11: Администрация Президента Республики Казахстан
B12: 106 | C12: Адам құқықтары жөніндегі ұлттық орталық | D12: 804.47123 | E12: Национальный центр по правам человека
B13: 107 | C13: Қазақстан Республикасы Жоғары Сот Кеңесінің Аппараты | D13: 1067.4368 | E13: Аппарат Высшего Судебного Совета Республики Казахстан
B14: 109 | C14: Қазақстан Республикасы үкіметінің Аппараты_x000D_ | D14: 3844.9471 | E14: Аппарат Правительства Республики Казахстан
B15: 110 | C15: Облыс мәслихатының аппараты | D15: 1736.6674 | E15: Аппарат маслихата области
B16: 111 | C16: Республикалық маңызы бар қала, астана мәслихатының аппараты | D16: 459.5372 | E16: Аппарат маслихата города республиканского значения, столицы
B17: 112 | C17: Аудан (облыстық маңызы бар қала) мәслихатының аппараты | D17: 8066.6056 | E17: Аппарат маслихата района (города областного значения)
B18: 120 | C18: Облыс әкімінің аппараты | D18: 34273.549 | E18: Аппарат акима области
B19: 121 | C19: Республикалық маңызы бар қала, астана әкімінің аппараты | D19: 5724.7868 | E19: Аппарат акима города республиканского значения, столицы
B20: 122 | C20: Аудан (облыстық маңызы бар қала) әкімінің аппараты | D20: 62260.456 | E20: Аппарат акима района (города областного значения)
B21: 123 | C21: Қаладағы аудан, аудандық маңызы бар қала, кент, ауыл, ауылдық округ әкімінің аппараты | D21: 265552.38 | E21: Аппарат акима района в городе, города районного значения, поселка, села, сельского округа
B22: 124 | C22: Аудандық маңызы бар қала, ауыл, кент, ауылдық округ әкімінің аппараты | D22: 202072.2 | E22: Аппарат акима города районного значения, села, поселка, сельского округа
... B224: 821 | C224: Ауданның (облыстық маңызы бар қаланың) қоғамдық даму бөлімі | D224: 762.1748 | E224: Отдел общественного развития района (города областного значения)

Sheet табл 6
A1: 6-кесте | D1: Таблица 6
A2: ШЫҒЫНДАРДЫҢ ЭКОНОМИКАЛЫҚ ЖІКТЕМЕСІ | D2: ИСПОЛНЕНИЕ ГОСУДАРСТВЕННОГО БЮДЖЕТА ПО
A3: БОЙЫНША МЕМЛЕКЕТТІК БЮДЖЕТТІК ОРЫНДАЛУЫ | D3: ЭКОНОМИЧЕСКОЙ КЛАССИФИКАЦИИ РАСХОДОВ
A4: (млн.теңге) | D4: (млн.тенге)
A5: Cанаты/_x000D_ Категория | B5: Iшкi сыныбы/_x000D_ Подкласс | C5: Атауы | D5: 2025 ж. қаңтар-шілде/январь-июль отчет 2025 г. | E5: Наименование
A7: 1 | B7: 2 | C7: 3 | D7: 4 | E7: 5
C8: БАРЛЫҒЫ | D8: 18031425 | E8: ВСЕГО
A9: 1 | C9: Ағымдағы шығындар | D9: 15371617 | E9: Текущие затраты
A10: 1 | B10: 110 | C10: Жалақы | D10: 2755362.3 | E10: Заработная плата
B11: 120 | C11: Жұмыс берушілердің жарналары | D11: 261271.42 | E11: Взносы работодателей
B12: 130 | C12: Қазақстан Республикасының заңнамалық актілеріне сәйкес азаматтардың жекелеген санаттарына жалақы төлеу және жарналар аудару | D12: 108909.95 | E12: Выплата заработной платы отдельным категориям граждан и отчисления взносов в соответствии с законодательными актами Республики Казахстан
B13: 140 | C13: Қорлар сатып алу | D13: 236901.77 | E13: Приобретение запасов
B14: 150 | C14: Қызметтер мен жұмыстарды сатып алу | D14: 2815634.4 | E14: Приобретение услуг и работ
B15: 160 | C15: Басқа да ағымдағы шығындар | D15: 1260790.4 | E15: Другие текущие затраты
B16: 170 | C16: Мемлекеттік емес қарыздар бойынша шығыстарды өтеу | D16: 25693.549 | E16: Возмещение расходов по негосударственным займам
B17: 210 | C17: Ішкі қарыздар бойынша сыйақы төлемдері | D17: 1797503.7 | E17: Выплаты вознаграждений по внутренним займам
B18: 220 | C18: Сыртқы заемдар бойынша сыйақылар төлеу | D18: 237711.73 | E18: Выплаты вознаграждений по внешним займам
B19: 310 | C19: Бюджеттік субсидиялар | D19: 1023959.7 | E19: Бюджетные субсидии
B20: 320 | C20: Жеке тұлғаларға берілетін трансферттер | D20: 3957426.2 | E20: Трансферты физическим лицам
B21: 340 | C21: Шетелге берiлетiн ағымдағы трансферттер | D21: 16651.768 | E21: Текущие трансферты за границу
B22: 360 | C22: Нысаналы жарна | D22: 873800 | E22: Целевой взнос
A23: 2 | C23: Күрделі шығындар | D23: 1985666.2 | E23: Капитальные затраты
A24: 2 | B24: 410 | C24: Негiзгi құралдарды, материалдық емес және биологиялық активтерді сатып алу | D24: 346961.39 | E24: Приобретение основных средств, нематериальных и биологических активов
B25: 420 | C25: Негізгі қаражатты күрделі жөндеу | D25: 236643.2 | E25: Капитальный ремонт основных средств
B26: 430 | C26: Дамуға бағытталған күрделі шығындар | D26: 1402061.6 | E26: Капитальные затраты, направленные на развитие
A27: 3 | C27: Бюджеттік кредиттер | D27: 281409.96 | E27: Бюджетные кредиты
A28: 3 | B28: 510 | C28: Ішкі бюджеттік кредиттер | D28: 281409.96 | E28: Внутренние бюджетные кредиты
A29: 4 | C29: Қаржы активтерін сатып алу | D29: 298697.01 | E29: Приобретение финансовых активов
A30: 4 | B30: 610 | C30: Қаржы активтерін сатып алу | D30: 298559.68 | E30: Приобретение финансовых активов
B31: 620 | C31: Елден тысқары жерлерден қаржы активтерін сатып алу | D31: 137.32896 | E31: Приобретение финансовых активов за пределами страны
A32: 6 | C32: Мемлекеттік-жекешелік әріптестік жобалар бойынша мемлекеттік міндеттемелерді орындау | D32: 94034.599 | E32: Выполнение государственных обязательств по проектам государственно-частного партнерства
A33: 6 | B33: 810 | C33: Мемлекеттік концессиялық міндеттемелерді орындау | D33: 94034.599 | E33: Выполнение государственных концессионных обязательств

Sheet табл 7
A1: 7-кесте | E1: Таблица 7
A2: РЕСПУБЛИКАЛЫҚ БЮДЖЕТТІҢ АТҚАРЫЛУЫ | E2: ИСПОЛНЕНИЕ РЕСПУБЛИКАНСКОГО БЮДЖЕТА
A3: (млн.теңге) | E3: (млн. тенге)
A5: Атауы | B5: 2022 ж. есеп/ 2022 г. отчет | C5: 2023 ж. есеп/ 2023 г. отчет | D5: 2024 ж. есеп/ 2024 г. отчет | F5: 2025 ж. қантар-шілде есеп/январь-июль отчет 2025 г. | G5: Наименование
D6: жылдық/ годовой | E6: қантар-шілде/январь-июль
A7: 1 | B7: 2 | C7: 3 | D7: 4 | E7: 5 | F7: 6 | G7: 7
A8: I. КІРІСТЕР | B8: 15963398 | C8: 19037979 | D8: 19624012 | E8: 10266523 | F8: 11543427 | G8: I. ДОХОДЫ
A9: Салықтық түсімдер_x000D_ оның iшiнде: | B9: 10026825 | C9: 12912428 | D9: 12307810 | E9: 6068667 | F9: 7239542.7 | G9: Налоговые поступления,_x000D_ в том числе:
A10: корпорациялық табыс салығы | B10: 2920802.8 | C10: 3889594.5 | D10: 3653190.8 | E10: 1783905.2 | F10: 2237617.7 | G10: корпоративный подоходный налог
A11: қосылған құн салығы | B11: 4226358.8 | C11: 5674110.6 | D11: 5179378.1 | E11: 2508711.3 | F11: 3067591.1 | G11: налог на добавленную стоимость
A12: акциздер | B12: 153619.22 | C12: 161890.43 | D12: 125189.66 | E12: 69445.916 | F12: 68224.961 | G12: акцизы
A13: Салықтық емес түсімдер | B13: 438204.42 | C13: 1617610.1 | D13: 1201438.2 | E13: 876897.02 | F13: 459781.24 | G13: Неналоговые поступления
A14: Негізгі капиталды сатудан түсетін түсімдер | B14: 6954.9546 | C14: 735.69631 | D14: 6170.4309 | E14: 4684.4031 | F14: 2062.5326 | G14: Поступления от продажи основного капитала
A15: Трансферттердің түсімдері | B15: 5491414.1 | C15: 4507205 | D15: 6108593.6 | E15: 3316274.8 | F15: 3842040.4 | G15: Поступления трансфертов
A16: II. ШЫҒЫНДАР | B16: 17791797 | C16: 21547819 | D16: 23106552 | E16: 12953781 | F16: 13382506 | G16: II. ЗАТРАТЫ
A17: 1. Жалпы сипаттағы мемлекеттiк қызметтер | B17: 1047844 | C17: 1137687.2 | D17: 1293447.3 | E17: 641631.58 | F17: 597063.17 | G17: 1. Государственные услуги общего характера
A18: 2. Қорғаныс | B18: 1073075.9 | C18: 1100070.9 | D18: 1038491.2 | E18: 520472.5 | F18: 484052.08 | G18: 2. Оборона
A19: 3. Қоғамдық тәртіп, қауіпсіздік, құқықтық, сот, қылмыстық-атқару қызметі | B19: 1074316.3 | C19: 1275903.8 | D19: 1287986.9 | E19: 643346.68 | F19: 682846.03 | G19: 3. Общественный порядок, безопасность, правовая, судебная, уголовно-исполнительная деятельность
... A45: Өтеу | B45: 208253.95 | C45: 660721.39 | D45: 1154283.9 | E45: 197820.32 | F45: 1527454 | G45: Погашение

Sheet табл 8 (дох)
B2: 8-кесте | H2: Таблица 8
F3: РЕСПУБЛИКАЛЫҚ БЮДЖЕТТІҢ АТҚАРЫЛУЫ/ ИСПОЛНЕНИЕ РЕСПУБЛИКАНСКОГО БЮДЖЕТА
B4: (млн.теңге) | H4: (млн.тенге)
B5: Санаты/ Категория | C5: Сыныбы/ Класс | D5: Сыныпшасы/ Подкласс | E5: Ерешелігі/ Специфика | F5: Атауы | G5: 2025 ж. қаңтар-шілде есеп/_x000D_ январь-июль отчет 2025 г. | H5: Наименование
B6: 1 | C6: 2 | D6: 3 | E6: 4 | F6: 5 | G6: 6 | H6: 7
F7: ТҮСІМДЕР | G7: 11692016 | H7: ПОСТУПЛЕНИЯ
F8: оның ішінде: | H8: в том числе:
F9: КІРІСТЕР | G9: 11543427 | H9: ДОХОДЫ
B10: 1 | F10: Салықтық түсімдер | G10: 7239542.7 | H10: Налоговые поступления
C11: 01 | F11: Табыс салығы | G11: 2237617.7 | H11: Подоходный налог
D12: 1 | F12: Корпорациялық табыс салығы | G12: 2237617.7 | H12: Корпоративный подоходный налог
B13: 1 | C13: 01 | D13: 1 | E13: 10 | F13: Мұнай секторы ұйымдарынан түсетін түсімдерді қоспағанда, ірі кәсіпкерлік субъектілерінен – заңды тұлғалардан алынатын корпоративтік табыс салығы | G13: 2237617.7 | H13: Корпоративный подоходный налог с юридических лиц – субъектов крупного предпринимательства, за исключением поступлений от организаций нефтяного сектора
C14: 05 | F14: Тауарларға, жұмыстарға және қызметтерге салынатын iшкi салықтар | G14: 3751789.7 | H14: Внутренние налоги на товары, работы и услуги
D15: 1 | F15: Қосылған құн салығы | G15: 3067591.1 | H15: Налог на добавленную стоимость
C16: 05 | D16: 1 | E16: 01 | F16: Қазақстан Республикасының аумағында өндiрiлген тауарларға, орындалған жұмыстарға және көрсетілген қызметтерге салынатын қосылған құн салығы | G16: 1104662.5 | H16: Hалог на добавленную стоимость на произведенные товары, выполненные работы и оказанные услуги на территории Республики Казахстан
E17: 02 | F17: Ресей Федерациясы және Беларусь Республикасының аумағынан импортталатын тауарларға салынатын қосылған құн салығынан басқа, Қазақстан Республикасының аумағына импортталатын тауарларға салынатын қосылған құн салығы | G17: 1107698.1 | H17: Hалог на добавленную стоимость на товары, импортируемые на территорию Республики Казахстан, кроме налога на добавленнуюстоимость на товары, импортируемые с территории Российской Федерации и Республики Беларусь
E18: 04 | F18: Резидент емес үшін қосылған құн салығы | G18: 122175.14 | H18: Налог на добавленную стоимость за нерезидента
E19: 14 | F19: Салық төлеушінің бұрын бюджеттен қайтарылған және салықтық тексеру жүргізу барысында қайтарылуы расталмаған қосылған құн салығының асып кеткен сомасын аударуы (қайтаруы), өсімпұл сомасын аударуы | G19: 4503.0997 | H19: Перечисление (возврат) налогоплательщиком суммы превышения налога на добавленную стоимость, ранее возвращенной из бюджета и не подтвержденной к возврату при проведении налоговой проверки, перечисление суммы пени
E20: 15 | F20: Еуразиялық экономикалық одаққа мүше мемлекеттер аумағынан импортталған тауарларға қосылған құн салығы | G20: 697884.35 | H20: Налог на добавленную стоимость на товары, импортированные стерритории государств-членов Евразийского экономического союза
E21: 16 | F21: Тауарлармен электрондық сауданы жүзеге асыру, жеке тұлғаларға электрондық нысанда қызметтер көрсету кезінде шетелдік компаниялардан түсетін қосылған құн салығы | G21: 30667.93 | H21: Налог на добавленную стоимость с иностранных интернет компаний при осуществлении электронной торговли товарами, оказании услуг в электронной форме физическим лицам
D22: 2 | F22: Акциздер | G22: 68224.961 | H22: Акцизы
D23: 2 | E23: 76 | F23: Қазақстан Республикасының аумағына Еуразиялық экономикалық одаққа мүше мемлекеттердің аумағынан әкелінетін темекі өнімдері | G23: 7013.0455 | H23: Табачные изделия, ввозимые на территорию Республики Казахстан с территории государств-членов Евразийского экономического союза
E24: 77 | F24: Қазақстан Республикасының аумағына Еуразиялық экономикалық одаққа мүше мемлекеттердің аумағынан әкелінетін спирттiң және (немесе) шарап материалының, алкоголь өнімдерінің барлық түрлерi | G24: 9691.7062 | H24: Все виды спирта и (или) виноматериала, алкогольной продукции, ввозимых на территорию Республики Казахстан с территории государств-членов Евразийского экономического союза
E25: 78 | F25: Қазақстан Республикасының аумағына Еуразиялық экономикалық одаққа мүше мемлекеттердің аумағынан әкелінетін акцизделетінөнімнің өзге түрлері | G25: 10.8828 | H25: Прочие виды подакцизной продукции, ввозимой на территорию Республики Казахстан с территории государств-членов Евразийского экономического союза
E26: 79 | F26: Қазақстан Республикасы аумағына Еуразиялық экономикалық одаққа мүше мемлекеттердің аумағынан әкелінетін бензин (авиациялықты қоспағанда) және дизель отыны | G26: 10633.958 | H26: Бензин (за исключением авиационного) и дизельное топливо, ввозимых на территорию Республики Казахстан с территории государств-членов Евразийского экономического союза
E27: 80 | F27: Еуразиялық экономикалық одаққа мүше болып табылмайтын мемлекеттердің аумағынан әкелінетін, Қазақстан Республикасының аумағына импортталатын спирттің және (немесе) шарап материалының, алкоголь өнімдерінің барлық түрлері | G27: 9132.9916 | H27: Все виды спирта и (или) виноматериала, алкогольной продукции, импортируемых на территорию Республики Казахстан с территории государств, не являющихся членами Евразийского экономического союза
E28: 81 | F28: Еуразиялық экономикалық одаққа мүше болып табылмайтын мемлекеттердің аумағынан әкелінетін, Қазақстан Республикасының аумағына импортталатын темекі өнімдері | G28: 29093.108 | H28: Табачные изделия, импортируемые на территорию Республики Казахстан с территории государств, не являющихся членами Евразийского экономического союза
E29: 82 | F29: Еуразиялық экономикалық одаққа мүше болып табылмайтын мемлекеттердің аумағынан әкелінетін, Қазақстан Республикасының аумағына импортталатын акцизделетін өнімдердің өзге түрлері | G29: 2577.8349 | H29: Прочие виды подакцизных продукций, импортируемые на территорию Республики Казахстан с территории государств, не являющихся членами Евразийского экономического союза
E30: 83 | F30: Еуразиялық экономикалық одаққа мүше болып табылмайтын мемлекеттер аумағынан әкелінетін, Қазақстан Республикасының аумағына импортталатын бензин (авиациялықты қоспағанда) және дизель отыны | G30: 71.434439 | H30: Бензин (за исключением авиационного) и дизельное топливо, импортируемых на территорию Республики Казахстан с территориигосударств, не являющихся членами Евразийского экономического союза
D31: 3 | F31: Табиғи және басқа да ресурстарды пайдаланғаны үшiн түсетiн түсiмдер | G31: 596259.49 | H31: Поступления за использование природных и других ресурсов
D32: 3 | E32: 01 | F32: Қалааралық және (немесе) халықаралық телефон байланысын, сондай-ақ ұялы байланысты бергені үшін төлемақы | G32: 7793.3647 | H32: Плата за предоставление междугородной и (или) международнойтелефонной связи, а также сотовой связи
E33: 02 | F33: Үстеме пайда салығы, мұнай секторы ұйымдарынан түсетін түсімдерден басқа | G33: 155.32398 | H33: Налог на сверхприбыль, за исключением поступлений от организаций нефтяного сектора
E34: 05 | F34: Бонустар, мұнай секторы ұйымдарынан түсетін түсімдерден басқа | G34: 19546.681 | H34: Бонусы, за исключением поступлений от организаций нефтяногосектора
E35: 06 | F35: Пайдалы қазбаларды өндіруге салынатын салық, мұнай секторы ұйымдарынан түсетін түсімдерден басқа | G35: 536314.47 | H35: Налог на добычу полезных ископаемых, за исключением поступлений от организаций нефтяного сектора
E36: 07 | F36: Мұнай секторы ұйымдарынан түсетін түсімдерді қоспағанда, экспортқа салынатын рента салығы | G36: 1792.9649 | H36: Рентный налог на экспорт, за исключением поступлений от организаций нефтяного сектора
E37: 09 | F37: Радиожиілік спектрін пайдаланғаны үшін төлем | G37: 27556.743 | H37: Плата за использование радиочастотного спектра
E38: 12 | F38: Мұнай секторы ұйымдарынан түсетін түсімдерді қоспағанда, өнімді бөлу туралы келісімшарт бойынша қызметін жүзеге асыратын жер қойнауын пайдаланушының қосымша төлемі | G38: 0.01176 | H38: Дополнительный платеж недропользователя, осуществляющего деятельность по контракту о разделе продукции, за исключением поступлений от организаций нефтяного сектора
E39: 13 | F39: Республикалық маңызы бар ерекше қорғалатын табиғи аумақтарды пайдаланғаны үшін төлем | G39: 6.7306857 | H39: Плата за использование особо охраняемых природных территорий республиканского значения
E40: 17 | F40: Цифрлық майнинг үшін төлемақы | G40: 3093.2012 | H40: Плата за цифровой майнинг
D41: 4 | F41: Кәсiпкерлiк және кәсiби қызметтi жүргiзгенi үшiн алынатын алымдар | G41: 10799.642 | H41: Сборы за ведение предпринимательской и профессиональной деятельности
D42: 4 | E42: 06 | F42: Автокөлік құралдарының Қазақстан Республикасының аумағымен жүріп өткені үшін алым | G42: 10631.722 | H42: Сбор за проезд автотранспортных средств по территории Республики Казахстан
E43: 13 | F43: Телевизия және радио хабарларын тарату ұйымдарына радиожиілік спектрін пайдалануға рұқсат бергені үшін алым | G43: 2.02498 | H43: Сбор за выдачу разрешения на использование радиочастотного спектра телевизионным и радиовещательным организациям
E44: 19 | F44: Сыртқы (көрнекі) жарнаманы аудандық маңызы бар қалалар, ауылдар, кенттер, ауылдық округтер аумақтары арқылы өтетін республикалық маңызы бар жалпыға ортақ пайдаланылатын автомобиль жолдарының бөлiнген белдеуiндегі жарнаманы тұрақты орналаст | G44: 4.5993203 | H44: Плата за размещение наружной (визуальной) рекламы на объектах стационарного размещения рекламы в полосе отвода автомобильных дорог общего пользования республиканского значения, заисключением платы за размещение наружной (визуальной) реклам
E45: 28 | F45: Республикалық бюджетке төленетін тіркелгені үшін алым | G45: 60.693004 | H45: Регистрационный сбор, зачисляемый в республиканский бюджет
E46: 31 | F46: Микроқаржы ұйымдарын есептік тіркеуден өткізгені және оларды микроқаржы ұйымдарының тізіліміне енгізгені үшін алым | G46: 0 | H46: Сбор за прохождение учетной регистрации микрофинансовых организаций и включение их в реестр микрофинансовых организаций
E47: 32 | F47: Банк және сақтандыру нарықтарына қатысушылар үшін рұқсат беру құжаттарын, келісім бергені үшін алым | G47: 13.2937 | H47: Сбор за выдачу разрешительных документов, согласия для участников банковского и страхового рынков
E48: 35 | F48: Азаматтық авиация саласындағы уәкілетті ұйым Қазақстан Республикасының әуе кеңістігін пайдалануды және авиация қызметінреттейтін Қазақстан Республикасының заңнамасында белгіленген сертификаттау талаптарына сәйкестігіне беретін сертификатта | G48: 2.862496 | H48: Сбор за выдачу сертификатов, выдаваемых уполномоченной организацией в сфере гражданской авиации, на соответствие сертификационным требованиям, установленным законодательством Республики Казахстан и деятельность авиации
E49: 36 | F49: "Астана" халықаралық қаржы орталығының инвестициялық резиденті болып табылатын шетелдіктің немесе азаматтығы жоқ адамның резиденттігін растайтын құжаттыбергені үшін алым | G49: 84.4461 | H49: Сбор за выдачу документа, подтверждающего резидентство иностранца или лица без гражданства, являющегося инвестиционным резидентом Международного финансового центра «Астана»
D50: 5 | F50: Ойын бизнесіне салық | G50: 8914.4564 | H50: Налог на игорный бизнес
D51: 5 | E51: 01 | F51: Ойын бизнесіне салық | G51: 8914.4564 | H51: Налог на игорный бизнес
C52: 06 | F52: Халықаралық сауда мен сыртқы операцияларға салынатын салықтар | G52: 1245535.1 | H52: Hалоги на международную торговлю и внешние операции
D53: 1 | F53: Кеден төлемдерi | G53: 1199236.9 | H53: Таможенные платежи
C54: 06 | D54: 1 | E54: 01 | F54: Еуразиялық экономикалық одақ туралы шартқа сәйкес төленген әкелінетін кедендік баждары (баламалы қолданылатын өзге де баждар, салықтар мен алымдар) | G54: 33103.859 | H54: Ввозные таможенные пошлины (иные пошлины, налоги и сборы, имеющие эквивалентное действие), уплаченные в соответствии с Договором о Евразийском экономическом союзе
E55: 02 | F55: Әкетілетін тауарларға салынатын кедендік баждар | G55: 6872.649 | H55: Таможенные пошлины на вывозимые товары
E56: 04 | F56: Кеден бажының бірыңғай ставкасын қолданумен жеке тұлғалардан өндіріп алынатын жеке пайдалануына әкелінетін тауарларға салынатын кеден баждары, салықтары | G56: 2207.9504 | H56: Таможенные пошлины, налоги на ввозимые физическими лицами товары для личного пользования с применением единых ставок таможенных пошлин, налогов
E57: 05 | F57: Әкелінетін тауарларға жиынтық кедендік төлем | G57: 280.77526 | H57: Совокупный таможенный платеж на ввозимые товары
E58: 06 | F58: Ресей Федерациясымен бөлінген кедендік баж | G58: 227010.88 | H58: Таможенные пошлины, распределенные Российской Федерацией
E59: 07 | F59: Беларусь Республикасымен бөлінген кедендік баж | G59: 13942.893 | H59: Таможенные пошлины, распределенные Республикой Беларусь
E60: 10 | F60: Мұнайға салынатын кедендік әкету бажы | G60: 880766.44 | H60: Вывозные таможенные пошлины на сырую нефть
E61: 11 | F61: Мұнайдан өндірілген тауарларға салынатын кедендік әкету бажы | G61: 16337.423 | H61: Вывозные таможенные пошлины на товары, выработанные из нефти
E62: 12 | F62: Кеден одағында кедендік әкелу баждарын (баламалы қолданысы бар өзге де баждарды, салықтар мен алымдарды) есепке жатқызужәне бөлу тәртібін белгілеу және қолдану туралы келісім күшіне енгенге дейін төлеу жөніндегі міндеті туындаған әкелінеті | G62: 2293.43 | H62: Таможенные пошлины на ввозимые товары и (или) ввозные таможенные пошлины, обязанность по уплате которых возникла до вступления в силу Соглашения об установлении и применении в таможенном союзе порядка зачисления и распределения ввозных тамо
E63: 13 | F63: Армения Республикасымен бөлінген кедендік баждар | G63: 6447.263 | H63: Таможенные пошлины, распределенные Республикой Армения
E64: 17 | F64: Қырғыз Республикасы бөлген кедендік баждар | G64: 9610.9152 | H64: Таможенные пошлины, распределенные Кыргызской Республикой
E65: 19 | F65: Алдағы кедендік баждарды, кедендік алымдарды, салықтарды, арнайы, демпингке қарсы, өтемақы баждарын төлеу есебіне, сондай-ақ кедендік баждарды, салықтарды арнайы, демпингке қарсы,өтемақы баждарын төлеу жөніндегі міндеттің орындалуын қамтам | G65: 362.44901 | H65: Авансовые платежи, вносимые в соответствии с таможенным законодательством Евразийского экономического союза и Республики Казахстан, в счет уплаты предстоящих таможенных платежей, налогов, специальных, антидемпинговых, компенсационных пошлин
D66: 2 | F66: Халықаралық сауда мен операцияларға салынатын басқа да салықтар | G66: 46298.184 | H66: Прочие налоги на международную торговлю и операции
D67: 2 | E67: 01 | F67: Қазақстан Республикасының кеден заңнамасына сәйкес төленетін кедендік алымдар | G67: 39217.424 | H67: Таможенные сборы, уплачиваемые в соответствии с таможенным законодательством Республики Казахстан
E68: 02 | F68: Еуразиялық экономикалық одақ туралы шартқа сәйкес төленген арнайы, демпингке қарсы, өтемақы баждары | G68: 788.32311 | H68: Специальные, антидемпинговые, компенсационные пошлины, уплаченные в соответствии с Договором о Евразийском экономическом союзе
E69: 05 | F69: Беларусь Республикасынан түсетін арнайы, демпингке қарсы, өтемақы баждары | G69: 306.08149 | H69: Специальные, антидемпинговые, компенсационные пошлины, поступившие от Республики Беларусь
E70: 06 | F70: Ресей Федерациясынан түсетін арнайы, демпингке қарсы, өтемақы баждары | G70: 5719.7426 | H70: Специальные, антидемпинговые, компенсационные пошлины, поступившие от Российской Федерации
E71: 08 | F71: Бөлуге жатпайтын арнайы, демпингке қарсы, өтемақы баждары | G71: 0.8072952 | H71: Специальные, антидемпинговые, компенсационные пошлины, не подлежащие распределению
E72: 09 | F72: Армения Республикасынан түсетін арнайы, демпингке қарсы, өтемақы баждары | G72: 73.728041 | H72: Специальные, антидемпинговые, компенсационные пошлины, поступившие от Республики Армения
E73: 11 | F73: Қырғыз Республикасынан түскен арнайы, демпингке қарсы, өтемақы баждары | G73: 192.07683 | H73: Специальные, антидемпинговые, компенсационные пошлины, поступившие от Кыргызской Республики
C74: 07 | F74: Басқа да салықтар | G74: 1696.5371 | H74: Прочие налоги
D75: 1 | F75: Басқа да салықтар | G75: 1696.5371 | H75: Прочие налоги
C76: 07 | D76: 1 | E76: 09 | F76: Республикалық бюджетке түсетін өзге де салық түсiмдері | G76: 1696.5371 | H76: Прочие налоговые поступления в республиканский бюджет
C77: 08 | F77: Заңдық мәнді іс-әрекеттерді жасағаны және (немесе) оған уәкілеттігі бар мемлекеттік органдар немесе лауазымды адамдар құжаттар бергені үшін алынатын міндетті төлемдер | G77: 2903.6062 | H77: Обязательные платежи, взимаемые за совершение юридически значимых действий и (или) выдачу документов, уполномоченными на то государственными органами или должностными лицами
D78: 1 | F78: Мемлекеттік баж | G78: 2903.6062 | H78: Государственная пошлина
C79: 08 | D79: 1 | E79: 01 | F79: Консулдық алым | G79: 2252.5553 | H79: Консульский сбор
E80: 25 | F80: Республикалық бюджетке төленетін мемлекеттік баж | G80: 651.05087 | H80: Государственная пошлина, зачисляемая в республиканский бюджет
B81: 2 | F81: Салықтық емес түсiмдер | G81: 459781.24 | H81: Неналоговые поступления
C82: 01 | F82: Кәсiпкерлiк қызмет пен меншiктен түсетiн кiрiстер | G82: 253110.4 | H82: Доходы от государственной собственности
D83: 1 | F83: Мемлекеттік кәсіпорындардың таза кірісі бөлігінің түсімдері | G83: 10866.331 | H83: Поступления части чистого дохода государственных предприятий
B84: 2 | C84: 01 | D84: 1 | E84: 01 | F84: Республикалық мемлекеттік кәсіпорындардың таза кірісінің бір бөлігінің түсімдері | G84: 10866.331 | H84: Поступления части чистого дохода республиканских государственных предприятий
D85: 3 | F85: Мемлекет меншігіндегі акциялардың мемлекеттік пакеттеріне дивидендтер | G85: 162096.99 | H85: Дивиденды на государственные пакеты акций, находящиеся в государственной собственности
D86: 3 | E86: 01 | F86: Республика меншіктегі акциялардың мемлекеттік пакеттеріне дивидендтер | G86: 162096.99 | H86: Дивиденды на государственные пакеты акций, находящиеся в республиканской собственности
D87: 4 | F87: Мемлекет меншігіндегі, заңды тұлғалардағы қатысу үлесіне кірістер | G87: 711.84948 | H87: Доходы на доли участия в юридических лицах, находящиеся в государственной собственности
D88: 4 | E88: 01 | F88: Республикалық меншіктегі заңды тұлғаларға қатысу үлесіне кірістер | G88: 711.84948 | H88: Доходы на доли участия в юридических лицах, находящиеся в республиканской собственности
D89: 5 | F89: Мемлекет меншігіндегі мүлікті жалға беруден түсетін кірістер | G89: 53381.525 | H89: Доходы от аренды имущества, находящегося в государственной собственности
D90: 5 | E90: 01 | F90: Республика меншіктегі мүлікті жалға беруден түсетін кірістер | G90: 2799.1158 | H90: Доходы от аренды имущества, находящегося в республиканскойсобственности
E91: 02 | F91: Әскери полигондарды пайдаланғаны үшін жалгерлік төлемнен түсетін түсімдер | G91: 5297.417 | H91: Поступления арендной платы за пользование военными полигонами
E92: 03 | F92: «Байқоныр» кешенін пайдаланғаны үшін жалгерлік төлемнен түсетін түсімдер | G92: 45284.993 | H92: Поступления арендной платы за пользование комплексом «Байконур»
D93: 6 | F93: Бюджет қаражатын банк шоттарына орналастырғаны үшін сыйақылар | G93: 2583.9266 | H93: Вознаграждения за размещение бюджетных средств на банковских счетах
D94: 6 | E94: 01 | F94: Қазақстан Республикасы Үкіметінің Қазақстан Республикасы Ұлттық банкіндегі депозиттері бойынша және бірыңғай қазынашылық шоттағы ақшаның күн сайынғы қалдығына сыйақылар | G94: 2583.9266 | H94: Вознаграждения по депозитам Правительства Республики Казахстан в Национальном Банке Республики Казахстан и на ежедневный остаток денег на едином казначейском счете
D95: 7 | F95: Мемлекеттік бюджеттен берілген кредиттер бойынша сыйақылар | G95: 893.19561 | H95: Вознаграждения по кредитам, выданным из государственного бюджета
D96: 7 | E96: 01 | F96: Облыстардың, республикалық маңызы бар қаланың, астананың жергілікті атқарушы органдарына ішкі көздер есебінен республикалық бюджеттен берілген бюджеттік кредиттер бойынша сыйақылар | G96: 65.372991 | H96: Вознаграждения по бюджетным кредитам, выданным из республиканского бюджета за счет внутренних источников местным исполнительным органам областей, города республиканского значения,столицы
E97: 02 | F97: Облыстардың, республикалық маңызы бар қаланың, астананың жергілікті атқарушы органдарына үкіметтік сыртқы қарыздар қаражаты есебінен республикалық бюджеттен берілген бюджеттік кредиттер бойынша сыйақылар | G97: 38.871187 | H97: Вознаграждения по бюджетным кредитам, выданным из республиканского бюджета за счет средств правительственных внешних займов местным исполнительным органам областей, города республиканского значения, столицы
E98: 04 | F98: Мамандандырылған ұйымдарға ішкі көздер есебінен республикалық бюджеттен берілген бюджеттік кредиттер бойынша сыйақылар | G98: 726.49041 | H98: Вознаграждения по бюджетным кредитам, выданным из республиканского бюджета за счет внутренних источников специализированным организациям
E99: 10 | F99: Заңды тұлғаларға үкіметтік сыртқы қарыздар қаражаты есебінен республикалық бюджеттен 2005 жылға дейін берілген бюджеттік кредиттер бойынша сыйақылар | G99: 49.837598 | H99: Вознаграждения по бюджетным кредитам, выданным из республиканского бюджета до 2005 года за счет средств правительственных внешних займов юридическим лицам
E100: 12 | F100: Жеке тұлғаларға республикалық бюджеттен берілген бюджеттік кредиттер бойынша сыйақылар | G100: 0.05002132 | H100: Вознаграждения по бюджетным кредитам, выданным из республиканского бюджета физическим лицам
E101: 14 | F101: Шетелдік мемлекеттерге берілген бюджеттік кредиттер бойынша сыйақылар | G101: 12.5734 | H101: Вознаграждения по бюджетным кредитам, выданным иностранным государствам
...

Sheet табл 8 (расх)
G3: (млн. тенге)
A4: (млн.теңге)
A6: Санаты/ Категория | B6: Сыныбы/ Класс | C6: Сыныпшасы/ Подкласс | D6: Ерешелігі/ Специфика | E6: Атауы | F6: 2025 қаңтар-шілде есеп/_x000D_ январь-июль отчет 2025г. | G6: Наименование
A7: 1 | B7: 2 | C7: 3 | D7: 4 | E7: 5 | F7: 6 | G7: 7
E8: ШЫҒЫСТАР | F8: 13605661 | G8: РАСХОДЫ
E9: оның ішінде: | G9: в том числе:
E10: II. ШЫҒЫНДАР | F10: 13382506 | G10: II. ЗАТРАТЫ
A11: 01 | E11: Жалпы сипаттағы мемлекеттiк қызметтер | F11: 597063.17 | G11: Государственные услуги общего характера
B12: 1 | E12: Мемлекеттiк басқарудың жалпы функцияларын орындайтын өкiлдi, атқарушы және басқа органдар | F12: 120958.91 | G12: Представительные, исполнительные и другие органы, выполняющие общие функции государственного управления
C13: 101 | E13: Қазақстан Республикасы Президентінің Әкімшілігі | F13: 10302.321 | G13: Администрация Президента Республики Казахстан
A14: 01 | B14: 1 | C14: 101 | D14: 001 | E14: Мемлекет басшысының қызметін қамтамасыз ету | F14: 10302.321 | G14: Обеспечение деятельности Главы государства
C15: 106 | E15: Адам құқықтары жөніндегі ұлттық орталық | F15: 804.47123 | G15: Национальный центр по правам человека
C16: 106 | D16: 001 | E16: Адамның және азаматтың құқықтары мен бостандықтарының сақталуын қадағалау жөніндегі қызметтер | F16: 744.29123 | G16: Услуги по наблюдению за соблюдением прав и свобод человека и гражданина
D17: 005 | E17: Қазақстандағы ұлттық құқық қорғау тетіктерінің тиімділігін күшейту | F17: 60.18 | G17: Усиление эффективности национальных правозащитных механизмов в Казахстане
C18: 107 | E18: Қазақстан Республикасы Жоғары Сот Кеңесінің Аппараты | F18: 638.54975 | G18: Аппарат Высшего Судебного Совета Республики Казахстан
C19: 107 | D19: 001 | E19: Қазақстан Республикасы Жоғары Сот Кеңесінің қызметін қамтамасыз ету жөнінде көрсетілетін қызметтер | F19: 638.54975 | G19: Услуги по обеспечению деятельности Высшего Судебного СоветаРеспублики Казахстан
C20: 109 | E20: Қазақстан Республикасы үкіметінің Аппараты_x000D_ | F20: 2600.2279 | G20: Аппарат Правительства Республики Казахстан
C21: 109 | D21: 001 | E21: Қазақстан Республикасы Премьер-Министрінің қызметін қамтамасыз ету жөніндегі көрсетілетін қызметтер | F21: 2600.2279 | G21: Услуги по обеспечению деятельности Премьер-Министра Республики Казахстан
C22: 626 | E22: Қазақстан Республикасының Стратегиялық жоспарлау және реформалар агенттігі | F22: 10955.141 | G22: Агентство по стратегическому планированию и реформам Республики Казахстан
C23: 626 | D23: 001 | E23: Реформаларды қалыптастыруға және тиімді іске асыруға жәрдемдесу жөніндегі көрсетілетін қызметтер, стратегиялық жоспарлау, мемлекеттік статистикалық қызмет салаларында мемлекеттік саясатты жүзеге асыру, мемлекеттік басқару жүйесі мен квазиме | F23: 10955.141 | G23: Услуги по содействию в формировании и эффективной реализации реформ, осуществление государственной политики в сферах стратегического планирования, государственной статистической деятельности, участие в совершенствовании системы государствен
D24: 101 | E24: Өкілдiк шығындарға арналған қаражат есебiнен іс-шаралар өткізу | F24: 0 | G24: Проведение мероприятий за счет средств на представительскиезатраты
C25: 637 | E25: Қазақстан Республикасы Конституциялық Сотының Аппараты | F25: 939.80843 | G25: Аппарат Конституционного Суда Республики Казахстан
C26: 637 | D26: 001 | E26: Республика аумағында Қазақстан Республикасы Конституциясының үстемдігін қамтамасыз ету | F26: 939.80843 | G26: Обеспечение верховенства Конституции Республики Казахстан на территории Республики
C27: 690 | E27: Қазақстан Республикасының Орталық сайлау комиссиясы | F27: 4729.3762 | G27: Центральная избирательная комиссия Республики Казахстан
C28: 690 | D28: 001 | E28: Сайлау өткізуді ұйымдастыру | F28: 550.27862 | G28: Организация проведения выборов
D29: 002 | E29: Сайлау өткізу | F29: 3841.0036 | G29: Проведение выборов
D30: 004 | E30: Облыстық бюджеттерге аудандардың (облыстық маңызы бар қалалардың) әкімдерін сайлауды қамтамасыз етуге және өткізуге берілетін ағымдағы нысаналы трансферттер | F30: 320.1767 | G30: Целевые текущие трансферты областным бюджетам на обеспечение и проведение выборов акимов районов (городов областного значения)
D31: 101 | E31: Өкілдiк шығындарға арналған қаражат есебiнен іс-шаралар өткізу | F31: 17.917296 | G31: Проведение мероприятий за счет средств на представительскиезатраты
C32: 693 | E32: Материалдық-техникалық қамтамасыз ету басқармасы | F32: 13944.705 | G32: Управление материально-технического обеспечения
C33: 693 | D33: 001 | E33: Қазақстан Республикасы Парламентінің қызметін қамтамасыз ету жөніндегі көрсетілетін қызметтер | F33: 13944.705 | G33: Услуги по обеспечению деятельности Парламента Республики Казахстан
C34: 694 | E34: Қазақстан Республикасы Президентiнiң Іс басқармасы | F34: 76044.307 | G34: Управление Делами Президента Республики Казахстан
C35: 694 | D35: 001 | E35: Қазақстан Республикасы Президенті Іс Басқармасының мемлекеттік функциялары мен өкілеттіктерін жүзеге асыруды қамтамасыз ету жөніндегі қызметтер | F35: 41308.958 | G35: Услуги по обеспечению осуществления государственных функцийи полномочий Управления делами Президента Республики Казахстан
D36: 009 | E36: Қазақстан Республикасы Президенттік орталығының қызметін қамтамасыз ету жөніндегі көрсетілетін қызметтер | F36: 740.71496 | G36: Услуги по обеспечению деятельности Президентского центра Республики Казахстан
D37: 109 | E37: Қазақстан Республикасы Үкіметінің шұғыл шығындарға арналғанрезервінің есебінен ағымды іс-шаралар өткізу_x000D_ | F37: 6768.0732 | G37: Проведение текущих мероприятий за счет резерва Правительства Республики Казахстан на неотложные затраты_x000D_
D38: 139 | E38: Қазақстан Республикасы Үкіметінің шұғыл шығындарға арналғанрезервінің есебінен дамуға бағытталған іс-шаралар өткізу | F38: 27226.56 | G38: Проведение мероприятий, направленных на развитие за счет резерва Правительства Республики Казахстан на неотложные затраты
B39: 2 | E39: Қаржылық қызмет | F39: 10521.148 | G39: Финансовая деятельность
C40: 217 | E40: Қазақстан Республикасының Қаржы министрлiгi | F40: 8031.5709 | G40: Министерство финансов Республики Казахстан
B41: 2 | C41: 217 | D41: 002 | E41: Халықаралық қаржы ұйымдары қаржыландыратын инвестициялық жобалардың аудитiн жүзеге асыру | F41: 0 | G41: Осуществление аудита инвестиционных проектов, финансируемыхмеждународными финансовыми организациями
D42: 094 | E42: Мемлекеттік активтерді басқару | F42: 99.205037 | G42: Управление государственными активами
D43: 205 | E43: Шекарадағы өткізу пункттерін жаңғырту және техникалық толықжарақтандыру | F43: 7932.3659 | G43: Модернизация и техническое дооснащение пунктов пропуска на границе
C44: 406 | E44: Қазақстан Республикасының Жоғары аудиторлық палатасы | F44: 2489.5768 | G44: Высшая аудиторская палата Республики Казахстан
C45: 406 | D45: 001 | E45: Қазақстан Республикасы Жоғары аудиторлық палатасының қызметін қамтамасыз ету жөніндегі көрсетілетін қызметтер | F45: 2478.2528 | G45: Услуги по обеспечению деятельности Высшей аудиторской палаты Республики Казахстан
D46: 101 | E46: Өкілдiк шығындарға арналған қаражат есебiнен іс-шаралар өткізу | F46: 11.32393 | G46: Проведение мероприятий за счет средств на представительскиезатраты
B47: 3 | E47: Сыртқы саяси қызмет | F47: 71999.216 | G47: Внешнеполитическая деятельность
C48: 204 | E48: Қазақстан Республикасының Сыртқы iстер министрлiгi | F48: 71880.573 | G48: Министерство иностранных дел Республики Казахстан
B49: 3 | C49: 204 | D49: 001 | E49: Сыртқы саяси қызметті үйлестіру жөніндегі көрсетілетін қызметтер | F49: 51647.329 | G49: Услуги по координации внешнеполитической деятельности
D50: 005 | E50: Шетелдік іссапарлар | F50: 2475.9028 | G50: Заграничные командировки
D51: 008 | E51: Шетелдегі дипломатиялық өкілдіктердің арнайы, инженерлік-техникалық және нақты қорғалуын қамтамасыз ету | F51: 111.82178 | G51: Обеспечение специальной, инженерно-технической и физическойзащиты дипломатических представительств за рубежом
D52: 013 | E52: Халықаралық ұйымдарда, Тәуелсіз Мемлекеттер Достастығының жарғылық және басқа органдарында Қазақстан Республикасының мүддесін білдіру | F52: 273.19926 | G52: Представление интересов Республики Казахстан в международных организациях, уставных и других органах Содружества Независимых Государств
D53: 017 | E53: Қазақстан Республикасының халықаралық ұйымдарға, өзге де халықаралық және басқа органдарға қатысуы | F53: 15516.938 | G53: Участие Республики Казахстан в международных организациях, иных международных и прочих органах
D54: 019 | E54: Ақпараттық-имидждік саясаттың іске асырылуын қамтамасыз ету | F54: 1511.4573 | G54: Обеспечение реализации информационно-имиджевой политики
D55: 045 | E55: Халықаралық бағыттағы үкіметтік емес ұйымдардың қызметін гранттық қаржыландыру | F55: 37.849404 | G55: Грантовое финансирование деятельности неправительственных организаций на международном направлении
D56: 101 | E56: Өкілдiк шығындарға арналған қаражат есебiнен іс-шаралар өткізу | F56: 306.07513 | G56: Проведение мероприятий за счет средств на представительскиезатраты
D57: 109 | E57: Қазақстан Республикасы Үкіметінің шұғыл шығындарға арналғанрезервінің есебінен ағымды іс-шаралар өткізу | F57: 0 | G57: Проведение текущих мероприятий за счет резерва Правительства Республики Казахстан на неотложные затраты
D58: 159 | E58: Қазақстан Республикасы мен Экономикалық ынтымақтастық және даму ұйымының арасындағы ынтымақтастық шеңберінде Қазақстан Республикасының әлеуметтік-экономикалық жағдайына зерттеулержүргізуді қамтамасыз ету | F58: 0 | G58: Обеспечение проведения исследований социально-экономического положения Республики Казахстан в рамках сотрудничества между Республикой Казахстан и Организацией экономического сотрудничества и развития
D59: 164 | E59: Қазақстанның Экономикалық ынтымақтастық және даму ұйымымен ынтымақтастығы шеңберінде Қазақстанның Экономикалық ынтымақтастық және даму ұйымының бастамалары мен құралдарына қатысуын қамтамасыз ету | F59: 0 | G59: Обеспечение участия Казахстана в инициативах и инструментахОрганизации экономического сотрудничества и развития в рамках сотрудничества Казахстана с Организацией экономического сотрудничества и развития
C60: 207 | E60: Қазақстан Республикасының Экология және табиғи ресурстар министрлігі | F60: 8.14408 | G60: Министерство экологии и природных ресурсов Республики Казахстан
C61: 207 | D61: 164 | E61: Қазақстанның Экономикалық ынтымақтастық және даму ұйымымен ынтымақтастығы шеңберінде Қазақстанның Экономикалық ынтымақтастық және даму ұйымының бастамалары мен құралдарына қатысуын қамтамасыз ету | F61: 8.14408 | G61: Обеспечение участия Казахстана в инициативах и инструментахОрганизации экономического сотрудничества и развития в рамках сотрудничества Казахстана с Организацией экономического сотрудничества и развития
C62: 217 | E62: Қазақстан Республикасының Қаржы министрлiгi | F62: 23.502995 | G62: Министерство финансов Республики Казахстан
C63: 217 | D63: 164 | E63: Қазақстанның Экономикалық ынтымақтастық және даму ұйымымен ынтымақтастығы шеңберінде Қазақстанның Экономикалық ынтымақтастық және даму ұйымының бастамалары мен құралдарына қатысуын қамтамасыз ету | F63: 23.502995 | G63: Обеспечение участия Казахстана в инициативах и инструментахОрганизации экономического сотрудничества и развития в рамках сотрудничества Казахстана с Организацией экономического сотрудничества и развития
C64: 224 | E64: Қазақстан Республикасының Оқу-ағарту министрлігі | F64: 0 | G64: Министерство просвещения Республики Казахстан
C65: 224 | D65: 164 | E65: Қазақстанның Экономикалық ынтымақтастық және даму ұйымы менынтымақтастығы шеңберінде Қазақстанның Экономикалық ынтымақтастық және даму ұйымының бастамалары мен құралдарына қатысуын қамтамасыз ету | F65: 0 | G65: Обеспечение участия Казахстана в инициативах и инструментахОрганизации экономического сотрудничества и развития в рамках сотрудничества Казахстана с Организацией экономического сотрудничества и развития
C66: 227 | E66: Қазақстан Республикасының Ғылым және жоғары білім министрлігі | F66: 6.7829972 | G66: Министерство науки и высшего образования Республики Казахстан
C67: 227 | D67: 164 | E67: Қазақстанның Экономикалық ынтымақтастық және даму ұйымымен ынтымақтастығы шеңберінде Қазақстанның Экономикалық ынтымақтастық және даму ұйымының бастамалары мен құралдарына қатысуын қамтамасыз ету | F67: 6.7829972 | G67: Обеспечение участия Казахстана в инициативах и инструментахОрганизации экономического сотрудничества и развития в рамках сотрудничества Казахстана с Организацией экономического сотрудничества и развития
C68: 228 | E68: Қазақстан Республикасының Көлік министрлігі | F68: 12.467971 | G68: Министерство транспорта Республики Казахстан
C69: 228 | D69: 164 | E69: Қазақстанның Экономикалық ынтымақтастық және даму ұйымымен ынтымақтастығы шеңберінде Қазақстанның Экономикалық ынтымақтастық және даму ұйымының бастамалары мен құралдарына қатысуын қамтамасыз ету | F69: 12.467971 | G69: Обеспечение участия Казахстана в инициативах и инструментахОрганизации экономического сотрудничества и развития в рамках сотрудничества Казахстана с Организацией экономического сотрудничества и развития
C70: 229 | E70: Қазақстан Республикасының Өнеркәсіп және құрылыс министрлігі | F70: 23.703557 | G70: Министерство промышленности и строительства Республики Казахстан
C71: 229 | D71: 164 | E71: Қазақстанның Экономикалық ынтымақтастық және даму ұйымымен ынтымақтастығы шеңберінде Қазақстанның Экономикалық ынтымақтастық және даму ұйымының бастамалары мен құралдарына қатысуын қамтамасыз ету | F71: 23.703557 | G71: Обеспечение участия Казахстана в инициативах и инструментахОрганизации экономического сотрудничества и развития в рамках сотрудничества Казахстана с Организацией экономического сотрудничества и развития
C72: 243 | E72: Қазақстан Республикасының Ұлттық экономика министрлігі | F72: 25.476077 | G72: Министерство национальной экономики Республики Казахстан
C73: 243 | D73: 057 | E73: Қазақстанның Экономикалық ынтымақтастық және даму ұйымымен ынтымақтастығы шеңберінде Қазақстанның Экономикалық ынтымақтастық және даму ұйымының бастамалары мен құралдарына қатысуы | F73: 0 | G73: Участие Казахстана в инициативах и инструментах Организацииэкономического сотрудничества и развития в рамках сотрудничества Казахстана с Организацией экономического сотрудничества и развития
D74: 096 | E74: Қазақстан Республикасы мен Экономикалық ынтымақтастық және даму ұйымының арасындағы ынтымақтастық шеңберінде Қазақстан Республикасының әлеуметтік-экономикалық жағдайына зерттеулер жүргізу Қазақстан Республикасы мен Экономикалық ынтымақтас | F74: 0 | G74: Проведение исследования социально-экономического положения Республики Казахстан в рамках сотрудничества между Республикой Казахстан и Организацией экономического сотрудничества и развития
D75: 164 | E75: Қазақстанның Экономикалық ынтымақтастық және даму ұйымымен ынтымақтастығы шеңберінде Қазақстанның Экономикалық ынтымақтастық және даму ұйымының бастамалары мен құралдарына қатысуын қамтамасыз ету | F75: 25.476077 | G75: Обеспечение участия Казахстана в инициативах и инструментахОрганизации экономического сотрудничества и развития в рамках сотрудничества Казахстана с Организацией экономического сотрудничества и развития
C76: 624 | E76: Қазақстан Республикасының Сыбайлас жемқорлыққа қарсы іс-қимыл агенттігі (Сыбайлас жемқорлыққа қарсы қызмет) | F76: 4.9996614 | G76: Агентство Республики Казахстан по противодействию коррупции(Антикоррупционная служба)
C77: 624 | D77: 164 | E77: Қазақстанның Экономикалық ынтымақтастық және даму ұйымымен ынтымақтастығы шеңберінде Қазақстанның Экономикалық ынтымақтастық және даму ұйымының бастамалары мен құралдарына қатысуын қамтамасыз ету | F77: 4.9996614 | G77: Обеспечение участия Казахстана в инициативах и инструментахОрганизации экономического сотрудничества и развития в рамках сотрудничества Казахстана с Организацией экономического сотрудничества и развития
C78: 626 | E78: Қазақстан Республикасының Стратегиялық жоспарлау және реформалар агенттігі | F78: 6.7827989 | G78: Агентство по стратегическому планированию и реформам Республики Казахстан
C79: 626 | D79: 159 | E79: Қазақстан Республикасы мен Экономикалық ынтымақтастық және даму ұйымының арасындағы ынтымақтастық шеңберінде Қазақстан Республикасының әлеуметтік-экономикалық жағдайына зерттеулержүргізуді қамтамасыз ету | F79: 0 | G79: Обеспечение проведения исследований социально-экономического положения Республики Казахстан в рамках сотрудничества между Республикой Казахстан и Организацией экономического сотрудничества и развития
D80: 164 | E80: Қазақстанның Экономикалық ынтымақтастық және даму ұйымымен ынтымақтастығы шеңберінде Қазақстанның Экономикалық ынтымақтастық және даму ұйымының бастамалары мен құралдарына қатысуын қамтамасыз ету | F80: 6.7827989 | G80: Обеспечение участия Казахстана в инициативах и инструментахОрганизации экономического сотрудничества и развития в рамках сотрудничества Казахстана с Организацией экономического сотрудничества и развития
C81: 627 | E81: Қазақстан Республикасының Бәсекелестікті қорғау және дамытуагенттігі | F81: 6.7829946 | G81: Агентство по защите и развитию конкуренции Республики Казахстан
C82: 627 | D82: 164 | E82: Қазақстанның Экономикалық ынтымақтастық және даму ұйымымен ынтымақтастығы шеңберінде Қазақстанның Экономикалық ынтымақтастық және даму ұйымының бастамалары мен құралдарына қатысуын қамтамасыз ету | F82: 6.7829946 | G82: Обеспечение участия Казахстана в инициативах и инструментахОрганизации экономического сотрудничества и развития в рамках сотрудничества Казахстана с Организацией экономического сотрудничества и развития
B83: 4 | E83: Iргелi ғылыми зерттеулер | F83: 86100.044 | G83: Фундаментальные научные исследования
C84: 202 | E84: Қазақстан Республикасының Төтенше жағдайлар министрлiгi | F84: 84.810775 | G84: Министерство по чрезвычайным ситуациям Республики Казахстан
B85: 4 | C85: 202 | D85: 131 | E85: Ғылыми және (немесе) ғылыми-техникалық қызмет субъектілерінбазалық қаржыландыруды қамтамасыз ету | F85: 84.810775 | G85: Обеспечение базового финансирования субъектов научной и (или) научно-технической деятельности
C86: 207 | E86: Қазақстан Республикасының Экология және табиғи ресурстар министрлігі | F86: 560.5045 | G86: Министерство экологии и природных ресурсов Республики Казахстан
C87: 207 | D87: 131 | E87: Ғылыми және (немесе) ғылыми-техникалық қызмет субъектілерінбазалық қаржыландыруды қамтамасыз ету | F87: 560.5045 | G87: Обеспечение базового финансирования субъектов научной и (или) научно-технической деятельности
C88: 208 | E88: Қазақстан Республикасының Қорғаныс министрлiгi | F88: 11.0068 | G88: Министерство обороны Республики Казахстан
C89: 208 | D89: 131 | E89: Ғылыми және (немесе) ғылыми-техникалық қызмет субъектілерінбазалық қаржыландыруды қамтамасыз ету | F89: 11.0068 | G89: Обеспечение базового финансирования субъектов научной и (или) научно-технической деятельности
C90: 212 | E90: Қазақстан Республикасының Ауыл шаруашылығы министрлiгi | F90: 1887.213 | G90: Министерство сельского хозяйства Республики Казахстан
C91: 212 | D91: 131 | E91: Ғылыми және (немесе) ғылыми-техникалық қызмет субъектілерін базалық қаржыландыруды қамтамасыз ету | F91: 1887.213 | G91: Обеспечение базового финансирования субъектов научной и (или) научно-технической деятельности
C92: 213 | E92: Қазақстан Республикасының Еңбек және халықты әлеуметтiк қорғау министрлiгi | F92: 118.0525 | G92: Министерство труда и социальной защиты населения РеспубликиКазахстан
C93: 213 | D93: 131 | E93: Ғылыми және (немесе) ғылыми-техникалық қызмет субъектілерін базалық қаржыландыруды қамтамасыз ету | F93: 118.0525 | G93: Обеспечение базового финансирования субъектов научной и (или) научно-технической деятельности
C94: 223 | E94: Қазақстан Республикасының Цифрлық даму, инновациялар және аэроғарыш өнеркәсібі министрлігі | F94: 97.21255 | G94: Министерство цифрового развития, инноваций и аэрокосмической промышленности Республики Казахстан
C95: 223 | D95: 131 | E95: Ғылыми және (немесе) ғылыми-техникалық қызмет субъектілерінбазалық қаржыландыруды қамтамасыз ету | F95: 97.21255 | G95: Обеспечение базового финансирования субъектов научной и (или) научно-технической деятельности
C96: 224 | E96: Қазақстан Республикасының Оқу-ағарту министрлігі | F96: 80.1 | G96: Министерство просвещения Республики Казахстан
C97: 224 | D97: 131 | E97: Ғылыми және (немесе) ғылыми-техникалық қызмет субъектілерінбазалық қаржыландыруды қамтамасыз ету | F97: 80.1 | G97: Обеспечение базового финансирования субъектов научной и (или) научно-технической деятельности
C98: 226 | E98: Қазақстан Республикасының Денсаулық сақтау министрлігі | F98: 1049.8597 | G98: Министерство здравоохранения Республики Казахстан
C99: 226 | D99: 131 | E99: Ғылыми және (немесе) ғылыми-техникалық қызмет субъектілерін базалық қаржыландыруды қамтамасыз ету | F99: 1049.8597 | G99: Обеспечение базового финансирования субъектов научной и (или) научно-технической деятельности
C100: 227 | E100: Қазақстан Республикасының Ғылым және жоғары білім министрлігі | F100: 81717.599 | G100: Министерство науки и высшего образования Республики Казахстан
C101: 227 | D101: 130 | E101: Ғылыми және (немесе) ғылыми-техникалық қызмет субъектілерінбазалық қаржыландыру | F101: 0 | G101: Базовое финансирование субъектов научной и (или) научно-технической деятельности
D102: 131 | E102: Ғылыми және (немесе) ғылыми-техникалық қызмет субъектілерінбазалық қаржыландыруды қамтамасыз ету | F102: 1765.9064 | G102: Обеспечение базового финансирования субъектов научной и (или) научно-технической деятельности
D103: 217 | E103: Ғылымды дамыту | F103: 79951.693 | G103: Развитие науки
...

Sheet табл 9
B2: Кесте 9 | D2: Таблица 9
B3: ШЫҒЫСТАРДЫҢ ВЕДОМСТВОЛЫҚ | D3: ИСПОЛНЕНИЕ РЕСПУБЛИКАНСКОГО БЮДЖЕТА
B4: СЫНЫПТАМАСЫ БОЙЫНША | D4: ПО ВЕДОМСТВЕННОЙ
B5: РЕСПУБЛИКАЛЫҚ БЮДЖЕТТІҢ АТҚАРАЛУЫ | D5: КЛАССИФИКАЦИИ РАСХОДОВ
B6: (млн. теңге) | D6: (млн. тенге)
B8: Бағдарламалард_x000D_ ың_x000D_ əкімшісі/_x000D_ Администратор_x000D_ программ | C8: Атауы | D8: 2025 ж. қаңтар-шілде есеп/_x000D_ январь-июль 2025 г. | E8: Наименование
B9: 1 | C9: 2 | D9: 3 | E9: 4
C10: БАРЛЫҒЫ | D10: 13605661 | E10: ВСЕГО
B11: 101 | C11: Қазақстан Республикасы Президентінің Әкімшілігі | D11: 10302.321 | E11: Администрация Президента Республики Казахстан
B12: 106 | C12: Адам құқықтары жөніндегі ұлттық орталық | D12: 804.47123 | E12: Национальный центр по правам человека
B13: 107 | C13: Қазақстан Республикасы Жоғары Сот Кеңесінің Аппараты | D13: 1067.4368 | E13: Аппарат Высшего Судебного Совета Республики Казахстан
B14: 109 | C14: Қазақстан Республикасы үкіметінің Аппараты_x000D_ | D14: 3844.9471 | E14: Аппарат Правительства Республики Казахстан
B15: 201 | C15: Қазақстан Республикасының Iшкi iстер министрлiгi | D15: 331278.37 | E15: Министерство внутренних дел Республики Казахстан
B16: 202 | C16: Қазақстан Республикасының Төтенше жағдайлар министрлiгi | D16: 78700.162 | E16: Министерство по чрезвычайным ситуациям Республики Казахстан
B17: 204 | C17: Қазақстан Республикасының Сыртқы iстер министрлiгi | D17: 73518.479 | E17: Министерство иностранных дел Республики Казахстан
B18: 207 | C18: Қазақстан Республикасының Экология және табиғи ресурстар министрлігі | D18: 45451.131 | E18: Министерство экологии и природных ресурсов Республики Казахстан
B19: 208 | C19: Қазақстан Республикасының Қорғаныс министрлiгi | D19: 361690.96 | E19: Министерство обороны Республики Казахстан
B20: 211 | C20: Қазақстан Республикасының Сауда және интеграция министрлігі | D20: 8918.6847 | E20: Министерство торговли и интеграции Республики Казахстан
B21: 212 | C21: Қазақстан Республикасының Ауыл шаруашылығы министрлiгi | D21: 333839.83 | E21: Министерство сельского хозяйства Республики Казахстан
B22: 213 | C22: Қазақстан Республикасының Еңбек және халықты әлеуметтiк қорғау министрлiгi | D22: 3480572 | E22: Министерство труда и социальной защиты населения РеспубликиКазахстан
... B50: 694 | C50: Қазақстан Республикасы Президентiнiң Іс басқармасы | D50: 123192.3 | E50: Управление Делами Президента Республики Казахстан

Sheet табл 10
A1: 10-кесте ШЫҒЫНДАРДЫҢ ЭКОНОМИКАЛЫҚ ЖІКТЕМЕСІ БОЙЫНША РЕСПУБЛИКАЛЫҚ БЮДЖЕТТІК ОРЫНДАЛУЫ (млн.теңге) | E1: Таблица 10 ИСПОЛНЕНИЕ РЕСПУБЛИКАНСКОГО БЮДЖЕТА ПО ЭКОНОМИЧЕСКОЙ КЛАССИФИКАЦИИ РАСХОДОВ (млн. тенге)
A3: Cанаты/_x000D_ Категория | B3: Iшкi сыныбы/_x000D_ Подкласс | C3: Ерекшелiгi/_x000D_ Специфика | D3: Атауы | F3: 2025 ж. қаңтар-шілде/_x000D_ январь-июль отчет 2025 г. | G3: Наименование
A4: 1 | B4: 2 | C4: 3 | D4: 4 | F4: 5 | G4: 6
D5: БАРЛЫҒЫ | F5: 13605661 | G5: ВСЕГО
A6: 1 | D6: Ағымдағы шығындар | F6: 12763971 | G6: Текущие затраты
A7: L01 Категория расходов | B7: 110 | D7: Жалақы | F7: 666220.08 | G7: Заработная плата
A8: 1 | B8: 110 | C8: 111 | D8: Еңбекке ақы төлеу | F8: 491268.8 | G8: Оплата труда
A9: 1 | C9: 112 | D9: Қосымша ақшалай төлемдер | F9: 83894.576 | G9: Дополнительные денежные выплаты
A10: 1 | C10: 113 | D10: Өтемақы төлемдері | F10: 86307.043 | G10: Компенсационные выплаты
A11: 1 | C11: 114 | D11: Міндетті кәсіптік зейнетақы жарналары | F11: 130.52484 | G11: Обязательные профессиональные пенсионные взносы
A12: 1 | C12: 116 | D12: Жұмыс берушілердің міндетті зейнетақы жарналары | F12: 4619.1388 | G12: Обязательные пенсионные взносы работодателей
A13: L01 Категория расходов | B13: 120 | D13: Жұмыс берушілердің жарналары | F13: 41126.634 | G13: Взносы работодателей
A14: 1 | B14: 120 | C14: 121 | D14: Әлеуметтік салық | F14: 14971.537 | G14: Социальный налог
A15: 1 | C15: 122 | D15: Мемлекеттiк әлеуметтiк сақтандыру қорына әлеуметтiк аударымдар | F15: 20133.096 | G15: Социальные отчисления в Государственный фонд социального страхования
A16: 1 | C16: 123 | D16: Мiндеттi сақтандыру жарналары | F16: 315.69274 | G16: Взносы на обязательное страхование
A17: 1 | C17: 124 | D17: Міндетті әлеуметтік медициналық сақтандыруға аударымдар | F17: 5706.3085 | G17: Отчисления на обязательное социальное медицинское страхование
A18: L01 Категория расходов | B18: 130 | D18: Қазақстан Республикасының заңнамалық актілеріне сәйкес азаматтардың жекелеген санаттарына жалақы төлеу және жарналар аудару | F18: 47276.701 | G18: Выплата заработной платы отдельным категориям граждан и отчисления взносов в соответствии с законодательными актами Республики Казахстан
A19: 1 | B19: 130 | C19: 131 | D19: Техникалық персоналдың еңбегіне ақы төлеу | F19: 41144.366 | G19: Оплата труда технического персонала
A20: 1 | C20: 134 | D20: Алқа билерге сыйақылар төлеу | F20: 294.48479 | G20: Выплата вознаграждений присяжным заседателям
A21: 1 | C21: 135 | D21: Техникалық персонал бойынша жұмыс берушілердің жарналары | F21: 5168.996 | G21: Взносы работодателей по техническому персоналу
A22: 1 | C22: 136 | D22: Техникалық персоналдың ел iшiндегi iссапарлары мен қызметтiк сапарлары | F22: 655.64717 | G22: Командировки и служебные разъезды внутри страны технического персонала
A23: 1 | C23: 137 | D23: Қорғаушы мәжілістердің қызметтiк сапарлар | F23: 13.206975 | G23: Командировочные расходы присяжных заседателей
A24: L01 Категория расходов | B24: 140 | D24: Қорлар сатып алу | F24: 82369.683 | G24: Приобретение запасов
A25: 1 | B25: 140 | C25: 141 | D25: Азық-түлiк өнiмдерiн сатып алу | F25: 37704.465 | G25: Приобретение продуктов питания
A26: 1 | C26: 142 | D26: Дәрілік заттар және медициналық мақсаттағы өзге де бұйымдарды сатып алу | F26: 4804.5507 | G26: Приобретение лекарственных средств и прочих изделий медицинского назначения
A27: 1 | C27: 143 | D27: Заттай мүлiктердi, басқа да киім нысанын және арнаулы киім-кешектер сатып алу, тiгу және жөндеу | F27: 9648.4513 | G27: Приобретение, пошив и ремонт предметов вещевого имущества идругого форменного и специального обмундирования
A28: 1 | C28: 144 | D28: Отын, жанар-жағар май материалдарын сатып алу | F28: 17261.563 | G28: Приобретение топлива, горюче-смазочных материалов
A29: 1 | C29: 149 | D29: Өзге де қорларды сатып алу | F29: 12950.653 | G29: Приобретение прочих запасов
A30: L01 Категория расходов | B30: 150 | D30: Қызметтер мен жұмыстарды сатып алу | F30: 654879.36 | G30: Приобретение услуг и работ
A31: 1 | B31: 150 | C31: 151 | D31: Коммуналдық қызметтерге ақы төлеу | F31: 26965.145 | G31: Оплата коммунальных услуг
A32: 1 | C32: 152 | D32: Байланыс қызметтерiне ақы төлеу | F32: 11475.507 | G32: Оплата услуг связи
A33: 1 | C33: 153 | D33: Көлiктiк қызмет көрсетулерге ақы төлеу | F33: 6518.5967 | G33: Оплата транспортных услуг
A34: 1 | C34: 154 | D34: Зерттеулер бойынша қызметтерге ақы төлеу | F34: 83318.261 | G34: Оплата услуг по исследованиям
A35: 1 | C35: 155 | D35: Мемлекеттiк әлеуметтiк тапсырыс шеңберiнде көрсетілетін қызметтерге ақы төлеу | F35: 24.553732 | G35: Оплата услуг в рамках государственного социального заказа
A36: 1 | C36: 156 | D36: Консалтингтік қызметтерге ақы төлеу | F36: 468.07018 | G36: Оплата консалтинговых услуг
A37: 1 | C37: 157 | D37: Форумдар, семинарлар, конференциялар өткізуге және имидждік іс-шараларға арналған қызметтерге ақы төлеу | F37: 85.285255 | G37: Оплата услуг на проведение форумов, семинаров, конференций и на имиджевые мероприятия
A38: 1 | C38: 158 | D38: Ақпараттандыру саласындағы жұмыстар мен қызметтерге ақы төлеу | F38: 15388.719 | G38: Оплата работ и услуг в сфере информатизации
A39: 1 | C39: 159 | D39: Өзге де қызметтер мен жұмыстарға ақы төлеу | F39: 510635.22 | G39: Оплата прочих услуг и работ
A40: L01 Категория расходов | B40: 160 | D40: Басқа да ағымдағы шығындар | F40: 811568.19 | G40: Другие текущие затраты
A41: 1 | B41: 160 | C41: 161 | D41: Ел iшiндегi iссапарлар мен қызметтiк сапарлар | F41: 13636.275 | G41: Командировки и служебные разъезды внутри страны
A42: 1 | C42: 162 | D42: Елден тыс жерлерге iссапарлар мен қызметтiк сапарлар | F42: 5262.1039 | G42: Командировки и служебные разъезды за пределы страны
A43: 1 | C43: 164 | D43: Шетелдегi стипендиаттардың оқуына ақы төлеу | F43: 17463.394 | G43: Оплата обучения стипендиатов за рубежом
A44: 1 | C44: 165 | D44: Атқарушылық құжаттарының, сот актiлерiнiң орындалуы | F44: 3944.1858 | G44: Исполнение исполнительных документов, судебных актов
A45: 1 | C45: 166 | D45: Нысаналы салым | F45: 4205.373 | G45: Целевой вклад
A46: 1 | C46: 167 | D46: Ерекше шығындар | F46: 454513.18 | G46: Особые затраты
A47: 1 | C47: 169 | D47: Өзге де ағымдағы шығындар | F47: 312543.68 | G47: Прочие текущие затраты
A48: L01 Категория расходов | B48: 170 | D48: Мемлекеттік емес қарыздар бойынша шығыстарды өтеу | F48: 25693.549 | G48: Возмещение расходов по негосударственным займам
A49: 1 | B49: 170 | C49: 171 | D49: Мемлекеттік кепілдікпен мемлекеттік емес қарыздар бойынша шығыстарды өтеу | F49: 25693.549 | G49: Возмещение расходов по негосударственным займам под государственным займам под государственные гарантии
A50: L01 Категория расходов | B50: 210 | D50: Ішкі қарыздар бойынша сыйақы төлемдері | F50: 1780111.2 | G50: Выплаты вознаграждений по внутренним займам
A51: 1 | B51: 210 | C51: 211 | D51: Қазақстан Республикасы Үкіметінің ішкі қарыздары бойынша сыйақыларды төлеу | F51: 1780111.2 | G51: Выплаты вознаграждений по внутренним займам Правительства Республики Казахстан
A52: L01 Категория расходов | B52: 220 | D52: Сыртқы заемдар бойынша сыйақылар төлеу | F52: 237711.73 | G52: Выплаты вознаграждений по внешним займам
A53: 1 | B53: 220 | C53: 221 | D53: Қазақстан Республикасы Үкіметінің сыртқы қарыздары бойынша сыйақы төлемдері | F53: 237711.73 | G53: Выплаты вознаграждений по внешним займам Правительства Республики Казахстан
A54: L01 Категория расходов | B54: 310 | D54: Бюджеттік субсидиялар | F54: 139131.76 | G54: Бюджетные субсидии
A55: 1 | B55: 310 | C55: 311 | D55: Жеке және заңды тұлғаларға, оның ішінде шаруа (фермерлік) қожалықтарына берілетін субсидиялар | F55: 139131.76 | G55: Субсидии физическим и юридическим лицам, в том числе крестьянским (фермерским) хозяйствам
A56: L01 Категория расходов | B56: 320 | D56: Жеке тұлғаларға берілетін трансферттер | F56: 3722169.4 | G56: Трансферты физическим лицам
A57: 1 | B57: 320 | C57: 321 | D57: Арнайы мемлекеттік органдардың қызметкерлеріне және əскери қызметшілеріне тұрғын үй төлемдері | F57: 144242.98 | G57: Жилищные выплаты сотрудникам специальных государственных органов и военнослужащим
A58: 1 | C58: 322 | D58: Жеке тұлғаларға берiлетiн трансферттер | F58: 940647.3 | G58: Трансферты физическим лицам
A59: 1 | C59: 323 | D59: Зейнетақылар | F59: 2515548.8 | G59: Пенсии
A60: 1 | C60: 324 | D60: Стипендиялар | F60: 121730.31 | G60: Стипендии
A61: L01 Категория расходов | B61: 330 | D61: Мемлекеттiк басқарудың басқа деңгейлерiне берiлетiн ағымдағытрансферттер | F61: 3665264.9 | G61: Текущие трансферты другим уровням государственного управления
A62: 1 | B62: 330 | C62: 331 | D62: Субвенциялар | F62: 3358383.8 | G62: Субвенции
A63: 1 | C63: 339 | D63: Мемлекеттiк басқарудың басқа деңгейлерiне берiлетiн ағымдағы трансферттер | F63: 306881.06 | G63: Текущие трансферты другим уровням государственного управления
A64: L01 Категория расходов | B64: 340 | D64: Шетелге берiлетiн ағымдағы трансферттер | F64: 16647.973 | G64: Текущие трансферты за границу
A65: 1 | B65: 340 | C65: 341 | D65: Шетелдегi ұйымдарға ағымдағы трансферттер | F65: 16647.973 | G65: Текущие трансферты за границу
A66: L01 Категория расходов | B66: 360 | D66: Нысаналы жарна | F66: 873800 | G66: Целевой взнос
A67: 1 | B67: 360 | C67: 361 | D67: Нысаналы жарна | F67: 873800 | G67: Целевой взнос
A68: 2 | D68: Күрделі шығындар | F68: 585956.91 | G68: Капитальные затраты
A69: L01 Категория расходов | B69: 410 | D69: Негiзгi құралдарды, материалдық емес және биологиялық активтерді сатып алу | F69: 16531.7 | G69: Приобретение основных средств, нематериальных и биологических активов
A70: 2 | B70: 410 | C70: 412 | D70: Үй-жайлар, ғимараттар мен құрылыстарды, беру қондырғыларын сатып алу | F70: 2538.4905 | G70: Приобретение помещений, зданий, сооружений, передаточных устройств
A71: 2 | C71: 413 | D71: Көлік құралдарын сатып алу | F71: 1024.8956 | G71: Приобретение транспортных средств
A72: 2 | C72: 414 | D72: Машиналар, жабдықтар, өндірістік және шаруашылық мүккамал құралдарын сатып алу | F72: 5515.149 | G72: Приобретение машин, оборудования, инструментов, производственного и хозяйственного инвентаря
A73: 2 | C73: 416 | D73: Материалдық емес активтерді сатып алу | F73: 308.85763 | G73: Приобретение нематериальных активов
A74: 2 | C74: 418 | D74: Мемлекеттік кәсіпорындарды материалдық-техникалық жарақтандыру | F74: 7111.1702 | G74: Материально-техническое оснащение государственных предприятий
A75: 2 | C75: 419 | D75: Өзге де негізгі құралдарды сатып алу | F75: 33.13671 | G75: Приобретение прочих основных средств
A76: L01 Категория расходов | B76: 420 | D76: Негізгі қаражатты күрделі жөндеу | F76: 8556.9349 | G76: Капитальный ремонт основных средств
A77: 2 | B77: 420 | C77: 421 | D77: Жайларды, ғимараттарды, құрылыстарды, беру қондырғыларын күрделі жөндеу | F77: 5058.2479 | G77: Капитальный ремонт помещений, зданий, сооружений, передаточных устройств
A78: 2 | C78: 422 | D78: Жолдарды күрделі жөндеу | F78: 3498.687 | G78: Капитальный ремонт дорог
A79: L01 Категория расходов | B79: 430 | D79: Дамуға бағытталған күрделі шығындар | F79: 126607.1 | G79: Капитальные затраты, направленные на развитие
A80: 2 | B80: 430 | C80: 431 | D80: Жаңа объектілерді салу және қолдағы объектілерді реконструкциялау | F80: 112270.22 | G80: Строительство новых объектов и реконструкция имеющихся объектов
A81: 2 | C81: 432 | D81: Жолдар салу | F81: 12461.433 | G81: Строительство дорог
A82: 2 | C82: 434 | D82: Ақпараттық жүйелерді құру, енгізу және дамыту | F82: 1696.7105 | G82: Создание, внедрение и развитие информационных систем
A83: 2 | C83: 435 | D83: Мемлекеттік кәсіпорындардың жаңа объектілерін салу және қолдағы бар объектілерін реконструкциялау | F83: 178.73464 | G83: Строительство новых объектов и реконструкция имеющихся объектов государственных предприятий
A84: L01 Категория расходов | B84: 440 | D84: Дамуға арналған нысаналы трансферттер | F84: 434261.17 | G84: Целевые трансферты на развитие
A85: 2 | B85: 440 | C85: 441 | D85: Мемлекеттік басқарудың басқа деңгейлерін дамытуға арналған нысаналы трансферттер | F85: 434261.17 | G85: Целевые трансферты на развитие другим уровням государственного управления
A86: 3 | D86: Бюджеттік кредиттер | F86: 204000 | G86: Бюджетные кредиты
A87: L01 Категория расходов | B87: 510 | D87: Ішкі бюджеттік кредиттер | F87: 204000 | G87: Внутренние бюджетные кредиты
A88: 3 | B88: 510 | C88: 511 | D88: Бюджеттік инвестициялық жобаларды іске асыруға арналған бюджеттік кредиттерді қоспағанда, жергілікті атқарушы органдарға бюджеттік кредиттер | F88: 30000 | G88: Бюджетные кредиты местным исполнительным органам, за исключением бюджетных кредитов на реализацию бюджетных инвестиционных проектов
A89: 3 | C89: 513 | D89: Мамандандырылған ұйымдарға бюджеттік кредиттер | F89: 140000 | G89: Бюджетные кредиты специализированным организациям
A90: 3 | C90: 519 | D90: Өзге де ішкі бюджеттік кредиттер | F90: 34000 | G90: Прочие внутренние бюджетные кредиты
A91: 4 | D91: Қаржы активтерін сатып алу | F91: 19363.889 | G91: Приобретение финансовых активов
A92: L01 Категория расходов | B92: 610 | D92: Қаржы активтерін сатып алу | F92: 19226.56 | G92: Приобретение финансовых активов
A93: 4 | B93: 610 | C93: 612 | D93: Квазимемлекеттік сектордың жарғылық капиталын қалыптастыру және ұлғайту | F93: 19226.56 | G93: Формирование и увеличение уставных капиталов субъектов квазигосударственного сектора
A94: L01 Категория расходов | B94: 620 | D94: Елден тысқары жерлерден қаржы активтерін сатып алу | F94: 137.32896 | G94: Приобретение финансовых активов за пределами страны
A95: 4 | B95: 620 | C95: 621 | D95: Халқаралық ұйымдардың акцияларын сатып алу | F95: 137.32896 | G95: Приобретение акций международных организаций
A96: 6 | D96: Мемлекеттік-жекешелік әріптестік жобалар бойынша мемлекеттік міндеттемелерді орындау | F96: 32369.34 | G96: Выполнение государственных обязательств по проектам государственно-частного партнерства
A97: L01 Категория расходов | B97: 810 | D97: Мемлекеттік концессиялық міндеттемелерді орындау | F97: 32369.34 | G97: Выполнение государственных концессионных обязательств
A98: 6 | B98: 810 | C98: 812 | D98: Мемлекеттік-жекешелік әріптестік жобалар бойынша инвестициялық шығындарды өтеу бойынша мемлекеттік міндеттемелерді орындау | F98: 10472.874 | G98: Выполнение государственных обязательств по компенсации инвестиционных затрат по проектам государственно-частного партнерства
A99: 6 | C99: 813 | D99: Мемлекеттік-жекешелік әріптестік жобалар бойынша операциялық (пайдалану) шығындарды өтеу бойынша мемлекеттік міндеттемелерді орындау | F99: 390.7835 | G99: Выполнение государственных обязательств по компенсации операционных (эксплуатационных) затрат по проектам государственно-частного п
A100: 6 | C100: 814 | D100: Мемлекеттік-жекешелік әріптестік объектісін басқаруды жүзеге асырғаны үшін сыйақы төлемі бойынша мемлекеттік міндеттемелерді орындау | F100: 21505.683 | G100: Выполнение государственных обязательств по выплате вознаграждений за осуществление управления объектом государственно-частного парт

Sheet таб 11
A1: 11-кесте ШЫҒЫНДАРДЫҢ ЭКОНОМИКАЛЫҚ ЖІКТЕМЕСІ БОЙЫНША ЖЕРГІЛІКТІ БЮДЖЕТТІК ОРЫНДАЛУЫ (млн.теңге) | E1: Таблица 11 ИСПОЛНЕНИЕ МЕСТНОГО БЮДЖЕТА ПО ЭКОНОМИЧЕСКОЙ КЛАССИФИКАЦИИ РАСХОДОВ (млн. тенге)
A3: Cанаты/_x000D_ Категория | B3: Iшкi сыныбы/_x000D_ Подкласс | C3: Ерекшелiгi/_x000D_ Специфика | D3: Атауы | F3: 2025 ж. қаңтар-шілде/_x000D_ январь-июль отчет 2025 г. | G3: Наименование
A4: 1 | B4: 2 | C4: 3 | D4: 4 | F4: 5 | G4: 6
D5: БАРЛЫҒЫ | F5: 8922479.3 | G5: ВСЕГО
A6: 1 | D6: Ағымдағы шығындар | F6: 6640100.4 | G6: Текущие затраты
A7: L01 Категория расходов | B7: 110 | D7: Жалақы | F7: 2089142.2 | G7: Заработная плата
A8: 1 | B8: 110 | C8: 111 | D8: Еңбекке ақы төлеу | F8: 1835834.1 | G8: Оплата труда
A9: 1 | C9: 112 | D9: Қосымша ақшалай төлемдер | F9: 63570.066 | G9: Дополнительные денежные выплаты
A10: 1 | C10: 113 | D10: Өтемақы төлемдері | F10: 160352.72 | G10: Компенсационные выплаты
A11: 1 | C11: 114 | D11: Міндетті кәсіптік зейнетақы жарналары | F11: 7.0122609 | G11: Обязательные профессиональные пенсионные взносы
A12: 1 | C12: 116 | D12: Жұмыс берушілердің міндетті зейнетақы жарналары | F12: 29378.324 | G12: Обязательные пенсионные взносы работодателей
A13: L01 Категория расходов | B13: 120 | D13: Жұмыс берушілердің жарналары | F13: 220144.78 | G13: Взносы работодателей
A14: 1 | B14: 120 | C14: 121 | D14: Әлеуметтік салық | F14: 100132.36 | G14: Социальный налог
A15: 1 | C15: 122 | D15: Мемлекеттiк әлеуметтiк сақтандыру қорына әлеуметтiк аударымдар | F15: 73570.265 | G15: Социальные отчисления в Государственный фонд социального страхования
A16: 1 | C16: 123 | D16: Мiндеттi сақтандыру жарналары | F16: 681.11039 | G16: Взносы на обязательное страхование
A17: 1 | C17: 124 | D17: Міндетті әлеуметтік медициналық сақтандыруға аударымдар | F17: 45761.051 | G17: Отчисления на обязательное социальное медицинское страхование
A18: L01 Категория расходов | B18: 130 | D18: Қазақстан Республикасының заңнамалық актілеріне сәйкес азаматтардың жекелеген санаттарына жалақы төлеу және жарналар аудару | F18: 61633.245 | G18: Выплата заработной платы отдельным категориям граждан и отчисления взносов в соответствии с законодательными актами Республики Казахстан
A19: 1 | B19: 130 | C19: 131 | D19: Техникалық персоналдың еңбегіне ақы төлеу | F19: 53249.682 | G19: Оплата труда технического персонала
A20: 1 | C20: 133 | D20: Негізгі жұмыс орны бойынша мәслихат депутаттарына орташа жалақыны өтеу | F20: 0.534632 | G20: Возмещение средней заработной платы депутатам маслихата по их основному месту работы
A21: 1 | C21: 135 | D21: Техникалық персонал бойынша жұмыс берушілердің жарналары | F21: 7015.5253 | G21: Взносы работодателей по техническому персоналу
A22: 1 | C22: 136 | D22: Техникалық персоналдың ел iшiндегi iссапарлары мен қызметтiк сапарлары | F22: 1367.503 | G22: Командировки и служебные разъезды внутри страны технического персонала
A23: L01 Категория расходов | B23: 140 | D23: Қорлар сатып алу | F23: 154532.09 | G23: Приобретение запасов
A24: 1 | B24: 140 | C24: 141 | D24: Азық-түлiк өнiмдерiн сатып алу | F24: 19757.629 | G24: Приобретение продуктов питания
A25: 1 | C25: 142 | D25: Дәрілік заттар және медициналық мақсаттағы өзге де бұйымдарды сатып алу | F25: 51295.926 | G25: Приобретение лекарственных средств и прочих изделий медицинского назначения
A26: 1 | C26: 143 | D26: Заттай мүлiктердi, басқа да киім нысанын және арнаулы киім-кешектер сатып алу, тiгу және жөндеу | F26: 3069.7892 | G26: Приобретение, пошив и ремонт предметов вещевого имущества идругого форменного и специального обмундирования
A27: 1 | C27: 144 | D27: Отын, жанар-жағар май материалдарын сатып алу | F27: 30240.043 | G27: Приобретение топлива, горюче-смазочных материалов
A28: 1 | C28: 149 | D28: Өзге де қорларды сатып алу | F28: 50168.705 | G28: Приобретение прочих запасов
A29: L01 Категория расходов | B29: 150 | D29: Қызметтер мен жұмыстарды сатып алу | F29: 2160755 | G29: Приобретение услуг и работ
A30: 1 | B30: 150 | C30: 151 | D30: Коммуналдық қызметтерге ақы төлеу | F30: 101794.28 | G30: Оплата коммунальных услуг
A31: 1 | C31: 152 | D31: Байланыс қызметтерiне ақы төлеу | F31: 17468.594 | G31: Оплата услуг связи
A32: 1 | C32: 153 | D32: Көлiктiк қызмет көрсетулерге ақы төлеу | F32: 9872.0479 | G32: Оплата транспортных услуг
A33: 1 | C33: 154 | D33: Зерттеулер бойынша қызметтерге ақы төлеу | F33: 259.69787 | G33: Оплата услуг по исследованиям
A34: 1 | C34: 155 | D34: Мемлекеттiк әлеуметтiк тапсырыс шеңберiнде көрсетілетін қызметтерге ақы төлеу | F34: 23268.017 | G34: Оплата услуг в рамках государственного социального заказа
A35: 1 | C35: 157 | D35: Форумдар, семинарлар, конференциялар өткізуге және имидждік іс-шараларға арналған қызметтерге ақы төлеу | F35: 1276.5891 | G35: Оплата услуг на проведение форумов, семинаров, конференций и на имиджевые мероприятия
A36: 1 | C36: 158 | D36: Ақпараттандыру саласындағы жұмыстар мен қызметтерге ақы төлеу | F36: 20414.589 | G36: Оплата работ и услуг в сфере информатизации
A37: 1 | C37: 159 | D37: Өзге де қызметтер мен жұмыстарға ақы төлеу | F37: 1986401.2 | G37: Оплата прочих услуг и работ
A38: L01 Категория расходов | B38: 160 | D38: Басқа да ағымдағы шығындар | F38: 449267.09 | G38: Другие текущие затраты
A39: 1 | B39: 160 | C39: 161 | D39: Ел iшiндегi iссапарлар мен қызметтiк сапарлар | F39: 22001.721 | G39: Командировки и служебные разъезды внутри страны
A40: 1 | C40: 162 | D40: Елден тыс жерлерге iссапарлар мен қызметтiк сапарлар | F40: 2768.5644 | G40: Командировки и служебные разъезды за пределы страны
A41: 1 | C41: 163 | D41: Жалпыға бiрдей мiндеттi орта бiлiм қорының шығындары | F41: 46571.898 | G41: Затраты Фонда всеобщего обязательного среднего образования
A42: 1 | C42: 165 | D42: Атқарушылық құжаттарының, сот актiлерiнiң орындалуы | F42: 29275.332 | G42: Исполнение исполнительных документов, судебных актов
A43: 1 | C43: 169 | D43: Өзге де ағымдағы шығындар | F43: 348649.58 | G43: Прочие текущие затраты
A44: L01 Категория расходов | B44: 210 | D44: Ішкі қарыздар бойынша сыйақы төлемдері | F44: 17497.174 | G44: Выплаты вознаграждений по внутренним займам
A45: 1 | B45: 210 | C45: 212 | D45: Жоғары тұрған бюджеттен жергiлiктi атқарушы органдар алған қарыздар бойынша сыйақы төлемдері | F45: 104.68752 | G45: Выплаты вознаграждений по займам, полученным из вышестоящего бюджета местными исполнительными органами
A46: 1 | C46: 213 | D46: Бұл ерекшелiкте жергілікті атқарушы органдардың ішкі қарыздары бойынша сыйақыларды төлеу іске асырылады | F46: 17392.486 | G46: Выплаты вознаграждений по внутренним займам местных исполнительных органов
A47: L01 Категория расходов | B47: 310 | D47: Бюджеттік субсидиялар | F47: 884827.92 | G47: Бюджетные субсидии
A48: 1 | B48: 310 | C48: 311 | D48: Жеке және заңды тұлғаларға, оның ішінде шаруа (фермерлік) қожалықтарына берілетін субсидиялар | F48: 884827.92 | G48: Субсидии физическим и юридическим лицам, в том числе крестьянским (фермерским) хозяйствам
A49: L01 Категория расходов | B49: 320 | D49: Жеке тұлғаларға берілетін трансферттер | F49: 235256.8 | G49: Трансферты физическим лицам
A50: 1 | B50: 320 | C50: 321 | D50: Арнайы мемлекеттік органдардың қызметкерлеріне және əскери қызметшілеріне тұрғын үй төлемдері | F50: 33013.676 | G50: Жилищные выплаты сотрудникам специальных государственных органов и военнослужащим
A51: 1 | C51: 322 | D51: Жеке тұлғаларға берiлетiн трансферттер | F51: 155813.83 | G51: Трансферты физическим лицам
A52: 1 | C52: 324 | D52: Стипендиялар | F52: 46429.289 | G52: Стипендии
A53: L01 Категория расходов | B53: 330 | D53: Мемлекеттiк басқарудың басқа деңгейлерiне берiлетiн ағымдағытрансферттер | F53: 358902.63 | G53: Текущие трансферты другим уровням государственного управления
A54: 1 | B54: 330 | C54: 332 | D54: Бюджеттiк алып қоюлар | F54: 346642.91 | G54: Бюджетные изъятия
A55: 1 | C55: 336 | D55: Бюджет заңнамасымен қарастырылған жағдайларда жалпы сипаттағы трансферттерды қайтару | F55: 1400.276 | G55: Возврат трансфертов общего характера в случаях, предусмотренных бюджетным законодательством
A56: 1 | C56: 338 | D56: Нысаналы трансферттерді қайтару | F56: 8231.3767 | G56: Возврат целевых трансфертов
A57: 1 | C57: 339 | D57: Мемлекеттiк басқарудың басқа деңгейлерiне берiлетiн ағымдағы трансферттер | F57: 2628.07 | G57: Текущие трансферты другим уровням государственного управления
A58: L01 Категория расходов | B58: 340 | D58: Шетелге берiлетiн ағымдағы трансферттер | F58: 3.7942422 | G58: Текущие трансферты за границу
A59: 1 | B59: 340 | C59: 341 | D59: Шетелдегi ұйымдарға ағымдағы трансферттер | F59: 3.7942422 | G59: Текущие трансферты за границу
A60: L01 Категория расходов | B60: 350 | D60: Өзге де ағымдағы трансферттер | F60: 8137.7407 | G60: Прочие текущие трансферты
A61: 1 | B61: 350 | C61: 352 | D61: Қазақстан Республикасының Ұлттық қорынан тартылған қаражаттың бір бөлігін қайтару | F61: 8137.7407 | G61: Возврат части средств, привлеченных из Национального фонда Республики Казахстан
A62: 2 | D62: Күрделі шығындар | F62: 1833970.5 | G62: Капитальные затраты
A63: L01 Категория расходов | B63: 410 | D63: Негiзгi құралдарды, материалдық емес және биологиялық активтерді сатып алу | F63: 330429.69 | G63: Приобретение основных средств, нематериальных и биологических активов
A64: 2 | B64: 410 | C64: 411 | D64: Жер сатып алу | F64: 45484.117 | G64: Приобретение земли
A65: 2 | C65: 412 | D65: Үй-жайлар, ғимараттар мен құрылыстарды, беру қондырғыларын сатып алу | F65: 110885.32 | G65: Приобретение помещений, зданий, сооружений, передаточных устройств
A66: 2 | C66: 413 | D66: Көлік құралдарын сатып алу | F66: 67066.059 | G66: Приобретение транспортных средств
A67: 2 | C67: 414 | D67: Машиналар, жабдықтар, өндірістік және шаруашылық мүккамал құралдарын сатып алу | F67: 69329.146 | G67: Приобретение машин, оборудования, инструментов, производственного и хозяйственного инвентаря
A68: 2 | C68: 416 | D68: Материалдық емес активтерді сатып алу | F68: 827.12384 | G68: Приобретение нематериальных активов
A69: 2 | C69: 417 | D69: Биологиялық активтерді сатып алу | F69: 88.896323 | G69: Приобретение биологических активов
A70: 2 | C70: 418 | D70: Мемлекеттік кәсіпорындарды материалдық-техникалық жарақтандыру | F70: 26692.278 | G70: Материально-техническое оснащение государственных предприятий
A71: 2 | C71: 419 | D71: Өзге де негізгі құралдарды сатып алу | F71: 10056.749 | G71: Приобретение прочих основных средств
A72: L01 Категория расходов | B72: 420 | D72: Негізгі қаражатты күрделі жөндеу | F72: 228086.27 | G72: Капитальный ремонт основных средств
A73: 2 | B73: 420 | C73: 421 | D73: Жайларды, ғимараттарды, құрылыстарды, беру қондырғыларын күрделі жөндеу | F73: 108696.03 | G73: Капитальный ремонт помещений, зданий, сооружений, передаточных устройств
A74: 2 | C74: 422 | D74: Жолдарды күрделі жөндеу | F74: 75978.113 | G74: Капитальный ремонт дорог
A75: 2 | C75: 423 | D75: Мемлекеттiк кәсiпорындардың жайларын, ғимараттарын, құрылыстарын күрделі жөндеу | F75: 41918.17 | G75: Капитальный ремонт помещений, зданий, сооружений государственных предприятий
A76: 2 | C76: 429 | D76: Өзге де негізгі қаражатты күрделі жөндеу | F76: 1493.9542 | G76: Капитальный ремонт прочих основных средств
A77: L01 Категория расходов | B77: 430 | D77: Дамуға бағытталған күрделі шығындар | F77: 1275454.5 | G77: Капитальные затраты, направленные на развитие
A78: 2 | B78: 430 | C78: 431 | D78: Жаңа объектілерді салу және қолдағы объектілерді реконструкциялау | F78: 1113656.1 | G78: Строительство новых объектов и реконструкция имеющихся объектов
A79: 2 | C79: 432 | D79: Жолдар салу | F79: 161380.59 | G79: Строительство дорог
A80: 2 | C80: 435 | D80: Мемлекеттік кәсіпорындардың жаңа объектілерін салу және қолдағы бар объектілерін реконструкциялау | F80: 417.88965 | G80: Строительство новых объектов и реконструкция имеющихся объектов государственных предприятий
A81: 3 | D81: Бюджеттік кредиттер | F81: 107409.96 | G81: Бюджетные кредиты
A82: L01 Категория расходов | B82: 510 | D82: Ішкі бюджеттік кредиттер | F82: 107409.96 | G82: Внутренние бюджетные кредиты
A83: 3 | B83: 510 | C83: 513 | D83: Мамандандырылған ұйымдарға бюджеттік кредиттер | F83: 96603.168 | G83: Бюджетные кредиты специализированным организациям
A84: 3 | C84: 514 | D84: Жеке тұлғаларға берілетін бюджеттік кредиттер | F84: 407.829 | G84: Бюджетные кредиты физическим лицам
A85: 3 | C85: 519 | D85: Өзге де ішкі бюджеттік кредиттер | F85: 10398.967 | G85: Прочие внутренние бюджетные кредиты
A86: 4 | D86: Қаржы активтерін сатып алу | F86: 279333.12 | G86: Приобретение финансовых активов
A87: L01 Категория расходов | B87: 610 | D87: Қаржы активтерін сатып алу | F87: 279333.12 | G87: Приобретение финансовых активов
A88: 4 | B88: 610 | C88: 611 | D88: Заңды тұлғалардың қатысу үлесін, бағалы қағаздарын сатып алу | F88: 440.19267 | G88: Приобретение долей участия, ценных бумаг юридических лиц
A89: 4 | C89: 612 | D89: Квазимемлекеттік сектордың жарғылық капиталын қалыптастыру және ұлғайту | F89: 278892.93 | G89: Формирование и увеличение уставных капиталов субъектов квазигосударственного сектора
A90: 6 | D90: Мемлекеттік-жекешелік әріптестік жобалар бойынша мемлекеттік міндеттемелерді орындау | F90: 61665.258 | G90: Выполнение государственных обязательств по проектам государственно-частного партнерства
A91: L01 Категория расходов | B91: 810 | D91: Мемлекеттік концессиялық міндеттемелерді орындау | F91: 61665.258 | G91: Выполнение государственных концессионных обязательств
A92: 6 | B92: 810 | C92: 812 | D92: Мемлекеттік-жекешелік әріптестік жобалар бойынша инвестициялық шығындарды өтеу бойынша мемлекеттік міндеттемелерді орындау | F92: 12614.127 | G92: Выполнение государственных обязательств по компенсации инвестиционных затрат по проектам государственно-частного партнерства
A93: 6 | C93: 813 | D93: Мемлекеттік-жекешелік әріптестік жобалар бойынша операциялық (пайдалану) шығындарды өтеу бойынша мемлекеттік міндеттемелерді орындау | F93: 24909.025 | G93: Выполнение государственных обязательств по компенсации операционных (эксплуатационных) затрат по проектам государственно-частного п
A94: 6 | C94: 814 | D94: Мемлекеттік-жекешелік әріптестік объектісін басқаруды жүзеге асырғаны үшін сыйақы төлемі бойынша мемлекеттік міндеттемелерді орындау | F94: 10828.897 | G94: Выполнение государственных обязательств по выплате вознаграждений за осуществление управления объектом государственно-частного парт
A95: 6 | C95: 815 | D95: Мемлекеттік-жекешелік әріптестік жобалар бойынша өзге де төлемдер бойынша мемлекеттік міндеттемелерді орындау | F95: 13313.21 | G95: Выполнение государственных обязательств по прочим выплатам по проектам государственно-частного партнерства

Sheet табл 12
A1: 12-кесте | E1: Таблица 12
A2: ЖЕРГІЛІКТІ БЮДЖЕТТЕРДІҢ АТҚАРЫЛУЫ | E2: ИСПОЛНЕНИЕ МЕСТНЫХ БЮДЖЕТОВ
A3: (млн.теңге) | E3: (млн. тенге)
A5: Атауы | B5: 2022 ж. есеп/ 2022 г. отчет | C5: 2023 ж. есеп/ 2023 г. отчет | D5: 2024 ж. есеп/ 2024 г. отчет | F5: 2025 ж. қантар-шілде есеп/январь-июль отчет 2025 г. | G5: Наименование
D6: жылдық/ годовой | E6: қантар-шілде/январь-июль
A7: 1 | B7: 2 | C7: 3 | D7: 4 | E7: 5 | F7: 6 | G7: 7
A8: I. КІРІСТЕР | B8: 10976144 | C8: 13552443 | D8: 15346311 | E8: 8579318.7 | F8: 9284396.9 | G8: I. ДОХОДЫ
A9: Салықтық түсімдер_x000D_ оның iшiнде: | B9: 4816486 | C9: 5999776.2 | D9: 7392707.2 | E9: 4203555.8 | F9: 4833962.3 | G9: Налоговые поступления,_x000D_ в том числе:
A10: корпорациялық табыс салығы | B10: 1041693.1 | C10: 1156101.6 | D10: 1560100.6 | E10: 959476.07 | F10: 1039754 | G10: корпоративный подоходный налог
A11: жеке табыс салығы | B11: 1499712.4 | C11: 1992384.9 | D11: 2451640 | E11: 1403794.1 | F11: 1591651.2 | G11: индивидуальный подоходный налог
A12: әлеуметтік салық | B12: 1035129 | C12: 1321272.8 | D12: 1579329.4 | E12: 887436.98 | F12: 1042470.7 | G12: социальный налог
A13: акциздер | B13: 603647.65 | C13: 678325.27 | D13: 719720.32 | E13: 378160.01 | F13: 479115.09 | G13: акцизы
A14: Салықтық емес түсімдер | B14: 146944.73 | C14: 205639.7 | D14: 429128.27 | E14: 271741.75 | F14: 249412.25 | G14: Неналоговые поступления
A15: Негізгі капиталды сатудан түсетін түсімдер | B15: 232986.54 | C15: 181373.04 | D15: 195509.62 | E15: 104869.47 | F15: 101496.29 | G15: Поступления от продажи основного капитала
A16: Трансферттердің түсімдері | B16: 5779727.2 | C16: 7165654.2 | D16: 7328965.7 | E16: 3999151.6 | F16: 4099526.1 | G16: Поступления трансфертов
A17: II. ШЫҒЫНДАР | B17: 10443228 | C17: 12885357 | D17: 15049842 | E17: 7387666.3 | F17: 8546029.3 | G17: II. ЗАТРАТЫ
A18: 1. Жалпы сипаттағы мемлекеттiк қызметтер | B18: 373213.62 | C18: 498739.23 | D18: 626197.96 | E18: 322792.87 | F18: 331928.03 | G18: 1. Государственные услуги общего характера
A19: 2. Қорғаныс | B19: 46952.254 | C19: 74063.282 | D19: 146000.92 | E19: 76466.76 | F19: 60465.418 | G19: 2. Оборона
... A44: Өтеу | B44: 328271.04 | C44: 229127.97 | D44: 296668.47 | E44: 245660.07 | F44: 103995.54 | G44: Погашение
A45: Сыртқы | B45: -1516.9375 | C45: -1880.877 | D45: -868.7564 | E45: -868.7564 | F45: - | G45: Внешнее
A46: Түсімдер | B46: - | C46: - | D46: - | E46: - | F46: - | G46: Поступление
A47: Өтеу | B47: 1516.9375 | C47: 1880.877 | D47: 868.7564 | E47: 868.7564 | F47: - | G47: Погашение

Sheet табл 12.1
A1: 12.1-кесте | E1: Таблица 12.1
A2: АҚМОЛА ОБЛЫСЫ | E2: ИСПОЛНЕНИЕ БЮДЖЕТА
A3: БЮДЖЕТІНІҢ АТҚАРЫЛУЫ | E3: АКМОЛИНСКАЯ ОБЛАСТЬ
A4: (млн.теңге) | E4: (млн. тенге)
A5: Атауы | B5: 2022 ж. есеп/ 2022 г. отчет | C5: 2023 ж. есеп/ 2023 г. отчет | D5: 2024 ж. есеп/ 2024 г. отчет | F5: 2025 ж. қантар-шілде есеп/январь-июль отчет 2025 г. | G5: Наименование
D6: жылдық/ годовой | E6: қантар-шілде/январь-июль
A7: 1 | B7: 2 | C7: 3 | D7: 4 | E7: 5 | F7: 6 | G7: 7
A8: I. КІРІСТЕР | B8: 479342.52 | C8: 630074.59 | D8: 707086.76 | E8: 412812.61 | F8: 400854.06 | G8: I. ДОХОДЫ
A9: Салықтық түсімдер_x000D_ оның iшiнде: | B9: 131206.29 | C9: 166838.2 | D9: 193200.14 | E9: 108424.75 | F9: 119577.38 | G9: Налоговые поступления,_x000D_ в том числе:
A10: корпорациялық табыс салығы | B10: 18604.661 | C10: 26898.106 | D10: 29578.991 | E10: 17461.491 | F10: 17554.029 | G10: корпоративный подоходный налог
A11: жеке табыс салығы | B11: 43758.869 | C11: 57696.794 | D11: 70347.91 | E11: 40518.046 | F11: 44643.509 | G11: индивидуальный подоходный налог
A12: әлеуметтік салық | B12: 27495.02 | C12: 36673.221 | D12: 43624.91 | E12: 23646.578 | F12: 27753.449 | G12: социальный налог
A13: акциздер | B13: 20076.53 | C13: 18706.909 | D13: 21122.258 | E13: 10422.29 | F13: 11772.111 | G13: акцизы
A14: Салықтық емес түсімдер | B14: 6880.8375 | C14: 10031.309 | D14: 17228.574 | E14: 14473.789 | F14: 11192.096 | G14: Неналоговые поступления
A15: Негізгі капиталды сатудан түсетін түсімдер | B15: 4360.0479 | C15: 4230.2271 | D15: 6929.2453 | E15: 3716.1183 | F15: 9093.4907 | G15: Поступления от продажи основного капитала
A16: Трансферттердің түсімдері | B16: 336895.34 | C16: 448974.85 | D16: 489728.81 | E16: 286197.95 | F16: 260991.1 | G16: Поступления трансфертов
A17: II. ШЫҒЫНДАР | B17: 476797.2 | C17: 629557.51 | D17: 718203.43 | E17: 364544.46 | F17: 384650.31 | G17: II. ЗАТРАТЫ
A18: 1. Жалпы сипаттағы мемлекеттiк қызметтер | B18: 20688.527 | C18: 34057.909 | D18: 38754.396 | E18: 20140.521 | F18: 21797.017 | G18: 1. Государственные услуги общего характера
A19: 2. Қорғаныс | B19: 8863.386 | C19: 7702.9187 | D19: 8416.1057 | E19: 4549.5268 | F19: 4649.0263 | G19: 2. Оборона
... A44: Өтеу | B44: 7150.5953 | C44: 6116.8467 | D44: 10973.542 | E44: 9578.2712 | F44: 5569.4069 | G44: Погашение
A45: Сыртқы | B45: - | C45: - | D45: - | E45: - | F45: - | G45: Внешнее
A46: Түсімдер | B46: - | C46: - | D46: - | E46: - | F46: - | G46: Поступление
A47: Өтеу | B47: - | C47: - | D47: - | E47: - | F47: - | G47: Погашение

Sheet табл 12.2
A1: 12.2-кесте | E1: Таблица 12.2
A2: АҚТОБЕ ОБЛЫСЫ | E2: ИСПОЛНЕНИЕ БЮДЖЕТА
A3: БЮДЖЕТІНІҢ АТҚАРЫЛУЫ | E3: АКТЮБИНСКАЯ ОБЛАСТЬ
A4: (млн.теңге) | E4: (млн. тенге)
A5: Атауы | B5: 2022 ж. есеп/ 2022 г. отчет | C5: 2023 ж. есеп/ 2023 г. отчет | D5: 2024 ж. есеп/ 2024 г. отчет | F5: 2025 ж. қантар-шілде есеп/январь-июль отчет 2025 г. | G5: Наименование
D6: жылдық/ годовой | E6: қантар-шілде/январь-июль
A7: 1 | B7: 2 | C7: 3 | D7: 4 | E7: 5 | F7: 6 | G7: 7
A8: I. КІРІСТЕР | B8: 439365.9 | C8: 601085.02 | D8: 676122.67 | E8: 366228.82 | F8: 351918.83 | G8: I. ДОХОДЫ
A9: Салықтық түсімдер_x000D_ оның iшiнде: | B9: 169788.03 | C9: 217147.69 | D9: 258870.07 | E9: 145414.37 | F9: 163106.48 | G9: Налоговые поступления,_x000D_ в том числе:
A10: корпорациялық табыс салығы | B10: 22794.56 | C10: 27092.378 | D10: 35280.087 | E10: 20187.513 | F10: 26128.24 | G10: корпоративный подоходный налог
A11: жеке табыс салығы | B11: 53618.784 | C11: 71801.508 | D11: 89575.631 | E11: 51557.114 | F11: 57710.571 | G11: индивидуальный подоходный налог
A12: әлеуметтік салық | B12: 39432.497 | C12: 50661.538 | D12: 60866.559 | E12: 34558.605 | F12: 37677.079 | G12: социальный налог
A13: акциздер | B13: 11907.391 | C13: 12786.271 | D13: 18850.711 | E13: 8361.1062 | F13: 9805.6733 | G13: акцизы
A14: Салықтық емес түсімдер | B14: 9083.1145 | C14: 11013.336 | D14: 22063.261 | E14: 15298.997 | F14: 9526.3089 | G14: Неналоговые поступления
A15: Негізгі капиталды сатудан түсетін түсімдер | B15: 6278.8853 | C15: 5032.1948 | D15: 6404.1867 | E15: 1939.0239 | F15: 2091.4493 | G15: Поступления от продажи основного капитала
A16: Трансферттердің түсімдері | B16: 254215.87 | C16: 367891.79 | D16: 388785.15 | E16: 203576.43 | F16: 177194.59 | G16: Поступления трансфертов
A17: II. ШЫҒЫНДАР | B17: 430148.05 | C17: 572439.64 | D17: 692559.6 | E17: 332533.93 | F17: 354665.11 | G17: II. ЗАТРАТЫ
A18: 1. Жалпы сипаттағы мемлекеттiк қызметтер | B18: 18351.498 | C18: 38185.996 | D18: 53420.173 | E18: 29806.061 | F18: 18793.709 | G18: 1. Государственные услуги общего характера
A19: 2. Қорғаныс | B19: 2054.6106 | C19: 3456.9188 | D19: 6083.1211 | E19: 1956.2799 | F19: 3211.578 | G19: 2. Оборона
... A37: Қаржылық активтерді сатып алу | B37: 168.3192 | C37: 102 | D37: 194.7798 | E37: 194.7798 | F37: 311.075 | G37: Приобретение финансовых активов
A38: Мемлекеттің қаржы активтерін сатудан түсетін түсімдер | B38: -1.927458 | G38: Поступления от продажи финансовых активов государства
A39: V. БЮДЖЕТ ТАПШЫЛЫҒЫ (ПРОФИЦИТІ) | B39: 3321.1958 | C39: 11136.075 | D39: -17543.714 | E39: 39600.047 | F39: -119.82452 | G39: V. ДЕФИЦИТ (ПРОФИЦИТ) БЮДЖЕТА
A41: VII. БЮДЖЕТТІҢ ТАПШЫЛЫҒЫН ҚАРЖЫЛАНДЫРУ (ПРОФИЦИТТІ ПАЙДАЛАНУ | B41: -3321.1958 | C41: -11136.075 | D41: -17543.714 | E41: -39600.047 | F41: 119.82452 | G41: VII. ФИНАНСИРОВАНИЕ ДЕФИЦИТА (ИСПОЛЬЗОВАНИЕ ПРОФИЦИТА) БЮДЖЕТА
A42: Ішкі | B42: -34443.176 | C42: -312074.58 | D42: -6027.6511 | E42: -469600.19 | F42: 119.82452 | G42: Внутреннее
A43: Түсімдер | B43: -23232.618 | C43: -301203.36 | D43: 7654.2188 | E43: -460555.19 | F43: 9282.3511 | G43: Поступление
A44: Өтеу | B44: 11210.558 | C44: 10871.218 | D44: 13681.87 | E44: 9045.0003 | F44: 9162.5266 | G44: Погашение
A45: Сыртқы | B45: - | C45: - | D45: - | E45: - | F45: - | G45: Внешнее
A46: Түсімдер | B46: - | C46: - | D46: - | E46: - | F46: - | G46: Поступление
A47: Өтеу | B47: - | C47: - | D47: - | E47: - | F47: - | G47: Погашение

Sheet табл 12.3
A1: 12.3-кесте | E1: Таблица 12.3
A2: АЛМАТЫ ОБЛЫСЫ | E2: ИСПОЛНЕНИЕ БЮДЖЕТА
A3: БЮДЖЕТІНІҢ АТҚАРЫЛУЫ | E3: АЛМАТИНСКАЯ ОБЛАСТЬ
A4: (млн.теңге) | E4: (млн. тенге)
A5: Атауы | B5: 2022 ж. есеп/ 2022 г. отчет | C5: 2023 ж. есеп/ 2023 г. отчет | D5: 2024 ж. есеп/ 2024 г. отчет | F5: 2025 ж. қантар-шілде есеп/январь-июль отчет 2025 г. | G5: Наименование
D6: жылдық/ годовой | E6: қантар-шілде/январь-июль
A7: 1 | B7: 2 | C7: 3 | D7: 4 | E7: 5 | F7: 6 | G7: 7
A8: I. КІРІСТЕР | B8: 727110.2 | C8: 755699.04 | D8: 832469.88 | E8: 470852.8 | F8: 527583.04 | G8: I. ДОХОДЫ
A9: Салықтық түсімдер_x000D_ оның iшiнде: | B9: 420356.25 | C9: 388446.56 | D9: 491276.75 | E9: 270794.87 | F9: 336375.22 | G9: Налоговые поступления,_x000D_ в том числе:
A10: корпорациялық табыс салығы | B10: 76082.806 | C10: 34158.596 | D10: 57113.634 | E10: 34537.112 | F10: 43994.928 | G10: корпоративный подоходный налог
A11: жеке табыс салығы | B11: 79789.776 | C11: 85030.922 | D11: 118580.99 | E11: 74695.847 | F11: 69175.615 | G11: индивидуальный подоходный налог
A12: әлеуметтік салық | B12: 38557.426 | C12: 40395.425 | D12: 54091.398 | E12: 29793.518 | F12: 35768.339 | G12: социальный налог
A13: акциздер | B13: 192892.72 | C13: 199121.45 | D13: 226071.95 | E13: 109737.21 | F13: 160712.32 | G13: акцизы
A14: Салықтық емес түсімдер | B14: 6533.346 | C14: 5738.8874 | D14: 20653.374 | E14: 15019.575 | F14: 9839.3319 | G14: Неналоговые поступления
A15: Негізгі капиталды сатудан түсетін түсімдер | B15: 7164.6916 | C15: 6153.3465 | D15: 8607.4865 | E15: 4786.8027 | F15: 6435.9816 | G15: Поступления от продажи основного капитала
A16: Трансферттердің түсімдері | B16: 293055.91 | C16: 355360.25 | D16: 311932.27 | E16: 180251.56 | F16: 174932.5 | G16: Поступления трансфертов
A17: II. ШЫҒЫНДАР | B17: 709629.21 | C17: 752774.03 | D17: 838922.5 | E17: 439658.44 | F17: 488840.25 | G17: II. ЗАТРАТЫ
A18: 1. Жалпы сипаттағы мемлекеттiк қызметтер | B18: 31480.892 | C18: 26808.017 | D18: 24546.153 | E18: 12337.232 | F18: 16473.846 | G18: 1. Государственные услуги общего характера
A19: 2. Қорғаныс | B19: 1866.7625 | C19: 2158.7445 | D19: 4038.0936 | E19: 1292.4383 | F19: 2893.4562 | G19: 2. Оборона
... A37: Қаржылық активтерді сатып алу | B37: 3727.148 | C37: 7439.182 | D37: 8291.7479 | E37: 7591.7479 | F37: 6322.458 | G37: Приобретение финансовых активов
A38: Мемлекеттің қаржы активтерін сатудан түсетін түсімдер | C38: 5.1049999 | F38: 4.946728 | G38: Поступления от продажи финансовых активов государства
A39: V. БЮДЖЕТ ТАПШЫЛЫҒЫ (ПРОФИЦИТІ) | B39: 14886.511 | C39: -32271.614 | D39: -19347.425 | E39: 27697.673 | F39: 34510.08 | G39: V. ДЕФИЦИТ (ПРОФИЦИТ) БЮДЖЕТА
A41: VII. БЮДЖЕТТІҢ ТАПШЫЛЫҒЫН ҚАРЖЫЛАНДЫРУ (ПРОФИЦИТТІ ПАЙДАЛАНУ | B41: -14886.511 | C41: 32271.614 | D41: -19347.425 | E41: -27697.673 | F41: -34510.08 | G41: VII. ФИНАНСИРОВАНИЕ ДЕФИЦИТА (ИСПОЛЬЗОВАНИЕ ПРОФИЦИТА) БЮДЖЕТА
A42: Ішкі | B42: -164838.76 | C42: 76147.561 | D42: 3774.7945 | E42: -270015.67 | F42: -34510.08 | G42: Внутреннее
A43: Түсімдер | B43: -153888.28 | C43: 80801.049 | D43: 15303.941 | E43: -259590.47 | F43: -26747.594 | G43: Поступление
A44: Өтеу | B44: 10950.477 | C44: 4653.4875 | D44: 11529.146 | E44: 10425.2 | F44: 7762.4859 | G44: Погашение
A45: Сыртқы | B45: - | C45: - | D45: - | E45: - | F45: - | G45: Внешнее
A46: Түсімдер | B46: - | C46: - | D46: - | E46: - | F46: - | G46: Поступление
A47: Өтеу | B47: - | C47: - | D47: - | E47: - | F47: - | G47: Погашение

Sheet табл 12.4
A1: 12.4-кесте | E1: Таблица 12.4
A2: АТЫРАУ ОБЛЫСЫ | E2: ИСПОЛНЕНИЕ БЮДЖЕТА
A3: БЮДЖЕТІНІҢ АТҚАРЫЛУЫ | E3: АТЫРАУСКАЯ ОБЛАСТЬ
A4: (млн.теңге) | E4: (млн. тенге)
A5: Атауы | B5: 2022 ж. есеп/ 2022 г. отчет | C5: 2023 ж. есеп/ 2023 г. отчет | D5: 2024 ж. есеп/ 2024 г. отчет | F5: 2025 ж. қантар-шілде есеп/январь-июль отчет 2025 г. | G5: Наименование
D6: жылдық/ годовой | E6: қантар-шілде/январь-июль
A7: 1 | B7: 2 | C7: 3 | D7: 4 | E7: 5 | F7: 6 | G7: 7
A8: I. КІРІСТЕР | B8: 681966.2 | C8: 733369.76 | D8: 898777.25 | E8: 474266.03 | F8: 486966.94 | G8: I. ДОХОДЫ
A9: Салықтық түсімдер_x000D_ оның iшiнде: | B9: 541393.16 | C9: 643622.37 | D9: 783514.64 | E9: 416998.97 | F9: 456408.82 | G9: Налоговые поступления,_x000D_ в том числе:
A10: корпорациялық табыс салығы | B10: 60789.753 | C10: 74074.302 | D10: 60322.062 | E10: 36525.105 | F10: 35299.441 | G10: корпоративный подоходный налог
A11: жеке табыс салығы | B11: 160885.91 | C11: 176724.85 | D11: 170721.06 | E11: 103189.48 | F11: 96854.314 | G11: индивидуальный подоходный налог
A12: әлеуметтік салық | B12: 142985.12 | C12: 161262.4 | D12: 161395.59 | E12: 95405.636 | F12: 96679.66 | G12: социальный налог
A13: акциздер | B13: 82308.586 | C13: 120507.84 | D13: 122879.83 | E13: 74269.376 | F13: 89265.532 | G13: акцизы
A14: Салықтық емес түсімдер | B14: 8906.1194 | C14: 16168.04 | D14: 32940.563 | E14: 27242.189 | F14: 11122.404 | G14: Неналоговые поступления
A15: Негізгі капиталды сатудан түсетін түсімдер | B15: 7661.9213 | C15: 2333.9873 | D15: 2568.7507 | E15: 1521.7446 | F15: 1187.3091 | G15: Поступления от продажи основного капитала
A16: Трансферттердің түсімдері | B16: 124005.01 | C16: 71245.364 | D16: 79753.298 | E16: 28503.126 | F16: 18248.405 | G16: Поступления трансфертов
A17: II. ШЫҒЫНДАР | B17: 647544.75 | C17: 670273.07 | D17: 939255.77 | E17: 453327.62 | F17: 470477.73 | G17: II. ЗАТРАТЫ
A18: 1. Жалпы сипаттағы мемлекеттiк қызметтер | B18: 14547.242 | C18: 18263.609 | D18: 30985.339 | E18: 18320.181 | F18: 15771.058 | G18: 1. Государственные услуги общего характера
A19: 2. Қорғаныс | B19: 2560.754 | C19: 3723.3195 | D19: 60454.116 | E19: 45593.878 | F19: 15858.87 | G19: 2. Оборона
... A44: Өтеу | B44: 12555.846 | C44: 10689.549 | D44: 9794.9234 | E44: 9090.5969 | F44: 2328.6832 | G44: Погашение
A45: Сыртқы | B45: - | C45: - | D45: - | E45: - | F45: - | G45: Внешнее
A46: Түсімдер | B46: - | C46: - | D46: - | E46: - | F46: - | G46: Поступление
A47: Өтеу | B47: - | C47: - | D47: - | E47: - | F47: - | G47: Погашение

Sheet табл 12.5
A1: 12.5-кесте | E1: Таблица 12.5
A2: ШЫҒЫС-ҚАЗАҚСТАН ОБЛЫСЫ | E2: ИСПОЛНЕНИЕ БЮДЖЕТА
A3: БЮДЖЕТІНІҢ АТҚАРЫЛУЫ | E3: ВОСТ-КАЗАХСТАНСКАЯ ОБЛАСТЬ
A4: (млн.теңге) | E4: (млн. тенге)
A5: Атауы | B5: 2022 ж. есеп/ 2022 г. отчет | C5: 2023 ж. есеп/ 2023 г. отчет | D5: 2024 ж. есеп/ 2024 г. отчет | F5: 2025 ж. қантар-шілде есеп/январь-июль отчет 2025 г. | G5: Наименование
D6: жылдық/ годовой | E6: қантар-шілде/январь-июль
A7: 1 | B7: 2 | C7: 3 | D7: 4 | E7: 5 | F7: 6 | G7: 7
A8: I. КІРІСТЕР | B8: 562747.34 | C8: 485874.5 | D8: 554729.11 | E8: 305740.46 | F8: 303139.31 | G8: I. ДОХОДЫ
A9: Салықтық түсімдер_x000D_ оның iшiнде: | B9: 174505.46 | C9: 164390.14 | D9: 205394.71 | E9: 117339.64 | F9: 128576.33 | G9: Налоговые поступления,_x000D_ в том числе:
A10: корпорациялық табыс салығы | B10: 25605.38 | C10: 31322.068 | D10: 43204.659 | E10: 25541.462 | F10: 31286.826 | G10: корпоративный подоходный налог
A11: жеке табыс салығы | B11: 65842.061 | C11: 63550.133 | D11: 79837.166 | E11: 45652.863 | F11: 48020.912 | G11: индивидуальный подоходный налог
A12: әлеуметтік салық | B12: 48405.527 | C12: 44809.692 | D12: 53880.619 | E12: 30679.509 | F12: 32462.306 | G12: социальный налог
A13: акциздер | B13: 248.72341 | C13: 170.14397 | D13: 180.05535 | E13: 96.98753 | F13: 108.54467 | G13: акцизы
A14: Салықтық емес түсімдер | B14: 7127.6867 | C14: 5257.0033 | D14: 6223.1357 | E14: 3905.7392 | F14: 3312.9212 | G14: Неналоговые поступления
A15: Негізгі капиталды сатудан түсетін түсімдер | B15: 19509.245 | C15: 6863.7925 | D15: 6662.0791 | E15: 1941.4042 | F15: 1564.5763 | G15: Поступления от продажи основного капитала
A16: Трансферттердің түсімдері | B16: 361604.95 | C16: 309363.57 | D16: 336449.19 | E16: 182553.68 | F16: 169685.48 | G16: Поступления трансфертов
A17: II. ШЫҒЫНДАР | B17: 439783.11 | C17: 474312.87 | D17: 547229.27 | E17: 281183.5 | F17: 297468.31 | G17: II. ЗАТРАТЫ
A18: 1. Жалпы сипаттағы мемлекеттiк қызметтер | B18: 18081.748 | C18: 28901.504 | D18: 34187.037 | E18: 18074.208 | F18: 15618.426 | G18: 1. Государственные услуги общего характера
A19: 2. Қорғаныс | B19: 1524.8654 | C19: 2283.3219 | D19: 4437.5789 | E19: 1439.9617 | F19: 1775.5374 | G19: 2. Оборона
... A44: Өтеу | B44: 13287.252 | C44: 8649.0233 | D44: 17926.718 | E44: 17030.175 | F44: 7753.1232 | G44: Погашение
A45: Сыртқы | B45: - | C45: - | D45: - | E45: - | F45: - | G45: Внешнее
A46: Түсімдер | B46: - | C46: - | D46: - | E46: - | F46: - | G46: Поступление
A47: Өтеу | B47: - | C47: - | D47: - | E47: - | F47: - | G47: Погашение

Sheet табл 12.6
A1: 12.6-кесте | E1: Таблица 12.6
A2: ЖАМБЫЛ ОБЛЫСЫ | E2: ИСПОЛНЕНИЕ БЮДЖЕТА
A3: БЮДЖЕТІНІҢ АТҚАРЫЛУЫ | E3: ЖАМБЫЛСКАЯ ОБЛАСТЬ
A4: (млн.теңге) | E4: (млн. тенге)
A5: Атауы | B5: 2022 ж. есеп/ 2022 г. отчет | C5: 2023 ж. есеп/ 2023 г. отчет | D5: 2024 ж. есеп/ 2024 г. отчет | F5: 2025 ж. қантар-шілде есеп/январь-июль отчет 2025 г. | G5: Наименование
D6: жылдық/ годовой | E6: қантар-шілде/январь-июль
A7: 1 | B7: 2 | C7: 3 | D7: 4 | E7: 5 | F7: 6 | G7: 7
A8: I. КІРІСТЕР | B8: 557710.35 | C8: 647650.25 | D8: 701413.92 | E8: 387882.22 | F8: 432837.61 | G8: I. ДОХОДЫ
A9: Салықтық түсімдер_x000D_ оның iшiнде: | B9: 101009.01 | C9: 128310.79 | D9: 152453.16 | E9: 86453.214 | F9: 101047.55 | G9: Налоговые поступления,_x000D_ в том числе:
A10: корпорациялық табыс салығы | B10: 10857.684 | C10: 11965.332 | D10: 17174.038 | E10: 9351.0527 | F10: 10952.429 | G10: корпоративный подоходный налог
A11: жеке табыс салығы | B11: 35472.602 | C11: 46482.26 | D11: 59716.78 | E11: 33447.379 | F11: 38884.774 | G11: индивидуальный подоходный налог
A12: әлеуметтік салық | B12: 26573.441 | C12: 33811.337 | D12: 39604.881 | E12: 21963.061 | F12: 25471.211 | G12: социальный налог
A13: акциздер | B13: 3767.0016 | C13: 3309.4974 | D13: 3204.864 | E13: 2018.4093 | F13: 1773.4714 | G13: акцизы
A14: Салықтық емес түсімдер | B14: 6391.289 | C14: 11502.799 | D14: 15521.033 | E14: 9631.7595 | F14: 7323.1747 | G14: Неналоговые поступления
A15: Негізгі капиталды сатудан түсетін түсімдер | B15: 11956.832 | C15: 10922.824 | D15: 11602.388 | E15: 5904.9996 | F15: 8540.9726 | G15: Поступления от продажи основного капитала
A16: Трансферттердің түсімдері | B16: 438353.22 | C16: 496913.84 | D16: 521837.33 | E16: 285892.24 | F16: 315925.92 | G16: Поступления трансфертов
A17: II. ШЫҒЫНДАР | B17: 557540.98 | C17: 630861.77 | D17: 727944.33 | E17: 370471.59 | F17: 424546.71 | G17: II. ЗАТРАТЫ
A18: 1. Жалпы сипаттағы мемлекеттiк қызметтер | B18: 19965.486 | C18: 27013.526 | D18: 28305.006 | E18: 14805.253 | F18: 17267.892 | G18: 1. Государственные услуги общего характера
A19: 2. Қорғаныс | B19: 1238.2558 | C19: 1863.5947 | D19: 2279.1128 | E19: 630.22812 | F19: 1782.5771 | G19: 2. Оборона
... A37: Қаржылық активтерді сатып алу | B37: 1540.566 | C37: 1147.061 | D37: 1540.7038 | E37: 642.61068 | F37: 322.63108 | G37: Приобретение финансовых активов
A38: Мемлекеттің қаржы активтерін сатудан түсетін түсімдер | B38: 0.49544 | G38: Поступления от продажи финансовых активов государства
A39: V. БЮДЖЕТ ТАПШЫЛЫҒЫ (ПРОФИЦИТІ) | B39: -7805.1251 | C39: -10370.017 | D39: -40655.204 | E39: 10130.995 | F39: 10780.672 | G39: V. ДЕФИЦИТ (ПРОФИЦИТ) БЮДЖЕТА
A41: VII. БЮДЖЕТТІҢ ТАПШЫЛЫҒЫН ҚАРЖЫЛАНДЫРУ (ПРОФИЦИТТІ ПАЙДАЛАНУ | B41: 7805.1251 | C41: 10370.017 | D41: -40655.204 | E41: -10130.995 | F41: -10780.672 | G41: VII. ФИНАНСИРОВАНИЕ ДЕФИЦИТА (ИСПОЛЬЗОВАНИЕ ПРОФИЦИТА) БЮДЖЕТА
A42: Ішкі | B42: -27361.525 | C42: -97791.222 | D42: 241677.71 | E42: -209866.83 | F42: -10780.672 | G42: Внутреннее
A43: Түсімдер | B43: -12063.136 | C43: -78965.845 | D43: 269955.92 | E43: -191103.48 | F43: -3822.1339 | G43: Поступление
A44: Өтеу | B44: 15298.389 | C44: 18825.377 | D44: 28278.215 | E44: 18763.347 | F44: 6958.5386 | G44: Погашение
A45: Сыртқы | B45: - | C45: - | D45: - | E45: - | F45: - | G45: Внешнее
A46: Түсімдер | B46: - | C46: - | D46: - | E46: - | F46: - | G46: Поступление
A47: Өтеу | B47: - | C47: - | D47: - | E47: - | F47: - | G47: Погашение

Sheet табл 12.7
A1: 12.7-кесте | E1: Таблица 12.7
A2: БАТЫС ҚАЗАҚСТАН ОБЛЫСЫ | E2: ИСПОЛНЕНИЕ БЮДЖЕТА
A3: БЮДЖЕТІНІҢ АТҚАРЫЛУЫ | E3: ЗАП-КАЗАХСТАНСКАЯ ОБЛАСТЬ
A4: (млн.теңге) | E4: (млн. тенге)
A5: Атауы | B5: 2022 ж. есеп/ 2022 г. отчет | C5: 2023 ж. есеп/ 2023 г. отчет | D5: 2024 ж. есеп/ 2024 г. отчет | F5: 2025 ж. қантар-шілде есеп/январь-июль отчет 2025 г. | G5: Наименование
D6: жылдық/ годовой | E6: қантар-шілде/январь-июль
A7: 1 | B7: 2 | C7: 3 | D7: 4 | E7: 5 | F7: 6 | G7: 7
A8: I. КІРІСТЕР | B8: 355921.06 | C8: 453047.34 | D8: 532073.16 | E8: 289750.22 | F8: 300224.04 | G8: I. ДОХОДЫ
A9: Салықтық түсімдер_x000D_ оның iшiнде: | B9: 136040.88 | C9: 176101.88 | D9: 197849.71 | E9: 116490.23 | F9: 129535.32 | G9: Налоговые поступления,_x000D_ в том числе:
A10: корпорациялық табыс салығы | B10: 17876.508 | C10: 23819.677 | D10: 29745.342 | E10: 18088.896 | F10: 20104.875 | G10: корпоративный подоходный налог
A11: жеке табыс салығы | B11: 46152.443 | C11: 60446.744 | D11: 71402.108 | E11: 41565.586 | F11: 44727.732 | G11: индивидуальный подоходный налог
A12: әлеуметтік салық | B12: 58464.761 | C12: 65791.879 | D12: 73256 | E12: 43152.362 | F12: 47351.809 | G12: социальный налог
A13: акциздер | B13: 1784.5321 | C13: 4116.8709 | D13: 2316.8132 | E13: 1711.1888 | F13: 1219.6526 | G13: акцизы
A14: Салықтық емес түсімдер | B14: 4223.8187 | C14: 5184.1237 | D14: 6731.9796 | E14: 3777.3414 | F14: 4877.435 | G14: Неналоговые поступления
A15: Негізгі капиталды сатудан түсетін түсімдер | B15: 7882.4974 | C15: 8859.4531 | D15: 6142.5363 | E15: 4710.9874 | F15: 7301.5691 | G15: Поступления от продажи основного капитала
A16: Трансферттердің түсімдері | B16: 207773.86 | C16: 262901.88 | D16: 321348.93 | E16: 164771.66 | F16: 158509.71 | G16: Поступления трансфертов
A17: II. ШЫҒЫНДАР | B17: 340221.25 | C17: 445141.74 | D17: 559071.76 | E17: 280666.65 | F17: 289783.51 | G17: II. ЗАТРАТЫ
A18: 1. Жалпы сипаттағы мемлекеттiк қызметтер | B18: 16648.76 | C18: 23456.157 | D18: 42350.09 | E18: 21004.141 | F18: 17329.035 | G18: 1. Государственные услуги общего характера
A19: 2. Қорғаныс | B19: 1120.9243 | C19: 2958.5653 | D19: 3981.6445 | E19: 1153.5173 | F19: 1220.9911 | G19: 2. Оборона
... A35: Бюджеттік кредиттерді өтеу | B35: 5275.0286 | C35: 3136.1149 | D35: 5811.1896 | E35: 3602.9406 | F35: 4788.8675 | G35: Погашение бюджетных кредитов
A36: IV. ҚАРЖЫ АКТИВТЕРІМЕН ОПЕРАЦИЯЛАР БОЙЫНША САЛЬДО - ҚАРЖЫ АК | C36: 12.583 | D36: 2001.398 | E36: 1999.29 | F36: 17.67 | G36: IV. САЛЬДО ПО ОПЕРАЦИЯМ С ФИНАНСОВЫМИ АКТИВАМИ
A37: Қаржылық активтерді сатып алу | C37: 12.583 | D37: 2001.398 | E37: 1999.29 | F37: 17.67 | G37: Приобретение финансовых активов
A38: V. БЮДЖЕТ ТАПШЫЛЫҒЫ (ПРОФИЦИТІ) | B38: 14658.841 | C38: -5596.7209 | D38: -37075.479 | E38: 3614.7539 | F38: 10357.656 | G38: V. ДЕФИЦИТ (ПРОФИЦИТ) БЮДЖЕТА
A40: VII. БЮДЖЕТТІҢ ТАПШЫЛЫҒЫН ҚАРЖЫЛАНДЫРУ (ПРОФИЦИТТІ ПАЙДАЛАНУ | B40: -14658.841 | C40: 5596.7209 | D40: -37075.479 | E40: -3614.7539 | F40: -10357.656 | G40: VII. ФИНАНСИРОВАНИЕ ДЕФИЦИТА (ИСПОЛЬЗОВАНИЕ ПРОФИЦИТА) БЮДЖЕТА
A41: Ішкі | B41: -80854.731 | C41: -126662.63 | D41: 232779.58 | E41: -123495.67 | F41: -10357.656 | G41: Внутреннее
A42: Түсімдер | B42: -62360.325 | C42: -119750.59 | D42: 242914.29 | E42: -114567.13 | F42: -2484.8192 | G42: Поступление
A43: Өтеу | B43: 18494.406 | C43: 6912.0418 | D43: 10134.71 | E43: 8928.5402 | F43: 7872.8369 | G43: Погашение
A44: Сыртқы | B44: - | C44: - | D44: - | E44: - | F44: - | G44: Внешнее
A45: Түсімдер | B45: - | C45: - | D45: - | E45: - | F45: - | G45: Поступление
A46: Өтеу | B46: - | C46: - | D46: - | E46: - | F46: - | G46: Погашение

Sheet табл 12.8
A1: 12.8-кесте | E1: Таблица 12.8
A2: ҚАРАҒАНДЫ ОБЛЫСЫ | E2: ИСПОЛНЕНИЕ БЮДЖЕТА
A3: БЮДЖЕТІНІҢ АТҚАРЫЛУЫ | E3: КАРАГАНДИНСКАЯ ОБЛАСТЬ
A4: (млн.теңге) | E4: (млн. тенге)
A5: Атауы | B5: 2022 ж. есеп/ 2022 г. отчет | C5: 2023 ж. есеп/ 2023 г. отчет | D5: 2024 ж. есеп/ 2024 г. отчет | F5: 2025 ж. қантар-шілде есеп/январь-июль отчет 2025 г. | G5: Наименование
D6: жылдық/ годовой | E6: қантар-шілде/январь-июль
A7: 1 | B7: 2 | C7: 3 | D7: 4 | E7: 5 | F7: 6 | G7: 7
A8: I. КІРІСТЕР | B8: 601163.66 | C8: 686571.15 | D8: 782542.05 | E8: 468830.06 | F8: 477225.36 | G8: I. ДОХОДЫ
A9: Салықтық түсімдер_x000D_ оның iшiнде: | B9: 276736.66 | C9: 279296.66 | D9: 347457.48 | E9: 200265.36 | F9: 231919.49 | G9: Налоговые поступления,_x000D_ в том числе:
A10: корпорациялық табыс салығы | B10: 41790.778 | C10: 50643.141 | D10: 65372.599 | E10: 40530.432 | F10: 40976.222 | G10: корпоративный подоходный налог
A11: жеке табыс салығы | B11: 97720.215 | C11: 100657.78 | D11: 130633.83 | E11: 74652.51 | F11: 87870.576 | G11: индивидуальный подоходный налог
A12: әлеуметтік салық | B12: 69413.028 | C12: 70479.115 | D12: 85429.921 | E12: 48346.892 | F12: 58489.281 | G12: социальный налог
A13: акциздер | B13: 8175.2935 | C13: 8092.5258 | D13: 7686.1147 | E13: 4537.7809 | F13: 4873.6751 | G13: акцизы
A14: Салықтық емес түсімдер | B14: 8253.7204 | C14: 11211.452 | D14: 27590.047 | E14: 17952.142 | F14: 6946.295 | G14: Неналоговые поступления
A15: Негізгі капиталды сатудан түсетін түсімдер | B15: 8386.6656 | C15: 3103.0047 | D15: 4608.7489 | E15: 2206.8323 | F15: 3719.2537 | G15: Поступления от продажи основного капитала
A16: Трансферттердің түсімдері | B16: 307786.61 | C16: 392960.03 | D16: 402885.77 | E16: 248405.73 | F16: 234640.31 | G16: Поступления трансфертов
A17: II. ШЫҒЫНДАР | B17: 541666.71 | C17: 673296.69 | D17: 795649.24 | E17: 386246.77 | F17: 432742.35 | G17: II. ЗАТРАТЫ
A18: 1. Жалпы сипаттағы мемлекеттiк қызметтер | B18: 20749.235 | C18: 28618.703 | D18: 34271.162 | E18: 16990.394 | F18: 22243.079 | G18: 1. Государственные услуги общего характера
A19: 2. Қорғаныс | B19: 2672.9403 | C19: 2604.8186 | D19: 3295.2285 | E19: 1127.6435 | F19: 1434.559 | G19: 2. Оборона
... A44: Өтеу | B44: 10718.722 | C44: 5043.5343 | D44: 8113.2071 | E44: 6190.9537 | F44: 9345.2562 | G44: Погашение
A45: Сыртқы | B45: - | C45: - | D45: - | E45: - | F45: - | G45: Внешнее
A46: Түсімдер | B46: - | C46: - | D46: - | E46: - | F46: - | G46: Поступление
A47: Өтеу | B47: - | C47: - | D47: - | E47: - | F47: - | G47: Погашение

Sheet табл 12.9
A1: 12.9-кесте | E1: Таблица 12.9
A2: ҚЫЗЫЛОРДА ОБЛЫСЫ | E2: ИСПОЛНЕНИЕ БЮДЖЕТА
A3: БЮДЖЕТІНІҢ АТҚАРЫЛУЫ | E3: КЫЗЫЛОРДИНСКАЯ ОБЛАСТЬ
A4: (млн.теңге) | E4: (млн. тенге)
A5: Атауы | B5: 2022 ж. есеп/ 2022 г. отчет | C5: 2023 ж. есеп/ 2023 г. отчет | D5: 2024 ж. есеп/ 2024 г. отчет | F5: 2025 ж. қантар-шілде есеп/январь-июль отчет 2025 г. | G5: Наименование
D6: жылдық/ годовой | E6: қантар-шілде/январь-июль
A7: 1 | B7: 2 | C7: 3 | D7: 4 | E7: 5 | F7: 6 | G7: 7
A8: I. КІРІСТЕР | B8: 417735.97 | C8: 597172.6 | D8: 688375.1 | E8: 415927.16 | F8: 428697.11 | G8: I. ДОХОДЫ
A9: Салықтық түсімдер_x000D_ оның iшiнде: | B9: 68176.779 | C9: 89965.953 | D9: 113891.83 | E9: 62386.292 | F9: 75026.848 | G9: Налоговые поступления,_x000D_ в том числе:
A10: корпорациялық табыс салығы | B10: 7293.8047 | C10: 8720.5044 | D10: 16592.943 | E10: 7325.9244 | F10: 10022.59 | G10: корпоративный подоходный налог
A11: жеке табыс салығы | B11: 26007.383 | C11: 34223.426 | D11: 44987.131 | E11: 25472.058 | F11: 29530.225 | G11: индивидуальный подоходный налог
A12: әлеуметтік салық | B12: 19323.765 | C12: 25039.27 | D12: 30129.397 | E12: 17064.87 | F12: 19998.248 | G12: социальный налог
A13: акциздер | B13: 127.02314 | C13: 139.68694 | D13: 116.04345 | E13: 61.415308 | F13: 67.273945 | G13: акцизы
A14: Салықтық емес түсімдер | B14: 5589.3801 | C14: 10570.979 | D14: 33610.595 | E14: 28270.327 | F14: 12267.585 | G14: Неналоговые поступления
A15: Негізгі капиталды сатудан түсетін түсімдер | B15: 5075.3512 | C15: 9002.805 | D15: 10672.773 | E15: 4549.7453 | F15: 6188.0997 | G15: Поступления от продажи основного капитала
A16: Трансферттердің түсімдері | B16: 338894.46 | C16: 487632.86 | D16: 530199.9 | E16: 320720.8 | F16: 335214.58 | G16: Поступления трансфертов
A17: II. ШЫҒЫНДАР | B17: 415462.88 | C17: 569744.49 | D17: 707644.21 | E17: 361542.88 | F17: 395179.58 | G17: II. ЗАТРАТЫ
A18: 1. Жалпы сипаттағы мемлекеттiк қызметтер | B18: 19825.775 | C18: 21548.543 | D18: 25338.796 | E18: 12344.473 | F18: 16980.031 | G18: 1. Государственные услуги общего характера
A19: 2. Қорғаныс | B19: 1595.6792 | C19: 1831.1092 | D19: 2739.7235 | E19: 876.48651 | F19: 1108.7819 | G19: 2. Оборона
... A37: Қаржылық активтерді сатып алу | B37: 4357.5615 | C37: 11297.835 | D37: 7312.6936 | E37: 2255.2891 | F37: 1077.3033 | G37: Приобретение финансовых активов
A38: Мемлекеттің қаржы активтерін сатудан түсетін түсімдер | C38: 10.944182 | D38: 5.041745 | E38: 4.347245 | F38: 9.155687 | G38: Поступления от продажи финансовых активов государства
A39: V. БЮДЖЕТ ТАПШЫЛЫҒЫ (ПРОФИЦИТІ) | B39: -7332.7874 | C39: 8840.5622 | D39: -35564.174 | E39: 52484.258 | F39: 36653.653 | G39: V. ДЕФИЦИТ (ПРОФИЦИТ) БЮДЖЕТА
A41: VII. БЮДЖЕТТІҢ ТАПШЫЛЫҒЫН ҚАРЖЫЛАНДЫРУ (ПРОФИЦИТТІ ПАЙДАЛАНУ | B41: 7332.7874 | C41: -8840.5622 | D41: -35564.174 | E41: -52484.258 | F41: -36653.653 | G41: VII. ФИНАНСИРОВАНИЕ ДЕФИЦИТА (ИСПОЛЬЗОВАНИЕ ПРОФИЦИТА) БЮДЖЕТА
A42: Ішкі | B42: 75339.843 | C42: -160335.33 | D42: 86560.111 | E42: -625390.74 | F42: -36653.653 | G42: Внутреннее
A43: Түсімдер | B43: 84754.964 | C43: -149731.8 | D43: 98509.642 | E43: -617690.29 | F43: -24899.763 | G43: Поступление
A44: Өтеу | B44: 9415.1203 | C44: 10603.525 | D44: 11949.531 | E44: 7700.4514 | F44: 11753.89 | G44: Погашение
A45: Сыртқы | B45: -1516.9375 | C45: -1880.877 | D45: -868.7564 | E45: -868.7564 | F45: - | G45: Внешнее
A46: Түсімдер | B46: - | C46: - | D46: - | E46: - | F46: - | G46: Поступление
A47: Өтеу | B47: 1516.9375 | C47: 1880.877 | D47: 868.7564 | E47: 868.7564 | F47: - | G47: Погашение

Sheet табл 12.10
A1: 12.10-кесте | E1: Таблица 12.10
A2: ҚОСТАНАЙ ОБЛЫСЫ | E2: ИСПОЛНЕНИЕ БЮДЖЕТА
A3: БЮДЖЕТІНІҢ АТҚАРЫЛУЫ | E3: КОСТАНАЙСКАЯ ОБЛАСТЬ
A4: (млн.теңге) | E4: (млн. тенге)
A5: Атауы | B5: 2022 ж. есеп/ 2022 г. отчет | C5: 2023 ж. есеп/ 2023 г. отчет | D5: 2024 ж. есеп/ 2024 г. отчет | F5: 2025 ж. қантар-шілде есеп/январь-июль отчет 2025 г. | G5: Наименование
D6: жылдық/ годовой | E6: қантар-шілде/январь-июль
A7: 1 | B7: 2 | C7: 3 | D7: 4 | E7: 5 | F7: 6 | G7: 7
A8: I. КІРІСТЕР | B8: 438229 | C8: 604311.98 | D8: 628629.96 | E8: 401085.68 | F8: 387688.98 | G8: I. ДОХОДЫ
A9: Салықтық түсімдер_x000D_ оның iшiнде: | B9: 144076.63 | C9: 174857.99 | D9: 205358.32 | E9: 121145.24 | F9: 136253.03 | G9: Налоговые поступления,_x000D_ в том числе:
A10: корпорациялық табыс салығы | B10: 33859.442 | C10: 33911.561 | D10: 37426.524 | E10: 24679.81 | F10: 24154.84 | G10: корпоративный подоходный налог
A11: жеке табыс салығы | B11: 47237.783 | C11: 62045.659 | D11: 79538.501 | E11: 45917.467 | F11: 54901.542 | G11: индивидуальный подоходный налог
A12: әлеуметтік салық | B12: 32217.986 | C12: 40145.801 | D12: 48992.711 | E12: 27387.8 | F12: 31449.94 | G12: социальный налог
A13: акциздер | B13: 5054.0913 | C13: 5085.7443 | D13: 4367.686 | E13: 2804.9413 | F13: 3457.401 | G13: акцизы
A14: Салықтық емес түсімдер | B14: 5914.2177 | C14: 6220.1607 | D14: 11769.215 | E14: 8018.799 | F14: 6628.9315 | G14: Неналоговые поступления
A15: Негізгі капиталды сатудан түсетін түсімдер | B15: 5657.074 | C15: 5656.0616 | D15: 9621.5046 | E15: 4601.4929 | F15: 3065.1746 | G15: Поступления от продажи основного капитала
A16: Трансферттердің түсімдері | B16: 282581.07 | C16: 417577.77 | D16: 401880.92 | E16: 267320.15 | F16: 241741.85 | G16: Поступления трансфертов
A17: II. ШЫҒЫНДАР | B17: 421205.17 | C17: 547560.7 | D17: 628666.42 | E17: 317367.91 | F17: 351268.21 | G17: II. ЗАТРАТЫ
A18: 1. Жалпы сипаттағы мемлекеттiк қызметтер | B18: 20142.484 | C18: 30915.334 | D18: 40995.492 | E18: 24932.846 | F18: 16341.68 | G18: 1. Государственные услуги общего характера
A19: 2. Қорғаныс | B19: 872.68626 | C19: 1571.8601 | D19: 2531.2785 | E19: 833.67443 | F19: 2209.7935 | G19: 2. Оборона
... A44: Өтеу | B44: 9230.309 | C44: 13617.529 | D44: 11793.154 | E44: 10234.208 | F44: 4219.5083 | G44: Погашение
A45: Сыртқы | B45: - | C45: - | D45: - | E45: - | F45: - | G45: Внешнее
A46: Түсімдер | B46: - | C46: - | D46: - | E46: - | F46: - | G46: Поступление
A47: Өтеу | B47: - | C47: - | D47: - | E47: - | F47: - | G47: Погашение

Sheet табл 12.11
A1: 12.11-кесте | E1: Таблица 12.11
A2: МАҢҒЫСТАУ ОБЛЫСЫ | E2: ИСПОЛНЕНИЕ БЮДЖЕТА
A3: БЮДЖЕТІНІҢ АТҚАРЫЛУЫ | E3: МАНГИСТАУСКАЯ ОБЛАСТЬ
A4: (млн.теңге) | E4: (млн. тенге)
A5: Атауы | B5: 2022 ж. есеп/ 2022 г. отчет | C5: 2023 ж. есеп/ 2023 г. отчет | D5: 2024 ж. есеп/ 2024 г. отчет | F5: 2025 ж. қантар-шілде есеп/январь-июль отчет 2025 г. | G5: Наименование
D6: жылдық/ годовой | E6: қантар-шілде/январь-июль
A7: 1 | B7: 2 | C7: 3 | D7: 4 | E7: 5 | F7: 6 | G7: 7
A8: I. КІРІСТЕР | B8: 351894.12 | C8: 475001.67 | D8: 565387.99 | E8: 291295.33 | F8: 354703.94 | G8: I. ДОХОДЫ
A9: Салықтық түсімдер_x000D_ оның iшiнде: | B9: 201132.45 | C9: 249915.93 | D9: 290147.77 | E9: 166355.22 | F9: 183470.23 | G9: Налоговые поступления,_x000D_ в том числе:
A10: корпорациялық табыс салығы | B10: 29409.688 | C10: 30124.379 | D10: 31655.206 | E10: 20690.266 | F10: 19326.709 | G10: корпоративный подоходный налог
A11: жеке табыс салығы | B11: 75641.827 | C11: 95760.861 | D11: 117448.69 | E11: 67315.772 | F11: 75531.591 | G11: индивидуальный подоходный налог
A12: әлеуметтік салық | B12: 57287.788 | C12: 72326.61 | D12: 85395.26 | E12: 48575.922 | F12: 57178.808 | G12: социальный налог
A13: акциздер | B13: 619.41999 | C13: 1636.9414 | D13: 1512.377 | E13: 611.98159 | F13: 256.42344 | G13: акцизы
A14: Салықтық емес түсімдер | B14: 6596.3625 | C14: 8955.6703 | D14: 11116.334 | E14: 6488.2759 | F14: 37801.408 | G14: Неналоговые поступления
A15: Негізгі капиталды сатудан түсетін түсімдер | B15: 5934.8791 | C15: 6033.2791 | D15: 4729.1387 | E15: 2181.8467 | F15: 1693.8873 | G15: Поступления от продажи основного капитала
A16: Трансферттердің түсімдері | B16: 138230.43 | C16: 210096.79 | D16: 259394.75 | E16: 116269.99 | F16: 131738.42 | G16: Поступления трансфертов
A17: II. ШЫҒЫНДАР | B17: 335696.2 | C17: 445032.94 | D17: 548979.79 | E17: 231884.06 | F17: 323260.89 | G17: II. ЗАТРАТЫ
A18: 1. Жалпы сипаттағы мемлекеттiк қызметтер | B18: 9629.0065 | C18: 13009.328 | D18: 19808.839 | E18: 8297.6948 | F18: 11516.375 | G18: 1. Государственные услуги общего характера
A19: 2. Қорғаныс | B19: 1420.4398 | C19: 2131.3234 | D19: 3018.473 | E19: 429.22488 | F19: 2741.3203 | G19: 2. Оборона
... A37: Қаржылық активтерді сатып алу | B37: 892.767 | C37: 3678.269 | D37: 2831.235 | E37: 2516.235 | F37: 3771.846 | G37: Приобретение финансовых активов
A38: Мемлекеттің қаржы активтерін сатудан түсетін түсімдер | C38: 36.150285 | G38: Поступления от продажи финансовых активов государства
A39: V. БЮДЖЕТ ТАПШЫЛЫҒЫ (ПРОФИЦИТІ) | B39: 9420.301 | C39: 24445.137 | D39: 10865.029 | E39: 57682.643 | F39: 29989.054 | G39: V. ДЕФИЦИТ (ПРОФИЦИТ) БЮДЖЕТА
A41: VII. БЮДЖЕТТІҢ ТАПШЫЛЫҒЫН ҚАРЖЫЛАНДЫРУ (ПРОФИЦИТТІ ПАЙДАЛАНУ | B41: -9420.301 | C41: -24445.137 | D41: 10865.029 | E41: -57682.643 | F41: -29989.054 | G41: VII. ФИНАНСИРОВАНИЕ ДЕФИЦИТА (ИСПОЛЬЗОВАНИЕ ПРОФИЦИТА) БЮДЖЕТА
A42: Ішкі | B42: -70614.803 | C42: -312630.52 | D42: -244298.81 | E42: -656581.1 | F42: -29989.054 | G42: Внутреннее
A43: Түсімдер | B43: -59262.314 | C43: -311173.63 | D43: -238722.45 | E43: -652127.25 | F43: -26978.997 | G43: Поступление
A44: Өтеу | B44: 11352.488 | C44: 1456.89 | D44: 5576.3587 | E44: 4453.8431 | F44: 3010.0571 | G44: Погашение
A45: Сыртқы | B45: - | C45: - | D45: - | E45: - | F45: - | G45: Внешнее
A46: Түсімдер | B46: - | C46: - | D46: - | E46: - | F46: - | G46: Поступление
A47: Өтеу | B47: - | C47: - | D47: - | E47: - | F47: - | G47: Погашение

Sheet табл 12.12
A1: 12.12-кесте | E1: Таблица 12.12
A2: ПАВЛОДАР ОБЛЫСЫ | E2: ИСПОЛНЕНИЕ БЮДЖЕТА
A3: БЮДЖЕТІНІҢ АТҚАРЫЛУЫ | E3: ПАВЛОДАРСКАЯ ОБЛАСТЬ
A4: (млн.теңге) | E4: (млн. тенге)
A5: Атауы | B5: 2022 ж. есеп/ 2022 г. отчет | C5: 2023 ж. есеп/ 2023 г. отчет | D5: 2024 ж. есеп/ 2024 г. отчет | F5: 2025 ж. қантар-шілде есеп/январь-июль отчет 2025 г. | G5: Наименование
D6: жылдық/ годовой | E6: қантар-шілде/январь-июль
A7: 1 | B7: 2 | C7: 3 | D7: 4 | E7: 5 | F7: 6 | G7: 7
A8: I. КІРІСТЕР | B8: 457265.76 | C8: 530607.87 | D8: 568290.97 | E8: 324613.37 | F8: 358965.99 | G8: I. ДОХОДЫ
A9: Салықтық түсімдер_x000D_ оның iшiнде: | B9: 257861.33 | C9: 311139.96 | D9: 355688.78 | E9: 198694.28 | F9: 224180.25 | G9: Налоговые поступления,_x000D_ в том числе:
A10: корпорациялық табыс салығы | B10: 23499.142 | C10: 24425.448 | D10: 34139.694 | E10: 21591.694 | F10: 23473.672 | G10: корпоративный подоходный налог
A11: жеке табыс салығы | B11: 52114.956 | C11: 67868.655 | D11: 86404.401 | E11: 50075.72 | F11: 56828.575 | G11: индивидуальный подоходный налог
A12: әлеуметтік салық | B12: 37181.825 | C12: 47871.635 | D12: 58092.974 | E12: 33022.762 | F12: 38039.001 | G12: социальный налог
A13: акциздер | B13: 107719.1 | C13: 125534.48 | D13: 129598.29 | E13: 67078.119 | F13: 78881.041 | G13: акцизы
A14: Салықтық емес түсімдер | B14: 4151.6239 | C14: 4507.2143 | D14: 6402.786 | E14: 3482.9151 | F14: 4542.3045 | G14: Неналоговые поступления
A15: Негізгі капиталды сатудан түсетін түсімдер | B15: 8068.3621 | C15: 7729.2877 | D15: 7851.1996 | E15: 4263.9471 | F15: 5211.1253 | G15: Поступления от продажи основного капитала
A16: Трансферттердің түсімдері | B16: 187184.45 | C16: 207231.4 | D16: 198348.21 | E16: 118172.23 | F16: 125032.31 | G16: Поступления трансфертов
A17: II. ШЫҒЫНДАР | B17: 457710.46 | C17: 528208.21 | D17: 579464.48 | E17: 304683.16 | F17: 341097.1 | G17: II. ЗАТРАТЫ
A18: 1. Жалпы сипаттағы мемлекеттiк қызметтер | B18: 20029.081 | C18: 42863.349 | D18: 33133.36 | E18: 16592.87 | F18: 23885.461 | G18: 1. Государственные услуги общего характера
A19: 2. Қорғаныс | B19: 1538.3453 | C19: 1786.6605 | D19: 2384.4454 | E19: 1039.9119 | F19: 1197.0141 | G19: 2. Оборона
... A44: Өтеу | B44: 13085.128 | C44: 7885.5148 | D44: 7755.4174 | E44: 6876.8722 | F44: 6160.77 | G44: Погашение
A45: Сыртқы | B45: - | C45: - | D45: - | E45: - | F45: - | G45: Внешнее
A46: Түсімдер | B46: - | C46: - | D46: - | E46: - | F46: - | G46: Поступление
A47: Өтеу | B47: - | C47: - | D47: - | E47: - | F47: - | G47: Погашение

Sheet табл 12.13
A1: 12.13-кесте | E1: Таблица 12.13
A2: СОЛТҮСТІК-ҚАЗАҚСТАН ОБЛЫСЫ | E2: ИСПОЛНЕНИЕ БЮДЖЕТА
A3: БЮДЖЕТІНІҢ АТҚАРЫЛУЫ | E3: СЕВ-КАЗАХСТАНСКАЯ ОБЛАСТЬ
A4: (млн.теңге) | E4: (млн. тенге)
A5: Атауы | B5: 2022 ж. есеп/ 2022 г. отчет | C5: 2023 ж. есеп/ 2023 г. отчет | D5: 2024 ж. есеп/ 2024 г. отчет | F5: 2025 ж. қантар-шілде есеп/январь-июль отчет 2025 г. | G5: Наименование
D6: жылдық/ годовой | E6: қантар-шілде/январь-июль
A7: 1 | B7: 2 | C7: 3 | D7: 4 | E7: 5 | F7: 6 | G7: 7
A8: I. КІРІСТЕР | B8: 411923.16 | C8: 479286.16 | D8: 499744.12 | E8: 281443.86 | F8: 305871.54 | G8: I. ДОХОДЫ
A9: Салықтық түсімдер_x000D_ оның iшiнде: | B9: 86449.968 | C9: 104168.43 | D9: 114911.18 | E9: 65635.803 | F9: 74854.358 | G9: Налоговые поступления,_x000D_ в том числе:
A10: корпорациялық табыс салығы | B10: 14246.799 | C10: 19981.616 | D10: 20968.836 | E10: 12109.034 | F10: 13236.017 | G10: корпоративный подоходный налог
A11: жеке табыс салығы | B11: 26590.562 | C11: 33665.851 | D11: 42183.254 | E11: 24014.048 | F11: 27603.29 | G11: индивидуальный подоходный налог
A12: әлеуметтік салық | B12: 16721.482 | C12: 20700.577 | D12: 24710.833 | E12: 13859.059 | F12: 15764.696 | G12: социальный налог
A13: акциздер | B13: 16863.605 | C13: 13585.507 | D13: 11347.819 | E13: 5973.6034 | F13: 7181.032 | G13: акцизы
A14: Салықтық емес түсімдер | B14: 3517.6964 | C14: 4418.0267 | D14: 5764.0759 | E14: 3209.3342 | F14: 5108.3897 | G14: Неналоговые поступления
A15: Негізгі капиталды сатудан түсетін түсімдер | B15: 6843.2221 | C15: 11077.734 | D15: 6402.5728 | E15: 1482.7395 | F15: 5482.3698 | G15: Поступления от продажи основного капитала
A16: Трансферттердің түсімдері | B16: 315112.27 | C16: 359621.97 | D16: 372666.29 | E16: 211115.98 | F16: 220426.43 | G16: Поступления трансфертов
A17: II. ШЫҒЫНДАР | B17: 378633.97 | C17: 456049.77 | D17: 519516.5 | E17: 278953.82 | F17: 294151.5 | G17: II. ЗАТРАТЫ
A18: 1. Жалпы сипаттағы мемлекеттiк қызметтер | B18: 15791.163 | C18: 21153.388 | D18: 46477.998 | E18: 19095.049 | F18: 19411.311 | G18: 1. Государственные услуги общего характера
A19: 2. Қорғаныс | B19: 853.0642 | C19: 1551.1442 | D19: 2113.6186 | E19: 511.35031 | F19: 957.95735 | G19: 2. Оборона
... A35: Бюджеттік кредиттерді өтеу | B35: 2156.3395 | C35: 2437.6831 | D35: 4274.9727 | E35: 2923.5149 | F35: 2851.655 | G35: Погашение бюджетных кредитов
A36: IV. ҚАРЖЫ АКТИВТЕРІМЕН ОПЕРАЦИЯЛАР БОЙЫНША САЛЬДО - ҚАРЖЫ АК | B36: 29973.455 | C36: 7499.9987 | D36: 33.974 | E36: -1.026 | G36: IV. САЛЬДО ПО ОПЕРАЦИЯМ С ФИНАНСОВЫМИ АКТИВАМИ
A37: Қаржылық активтерді сатып алу | B37: 29975.55 | C37: 7500 | D37: 35 | G37: Приобретение финансовых активов
A38: Мемлекеттің қаржы активтерін сатудан түсетін түсімдер | B38: 2.094767 | C38: 0.001336 | D38: 1.026 | E38: 1.026 | G38: Поступления от продажи финансовых активов государства
A39: V. БЮДЖЕТ ТАПШЫЛЫҒЫ (ПРОФИЦИТІ) | B39: -1028.2882 | C39: -2878.5917 | D39: -23552.591 | E39: -875.09576 | F39: 6501.6998 | G39: V. ДЕФИЦИТ (ПРОФИЦИТ) БЮДЖЕТА
A41: VII. БЮДЖЕТТІҢ ТАПШЫЛЫҒЫН ҚАРЖЫЛАНДЫРУ (ПРОФИЦИТТІ ПАЙДАЛАНУ | B41: 1028.2882 | C41: 2878.5917 | D41: -23552.591 | E41: 875.09576 | F41: -6501.6998 | G41: VII. ФИНАНСИРОВАНИЕ ДЕФИЦИТА (ИСПОЛЬЗОВАНИЕ ПРОФИЦИТА) БЮДЖЕТА
A42: Ішкі | B42: 1085.8274 | C42: -63363.316 | D42: 244902.68 | E42: -33388.281 | F42: -6501.6998 | G42: Внутреннее
A43: Түсімдер | B43: 12720.555 | C43: -48522.388 | D43: 256392.58 | E43: -27296.614 | F43: -4268.0893 | G43: Поступление
A44: Өтеу | B44: 11634.728 | C44: 14840.928 | D44: 11489.901 | E44: 6091.6668 | F44: 2233.6105 | G44: Погашение
A45: Сыртқы | B45: - | C45: - | D45: - | E45: - | F45: - | G45: Внешнее
A46: Түсімдер | B46: - | C46: - | D46: - | E46: - | F46: - | G46: Поступление
A47: Өтеу | B47: - | C47: - | D47: - | E47: - | F47: - | G47: Погашение

Sheet табл 12.14
A1: 12.14-кесте | E1: Таблица 12.14
A2: ТҮРКІСТАН ОБЛЫСЫ | E2: ИСПОЛНЕНИЕ БЮДЖЕТА
A3: БЮДЖЕТІНІҢ АТҚАРЫЛУЫ | E3: ТУРКЕСТАНСКАЯ ОБЛАСТЬ
A4: (млн.теңге) | E4: (млн. тенге)
A5: Атауы | B5: 2022 ж. есеп/ 2022 г. отчет | C5: 2023 ж. есеп/ 2023 г. отчет | D5: 2024 ж. есеп/ 2024 г. отчет | F5: 2025 ж. қантар-шілде есеп/январь-июль отчет 2025 г. | G5: Наименование
D6: жылдық/ годовой | E6: қантар-шілде/январь-июль
A7: 1 | B7: 2 | C7: 3 | D7: 4 | E7: 5 | F7: 6 | G7: 7
A8: I. КІРІСТЕР | B8: 1093249.8 | C8: 1355385.2 | D8: 1482111.7 | E8: 787625.19 | F8: 883398.28 | G8: I. ДОХОДЫ
A9: Салықтық түсімдер_x000D_ оның iшiнде: | B9: 112612.55 | C9: 149133.74 | D9: 192225.51 | E9: 101589.97 | F9: 135130.52 | G9: Налоговые поступления,_x000D_ в том числе:
A10: корпорациялық табыс салығы | B10: 10090.392 | C10: 12501.811 | D10: 29399.857 | E10: 10389.994 | F10: 21855.67 | G10: корпоративный подоходный налог
A11: жеке табыс салығы | B11: 46292.272 | C11: 59251.623 | D11: 76377.383 | E11: 42332.789 | F11: 52623.091 | G11: индивидуальный подоходный налог
A12: әлеуметтік салық | B12: 35788.861 | C12: 45981.778 | D12: 52625.318 | E12: 29278.442 | F12: 35966.158 | G12: социальный налог
A13: акциздер | B13: 427.36189 | C13: 412.31388 | D13: 402.20076 | E13: 214.07301 | F13: 287.00378 | G13: акцизы
A14: Салықтық емес түсімдер | B14: 12995.992 | C14: 16833.17 | D14: 37569.665 | E14: 26589.81 | F14: 24227.225 | G14: Неналоговые поступления
A15: Негізгі капиталды сатудан түсетін түсімдер | B15: 38422.814 | C15: 19654.299 | D15: 23284.113 | E15: 15448.746 | F15: 3552.5622 | G15: Поступления от продажи основного капитала
A16: Трансферттердің түсімдері | B16: 929218.4 | C16: 1169764 | D16: 1229032.5 | E16: 643996.66 | F16: 720487.97 | G16: Поступления трансфертов
A17: II. ШЫҒЫНДАР | B17: 1091950.3 | C17: 1324232.9 | D17: 1469273.5 | E17: 740321.17 | F17: 855144.34 | G17: II. ЗАТРАТЫ
A18: 1. Жалпы сипаттағы мемлекеттiк қызметтер | B18: 30411.011 | C18: 37613.034 | D18: 41735.89 | E18: 22867.843 | F18: 26457.559 | G18: 1. Государственные услуги общего характера
A19: 2. Қорғаныс | B19: 1834.4717 | C19: 7115.7448 | D19: 4702.653 | E19: 1756.6103 | F19: 2772.2117 | G19: 2. Оборона
... A44: Өтеу | B44: 26919.364 | C44: 52102.681 | D44: 48890.025 | E44: 47952.415 | F44: 7039.5688 | G44: Погашение
A45: Сыртқы | B45: - | C45: - | D45: - | E45: - | F45: - | G45: Внешнее
A46: Түсімдер | B46: - | C46: - | D46: - | E46: - | F46: - | G46: Поступление
A47: Өтеу | B47: - | C47: - | D47: - | E47: - | F47: - | G47: Погашение

Sheet табл 12.15
A1: 12.15-кесте | E1: Таблица 12.15
A2: ШЫМКЕНТ Қ. | E2: ИСПОЛНЕНИЕ БЮДЖЕТА
A3: БЮДЖЕТІНІҢ АТҚАРЫЛУЫ | E3: Г.ШЫМКЕНТ
A4: (млн.теңге) | E4: (млн. тенге)
A5: Атауы | B5: 2022 ж. есеп/ 2022 г. отчет | C5: 2023 ж. есеп/ 2023 г. отчет | D5: 2024 ж. есеп/ 2024 г. отчет | F5: 2025 ж. қантар-шілде есеп/январь-июль отчет 2025 г. | G5: Наименование
D6: жылдық/ годовой | E6: қантар-шілде/январь-июль
A7: 1 | B7: 2 | C7: 3 | D7: 4 | E7: 5 | F7: 6 | G7: 7
A8: I. КІРІСТЕР | B8: 594277.32 | C8: 627061.85 | D8: 735887.74 | E8: 391278.19 | F8: 445117.44 | G8: I. ДОХОДЫ
A9: Салықтық түсімдер_x000D_ оның iшiнде: | B9: 245644.64 | C9: 305471.98 | D9: 370511.82 | E9: 200361.81 | F9: 250298.66 | G9: Налоговые поступления,_x000D_ в том числе:
A10: корпорациялық табыс салығы | B10: 25315.737 | C10: 29134.129 | D10: 41909.805 | E10: 23677.725 | F10: 30715.067 | G10: корпоративный подоходный налог
A11: жеке табыс салығы | B11: 41223.421 | C11: 55307.321 | D11: 80327.448 | E11: 44199.751 | F11: 56721.71 | G11: индивидуальный подоходный налог
A12: әлеуметтік салық | B12: 28610.328 | C12: 38666.348 | D12: 50978.411 | E12: 28287.246 | F12: 33549.334 | G12: социальный налог
A13: акциздер | B13: 128275.7 | C13: 140181.27 | D13: 148639.15 | E13: 77009.57 | F13: 96409.031 | G13: акцизы
A14: Салықтық емес түсімдер | B14: 11701.14 | C14: 12877.295 | D14: 20094.627 | E14: 13247.056 | F14: 8789.3186 | G14: Неналоговые поступления
A15: Негізгі капиталды сатудан түсетін түсімдер | B15: 23217.94 | C15: 24378.713 | D15: 31129.909 | E15: 16257.024 | F15: 8876.3938 | G15: Поступления от продажи основного капитала
A16: Трансферттердің түсімдері | B16: 313713.6 | C16: 284333.86 | D16: 314151.39 | E16: 161412.3 | F16: 177153.06 | G16: Поступления трансфертов
A17: II. ШЫҒЫНДАР | B17: 561567.31 | C17: 621600.2 | D17: 741031.51 | E17: 354387.63 | F17: 429774.45 | G17: II. ЗАТРАТЫ
A18: 1. Жалпы сипаттағы мемлекеттiк қызметтер | B18: 5134.2192 | C18: 6097.5574 | D18: 14228.974 | E18: 6034.9257 | F18: 10798.003 | G18: 1. Государственные услуги общего характера
A19: 2. Қорғаныс | B19: 2589.1297 | C19: 4312.2946 | D19: 8394.1274 | E19: 4521.6716 | F19: 3158.9617 | G19: 2. Оборона
... A35: Бюджеттік кредиттерді өтеу | B35: 609.00727 | C35: 709.3846 | D35: 369.06413 | E35: 167.80143 | F35: 1876.5791 | G35: Погашение бюджетных кредитов
A36: IV. ҚАРЖЫ АКТИВТЕРІМЕН ОПЕРАЦИЯЛАР БОЙЫНША САЛЬДО - ҚАРЖЫ АК | B36: 417.10246 | C36: 1040.141 | D36: 4546.9162 | E36: -62.676182 | G36: IV. САЛЬДО ПО ОПЕРАЦИЯМ С ФИНАНСОВЫМИ АКТИВАМИ
A37: Қаржылық активтерді сатып алу | B37: 462.073 | C37: 1040.141 | D37: 4650.2915 | E37: 0 | G37: Приобретение финансовых активов
A38: Мемлекеттің қаржы активтерін сатудан түсетін түсімдер | B38: 44.970536 | D38: 103.37533 | E38: 62.676182 | G38: Поступления от продажи финансовых активов государства
A39: V. БЮДЖЕТ ТАПШЫЛЫҒЫ (ПРОФИЦИТІ) | B39: 32501.917 | C39: 825.89571 | D39: -34037.623 | E39: 32121.041 | F39: 12219.56 | G39: V. ДЕФИЦИТ (ПРОФИЦИТ) БЮДЖЕТА
A41: VII. БЮДЖЕТТІҢ ТАПШЫЛЫҒЫН ҚАРЖЫЛАНДЫРУ (ПРОФИЦИТТІ ПАЙДАЛАНУ | B41: -32501.917 | C41: -825.89571 | D41: -34037.623 | E41: -32121.041 | F41: -12219.56 | G41: VII. ФИНАНСИРОВАНИЕ ДЕФИЦИТА (ИСПОЛЬЗОВАНИЕ ПРОФИЦИТА) БЮДЖЕТА
A42: Ішкі | B42: -65751.323 | C42: 53721.326 | D42: -11866.888 | E42: -743131.39 | F42: -12219.56 | G42: Внутреннее
A43: Түсімдер | B43: -26231.055 | C43: 76211.623 | D43: -2021.0519 | E43: -741727.11 | F43: -11351.05 | G43: Поступление
A44: Өтеу | B44: 39520.268 | C44: 22490.297 | D44: 9845.836 | E44: 1404.273 | F44: 868.51 | G44: Погашение
A45: Сыртқы | B45: - | C45: - | D45: - | E45: - | F45: - | G45: Внешнее
A46: Түсімдер | B46: - | C46: - | D46: - | E46: - | F46: - | G46: Поступление
A47: Өтеу | B47: - | C47: - | D47: - | E47: - | F47: - | G47: Погашение

Sheet табл 12.16
A1: 12.16-кесте | E1: Таблица 12.16
A2: АЛМАТЫ Қ. | E2: ИСПОЛНЕНИЕ БЮДЖЕТА
A3: БЮДЖЕТІНІҢ АТҚАРЫЛУЫ | E3: Г.АЛМАТЫ
A4: (млн.теңге) | E4: (млн. тенге)
A5: Атауы | B5: 2022 ж. есеп/ 2022 г. отчет | C5: 2023 ж. есеп/ 2023 г. отчет | D5: 2024 ж. есеп/ 2024 г. отчет | F5: 2025 ж. қантар-шілде есеп/январь-июль отчет 2025 г. | G5: Наименование
D6: жылдық/ годовой | E6: қантар-шілде/январь-июль
A7: 1 | B7: 2 | C7: 3 | D7: 4 | E7: 5 | F7: 6 | G7: 7
A8: I. КІРІСТЕР | B8: 1399237.9 | C8: 1637208.5 | D8: 1968721 | E8: 1121822 | F8: 1314936 | G8: I. ДОХОДЫ
A9: Салықтық түсімдер_x000D_ оның iшiнде: | B9: 1122101.8 | C9: 1458171.8 | D9: 1810913.8 | E9: 1060473.6 | F9: 1218686.3 | G9: Налоговые поступления,_x000D_ в том числе:
A10: корпорациялық табыс салығы | B10: 441667.45 | C10: 480314.07 | D10: 632526.82 | E10: 394626.72 | F10: 430263.8 | G10: корпоративный подоходный налог
A11: жеке табыс салығы | B11: 376430.03 | C11: 550653.94 | D11: 663170.95 | E11: 374372.07 | F11: 433330.75 | G11: индивидуальный подоходный налог
A12: әлеуметтік салық | B12: 207296.3 | C12: 283392.46 | D12: 353665.14 | E12: 195463.87 | F12: 240594.52 | G12: социальный налог
A13: акциздер | B13: 22972.399 | C13: 24182.211 | D13: 20738.486 | E13: 12853.168 | F13: 12526.295 | G13: акцизы
A14: Салықтық емес түсімдер | B14: 16584.992 | C14: 28489.614 | D14: 53614.391 | E14: 30523.988 | F14: 42799.735 | G14: Неналоговые поступления
A15: Негізгі капиталды сатудан түсетін түсімдер | B15: 36457.864 | C15: 24703.233 | D15: 9841.7819 | E15: 5910.6945 | F15: 5681.8931 | G15: Поступления от продажи основного капитала
A16: Трансферттердің түсімдері | B16: 224093.22 | C16: 125843.88 | D16: 94351.102 | E16: 24913.71 | F16: 47768.09 | G16: Поступления трансфертов
A17: II. ШЫҒЫНДАР | B17: 1101542.2 | C17: 1397412.5 | D17: 1591047.9 | E17: 737356.46 | F17: 1043310.9 | G17: II. ЗАТРАТЫ
A18: 1. Жалпы сипаттағы мемлекеттiк қызметтер | B18: 13202.9 | C18: 25740.582 | D18: 26609.068 | E18: 13511.995 | F18: 14617.019 | G18: 1. Государственные услуги общего характера
A19: 2. Қорғаныс | B19: 8598.6902 | C19: 17949.3 | D19: 13685.076 | E19: 4197.5204 | F19: 6528.1733 | G19: 2. Оборона
... A44: Өтеу | B44: 54597.504 | C44: 1697.1099 | D44: 15850.324 | E44: 14364.544 | F44: 2567.9696 | G44: Погашение
A45: Сыртқы | B45: - | C45: - | D45: - | E45: - | F45: - | G45: Внешнее
A46: Түсімдер | B46: - | C46: - | D46: - | E46: - | F46: - | G46: Поступление
A47: Өтеу | B47: - | C47: - | D47: - | E47: - | F47: - | G47: Погашение

Sheet табл 12.17
A1: 12.17-кесте | E1: Таблица 12.17
A2: АСТАНА Қ. | E2: ИСПОЛНЕНИЕ БЮДЖЕТА
A3: БЮДЖЕТІНІҢ АТҚАРЫЛУЫ | E3: Г.АСТАНА
A4: (млн.теңге) | E4: (млн. тенге)
A5: Атауы | B5: 2022 ж. есеп/ 2022 г. отчет | C5: 2023 ж. есеп/ 2023 г. отчет | D5: 2024 ж. есеп/ 2024 г. отчет | F5: 2025 ж. қантар-шілде есеп/январь-июль отчет 2025 г. | G5: Наименование
D6: жылдық/ годовой | E6: қантар-шілде/январь-июль
A7: 1 | B7: 2 | C7: 3 | D7: 4 | E7: 5 | F7: 6 | G7: 7
A8: I. КІРІСТЕР | B8: 898608.87 | C8: 1214113.6 | D8: 1362235.7 | E8: 769055.45 | F8: 878503.25 | G8: I. ДОХОДЫ
A9: Салықтық түсімдер_x000D_ оның iшiнде: | B9: 556603.65 | C9: 740597.87 | D9: 999235.25 | E9: 590140.85 | F9: 664944.24 | G9: Налоговые поступления,_x000D_ в том числе:
A10: корпорациялық табыс салығы | B10: 174626.78 | C10: 213956.37 | D10: 345278.42 | E10: 223589.99 | F10: 218763.49 | G10: корпоративный подоходный налог
A11: жеке табыс салығы | B11: 193983.18 | C11: 274609.96 | D11: 345535.64 | E11: 192888.44 | F11: 234937.25 | G11: индивидуальный подоходный налог
A12: әлеуметтік салық | B12: 130486.4 | C12: 172818.42 | D12: 217507.87 | E12: 118672.62 | F12: 151190.23 | G12: социальный налог
A13: акциздер | B13: 335.26185 | C13: 494.4745 | D13: 398.92685 | E13: 243.05692 | F13: 330.98504 | G13: акцизы
A14: Салықтық емес түсімдер | B14: 19576.334 | C14: 21947.539 | D14: 72224.371 | E14: 25154.972 | F14: 28726.276 | G14: Неналоговые поступления
A15: Негізгі капиталды сатудан түсетін түсімдер | B15: 26325.768 | C15: 13395.537 | D15: 16189.97 | E15: 12649.731 | F15: 5943.5237 | G15: Поступления от продажи основного капитала
A16: Трансферттердің түсімдері | B16: 296103.12 | C16: 438172.65 | D16: 274586.08 | E16: 141109.9 | F16: 178889.21 | G16: Поступления трансфертов
A17: II. ШЫҒЫНДАР | B17: 856289.05 | C17: 1104676.1 | D17: 1274128.6 | E17: 596040.86 | F17: 734744.37 | G17: II. ЗАТРАТЫ
A18: 1. Жалпы сипаттағы мемлекеттiк қызметтер | B18: 40014.73 | C18: 24279.956 | D18: 39994.935 | E18: 22598.038 | F18: 15234.066 | G18: 1. Государственные услуги общего характера
A19: 2. Қорғаныс | B19: 4167.4934 | C19: 4020.8667 | D19: 5256.4435 | E19: 1355.1863 | F19: 3859.4191 | G19: 2. Оборона
... A44: Өтеу | B44: 39215.369 | C44: 15390.112 | D44: 37195.777 | E44: 35577.582 | F44: 7253.9249 | G44: Погашение
A45: Сыртқы | B45: - | C45: - | D45: - | E45: - | F45: - | G45: Внешнее
A46: Түсімдер | B46: - | C46: - | D46: - | E46: - | F46: - | G46: Поступление
A47: Өтеу | B47: - | C47: - | D47: - | E47: - | F47: - | G47: Погашение

Sheet табл 12.18
A1: 12.18-кесте | E1: Таблица 12.18
A2: ЖЕТІСУ ОБЛЫСЫ | E2: ИСПОЛНЕНИЕ БЮДЖЕТА
A3: БЮДЖЕТІНІҢ АТҚАРЫЛУЫ | E3: ОБЛАСТЬ ЖЕТІСУ
A4: (млн.теңге) | E4: (млн. тенге)
A5: Атауы | B5: 2022 ж. есеп/ 2022 г. отчет | C5: 2023 ж. есеп/ 2023 г. отчет | D5: 2024 ж. есеп/ 2024 г. отчет | F5: 2025 ж. қантар-шілде есеп/январь-июль отчет 2025 г. | G5: Наименование
D6: жылдық/ годовой | E6: қантар-шілде/январь-июль
A7: 1 | B7: 2 | C7: 3 | D7: 4 | E7: 5 | F7: 6 | G7: 7
A8: I. КІРІСТЕР | B8: 314563.64 | C8: 463421.37 | D8: 542203.66 | E8: 286565.7 | F8: 294988.02 | G8: I. ДОХОДЫ
A9: Салықтық түсімдер_x000D_ оның iшiнде: | B9: 18067.345 | C9: 66904.461 | D9: 87798.583 | E9: 49109.69 | F9: 60091.3 | G9: Налоговые поступления,_x000D_ в том числе:
A10: корпорациялық табыс салығы | B10: 2806.2266 | C10: 9017.648 | D10: 13383.169 | E10: 7204.7748 | F10: 9716.6923 | G10: корпоративный подоходный налог
A11: жеке табыс салығы | B11: 7258.0591 | C11: 25930.316 | D11: 34956.565 | E11: 19650.934 | F11: 23896.056 | G11: индивидуальный подоходный налог
A12: әлеуметтік салық | B12: 5466.8729 | C12: 18598.439 | D12: 23298.185 | E12: 12799.936 | F12: 15248.208 | G12: социальный налог
A13: акциздер | B13: 35.103894 | C13: 108.67661 | D13: 115.49381 | E13: 61.106858 | F13: 68.660767 | G13: акцизы
A14: Салықтық емес түсімдер | B14: 811.24923 | C14: 7011.9315 | D14: 15570.046 | E14: 13107.819 | F14: 8758.5771 | G14: Неналоговые поступления
A15: Негізгі капиталды сатудан түсетін түсімдер | B15: 1516.0592 | C15: 1881.3507 | D15: 14651.2 | E15: 8381.1039 | F15: 6634.5297 | G15: Поступления от продажи основного капитала
A16: Трансферттердің түсімдері | B16: 294168.99 | C16: 387623.63 | D16: 424183.83 | E16: 215967.08 | F16: 219503.62 | G16: Поступления трансфертов
A17: II. ШЫҒЫНДАР | B17: 333888.75 | C17: 468267.8 | D17: 529861.03 | E17: 253255.93 | F17: 295661.32 | G17: II. ЗАТРАТЫ
A18: 1. Жалпы сипаттағы мемлекеттiк қызметтер | B18: 15467.947 | C18: 21805.231 | D18: 21189.219 | E18: 11217.359 | F18: 13656.831 | G18: 1. Государственные услуги общего характера
A19: 2. Қорғаныс | B19: 857.189 | C19: 2597.8495 | D19: 4147.4281 | E19: 1609.6275 | F19: 1632.8887 | G19: 2. Оборона
... A37: Қаржылық активтерді сатып алу | B37: 229 | C37: 1369.6586 | D37: 2879.5543 | E37: 2879.5543 | F37: 1662.649 | G37: Приобретение финансовых активов
A38: Мемлекеттің қаржы активтерін сатудан түсетін түсімдер | C38: 139.67744 | D38: 16.454256 | G38: Поступления от продажи финансовых активов государства
A39: V. БЮДЖЕТ ТАПШЫЛЫҒЫ (ПРОФИЦИТІ) | B39: -22710.45 | C39: -15200.423 | D39: -1835.6411 | E39: 26566.022 | F39: -1033.3218 | G39: V. ДЕФИЦИТ (ПРОФИЦИТ) БЮДЖЕТА
A41: VII. БЮДЖЕТТІҢ ТАПШЫЛЫҒЫН ҚАРЖЫЛАНДЫРУ (ПРОФИЦИТТІ ПАЙДАЛАНУ | B41: 22710.45 | C41: 15200.423 | D41: -1835.6411 | E41: -26566.022 | F41: 1033.3218 | G41: VII. ФИНАНСИРОВАНИЕ ДЕФИЦИТА (ИСПОЛЬЗОВАНИЕ ПРОФИЦИТА) БЮДЖЕТА
A42: Ішкі | B42: 249468.62 | C42: 105211.69 | D42: -202290.09 | E42: -248018.17 | F42: 1033.3218 | G42: Внутреннее
A43: Түсімдер | B43: 255500.31 | C43: 112586.44 | D43: -190675.47 | E43: -237206.43 | F43: 2426.0736 | G43: Поступление
A44: Өтеу | B44: 6031.6945 | C44: 7374.7509 | D44: 11614.621 | E44: 10811.745 | F44: 1392.7518 | G44: Погашение
A45: Сыртқы | B45: - | C45: - | D45: - | E45: - | F45: - | G45: Внешнее
A46: Түсімдер | B46: - | C46: - | D46: - | E46: - | F46: - | G46: Поступление
A47: Өтеу | B47: - | C47: - | D47: - | E47: - | F47: - | G47: Погашение

Sheet табл 12.19
A1: 12.19-кесте | E1: Таблица 12.19
A2: АБАЙ ОБЛЫСЫ | E2: ИСПОЛНЕНИЕ БЮДЖЕТА
A3: БЮДЖЕТІНІҢ АТҚАРЫЛУЫ | E3: ОБЛАСТЬ АБАЙ
A4: (млн.теңге) | E4: (млн. тенге)
A5: Атауы | B5: 2022 ж. есеп/ 2022 г. отчет | C5: 2023 ж. есеп/ 2023 г. отчет | D5: 2024 ж. есеп/ 2024 г. отчет | F5: 2025 ж. қантар-шілде есеп/январь-июль отчет 2025 г. | G5: Наименование
D6: жылдық/ годовой | E6: қантар-шілде/январь-июль
A7: 1 | B7: 2 | C7: 3 | D7: 4 | E7: 5 | F7: 6 | G7: 7
A8: I. КІРІСТЕР | B8: 123963.96 | C8: 406297.42 | D8: 436986.27 | E8: 233494.51 | F8: 242705.3 | G8: I. ДОХОДЫ
A9: Салықтық түсімдер_x000D_ оның iшiнде: | B9: 23640.793 | C9: 96670.78 | D9: 120573.62 | E9: 67226.628 | F9: 75621.989 | G9: Налоговые поступления,_x000D_ в том числе:
A10: корпорациялық табыс салығы | B10: 3442.4366 | C10: 10602.802 | D10: 15174.453 | E10: 9270.7056 | F10: 9728.2281 | G10: корпоративный подоходный налог
A11: жеке табыс салығы | B11: 8475.622 | C11: 35508.593 | D11: 47635.001 | E11: 26707.707 | F11: 29904.394 | G11: индивидуальный подоходный налог
A12: әлеуметтік салық | B12: 6413.9815 | C12: 25133.408 | D12: 31334.967 | E12: 17089.183 | F12: 19917.503 | G12: социальный налог
A13: акциздер | B13: 47.402816 | C13: 120.5248 | D13: 136.75735 | E13: 74.769957 | F13: 98.465503 | G13: акцизы
A14: Салықтық емес түсімдер | B14: 1403.9666 | C14: 5854.4088 | D14: 7963.6674 | E14: 4422.113 | F14: 4032.5321 | G14: Неналоговые поступления
A15: Негізгі капиталды сатудан түсетін түсімдер | B15: 1877.6062 | C15: 9525.8628 | D15: 7036.9998 | E15: 2061.3742 | F15: 8612.5696 | G15: Поступления от продажи основного капитала
A16: Трансферттердің түсімдері | B16: 97041.596 | C16: 294246.37 | D16: 301411.98 | E16: 159784.39 | F16: 154438.21 | G16: Поступления трансфертов
A17: II. ШЫҒЫНДАР | B17: 241281 | C17: 400475.3 | D17: 450819.22 | E17: 220171.82 | F17: 240538.16 | G17: II. ЗАТРАТЫ
A18: 1. Жалпы сипаттағы мемлекеттiк қызметтер | B18: 13142.849 | C18: 18110.235 | D18: 18833.812 | E18: 9173.393 | F18: 11711.53 | G18: 1. Государственные услуги общего характера
A19: 2. Қорғаныс | B19: 454.4762 | C19: 1514.0761 | D19: 2981.9366 | E19: 1253.4591 | F19: 885.88154 | G19: 2. Оборона
... A44: Өтеу | B44: 6760.4604 | C44: 9196.8776 | D44: 11801.966 | E44: 11047.178 | F44: 370.31002 | G44: Погашение
A45: Сыртқы | B45: - | C45: - | D45: - | E45: - | F45: - | G45: Внешнее
A46: Түсімдер | B46: - | C46: - | D46: - | E46: - | F46: - | G46: Поступление
A47: Өтеу | B47: - | C47: - | D47: - | E47: - | F47: - | G47: Погашение

Sheet табл 12.20
A1: 12.20-кесте | E1: Таблица 12.20
A2: ҰЛЫТАУ ОБЛЫСЫ | E2: ИСПОЛНЕНИЕ БЮДЖЕТА
A3: БЮДЖЕТІНІҢ АТҚАРЫЛУЫ | E3: ОБЛАСТЬ УЛЫТАУ
A4: (млн.теңге) | E4: (млн. тенге)
A5: Атауы | B5: 2022 ж. есеп/ 2022 г. отчет | C5: 2023 ж. есеп/ 2023 г. отчет | D5: 2024 ж. есеп/ 2024 г. отчет | F5: 2025 ж. қантар-шілде есеп/январь-июль отчет 2025 г. | G5: Наименование
D6: жылдық/ годовой | E6: қантар-шілде/январь-июль
A7: 1 | B7: 2 | C7: 3 | D7: 4 | E7: 5 | F7: 6 | G7: 7
A8: I. КІРІСТЕР | B8: 69867.744 | C8: 169203.26 | D8: 182521.75 | E8: 98748.99 | F8: 108071.92 | G8: I. ДОХОДЫ
A9: Салықтық түсімдер_x000D_ оның iшiнде: | B9: 29082.263 | C9: 88623.044 | D9: 101434.1 | E9: 58255.003 | F9: 68858.07 | G9: Налоговые поступления,_x000D_ в том числе:
A10: корпорациялық табыс салығы | B10: 1033.0279 | C10: 3437.64 | D10: 3853.4637 | E10: 2096.3767 | F10: 2200.2079 | G10: корпоративный подоходный налог
A11: жеке табыс салығы | B11: 15216.672 | C11: 35167.663 | D11: 42259.528 | E11: 25568.491 | F11: 27954.68 | G11: индивидуальный подоходный налог
A12: әлеуметтік салық | B12: 7006.6025 | C12: 26713.417 | D12: 30448.408 | E12: 18389.113 | F12: 21920.926 | G12: социальный налог
A13: акциздер | B13: 10.406807 | C13: 31.923543 | D13: 34.491962 | E13: 19.852653 | F13: 20.503629 | G13: акцизы
A14: Салықтық емес түсімдер | B14: 701.8482 | C14: 1846.7391 | D14: 4476.532 | E14: 1924.8127 | F14: 1590.0016 | G14: Неналоговые поступления
A15: Негізгі капиталды сатудан түсетін түсімдер | B15: 388.8179 | C15: 836.04433 | D15: 573.04005 | E15: 353.11605 | F15: 619.5569 | G15: Поступления от продажи основного капитала
A16: Трансферттердің түсімдері | B16: 39694.814 | C16: 77897.437 | D16: 76038.08 | E16: 38216.058 | F16: 37004.29 | G16: Поступления трансфертов
A17: II. ШЫҒЫНДАР | B17: 104669.26 | C17: 173439.18 | D17: 190573.16 | E17: 83067.682 | F17: 98724.206 | G17: II. ЗАТРАТЫ
A18: 1. Жалпы сипаттағы мемлекеттiк қызметтер | B18: 9909.0703 | C18: 10297.274 | D18: 11032.221 | E18: 4648.3875 | F18: 6024.1019 | G18: 1. Государственные услуги общего характера
A19: 2. Қорғаныс | B19: 268.0898 | C19: 928.85161 | D19: 1060.7158 | E19: 338.56335 | F19: 586.41973 | G19: 2. Оборона
... A35: Бюджеттік кредиттерді өтеу | B35: 43.306982 | C35: 124.1571 | D35: 241.9638 | E35: 118.21489 | F35: 195.82147 | G35: Погашение бюджетных кредитов
A36: IV. ҚАРЖЫ АКТИВТЕРІМЕН ОПЕРАЦИЯЛАР БОЙЫНША САЛЬДО - ҚАРЖЫ АК | B36: 605.2533 | C36: 600 | G36: IV. САЛЬДО ПО ОПЕРАЦИЯМ С ФИНАНСОВЫМИ АКТИВАМИ
A37: Қаржылық активтерді сатып алу | B37: 605.2533 | C37: 600 | G37: Приобретение финансовых активов
A38: V. БЮДЖЕТ ТАПШЫЛЫҒЫ (ПРОФИЦИТІ) | B38: -36168.732 | C38: -9643.875 | D38: -11952.578 | E38: 15644.459 | F38: 8043.534 | G38: V. ДЕФИЦИТ (ПРОФИЦИТ) БЮДЖЕТА
A40: VII. БЮДЖЕТТІҢ ТАПШЫЛЫҒЫН ҚАРЖЫЛАНДЫРУ (ПРОФИЦИТТІ ПАЙДАЛАНУ | B40: 36168.732 | C40: 9643.875 | D40: -11952.578 | E40: -15644.459 | F40: -8043.534 | G40: VII. ФИНАНСИРОВАНИЕ ДЕФИЦИТА (ИСПОЛЬЗОВАНИЕ ПРОФИЦИТА) БЮДЖЕТА
A41: Ішкі | B41: 434411.53 | C41: 27104.05 | D41: 46198.148 | E41: -189067.8 | F41: -8043.534 | G41: Внутреннее
A42: Түсімдер | B42: 435253.89 | C42: 27814.732 | D42: 48671.376 | E42: -188974.59 | F42: -7671.7256 | G42: Поступление
A43: Өтеу | B43: 842.36092 | C43: 710.68167 | D43: 2473.2288 | E43: 93.20695 | F43: 371.80842 | G43: Погашение
A44: Сыртқы | B44: - | C44: - | D44: - | E44: - | F44: - | G44: Внешнее
A45: Түсімдер | B45: - | C45: - | D45: - | E45: - | F45: - | G45: Поступление
A46: Өтеу | B46: - | C46: - | D46: - | E46: - | F46: - | G46: Погашение

Sheet табл 13
B2: Отчет об исполнении консолидированного бюджета
B3: на 1 августа 2025 года
B4: Периодичность: месячная
B5: Единица измерения: тыс.тг
B7: Коды бюджетной классификации | C7: Наименование | D7: Скорректированный бюджет | E7: Исполнение | F7: % исполнение
B8: 1 | C8: 2 | D8: 3 | E8: 4 | F8: 5
C9: I. ДОХОДЫ | D9: 2.8996547e+10 | E9: 1.5387491e+10 | F9: 53.066633
C10: НАЛОГОВЫЕ ПОСТУПЛЕНИЯ | D10: 27948201869 | E10: 1.4354383e+10 | F10: 51.360666
B11: 1 | C11: Налоговые поступления | D11: 27948201869 | E11: 1.4354383e+10 | F11: 51.360666
C12: НЕНАЛОГОВЫЕ ПОСТУПЛЕНИЯ | D12: 737029967 | E12: 9.2844752e+08 | F12: 125.97147
B13: 2 | C13: Неналоговые поступления | D13: 737029967 | E13: 9.2844752e+08 | F13: 125.97147
C14: ПОСТУПЛЕНИЯ ОТ ПРОДАЖИ ОСНОВНОГО КАПИТАЛА | D14: 3.1131486e+08 | E14: 1.0466081e+08 | F14: 33.618956
B15: 3 | C15: Поступления от продажи основного капитала | D15: 3.1131486e+08 | E15: 1.0466081e+08 | F15: 33.618956
C16: ПОСТУПЛЕНИЯ ТРАНСФЕРТОВ | D16: 0 | E16: 0 | F16: 0
B17: 4 | C17: Поступления трансфертов | D17: 0 | E17: 0 | F17: 0
C18: II. ИНВЕСТИЦИОННЫЕ ДОХОДЫ ОТ УПРАВЛЕНИЯ НАЦИОНАЛЬНЫМ ФОНДОМ | D18: 888700000 | E18: -584471288 | F18: -65.766995
C19: III. ПОСТУПЛЕНИЯ ОТ ПРОДАЖИ ОРГАНИЗАЦИЕЙ, СПЕЦИАЛИЗИРУЮЩЕЙСЯ НА УЛУЧШЕНИИ КАЧЕСТВА КРЕДИТНЫХ ПОРТФЕЛЕЙ БАНКОВ ВТОРОГО УРОВНЯ, АКТИВОВ | D19: 0 | E19: 1000000 | F19: 0
C20: IV. ИНЫЕ ПОСТУПЛЕНИЯ И ДОХОДЫ, НЕ ЗАПРЕЩЕННЫЕ ЗАКОНОДАТЕЛЬСТВОМ РЕСПУБЛИКИ КАЗАХСТАН | D20: 0 | E20: 0 | F20: 0
C21: V. ПОСТУПЛЕНИЯ В ГФСС | D21: 1072924400 | E21: 622093327 | F21: 57.981096
C22: VI. ПОСТУПЛЕНИЯ В ФСМС | D22: 1156892414 | E22: 7.6539258e+08 | F22: 66.159357
C23: VII. ЗАТРАТЫ | D23: 31518387958 | E23: 1.658802e+10 | F23: 52.629657
B24: 1 | C24: Государственные услуги общего характера | D24: 1.9214156e+09 | E24: 8.933615e+08 | F24: 46.494966
B25: 2 | C25: Оборона | D25: 1.3732148e+09 | E25: 5.443675e+08 | F25: 39.641831
B26: 3 | C26: Общественный порядок, безопасность, правовая, судебная, уголовно-исполнительная деятельность | D26: 1.780676e+09 | E26: 9.0038043e+08 | F26: 50.563968
B27: 4 | C27: Образование | D27: 7003147445 | E27: 3.9517117e+09 | F27: 56.427653
B28: 5 | C28: Здравоохранение | D28: 7.2079264e+08 | E28: 2.5874507e+08 | F28: 35.897297
B29: 6 | C29: Социальная помощь и социальное обеспечение | D29: 6.8879219e+09 | E29: 3.8662045e+09 | F29: 56.130203
B30: 7 | C30: Жилищно-коммунальное хозяйство | D30: 2.7257462e+09 | E30: 1.0933396e+09 | F30: 40.111572
B31: 8 | C31: Культура, спорт, туризм и информационное пространство | D31: 1.207952e+09 | E31: 6.2643411e+08 | F31: 51.859189
B32: 9 | C32: Топливно-энергетический комплекс и недропользование | D32: 4.1714911e+08 | E32: 1.9359736e+08 | F32: 46.409631
B33: 10 | C33: Сельское, водное, лесное, рыбное хозяйство, особо охраняемые природные территории, охрана окружающей среды и животного мира, земельные отношения | D33: 1.3269834e+09 | E33: 6.9708166e+08 | F33: 52.531303
B34: 11 | C34: Промышленность, архитектурная, градостроительная и строительная деятельность | D34: 1.0619588e+08 | E34: 48331960 | F34: 45.512088
B35: 12 | C35: Транспорт и коммуникации | D35: 2.4109716e+09 | E35: 1.0629763e+09 | F35: 44.089128
... B37: 14 | C37: Обслуживание долга | D37: 2550090208 | E37: 2.0352154e+09 | F37: 79.809547
C38: VIII. ВЫПЛАТЫ С КСН ФКП | D38: 0 | E38: 102887.42 | F38: 0
C39: IX. ПОКРЫТИЕ РАСХОДОВ, СВЯЗАННЫХ С УПРАВЛЕНИЕМ НАЦИОНАЛЬНЫМ ФОНДОМ И ПРОВЕДЕНИЕМ ЕЖЕГОДНОГО ВНЕШНЕГО АУДИТА | D39: 84100000 | E39: 24774922 | F39: 29.458885
C40: X. РАСХОДЫ ГФСС | D40: 1041227798 | E40: 675351179 | F40: 64.86104
C41: XI. РАСХОДЫ ФСМС | D41: 3306127010 | E41: 1.5451518e+09 | F41: 46.736008
C42: XII. РАСХОДЫ ФПИО | D42: 0 | E42: 0 | F42: 0
C43: XIII. РАСХОДЫ СГФ | D43: 0 | E43: 238579033 | F43: 0
C44: XIV. ЧИСТОЕ БЮДЖЕТНОЕ КРЕДИТОВАНИЕ | D44: 3.6316174e+08 | E44: 1.3910102e+08
C45: БЮДЖЕТНЫЕ КРЕДИТЫ | D45: 6.3696888e+08 | E45: 2.8141146e+08 | F45: 44.179782
B46: 6 | C46: Социальная помощь и социальное обеспечение | D46: 493025 | E46: 63688.496 | F46: 12.917904
B47: 7 | C47: Жилищно-коммунальное хозяйство | D47: 95050373 | E47: 69052947 | F47: 72.648791
B48: 10 | C48: Сельское, водное, лесное, рыбное хозяйство, особо охраняемые природные территории, охрана окружающей среды и животного мира, земельные отношения | D48: 4.1858973e+08 | E48: 176294829 | F48: 42.116377
B49: 11 | C49: Промышленность, архитектурная, градостроительная и строительная деятельность | D49: 30000000 | E49: 0 | F49: 0
B50: 13 | C50: Прочие | D50: 27355750 | E50: 2000000 | F50: 7.3110772
C51: ПОГАШЕНИЕ БЮДЖЕТНЫХ КРЕДИТОВ | D51: 2.7380714e+08 | E51: 1.4231044e+08 | F51: 51.974702
B52: 5 | C52: Погашение бюджетных кредитов | D52: 2.7380714e+08 | E52: 1.4231044e+08 | F52: 51.974702
C53: XV. САЛЬДО ПО ОПЕРАЦИЯМ С ФИНАНСОВЫМИ АКТИВАМИ | D53: 524287430 | E53: 2.8460222e+08
C54: ПРИОБРЕТЕНИЕ ФИНАНСОВЫХ АКТИВОВ | D54: 528067619 | E54: 2.8819358e+08 | F54: 54.575129
B55: 1 | C55: Государственные услуги общего характера | D55: 15874081 | E55: 137328.96 | F55: 0.86511439
B56: 7 | C56: Жилищно-коммунальное хозяйство | D56: 373000 | E56: 373000 | F56: 100
B57: 10 | C57: Сельское, водное, лесное, рыбное хозяйство, особо охраняемые природные территории, охрана окружающей среды и животного мира, земельные отношения | D57: 30000000 | E57: 18000500 | F57: 60.001667
B58: 11 | C58: Промышленность, архитектурная, градостроительная и строительная деятельность | D58: 1017219 | E58: 1017219 | F58: 100
B59: 12 | C59: Транспорт и коммуникации | D59: 365365596 | E59: 178945096 | F59: 48.976997
B60: 13 | C60: Прочие | D60: 115437723 | E60: 89720440 | F60: 77.721942
C61: ПОСТУПЛЕНИЯ ОТ ПРОДАЖИ ФИНАНСОВЫХ АКТИВОВ ГОСУДАРСТВА | D61: 3780189 | E61: 3591365.9 | F61: 95.004931
B62: 6 | C62: Поступления от продажи финансовых активов государства | D62: 3780189 | E62: 3591365.9 | F62: 95.004931
C63: XVI. ДЕФИЦИТ (ПРОФИЦИТ) БЮДЖЕТА | D63: -4.7222284e+09 | E63: -3.3041769e+09
C64: XVII. НЕНЕФТЯНОЙ ДЕФИЦИТ (ПРОФИЦИТ) БЮДЖЕТА | D64: -6.3719284e+09 | E64: -4.1849434e+09
C65: XVIII. ФИНАНСИРОВАНИЕ ДЕФИЦИТА (ИСПОЛЬЗОВАНИЕ ПРОФИЦИТА) БЮДЖЕТА | D65: 4.7222284e+09 | E65: 3.3041769e+09
C66: ПОСТУПЛЕНИЕ ЗАЙМОВ | D66: 8670613839 | E66: 5.3358891e+09 | F66: 61.539923
B67: 7 | C67: Поступления займов | D67: 8670613839 | E67: 5.3358891e+09 | F67: 61.539923
C68: ПОГАШЕНИЕ ЗАЙМОВ | D68: 4285680537 | E68: 3.3317759e+09 | F68: 77.742051
B69: 16 | C69: Погашение займов | D69: 4285680537 | E69: 3.3317759e+09 | F69: 77.742051
C70: ИСПОЛЬЗУЕМЫЕ ОСТАТКИ БЮДЖЕТНЫХ СРЕДСТВ | D70: 3.3729512e+08 | E70: 1.3000638e+09
C71: Остатки бюджетных средств на начало финансового года | D71: 0 | E71: 3.6749286e+10 | F71: 0
C72: Остатки бюджетных средств на конец отчетного периода | D72: 0 | E72: 3.5449222e+10 | F72: 0

Sheet табл 14
A1: 14-кесте | F1: Таблица 14
A2: 1 тамызға 2025 жылға арналған Қазақстан Республикасы Ұлттық қорының қолма-қол ақшасын бақылау шотындағы ақша қозғалысы туралы есеп/ Движении денег на контрольном счете наличности Национального фонда Республики Казахстан на 1 августа 2025 года
A4: (млн.теңге)
F5: (млн. тенге)
A6: Бюджеттік сыныптама кодтары/ Коды бюджетной классификации | B6: Атауы | C6: Есепті қаржы жылына арналған жоспар/ План на отчетный финансовый год | D6: 2025 ж. қаңтар-шілде есеп/ январь-июль отчет 2025 г. | E6: Жоспарға атқару , % (4-б.:3-б.)/ Исполнение к плану , % (гр.4:гр.3) | F6: Наименование
A7: 1 | B7: 2 | C7: 3 | D7: 4 | E7: 5 | F7: 6
B8: I. КІРІСТЕР | C8: 4883384.8 | D8: 2293830.7 | E8: 47,0 | F8: I. ДОХОДЫ
A9: 1 | B9: Бекітілген тізбе бойынша мұнай секторын ұйымдастырудан түскен салықтық түсімдер | C9: 4882632.8 | D9: 2280877.1 | E9: 46,7 | F9: Налоговые поступления от организаций нефтяного сектора по утвержденному перечню
A10: 2 | B10: Мұнай секторын ұйымдастырудан түскен салықтық емес түсімдер | C10: 691.219 | D10: 11668.701 | E10: 1688,1 | F10: Неналоговые поступления от организаций нефтяного сектора
A11: 3 | B11: Негізгі капиталды сатудан түскен түсімдер | C11: 60.793 | D11: 1101.9848 | E11: 1812,7 | F11: Поступления от продажи основного капитала
A12: 5 | B12: Бюджеттік кредиттерді өтеу | C12: - | D12: 182.913 | E12: - | F12: Погашение бюджетных кредитов
A13: 303 | B13: II. ҚР ҰЛТТЫҚ ҚОРЫНЫҢ ҚБШ - СЫНА АУДАРЫМДАР | C13: - | D13: 2294526.1 | E13: - | F13: II. ПЕРЕВОДЫ С КСН НАЦИОНАЛЬНОГО ФОНДА РК

Sheet табл 15
B2: 15 - кесте | G2: таблица - 15
B4: ҚАЗАҚСТАН РЕСПУБЛИКАСЫ РЕСПУБЛИКАЛЫҚ БЮДЖЕТІНІҢ СЕКВЕСТРЛЕНБЕЙТІН БАҒДАРЛАМАЛАРЫНЫҢ АТҚАРЫЛУЫ | G4: ИСПОЛНЕНИЕ НЕСЕКВЕСТРИРУЕМЫХ ПРОГРАММ РЕСПУБЛИКАНСКОГО БЮДЖЕТА РЕСПУБЛИКИ КАЗАХСТАН
B5: (млн.теңге) | G5: (млн.теңге)
B7: Коды бюджетной классификации/Бюджеттік сыныптама кодтары | F7: Бағдарламаның атауы | G7: 2025 ж. қаңтар-шілде есеп/ январь-июль отчет 2025 г. | H7: Наименование программы
F8: Барлығы | G8: 4397711 | H8: Итого
B9: 04 | F9: Бiлiм беру | G9: 162684.91 | H9: Образование
C10: 224 | F10: Қазақстан Республикасының Оқу-ағарту министрлігі | G10: 152303.16 | H10: Министерство просвещения Республики Казахстан
